{
  "type": "Feature",
  "properties": {
    "gn:admin1_code":"04",
    "gn:asciiname":"Kl'ucovec",
    "gn:country_code":"SK",
    "gn:dem":111,
    "gn:feature_class":"P",
    "gn:feature_code":"PPL",
    "gn:name":"Kl\u2019\u00fa\u010dovec",
    "gn:population":0,
    "gn:timezone":"Europe/Bratislava",
    "iso:country":"SK",
    "name:und_x_variant":[
        "Kulcsod",
        "Kl\u2019\u00fa\u010dovec"
    ],
    "wof:name":"Kl'ucovec",
    "wof:placetype":"locality"
},
  "geometry": {"coordinates":[17.72007,47.79809],"type":"Point"}
}