{
  "type": "Feature",
  "properties": {
    "gn:admin1_code":"02",
    "gn:asciiname":"Chvalov",
    "gn:country_code":"SK",
    "gn:dem":200,
    "gn:feature_class":"P",
    "gn:feature_code":"PPL",
    "gn:name":"Chv\u00e1lov",
    "gn:population":0,
    "gn:timezone":"Europe/Bratislava",
    "iso:country":"SK",
    "wof:name":"Chvalov",
    "wof:placetype":"locality"
},
  "geometry": {"coordinates":[17.16667,48.51667],"type":"Point"}
}