{
  "type": "Feature",
  "properties": {
    "iso:country":"SK",
    "name:eng_x_preferred":[
        "Kolonia"
    ],
    "name:slk_x_preferred":[
        "Kol\u00f3nia"
    ],
    "wof:name":"Kolonia",
    "wof:placetype":"neighbourhood"
},
  "geometry": {"coordinates":[16.97607270786347,48.21690270966497],"type":"Point"}
}