{
  "type": "Feature",
  "properties": {
    "gn:admin1_code":"04",
    "gn:asciiname":"Peres Pusta",
    "gn:country_code":"SK",
    "gn:dem":177,
    "gn:feature_class":"P",
    "gn:feature_code":"PPL",
    "gn:name":"Peres Pusta",
    "gn:population":0,
    "gn:timezone":"Europe/Bratislava",
    "iso:country":"SK",
    "wof:name":"Peres Pusta",
    "wof:placetype":"locality"
},
  "geometry": {"coordinates":[18.49707,48.0269],"type":"Point"}
}