{
  "type": "Feature",
  "properties": {
    "gn:gn_country":"SK",
    "gn:gn_fcode":"PPL",
    "gn:gn_pop":0,
    "iso:country":"SK",
    "name:cat_x_preferred":[
        "Tur\u010dianske K\u013ea\u010dany"
    ],
    "name:ces_x_preferred":[
        "Tur\u010dianske K\u013ea\u010dany"
    ],
    "name:deu_x_preferred":[
        "Tur\u010dianske K\u013ea\u010dany"
    ],
    "name:eng_x_preferred":[
        "Tur\u010dianske K\u013ea\u010dany"
    ],
    "name:epo_x_preferred":[
        "Tur\u010dianske K\u013ea\u010dany"
    ],
    "name:eus_x_preferred":[
        "Tur\u010dianske K\u013ea\u010dany"
    ],
    "name:fra_x_preferred":[
        "Tur\u010dianske K\u013ea\u010dany"
    ],
    "name:hun_x_preferred":[
        "V\u00e1gkelecs\u00e9ny"
    ],
    "name:ita_x_preferred":[
        "Tur\u010dianske K\u013ea\u010dany"
    ],
    "name:msa_x_preferred":[
        "Tur\u010dianske K\u013ea\u010dany"
    ],
    "name:msa_x_variant":[
        "Ubl\u0315a"
    ],
    "name:nan_x_preferred":[
        "Tur\u010dianske K\u013ea\u010dany"
    ],
    "name:nld_x_preferred":[
        "Tur\u010dianske K\u013ea\u010dany"
    ],
    "name:pol_x_preferred":[
        "Tur\u010dianske K\u013ea\u010dany"
    ],
    "name:ron_x_preferred":[
        "Tur\u010dianske K\u013ea\u010dany"
    ],
    "name:slk_x_preferred":[
        "Tur\u010dianske K\u013ea\u010dany"
    ],
    "name:spa_x_preferred":[
        "Tur\u010dianske K\u013ea\u010dany"
    ],
    "name:srp_x_preferred":[
        "\u0422\u0443\u0440\u0447\u0458\u0430\u043d\u0441\u043a\u0435 \u041a\u0459\u0430\u0447\u0430\u043d\u0438"
    ],
    "name:unk_x_variant":[
        "K\u013ea\u010dany"
    ],
    "name:war_x_preferred":[
        "Tur\u010dianske K\u013ea\u010dany"
    ],
    "qs_pg:aaroncc":"SK",
    "qs_pg:gn_country":"SK",
    "qs_pg:gn_fcode":"PPL",
    "qs_pg:gn_pop":0,
    "qs_pg:name":"Tur\u010dianske Kl\u0315a\u010dany",
    "qs_pg:name_adm0":"Slovensk\u00e1",
    "qs_pg:name_adm1":"Zilinsky",
    "qs_pg:photos_9k":1,
    "qs_pg:photos_9r":1,
    "qs_pg:photos_all":4,
    "qs_pg:photos_sr":0,
    "qs_pg:pop_sr":0,
    "qs_pg:qs_pg_placetype":"locality",
    "qs_pg:qs_pg_placetype_gp":"Town",
    "qs_pg:woe_adm0":23424877,
    "woe:adm0_id":23424877,
    "woe:name_adm0":"Slovensk\u00e1",
    "woe:name_adm1":"Zilinsky",
    "woe:placetype":"Town",
    "wof:name":"Tur\u010dianske Kl\u0315a\u010dany",
    "wof:placetype":"locality"
},
  "geometry": {"coordinates":[18.94922,49.11627],"type":"Point"}
}