{
  "type": "Feature",
  "properties": {
    "gn:admin1_code":"03",
    "gn:asciiname":"Rudna",
    "gn:country_code":"SK",
    "gn:dem":354,
    "gn:feature_class":"P",
    "gn:feature_code":"PPL",
    "gn:name":"Rudn\u00e1",
    "gn:population":0,
    "gn:timezone":"Europe/Bratislava",
    "iso:country":"SK",
    "name:cat_x_preferred":[
        "Rudn\u00e1"
    ],
    "name:deu_x_preferred":[
        "Rudn\u00e1"
    ],
    "name:epo_x_preferred":[
        "Rudn\u00e1"
    ],
    "name:eus_x_preferred":[
        "Rudn\u00e1"
    ],
    "name:hun_x_preferred":[
        "Rozsny\u00f3rudna"
    ],
    "name:ita_x_preferred":[
        "Rudn\u00e1"
    ],
    "name:msa_x_preferred":[
        "Rudn\u00e1"
    ],
    "name:nld_x_preferred":[
        "Rudn\u00e1"
    ],
    "name:pol_x_preferred":[
        "Rudn\u00e1"
    ],
    "name:ron_x_preferred":[
        "Rudn\u00e1"
    ],
    "name:slk_x_preferred":[
        "Rudn\u00e1"
    ],
    "name:spa_x_preferred":[
        "Rudn\u00e1"
    ],
    "name:srp_x_preferred":[
        "\u0420\u0443\u0434\u043d\u0430"
    ],
    "name:ukr_x_preferred":[
        "\u0420\u0443\u0434\u043d\u0430"
    ],
    "name:und_x_variant":[
        "Rudn\u00e1"
    ],
    "name:war_x_preferred":[
        "Rudn\u00e1"
    ],
    "wof:name":"Rudna",
    "wof:placetype":"locality"
},
  "geometry": {"coordinates":[20.48943,48.65781],"type":"Point"}
}