{
  "type": "Feature",
  "properties": {
    "gn:admin1_code":"03",
    "gn:asciiname":"Rudna",
    "gn:country_code":"SK",
    "gn:dem":354,
    "gn:feature_class":"P",
    "gn:feature_code":"PPL",
    "gn:name":"Rudn\u00e1",
    "gn:population":0,
    "gn:timezone":"Europe/Bratislava",
    "iso:country":"SK",
    "name:und_x_variant":[
        "Rudn\u00e1"
    ],
    "wof:name":"Rudna",
    "wof:placetype":"locality"
},
  "geometry": {"coordinates":[20.48943,48.65781],"type":"Point"}
}