{
  "type": "Feature",
  "properties": {
    "gn:admin1_code":"05",
    "gn:asciiname":"Babie",
    "gn:country_code":"SK",
    "gn:dem":222,
    "gn:feature_class":"P",
    "gn:feature_code":"PPL",
    "gn:name":"Babie",
    "gn:population":0,
    "gn:timezone":"Europe/Bratislava",
    "iso:country":"SK",
    "name:cat_x_preferred":[
        "Babie"
    ],
    "name:ces_x_preferred":[
        "Babie"
    ],
    "name:epo_x_preferred":[
        "Babie"
    ],
    "name:eus_x_preferred":[
        "Babie"
    ],
    "name:fra_x_preferred":[
        "Babie"
    ],
    "name:hun_x_preferred":[
        "B\u00e1bafalva"
    ],
    "name:ita_x_preferred":[
        "Babie"
    ],
    "name:msa_x_preferred":[
        "Babie"
    ],
    "name:nld_x_preferred":[
        "Babie"
    ],
    "name:pol_x_preferred":[
        "Babie"
    ],
    "name:ron_x_preferred":[
        "Babie"
    ],
    "name:slk_x_preferred":[
        "Babie"
    ],
    "name:spa_x_preferred":[
        "Babie"
    ],
    "name:srp_x_preferred":[
        "\u0411\u0430\u0431\u0458\u0435"
    ],
    "name:ukr_x_preferred":[
        "\u0411\u0430\u0431'\u0454"
    ],
    "name:war_x_preferred":[
        "Babie"
    ],
    "wof:name":"Babie",
    "wof:placetype":"locality"
},
  "geometry": {"coordinates":[21.49127,49.06985],"type":"Point"}
}