{
  "type": "Feature",
  "properties": {
    "gn:admin1_code":"05",
    "gn:asciiname":"Babie",
    "gn:country_code":"SK",
    "gn:dem":222,
    "gn:feature_class":"P",
    "gn:feature_code":"PPL",
    "gn:name":"Babie",
    "gn:population":0,
    "gn:timezone":"Europe/Bratislava",
    "iso:country":"SK",
    "wof:name":"Babie",
    "wof:placetype":"locality"
},
  "geometry": {"coordinates":[21.49127,49.06985],"type":"Point"}
}