{
  "type": "Feature",
  "properties": {
    "gn:admin1_code":"01",
    "gn:asciiname":"Bratkovica",
    "gn:country_code":"SK",
    "gn:dem":823,
    "gn:feature_class":"P",
    "gn:feature_code":"PPL",
    "gn:name":"Bratkovica",
    "gn:population":0,
    "gn:timezone":"Europe/Bratislava",
    "iso:country":"SK",
    "wof:name":"Bratkovica",
    "wof:placetype":"locality"
},
  "geometry": {"coordinates":[19.61542,48.59334000000001],"type":"Point"}
}