{
  "type": "Feature",
  "properties": {
    "gn:admin1_code":"05",
    "gn:asciiname":"Hradisko",
    "gn:country_code":"SK",
    "gn:dem":289,
    "gn:feature_class":"P",
    "gn:feature_code":"PPL",
    "gn:name":"Hradisko",
    "gn:population":0,
    "gn:timezone":"Europe/Bratislava",
    "iso:country":"SK",
    "wof:name":"Hradisko",
    "wof:placetype":"locality"
},
  "geometry": {"coordinates":[21.58706,49.201],"type":"Point"}
}