{
  "type": "Feature",
  "properties": {
    "gn:admin1_code":"05",
    "gn:asciiname":"Hradisko",
    "gn:country_code":"SK",
    "gn:dem":289,
    "gn:feature_class":"P",
    "gn:feature_code":"PPL",
    "gn:name":"Hradisko",
    "gn:population":0,
    "gn:timezone":"Europe/Bratislava",
    "iso:country":"SK",
    "name:cat_x_preferred":[
        "Hradisko"
    ],
    "name:ces_x_preferred":[
        "Hradisko"
    ],
    "name:deu_x_preferred":[
        "Hradisko"
    ],
    "name:epo_x_preferred":[
        "Hradisko"
    ],
    "name:eus_x_preferred":[
        "Hradisko"
    ],
    "name:fra_x_preferred":[
        "Hradisko"
    ],
    "name:hun_x_preferred":[
        "Kisv\u00e1r"
    ],
    "name:ita_x_preferred":[
        "Hradisko"
    ],
    "name:msa_x_preferred":[
        "Hradisko"
    ],
    "name:nld_x_preferred":[
        "Hradisko"
    ],
    "name:pol_x_preferred":[
        "Hradisko"
    ],
    "name:ron_x_preferred":[
        "Hradisko"
    ],
    "name:rue_x_preferred":[
        "\u0413\u0440\u0430\u0434\u0457\u0441\u043a\u043e"
    ],
    "name:slk_x_preferred":[
        "Hradisko"
    ],
    "name:spa_x_preferred":[
        "Hradisko"
    ],
    "name:srp_x_preferred":[
        "\u0425\u0440\u0430\u0434\u0438\u0441\u043a\u043e"
    ],
    "name:ukr_x_preferred":[
        "\u0413\u0440\u0430\u0434\u0438\u0441\u044c\u043a\u043e"
    ],
    "name:war_x_preferred":[
        "Hradisko"
    ],
    "wof:name":"Hradisko",
    "wof:placetype":"locality"
},
  "geometry": {"coordinates":[21.58706,49.201],"type":"Point"}
}