{
  "type": "Feature",
  "properties": {
    "gn:admin1_code":"07",
    "gn:asciiname":"Padan",
    "gn:country_code":"SK",
    "gn:dem":114,
    "gn:feature_class":"P",
    "gn:feature_code":"PPL",
    "gn:name":"Pad\u00e1\u0148",
    "gn:population":0,
    "gn:timezone":"Europe/Bratislava",
    "iso:country":"SK",
    "name:und_x_variant":[
        "Pad\u00e1ny",
        "Pad\u00e1\u0148"
    ],
    "wof:name":"Padan",
    "wof:placetype":"locality"
},
  "geometry": {"coordinates":[17.68281,47.93129],"type":"Point"}
}