{
  "type": "Feature",
  "properties": {
    "gn:admin1_code":"04",
    "gn:asciiname":"Kmet'ovce",
    "gn:country_code":"SK",
    "gn:dem":214,
    "gn:feature_class":"P",
    "gn:feature_code":"PPL",
    "gn:name":"Kme\u0165ovce",
    "gn:population":0,
    "gn:timezone":"Europe/Bratislava",
    "iso:country":"SK",
    "name:hun_x_preferred":[
        "Diszn\u00f3s"
    ],
    "name:und_x_variant":[
        "Disno\u0161",
        "Kme\u0165ovce"
    ],
    "wof:name":"Kmet'ovce",
    "wof:placetype":"locality"
},
  "geometry": {"coordinates":[18.70585,48.26196],"type":"Point"}
}