{
  "type": "Feature",
  "properties": {
    "gn:country":"SK",
    "gn:fcode":"PPL",
    "gn:population":0,
    "iso:country":"SK",
    "name:cat_x_preferred":[
        "Jasenica"
    ],
    "name:ces_x_preferred":[
        "Jasenica"
    ],
    "name:deu_x_preferred":[
        "Jasenica"
    ],
    "name:eng_x_preferred":[
        "Jasenica"
    ],
    "name:epo_x_preferred":[
        "Jasenica"
    ],
    "name:eus_x_preferred":[
        "Jasenica"
    ],
    "name:fra_x_preferred":[
        "Jasenica"
    ],
    "name:hun_x_preferred":[
        "Jeszence"
    ],
    "name:ita_x_preferred":[
        "Jasenica"
    ],
    "name:msa_x_preferred":[
        "Jasenica"
    ],
    "name:nld_x_preferred":[
        "Jasenica"
    ],
    "name:ron_x_preferred":[
        "Jasenica"
    ],
    "name:slk_x_preferred":[
        "Jasenica"
    ],
    "name:spa_x_preferred":[
        "Vel\u0315k\u00e9 Z\u00e1lu\u017eie"
    ],
    "name:spa_x_variant":[
        "Jasenica"
    ],
    "name:srp_x_preferred":[
        "\u0408\u0430\u0441\u0435\u045a\u0438\u0446\u0430"
    ],
    "name:und_x_variant":[
        "Jesenica"
    ],
    "name:war_x_preferred":[
        "Jasenica"
    ],
    "qs_pg:aaroncc":"SK",
    "qs_pg:gn_country":"SK",
    "qs_pg:gn_fcode":"PPL",
    "qs_pg:gn_pop":0,
    "qs_pg:name":"Jasenica",
    "qs_pg:name_adm0":"Slovensk\u00e1",
    "qs_pg:name_adm1":"Trenciansky",
    "qs_pg:photos_9r":0,
    "qs_pg:photos_sr":0,
    "qs_pg:pop_sr":0,
    "qs_pg:qs_pg_placetype":"locality",
    "qs_pg:qs_pg_placetype_gp":"Town",
    "qs_pg:woe_adm0":23424877,
    "woe:adm0_id":23424877,
    "woe:name_adm0":"Slovensk\u00e1",
    "woe:name_adm1":"Trenciansky",
    "woe:placetype":"Town",
    "wof:name":"Jasenica",
    "wof:placetype":"locality"
},
  "geometry": {"coordinates":[18.45106,49.18012],"type":"Point"}
}