{
  "type": "Feature",
  "properties": {
    "gn:admin1_code":"05",
    "gn:asciiname":"Chabzany",
    "gn:country_code":"SK",
    "gn:dem":225,
    "gn:feature_class":"P",
    "gn:feature_code":"PPL",
    "gn:name":"Chab\u017eany",
    "gn:population":0,
    "gn:timezone":"Europe/Bratislava",
    "iso:country":"SK",
    "wof:name":"Chabzany",
    "wof:placetype":"locality"
},
  "geometry": {"coordinates":[21.27874,48.84421],"type":"Point"}
}