{
  "type": "Feature",
  "properties": {
    "gn:admin1_code":"07",
    "gn:asciiname":"Vradiste",
    "gn:country_code":"SK",
    "gn:dem":169,
    "gn:feature_class":"P",
    "gn:feature_code":"PPL",
    "gn:name":"Vr\u00e1di\u0161te",
    "gn:population":0,
    "gn:timezone":"Europe/Bratislava",
    "iso:country":"SK",
    "name:cat_x_preferred":[
        "Vr\u00e1di\u0161te"
    ],
    "name:ces_x_preferred":[
        "Vr\u00e1di\u0161te"
    ],
    "name:deu_x_preferred":[
        "Vr\u00e1di\u0161te"
    ],
    "name:epo_x_preferred":[
        "Vr\u00e1di\u0161te"
    ],
    "name:eus_x_preferred":[
        "Vr\u00e1di\u0161te"
    ],
    "name:fra_x_preferred":[
        "Vr\u00e1di\u0161te"
    ],
    "name:hun_x_preferred":[
        "V\u00e1rk\u00f6z"
    ],
    "name:ita_x_preferred":[
        "Vr\u00e1di\u0161te"
    ],
    "name:msa_x_preferred":[
        "Vr\u00e1di\u0161te"
    ],
    "name:nld_x_preferred":[
        "Vr\u00e1di\u0161te"
    ],
    "name:ron_x_preferred":[
        "Vr\u00e1di\u0161te"
    ],
    "name:slk_x_preferred":[
        "Vr\u00e1di\u0161te"
    ],
    "name:spa_x_preferred":[
        "Vr\u00e1di\u0161te"
    ],
    "name:srp_x_preferred":[
        "\u0412\u0440\u0430\u0434\u0438\u0448\u0442\u0435"
    ],
    "name:ukr_x_preferred":[
        "\u0412\u0440\u0430\u0434\u0456\u0448\u0442\u0435"
    ],
    "name:war_x_preferred":[
        "Vr\u00e1di\u0161te"
    ],
    "wof:name":"Vradiste",
    "wof:placetype":"locality"
},
  "geometry": {"coordinates":[17.19093,48.82361],"type":"Point"}
}