{
  "type": "Feature",
  "properties": {
    "gn:admin1_code":"07",
    "gn:asciiname":"Vradiste",
    "gn:country_code":"SK",
    "gn:dem":169,
    "gn:feature_class":"P",
    "gn:feature_code":"PPL",
    "gn:name":"Vr\u00e1di\u0161te",
    "gn:population":0,
    "gn:timezone":"Europe/Bratislava",
    "iso:country":"SK",
    "name:und_x_variant":[
        "Vr\u00e1di\u0161te"
    ],
    "wof:name":"Vradiste",
    "wof:placetype":"locality"
},
  "geometry": {"coordinates":[17.19093,48.82361],"type":"Point"}
}