{
  "type": "Feature",
  "properties": {
    "gn:gn_country":"SK",
    "gn:gn_fcode":"PPL",
    "gn:gn_pop":0,
    "iso:country":"SK",
    "name:cat_x_preferred":[
        "Rohov"
    ],
    "name:cze_x_preferred":[
        "Rohov"
    ],
    "name:dut_x_preferred":[
        "Rohov"
    ],
    "name:eng_x_preferred":[
        "Rohov"
    ],
    "name:epo_x_preferred":[
        "Rohov"
    ],
    "name:fre_x_preferred":[
        "Rohov"
    ],
    "name:ger_x_preferred":[
        "Rohov"
    ],
    "name:hun_x_preferred":[
        "Roh\u00f3"
    ],
    "name:ita_x_preferred":[
        "Rohov"
    ],
    "name:may_x_preferred":[
        "Rohov"
    ],
    "name:nan_x_preferred":[
        "Rohov"
    ],
    "name:por_x_preferred":[
        "Rohov"
    ],
    "name:slo_x_preferred":[
        "Rohov"
    ],
    "name:srp_x_preferred":[
        "\u0420\u043e\u0445\u043e\u0432"
    ],
    "name:war_x_preferred":[
        "Rohov"
    ],
    "qs_pg:aaroncc":"SK",
    "qs_pg:gn_country":"SK",
    "qs_pg:gn_fcode":"PPL",
    "qs_pg:gn_pop":0,
    "qs_pg:name":"Rohov",
    "qs_pg:name_adm0":"Slovensk\u00e1",
    "qs_pg:name_adm1":"Trnavsky",
    "qs_pg:photos_9r":0,
    "qs_pg:photos_sr":0,
    "qs_pg:pop_sr":0,
    "qs_pg:qs_pg_placetype":"locality",
    "qs_pg:qs_pg_placetype_gp":"Town",
    "qs_pg:woe_adm0":23424877,
    "woe:adm0_id":23424877,
    "woe:name_adm0":"Slovensk\u00e1",
    "woe:name_adm1":"Trnavsky",
    "woe:placetype":"Town",
    "wof:name":"Rohov",
    "wof:placetype":"locality"
},
  "geometry": {"coordinates":[17.34582,48.72718],"type":"Point"}
}