{
  "type": "Feature",
  "properties": {
    "gn:admin1_code":"04",
    "gn:asciiname":"Tekovske Trst'any",
    "gn:country_code":"SK",
    "gn:dem":162,
    "gn:feature_class":"P",
    "gn:feature_code":"PPL",
    "gn:name":"Tekovsk\u00e9 Trs\u0165any",
    "gn:population":0,
    "gn:timezone":"Europe/Bratislava",
    "iso:country":"SK",
    "name:hun_x_preferred":[
        "Hontn\u00e1das"
    ],
    "name:slk_x_historical":[
        "Nado\u0161any"
    ],
    "name:slk_x_preferred":[
        "Hontianske Trs\u0165any"
    ],
    "name:slk_x_variant":[
        "Nado\u0161any"
    ],
    "name:und_x_variant":[
        "Tekovsk\u00e9 Trs\u0165any"
    ],
    "wof:name":"Tekovske Trst'any",
    "wof:placetype":"locality"
},
  "geometry": {"coordinates":[18.80441,48.20816],"type":"Point"}
}