{
  "type": "Feature",
  "properties": {
    "gn:admin1_code":"04",
    "gn:asciiname":"Horny Lieskov",
    "gn:country_code":"SK",
    "gn:dem":363,
    "gn:feature_class":"P",
    "gn:feature_code":"PPL",
    "gn:name":"Horn\u00fd Lieskov",
    "gn:population":0,
    "gn:timezone":"Europe/Bratislava",
    "iso:country":"SK",
    "name:cat_x_preferred":[
        "Horn\u00fd Lieskov"
    ],
    "name:ces_x_preferred":[
        "Horn\u00fd Lieskov"
    ],
    "name:epo_x_preferred":[
        "Horn\u00fd Lieskov"
    ],
    "name:eus_x_preferred":[
        "Horn\u00fd Lieskov"
    ],
    "name:fra_x_preferred":[
        "Horn\u00fd Lieskov"
    ],
    "name:hun_x_preferred":[
        "Fels\u0151mogyor\u00f3d"
    ],
    "name:ita_x_preferred":[
        "Horn\u00fd Lieskov"
    ],
    "name:msa_x_preferred":[
        "Horn\u00fd Lieskov"
    ],
    "name:nld_x_preferred":[
        "Horn\u00fd Lieskov"
    ],
    "name:ron_x_preferred":[
        "Horn\u00fd Lieskov"
    ],
    "name:slk_x_preferred":[
        "Horn\u00fd Lieskov"
    ],
    "name:spa_x_preferred":[
        "Horn\u00fd Lieskov"
    ],
    "name:srp_x_preferred":[
        "\u0425\u043e\u0440\u043d\u0438 \u0409\u0435\u0441\u043a\u043e\u0432"
    ],
    "name:und_x_variant":[
        "Horn\u00fd Lieskov"
    ],
    "name:war_x_preferred":[
        "Horn\u00fd Lieskov"
    ],
    "wof:name":"Horny Lieskov",
    "wof:placetype":"locality"
},
  "geometry": {"coordinates":[18.43605,49.06485],"type":"Point"}
}