{
  "type": "Feature",
  "properties": {
    "gn:admin1_code":"04",
    "gn:asciiname":"Horny Lieskov",
    "gn:country_code":"SK",
    "gn:dem":363,
    "gn:feature_class":"P",
    "gn:feature_code":"PPL",
    "gn:name":"Horn\u00fd Lieskov",
    "gn:population":0,
    "gn:timezone":"Europe/Bratislava",
    "iso:country":"SK",
    "name:und_x_variant":[
        "Horn\u00fd Lieskov"
    ],
    "wof:name":"Horny Lieskov",
    "wof:placetype":"locality"
},
  "geometry": {"coordinates":[18.43605,49.06485],"type":"Point"}
}