{
  "type": "Feature",
  "properties": {
    "gn:admin1_code":"05",
    "gn:asciiname":"Klenov",
    "gn:country_code":"SK",
    "gn:dem":552,
    "gn:feature_class":"P",
    "gn:feature_code":"PPL",
    "gn:name":"Klenov",
    "gn:population":0,
    "gn:timezone":"Europe/Bratislava",
    "iso:country":"SK",
    "name:cat_x_preferred":[
        "Klenov"
    ],
    "name:ces_x_preferred":[
        "Klenov"
    ],
    "name:deu_x_preferred":[
        "Klenov"
    ],
    "name:epo_x_preferred":[
        "Klenov"
    ],
    "name:eus_x_preferred":[
        "Klenov"
    ],
    "name:fra_x_preferred":[
        "Klenov"
    ],
    "name:hun_x_preferred":[
        "Kelemb\u00e9r"
    ],
    "name:ita_x_preferred":[
        "Klenov"
    ],
    "name:msa_x_preferred":[
        "Klenov"
    ],
    "name:nld_x_preferred":[
        "Klenov"
    ],
    "name:pol_x_preferred":[
        "Klenov"
    ],
    "name:ron_x_preferred":[
        "Klenov"
    ],
    "name:rue_x_preferred":[
        "\u041a\u043b\u0435\u043d\u043e\u0432"
    ],
    "name:slk_x_preferred":[
        "Klenov"
    ],
    "name:spa_x_preferred":[
        "Klenov"
    ],
    "name:srp_x_preferred":[
        "\u041a\u0459\u0435\u043d\u043e\u0432"
    ],
    "name:ukr_x_preferred":[
        "\u041a\u043b\u0435\u043d\u043e\u0432"
    ],
    "name:und_x_variant":[
        "Klembarok",
        "Klenov"
    ],
    "name:war_x_preferred":[
        "Klenov"
    ],
    "wof:name":"Klenov",
    "wof:placetype":"locality"
},
  "geometry": {"coordinates":[21.05598,48.92667],"type":"Point"}
}