{
  "type": "Feature",
  "properties": {
    "gn:admin1_code":"05",
    "gn:asciiname":"Klenov",
    "gn:country_code":"SK",
    "gn:dem":552,
    "gn:feature_class":"P",
    "gn:feature_code":"PPL",
    "gn:name":"Klenov",
    "gn:population":0,
    "gn:timezone":"Europe/Bratislava",
    "iso:country":"SK",
    "name:und_x_variant":[
        "Klembarok",
        "Klenov"
    ],
    "wof:name":"Klenov",
    "wof:placetype":"locality"
},
  "geometry": {"coordinates":[21.05598,48.92667],"type":"Point"}
}