{
  "type": "Feature",
  "properties": {
    "gn:admin1_code":"04",
    "gn:asciiname":"Tekovske Luzianky",
    "gn:country_code":"SK",
    "gn:dem":153,
    "gn:feature_class":"P",
    "gn:feature_code":"PPL",
    "gn:name":"Tekovsk\u00e9 Lu\u017eianky",
    "gn:population":0,
    "gn:timezone":"Europe/Bratislava",
    "iso:country":"SK",
    "name:und_x_variant":[
        "Kis-Sall\u00f3",
        "Tekovsk\u00e9 \u0160arlu\u017eky",
        "Tekovsk\u00e9 Lu\u017eianky"
    ],
    "wof:name":"Tekovske Luzianky",
    "wof:placetype":"locality"
},
  "geometry": {"coordinates":[18.54616,48.10149000000001],"type":"Point"}
}