{
  "type": "Feature",
  "properties": {
    "gn:admin1_code":"05",
    "gn:asciiname":"Lucivna",
    "gn:country_code":"SK",
    "gn:dem":766,
    "gn:feature_class":"P",
    "gn:feature_code":"PPL",
    "gn:name":"Lu\u010divn\u00e1",
    "gn:population":0,
    "gn:timezone":"Europe/Bratislava",
    "iso:country":"SK",
    "name:und_x_variant":[
        "Lu\u010divn\u00e1"
    ],
    "wof:name":"Lucivna",
    "wof:placetype":"locality"
},
  "geometry": {"coordinates":[20.14242,49.05152],"type":"Point"}
}