{
  "type": "Feature",
  "properties": {
    "gn:admin1_code":"05",
    "gn:asciiname":"Lucivna",
    "gn:country_code":"SK",
    "gn:dem":766,
    "gn:feature_class":"P",
    "gn:feature_code":"PPL",
    "gn:name":"Lu\u010divn\u00e1",
    "gn:population":0,
    "gn:timezone":"Europe/Bratislava",
    "iso:country":"SK",
    "name:cat_x_preferred":[
        "Lu\u010divn\u00e1"
    ],
    "name:ces_x_preferred":[
        "Lu\u010divn\u00e1"
    ],
    "name:deu_x_preferred":[
        "Lu\u010divn\u00e1"
    ],
    "name:epo_x_preferred":[
        "Lu\u010divn\u00e1"
    ],
    "name:eus_x_preferred":[
        "Lu\u010divn\u00e1"
    ],
    "name:fra_x_preferred":[
        "Lu\u010divn\u00e1"
    ],
    "name:hun_x_preferred":[
        "Lucsivna"
    ],
    "name:ita_x_preferred":[
        "Lu\u010divn\u00e1"
    ],
    "name:msa_x_preferred":[
        "Lu\u010divn\u00e1"
    ],
    "name:nld_x_preferred":[
        "Lu\u010divn\u00e1"
    ],
    "name:pol_x_preferred":[
        "\u0141uczywna"
    ],
    "name:ron_x_preferred":[
        "Lu\u010divn\u00e1"
    ],
    "name:rue_x_preferred":[
        "\u041b\u0443\u0447\u0456\u0432\u043d\u0430"
    ],
    "name:slk_x_preferred":[
        "Lu\u010divn\u00e1"
    ],
    "name:spa_x_preferred":[
        "Lu\u010divn\u00e1"
    ],
    "name:srp_x_preferred":[
        "\u041b\u0443\u0447\u0438\u0432\u043d\u0430"
    ],
    "name:ukr_x_preferred":[
        "\u041b\u0443\u0447\u0438\u0432\u043d\u0430"
    ],
    "name:und_x_variant":[
        "Lu\u010divn\u00e1"
    ],
    "name:war_x_preferred":[
        "Lu\u010divn\u00e1"
    ],
    "wof:name":"Lucivna",
    "wof:placetype":"locality"
},
  "geometry": {"coordinates":[20.14242,49.05152],"type":"Point"}
}