{
  "type": "Feature",
  "properties": {
    "gn:admin1_code":"05",
    "gn:asciiname":"Radacov",
    "gn:country_code":"SK",
    "gn:dem":294,
    "gn:feature_class":"P",
    "gn:feature_code":"PPL",
    "gn:name":"Rada\u010dov",
    "gn:population":0,
    "gn:timezone":"Europe/Bratislava",
    "iso:country":"SK",
    "wof:name":"Radacov",
    "wof:placetype":"locality"
},
  "geometry": {"coordinates":[21.18919,48.93412],"type":"Point"}
}