{
  "type": "Feature",
  "properties": {
    "gn:gn_country":"SK",
    "gn:gn_fcode":"PPL",
    "gn:gn_pop":0,
    "iso:country":"SK",
    "name:cat_x_preferred":[
        "Most pri Bratislave"
    ],
    "name:cze_x_preferred":[
        "Most pri Bratislave"
    ],
    "name:dut_x_preferred":[
        "Most pri Bratislave"
    ],
    "name:eng_x_preferred":[
        "Most pri Bratislave"
    ],
    "name:epo_x_preferred":[
        "Most pri Bratislave"
    ],
    "name:fre_x_preferred":[
        "Most pri Bratislave"
    ],
    "name:ger_x_preferred":[
        "Most pri Bratislave"
    ],
    "name:hun_x_preferred":[
        "Dunahidas"
    ],
    "name:ita_x_preferred":[
        "Most pri Bratislave"
    ],
    "name:may_x_preferred":[
        "Most pri Bratislave"
    ],
    "name:nan_x_preferred":[
        "Most pri Bratislave"
    ],
    "name:por_x_preferred":[
        "Most pri Bratislave"
    ],
    "name:slo_x_preferred":[
        "Most pri Bratislave"
    ],
    "name:srp_x_preferred":[
        "\u041c\u043e\u0441\u0442 \u043f\u0440\u0438 \u0411\u0440\u0430\u0442\u0438\u0441\u043b\u0430\u0432\u0438"
    ],
    "name:unk_x_variant":[
        "Bruck"
    ],
    "name:war_x_preferred":[
        "Most pri Bratislave"
    ],
    "qs_pg:aaroncc":"SK",
    "qs_pg:gn_country":"SK",
    "qs_pg:gn_fcode":"PPL",
    "qs_pg:gn_pop":0,
    "qs_pg:name":"Most na Ostrove",
    "qs_pg:name_adm0":"Slovensk\u00e1",
    "qs_pg:name_adm1":"Bratislavsky",
    "qs_pg:photos_9k":1,
    "qs_pg:photos_9r":1,
    "qs_pg:photos_all":1,
    "qs_pg:photos_sr":0,
    "qs_pg:pop_sr":0,
    "qs_pg:qs_pg_placetype":"locality",
    "qs_pg:qs_pg_placetype_gp":"Town",
    "qs_pg:woe_adm0":23424877,
    "woe:adm0_id":23424877,
    "woe:name_adm0":"Slovensk\u00e1",
    "woe:name_adm1":"Bratislavsky",
    "woe:placetype":"Town",
    "wof:name":"Most na Ostrove",
    "wof:placetype":"locality"
},
  "geometry": {"coordinates":[17.27085,48.14204],"type":"Point"}
}