{
  "type": "Feature",
  "properties": {
    "gn:gn_country":"SK",
    "gn:gn_fcode":"PPL",
    "gn:gn_pop":0,
    "iso:country":"SK",
    "name:cat_x_preferred":[
        "Stre\u017eenice"
    ],
    "name:ces_x_preferred":[
        "Stre\u017eenice"
    ],
    "name:deu_x_preferred":[
        "Stre\u017eenice"
    ],
    "name:eng_x_preferred":[
        "Stre\u017eenice"
    ],
    "name:epo_x_preferred":[
        "Stre\u017eenice"
    ],
    "name:fra_x_preferred":[
        "Stre\u017eenice"
    ],
    "name:hun_x_preferred":[
        "Kebeles"
    ],
    "name:ita_x_preferred":[
        "Stre\u017eenice"
    ],
    "name:msa_x_preferred":[
        "Stre\u017eenice"
    ],
    "name:nan_x_preferred":[
        "Stre\u017eenice"
    ],
    "name:nld_x_preferred":[
        "Stre\u017eenice"
    ],
    "name:slk_x_preferred":[
        "Stre\u017eenice"
    ],
    "name:srp_x_preferred":[
        "\u0421\u0442\u0440\u0435\u0436\u0435\u045a\u0438\u0446\u0435"
    ],
    "name:war_x_preferred":[
        "Stre\u017eenice"
    ],
    "qs_pg:aaroncc":"SK",
    "qs_pg:gn_country":"SK",
    "qs_pg:gn_fcode":"PPL",
    "qs_pg:gn_pop":0,
    "qs_pg:name":"Stre\u017eenice",
    "qs_pg:name_adm0":"Slovensk\u00e1",
    "qs_pg:name_adm1":"Trenciansky",
    "qs_pg:photos_9r":0,
    "qs_pg:photos_sr":0,
    "qs_pg:pop_sr":0,
    "qs_pg:qs_pg_placetype":"locality",
    "qs_pg:qs_pg_placetype_gp":"Town",
    "qs_pg:woe_adm0":23424877,
    "woe:adm0_id":23424877,
    "woe:name_adm0":"Slovensk\u00e1",
    "woe:name_adm1":"Trenciansky",
    "woe:placetype":"Town",
    "wof:name":"Stre\u017eenice",
    "wof:placetype":"locality"
},
  "geometry": {"coordinates":[18.30581,49.1078],"type":"Point"}
}