{
  "type": "Feature",
  "properties": {
    "gn:admin1_code":"01",
    "gn:asciiname":"Muranska Dlha Luka",
    "gn:country_code":"SK",
    "gn:dem":343,
    "gn:feature_class":"P",
    "gn:feature_code":"PPL",
    "gn:name":"Mur\u00e1nska Dlh\u00e1 L\u00faka",
    "gn:population":0,
    "gn:timezone":"Europe/Bratislava",
    "iso:country":"SK",
    "name:und_x_variant":[
        "Mur\u00e1nska Dlh\u00e1 L\u00faka"
    ],
    "wof:name":"Muranska Dlha Luka",
    "wof:placetype":"locality"
},
  "geometry": {"coordinates":[20.08025,48.71587],"type":"Point"}
}