{
  "type": "Feature",
  "properties": {
    "gn:admin1_code":"01",
    "gn:asciiname":"Muranska Dlha Luka",
    "gn:country_code":"SK",
    "gn:dem":343,
    "gn:feature_class":"P",
    "gn:feature_code":"PPL",
    "gn:name":"Mur\u00e1nska Dlh\u00e1 L\u00faka",
    "gn:population":0,
    "gn:timezone":"Europe/Bratislava",
    "iso:country":"SK",
    "name:cat_x_preferred":[
        "Mur\u00e1nska Dlh\u00e1 L\u00faka"
    ],
    "name:ces_x_preferred":[
        "Mur\u00e1nska Dlh\u00e1 L\u00faka"
    ],
    "name:deu_x_preferred":[
        "Mur\u00e1nska Dlh\u00e1 L\u00faka"
    ],
    "name:epo_x_preferred":[
        "Mur\u00e1nska Dlh\u00e1 L\u00faka"
    ],
    "name:eus_x_preferred":[
        "Mur\u00e1nska Dlh\u00e1 L\u00faka"
    ],
    "name:fra_x_preferred":[
        "Mur\u00e1nska Dlh\u00e1 L\u00faka"
    ],
    "name:hun_x_preferred":[
        "Mur\u00e1nyhossz\u00far\u00e9t"
    ],
    "name:ita_x_preferred":[
        "Mur\u00e1nska Dlh\u00e1 L\u00faka"
    ],
    "name:msa_x_preferred":[
        "Mur\u00e1nska Dlh\u00e1 L\u00faka"
    ],
    "name:nld_x_preferred":[
        "Mur\u00e1nska Dlh\u00e1 L\u00faka"
    ],
    "name:pol_x_preferred":[
        "Mur\u00e1nska Dlh\u00e1 L\u00faka"
    ],
    "name:ron_x_preferred":[
        "Mur\u00e1nska Dlh\u00e1 L\u00faka"
    ],
    "name:slk_x_preferred":[
        "Mur\u00e1nska Dlh\u00e1 L\u00faka"
    ],
    "name:spa_x_preferred":[
        "Mur\u00e1nska Dlh\u00e1 L\u00faka"
    ],
    "name:srp_x_preferred":[
        "\u041c\u0443\u0440\u0430\u043d\u0441\u043a\u0430 \u0414\u0443\u0433\u0430 \u041b\u0443\u043a\u0430"
    ],
    "name:ukr_x_preferred":[
        "\u041c\u0443\u0440\u0430\u043d\u0441\u044c\u043a\u0430 \u0414\u043b\u0433\u0430 \u041b\u0443\u043a\u0430"
    ],
    "name:und_x_variant":[
        "Mur\u00e1nska Dlh\u00e1 L\u00faka"
    ],
    "name:war_x_preferred":[
        "Mur\u00e1nska Dlh\u00e1 L\u00faka"
    ],
    "wof:name":"Muranska Dlha Luka",
    "wof:placetype":"locality"
},
  "geometry": {"coordinates":[20.08025,48.71587],"type":"Point"}
}