{
  "type": "Feature",
  "properties": {
    "gn:admin1_code":"03",
    "gn:asciiname":"Blatne Revistia",
    "gn:country_code":"SK",
    "gn:dem":105,
    "gn:feature_class":"P",
    "gn:feature_code":"PPL",
    "gn:name":"Blatn\u00e9 Revi\u0161tia",
    "gn:population":0,
    "gn:timezone":"Europe/Bratislava",
    "iso:country":"SK",
    "name:und_x_variant":[
        "Blatn\u00e9 Revi\u0161tia"
    ],
    "wof:name":"Blatne Revistia",
    "wof:placetype":"locality"
},
  "geometry": {"coordinates":[22.07954,48.73828],"type":"Point"}
}