{
  "type": "Feature",
  "properties": {
    "gn:admin1_code":"03",
    "gn:asciiname":"Blatne Revistia",
    "gn:country_code":"SK",
    "gn:dem":105,
    "gn:feature_class":"P",
    "gn:feature_code":"PPL",
    "gn:name":"Blatn\u00e9 Revi\u0161tia",
    "gn:population":0,
    "gn:timezone":"Europe/Bratislava",
    "iso:country":"SK",
    "name:cat_x_preferred":[
        "Blatn\u00e9 Revi\u0161tia"
    ],
    "name:ces_x_preferred":[
        "Blatn\u00e9 Revi\u0161tia"
    ],
    "name:epo_x_preferred":[
        "Blatn\u00e9 Revi\u0161tia"
    ],
    "name:eus_x_preferred":[
        "Blatn\u00e9 Revi\u0161tia"
    ],
    "name:fra_x_preferred":[
        "Blatn\u00e9 Revi\u0161tia"
    ],
    "name:hun_x_preferred":[
        "S\u00e1rosr\u0151cse"
    ],
    "name:ita_x_preferred":[
        "Blatn\u00e9 Revi\u0161tia"
    ],
    "name:msa_x_preferred":[
        "Blatn\u00e9 Revi\u0161tia"
    ],
    "name:nld_x_preferred":[
        "Blatn\u00e9 Revi\u0161tia"
    ],
    "name:pol_x_preferred":[
        "Blatn\u00e9 Revi\u0161tia"
    ],
    "name:ron_x_preferred":[
        "Blatn\u00e9 Revi\u0161tia"
    ],
    "name:rue_x_preferred":[
        "\u0411\u043b\u0430\u0442\u043d\u044b \u0420\u0435\u0432\u0456\u0449\u0430"
    ],
    "name:slk_x_preferred":[
        "Blatn\u00e9 Revi\u0161tia"
    ],
    "name:spa_x_preferred":[
        "Blatn\u00e9 Revi\u0161tia"
    ],
    "name:srp_x_preferred":[
        "\u0411\u043b\u0430\u0442\u045a\u0435 \u0420\u0435\u0432\u0438\u0448\u0442\u0458\u0430"
    ],
    "name:ukr_x_preferred":[
        "\u0411\u043b\u0430\u0442\u043d\u0435 \u0420\u0435\u0432\u0456\u0448\u0442\u044f"
    ],
    "name:war_x_preferred":[
        "Blatn\u00e9 Revi\u0161tia"
    ],
    "wof:name":"Blatne Revistia",
    "wof:placetype":"locality"
},
  "geometry": {"coordinates":[22.07954,48.73828],"type":"Point"}
}