{
  "type": "Feature",
  "properties": {
    "iso:country":"SK",
    "name:ara_x_preferred":[
        "\u062a\u064a\u0633\u0648\u0641\u064a\u062a\u0633"
    ],
    "name:cat_x_preferred":[
        "Tisovec"
    ],
    "name:ceb_x_preferred":[
        "Tisovec"
    ],
    "name:ces_x_preferred":[
        "Tisovec"
    ],
    "name:deu_x_preferred":[
        "Tisovec"
    ],
    "name:epo_x_preferred":[
        "Tisovec"
    ],
    "name:fas_x_preferred":[
        "\u062a\u06cc\u0633\u0648\u062a\u0633"
    ],
    "name:hrv_x_preferred":[
        "Tisovec"
    ],
    "name:hun_x_preferred":[
        "Tiszolc"
    ],
    "name:ita_x_preferred":[
        "Tisovec"
    ],
    "name:lav_x_preferred":[
        "Tisoveca"
    ],
    "name:msa_x_preferred":[
        "Tisovec"
    ],
    "name:nld_x_preferred":[
        "Tisovec"
    ],
    "name:pol_x_preferred":[
        "Tisovec"
    ],
    "name:ron_x_preferred":[
        "Tisovec"
    ],
    "name:rus_x_preferred":[
        "\u0422\u0438\u0441\u043e\u0432\u0435\u0446"
    ],
    "name:slk_x_preferred":[
        "Tisovec"
    ],
    "name:spa_x_preferred":[
        "Tisovec"
    ],
    "name:srp_x_preferred":[
        "\u0422\u0438\u0441\u043e\u0432\u0435\u0446"
    ],
    "name:swe_x_preferred":[
        "Tisovec"
    ],
    "name:tur_x_preferred":[
        "Tisovec"
    ],
    "name:ukr_x_preferred":[
        "\u0422\u0438\u0441\u043e\u0432\u0435\u0446\u044c"
    ],
    "name:war_x_preferred":[
        "Tisovec"
    ],
    "name:zho_x_preferred":[
        "\u5b63\u7d22\u97cb\u8328"
    ],
    "qs_pg:aaroncc":"SK",
    "qs_pg:name":"Tisovec",
    "qs_pg:name_adm0":"Slovensk\u00e1",
    "qs_pg:name_adm1":"Banskobystricky",
    "qs_pg:photos":5,
    "qs_pg:photos_1k":1,
    "qs_pg:photos_9k":1,
    "qs_pg:photos_9r":2,
    "qs_pg:photos_all":47,
    "qs_pg:photos_sr":1,
    "qs_pg:pop_sr":0,
    "qs_pg:qs_pg_placetype":"localadmin",
    "qs_pg:qs_pg_placetype_gp":"LocalAdmin",
    "qs_pg:woe_adm0":23424877,
    "woe:adm0_id":23424877,
    "woe:name_adm0":"Slovensk\u00e1",
    "woe:name_adm1":"Banskobystricky",
    "woe:placetype":"LocalAdmin",
    "wof:name":"Tisovec",
    "wof:placetype":"localadmin"
},
  "geometry": {"coordinates":[19.942245,48.682347],"type":"Point"}
}