{
  "type": "Feature",
  "properties": {
    "gn:admin1_code":"06",
    "gn:admin2_code":"308.0",
    "gn:asciiname":"Horne Kockovce",
    "gn:country_code":"SK",
    "gn:dem":284,
    "gn:feature_class":"P",
    "gn:feature_code":"PPL",
    "gn:name":"Horn\u00e9 Ko\u010dkovce",
    "gn:population":0,
    "gn:timezone":"Europe/Bratislava",
    "iso:country":"SK",
    "wof:name":"Horne Kockovce",
    "wof:placetype":"locality"
},
  "geometry": {"coordinates":[18.33382000000001,49.11791],"type":"Point"}
}