{
  "type": "Feature",
  "properties": {
    "gn:admin1_code":"08",
    "gn:asciiname":"Lietavska Zavadka",
    "gn:country_code":"SK",
    "gn:dem":493,
    "gn:feature_class":"P",
    "gn:feature_code":"PPL",
    "gn:name":"Lietavsk\u00e1 Z\u00e1vadka",
    "gn:population":0,
    "gn:timezone":"Europe/Bratislava",
    "iso:country":"SK",
    "wof:name":"Lietavska Zavadka",
    "wof:placetype":"locality"
},
  "geometry": {"coordinates":[18.63421,49.18267],"type":"Point"}
}