{
  "type": "Feature",
  "properties": {
    "gn:admin1_code":"04",
    "gn:asciiname":"Mala Cierna",
    "gn:country_code":"SK",
    "gn:dem":525,
    "gn:feature_class":"P",
    "gn:feature_code":"PPL",
    "gn:name":"Mal\u00e1 \u010cierna",
    "gn:population":0,
    "gn:timezone":"Europe/Bratislava",
    "iso:country":"SK",
    "name:cat_x_preferred":[
        "Mal\u00e1 \u010cierna"
    ],
    "name:ces_x_preferred":[
        "Mal\u00e1 \u010cierna"
    ],
    "name:deu_x_preferred":[
        "Mal\u00e1 \u010cierna"
    ],
    "name:epo_x_preferred":[
        "Mal\u00e1 \u010cierna"
    ],
    "name:eus_x_preferred":[
        "Mal\u00e1 \u010cierna"
    ],
    "name:fra_x_preferred":[
        "Mal\u00e1 \u010cierna"
    ],
    "name:hun_x_preferred":[
        "Kiscserna"
    ],
    "name:ita_x_preferred":[
        "Mal\u00e1 \u010cierna"
    ],
    "name:msa_x_preferred":[
        "Mal\u00e1 \u010cierna"
    ],
    "name:nld_x_preferred":[
        "Mal\u00e1 \u010cierna"
    ],
    "name:pol_x_preferred":[
        "Mal\u00e1 \u010cierna"
    ],
    "name:ron_x_preferred":[
        "Mal\u00e1 \u010cierna"
    ],
    "name:slk_x_preferred":[
        "Mal\u00e1 \u010cierna"
    ],
    "name:spa_x_preferred":[
        "Mal\u00e1 \u010cierna"
    ],
    "name:srp_x_preferred":[
        "\u041c\u0430\u043b\u0430 \u0427\u0458\u0435\u0440\u043d\u0430"
    ],
    "name:und_x_variant":[
        "Mal\u00e1 \u010cierna"
    ],
    "name:war_x_preferred":[
        "Mal\u00e1 \u010cierna"
    ],
    "wof:name":"Mala Cierna",
    "wof:placetype":"locality"
},
  "geometry": {"coordinates":[18.59706,49.10277],"type":"Point"}
}