{
  "type": "Feature",
  "properties": {
    "gn:gn_country":"SK",
    "gn:gn_fcode":"PPL",
    "gn:gn_pop":0,
    "iso:country":"SK",
    "name:deu_x_preferred":[
        "Vy\u0161n\u00e9 Op\u00e1tske"
    ],
    "name:epo_x_preferred":[
        "Vy\u0161n\u00e9 Op\u00e1tske"
    ],
    "name:fra_x_preferred":[
        "Vy\u0161n\u00e9 Op\u00e1tske"
    ],
    "name:hun_x_preferred":[
        "Szilv\u00e1sap\u00e1ti"
    ],
    "name:ita_x_preferred":[
        "Vy\u0161n\u00e9 Op\u00e1tske"
    ],
    "name:nld_x_preferred":[
        "Vy\u0161n\u00e9 Op\u00e1tske"
    ],
    "name:nor_x_preferred":[
        "Vy\u0161n\u00e9 Op\u00e1tske"
    ],
    "name:srp_x_preferred":[
        "\u0412\u0438\u0448\u045a\u0435 \u041e\u043f\u0430\u0442\u0441\u043a\u0435"
    ],
    "name:unk_x_variant":[
        "Vy\u0161nie Op\u00e1tske"
    ],
    "qs_pg:aaroncc":"SK",
    "qs_pg:gn_country":"SK",
    "qs_pg:gn_fcode":"PPL",
    "qs_pg:gn_pop":0,
    "qs_pg:name":"Vy\u0161n\u00e9 Op\u00e1tske",
    "qs_pg:name_adm0":"Slovensk\u00e1",
    "qs_pg:name_adm1":"Kosicky",
    "qs_pg:photos":17,
    "qs_pg:photos_1k":3,
    "qs_pg:photos_9k":1,
    "qs_pg:photos_9r":1,
    "qs_pg:photos_all":17,
    "qs_pg:photos_sr":1,
    "qs_pg:pop_sr":0,
    "qs_pg:qs_pg_placetype":"neighbourhood",
    "qs_pg:qs_pg_placetype_gp":"Suburb",
    "qs_pg:woe_adm0":23424877,
    "woe:adm0_id":23424877,
    "woe:name_adm0":"Slovensk\u00e1",
    "woe:name_adm1":"Kosicky",
    "woe:placetype":"Suburb",
    "wof:name":"Vy\u0161n\u00e9 Op\u00e1tske",
    "wof:placetype":"neighbourhood"
},
  "geometry": {"coordinates":[21.29028,48.70326],"type":"Point"}
}