{
  "type": "Feature",
  "properties": {
    "gn:admin1_code":"05",
    "gn:asciiname":"Bunetice",
    "gn:country_code":"SK",
    "gn:dem":412,
    "gn:feature_class":"P",
    "gn:feature_code":"PPL",
    "gn:name":"Bunetice",
    "gn:population":0,
    "gn:timezone":"Europe/Bratislava",
    "iso:country":"SK",
    "wof:name":"Bunetice",
    "wof:placetype":"locality"
},
  "geometry": {"coordinates":[21.39341,48.86088],"type":"Point"}
}