{
  "type": "Feature",
  "properties": {
    "gn:admin1_code":"05",
    "gn:asciiname":"Bunetice",
    "gn:country_code":"SK",
    "gn:dem":412,
    "gn:feature_class":"P",
    "gn:feature_code":"PPL",
    "gn:name":"Bunetice",
    "gn:population":0,
    "gn:timezone":"Europe/Bratislava",
    "iso:country":"SK",
    "name:cat_x_preferred":[
        "Bunetice"
    ],
    "name:epo_x_preferred":[
        "Bunetice"
    ],
    "name:eus_x_preferred":[
        "Bunetice"
    ],
    "name:fra_x_preferred":[
        "Bunetice"
    ],
    "name:hun_x_preferred":[
        "Bunyita"
    ],
    "name:ita_x_preferred":[
        "Bunetice"
    ],
    "name:msa_x_preferred":[
        "Bunetice"
    ],
    "name:nld_x_preferred":[
        "Bunetice"
    ],
    "name:pol_x_preferred":[
        "Bunetice"
    ],
    "name:ron_x_preferred":[
        "Bunetice"
    ],
    "name:slk_x_preferred":[
        "Bunetice"
    ],
    "name:spa_x_preferred":[
        "Bunetice"
    ],
    "name:srp_x_preferred":[
        "\u0411\u0443\u045a\u0435\u0442\u0438\u0446\u0435"
    ],
    "name:ukr_x_preferred":[
        "\u0411\u0443\u043d\u0435\u0442\u0456\u0446\u0435"
    ],
    "name:war_x_preferred":[
        "Bunetice"
    ],
    "wof:name":"Bunetice",
    "wof:placetype":"locality"
},
  "geometry": {"coordinates":[21.39341,48.86088],"type":"Point"}
}