{
  "type": "Feature",
  "properties": {
    "gn:admin1_code":"04",
    "gn:asciiname":"Klobusice",
    "gn:country_code":"SK",
    "gn:dem":245,
    "gn:feature_class":"P",
    "gn:feature_code":"PPL",
    "gn:name":"Klobu\u0161ice",
    "gn:population":0,
    "gn:timezone":"Europe/Bratislava",
    "iso:country":"SK",
    "wof:name":"Klobusice",
    "wof:placetype":"locality"
},
  "geometry": {"coordinates":[18.21934,48.98553],"type":"Point"}
}