{
  "type": "Feature",
  "properties": {
    "gn:admin1_code":"05",
    "gn:asciiname":"Remeniny",
    "gn:country_code":"SK",
    "gn:dem":183,
    "gn:feature_class":"P",
    "gn:feature_code":"PPL",
    "gn:name":"Remeniny",
    "gn:population":0,
    "gn:timezone":"Europe/Bratislava",
    "iso:country":"SK",
    "wof:name":"Remeniny",
    "wof:placetype":"locality"
},
  "geometry": {"coordinates":[21.55312,49.03542],"type":"Point"}
}