{
  "type": "Feature",
  "properties": {
    "gn:admin1_code":"05",
    "gn:asciiname":"Remeniny",
    "gn:country_code":"SK",
    "gn:dem":183,
    "gn:feature_class":"P",
    "gn:feature_code":"PPL",
    "gn:name":"Remeniny",
    "gn:population":0,
    "gn:timezone":"Europe/Bratislava",
    "iso:country":"SK",
    "name:cat_x_preferred":[
        "Remeniny"
    ],
    "name:epo_x_preferred":[
        "Remeniny"
    ],
    "name:eus_x_preferred":[
        "Remeniny"
    ],
    "name:fra_x_preferred":[
        "Remeniny"
    ],
    "name:hun_x_preferred":[
        "Remenye"
    ],
    "name:ita_x_preferred":[
        "Remeniny"
    ],
    "name:msa_x_preferred":[
        "Remeniny"
    ],
    "name:nld_x_preferred":[
        "Remeniny"
    ],
    "name:pol_x_preferred":[
        "Remeniny"
    ],
    "name:ron_x_preferred":[
        "Remeniny"
    ],
    "name:rue_x_preferred":[
        "\u0420\u0435\u043c\u0435\u043d\u0438\u043d\u044b"
    ],
    "name:slk_x_preferred":[
        "Remeniny"
    ],
    "name:spa_x_preferred":[
        "Remeniny"
    ],
    "name:srp_x_preferred":[
        "\u0420\u0435\u043c\u0435\u045a\u0438\u043d\u0438"
    ],
    "name:ukr_x_preferred":[
        "\u0420\u0435\u043c\u0435\u043d\u0438\u043d\u0438"
    ],
    "name:war_x_preferred":[
        "Remeniny"
    ],
    "wof:name":"Remeniny",
    "wof:placetype":"locality"
},
  "geometry": {"coordinates":[21.55312,49.03542],"type":"Point"}
}