{
  "type": "Feature",
  "properties": {
    "gn:admin1_code":"05",
    "gn:asciiname":"Ruska Volova",
    "gn:country_code":"SK",
    "gn:dem":252,
    "gn:feature_class":"P",
    "gn:feature_code":"PPL",
    "gn:name":"Rusk\u00e1 Volov\u00e1",
    "gn:population":0,
    "gn:timezone":"Europe/Bratislava",
    "iso:country":"SK",
    "name:cat_x_preferred":[
        "Rusk\u00e1 Volov\u00e1"
    ],
    "name:ces_x_preferred":[
        "Rusk\u00e1 Volov\u00e1"
    ],
    "name:epo_x_preferred":[
        "Rusk\u00e1 Volov\u00e1"
    ],
    "name:eus_x_preferred":[
        "Rusk\u00e1 Volov\u00e1"
    ],
    "name:fra_x_preferred":[
        "Rusk\u00e1 Volov\u00e1"
    ],
    "name:hun_x_preferred":[
        "Bark\u00f3ch\u00e1za"
    ],
    "name:ita_x_preferred":[
        "Rusk\u00e1 Volov\u00e1"
    ],
    "name:msa_x_preferred":[
        "Rusk\u00e1 Volov\u00e1"
    ],
    "name:nld_x_preferred":[
        "Rusk\u00e1 Volov\u00e1"
    ],
    "name:pol_x_preferred":[
        "Rusk\u00e1 Volov\u00e1"
    ],
    "name:ron_x_preferred":[
        "Rusk\u00e1 Volov\u00e1"
    ],
    "name:rue_x_preferred":[
        "\u0420\u0443\u0441\u044c\u043a\u0430 \u0412\u043e\u043b\u043e\u0432\u0430"
    ],
    "name:slk_x_preferred":[
        "Rusk\u00e1 Volov\u00e1"
    ],
    "name:spa_x_preferred":[
        "Rusk\u00e1 Volov\u00e1"
    ],
    "name:srp_x_preferred":[
        "\u0420\u0443\u0441\u043a\u0430 \u0412\u043e\u043b\u043e\u0432\u0430"
    ],
    "name:ukr_x_preferred":[
        "\u0420\u0443\u0441\u044c\u043a\u0430 \u0412\u043e\u043b\u043e\u0432\u0430"
    ],
    "name:war_x_preferred":[
        "Rusk\u00e1 Volov\u00e1"
    ],
    "wof:name":"Ruska Volova",
    "wof:placetype":"locality"
},
  "geometry": {"coordinates":[22.36628,48.94471],"type":"Point"}
}