{
  "type": "Feature",
  "properties": {
    "gn:admin1_code":"01",
    "gn:asciiname":"Rimavska Bana",
    "gn:country_code":"SK",
    "gn:dem":259,
    "gn:feature_class":"P",
    "gn:feature_code":"PPL",
    "gn:name":"Rimavsk\u00e1 Ba\u0148a",
    "gn:population":0,
    "gn:timezone":"Europe/Bratislava",
    "iso:country":"SK",
    "name:cat_x_preferred":[
        "Rimavsk\u00e1 Ba\u0148a"
    ],
    "name:deu_x_preferred":[
        "Rimavsk\u00e1 Ba\u0148a"
    ],
    "name:epo_x_preferred":[
        "Rimavsk\u00e1 Ba\u0148a"
    ],
    "name:eus_x_preferred":[
        "Rimavsk\u00e1 Ba\u0148a"
    ],
    "name:fra_x_preferred":[
        "Rimavsk\u00e1 Ba\u0148a"
    ],
    "name:hun_x_preferred":[
        "Rimab\u00e1nya"
    ],
    "name:ita_x_preferred":[
        "Rimavsk\u00e1 Ba\u0148a"
    ],
    "name:msa_x_preferred":[
        "Rimavsk\u00e1 Ba\u0148a"
    ],
    "name:nld_x_preferred":[
        "Rimavsk\u00e1 Ba\u0148a"
    ],
    "name:pol_x_preferred":[
        "Rimavsk\u00e1 Ba\u0148a"
    ],
    "name:ron_x_preferred":[
        "Rimavsk\u00e1 Ba\u0148a"
    ],
    "name:rue_x_preferred":[
        "\u0420\u0438\u043c\u0430\u0432\u0441\u043a\u0430 \u0411\u0430\u043d\u044f"
    ],
    "name:slk_x_preferred":[
        "Rimavsk\u00e1 Ba\u0148a"
    ],
    "name:spa_x_preferred":[
        "Rimavsk\u00e1 Ba\u0148a"
    ],
    "name:srp_x_preferred":[
        "\u0420\u0438\u043c\u0430\u0432\u0441\u043a\u0430 \u0411\u0430\u045a\u0430"
    ],
    "name:ukr_x_preferred":[
        "\u0420\u0456\u043c\u0430\u0432\u0441\u043a\u0430 \u0411\u0430\u043d\u044f"
    ],
    "name:war_x_preferred":[
        "Rimavsk\u00e1 Ba\u0148a"
    ],
    "wof:name":"Rimavska Bana",
    "wof:placetype":"locality"
},
  "geometry": {"coordinates":[19.9413,48.5121],"type":"Point"}
}