{
  "type": "Feature",
  "properties": {
    "gn:admin1_code":"01",
    "gn:asciiname":"Rimavska Bana",
    "gn:country_code":"SK",
    "gn:dem":259,
    "gn:feature_class":"P",
    "gn:feature_code":"PPL",
    "gn:name":"Rimavsk\u00e1 Ba\u0148a",
    "gn:population":0,
    "gn:timezone":"Europe/Bratislava",
    "iso:country":"SK",
    "name:und_x_variant":[
        "Rimavsk\u00e1 Ba\u0148a"
    ],
    "wof:name":"Rimavska Bana",
    "wof:placetype":"locality"
},
  "geometry": {"coordinates":[19.9413,48.5121],"type":"Point"}
}