{
  "type": "Feature",
  "properties": {
    "gn:admin1_code":"08",
    "gn:asciiname":"Horny Turcek",
    "gn:country_code":"SK",
    "gn:dem":696,
    "gn:feature_class":"P",
    "gn:feature_code":"PPL",
    "gn:name":"Horn\u00fd Tur\u010dek",
    "gn:population":0,
    "gn:timezone":"Europe/Bratislava",
    "iso:country":"SK",
    "name:und_x_variant":[
        "Ober-Tur\u010dek",
        "Horn\u00ed Tur\u010dek",
        "Horn\u00fd Tur\u010dek"
    ],
    "wof:name":"Horny Turcek",
    "wof:placetype":"locality"
},
  "geometry": {"coordinates":[18.92592,48.7576],"type":"Point"}
}