{
  "type": "Feature",
  "properties": {
    "gn:admin1_code":"01",
    "gn:asciiname":"Trenc",
    "gn:country_code":"SK",
    "gn:dem":164,
    "gn:feature_class":"P",
    "gn:feature_code":"PPL",
    "gn:name":"Tren\u010d",
    "gn:population":0,
    "gn:timezone":"Europe/Bratislava",
    "iso:country":"SK",
    "name:cat_x_preferred":[
        "Tren\u010d"
    ],
    "name:epo_x_preferred":[
        "Tren\u010d"
    ],
    "name:eus_x_preferred":[
        "Tren\u010d"
    ],
    "name:fra_x_preferred":[
        "Tren\u010d"
    ],
    "name:hun_x_preferred":[
        "T\u0151rincs"
    ],
    "name:ita_x_preferred":[
        "Tren\u010d"
    ],
    "name:msa_x_preferred":[
        "Tren\u010d"
    ],
    "name:nld_x_preferred":[
        "Tren\u010d"
    ],
    "name:pol_x_preferred":[
        "Tren\u010d"
    ],
    "name:ron_x_preferred":[
        "Tren\u010d"
    ],
    "name:slk_x_preferred":[
        "Tren\u010d"
    ],
    "name:spa_x_preferred":[
        "Tren\u010d"
    ],
    "name:srp_x_preferred":[
        "\u0422\u0440\u0435\u043d\u0447"
    ],
    "name:ukr_x_preferred":[
        "\u0422\u0440\u0435\u043d\u0447"
    ],
    "name:und_x_variant":[
        "T\u00f6rincs",
        "Tren\u010d"
    ],
    "name:war_x_preferred":[
        "Tren\u010d"
    ],
    "wof:name":"Trenc",
    "wof:placetype":"locality"
},
  "geometry": {"coordinates":[19.57937,48.22375],"type":"Point"}
}