{
  "type": "Feature",
  "properties": {
    "gn:admin1_code":"01",
    "gn:asciiname":"Trenc",
    "gn:country_code":"SK",
    "gn:dem":164,
    "gn:feature_class":"P",
    "gn:feature_code":"PPL",
    "gn:name":"Tren\u010d",
    "gn:population":0,
    "gn:timezone":"Europe/Bratislava",
    "iso:country":"SK",
    "name:und_x_variant":[
        "T\u00f6rincs",
        "Tren\u010d"
    ],
    "wof:name":"Trenc",
    "wof:placetype":"locality"
},
  "geometry": {"coordinates":[19.57937,48.22375],"type":"Point"}
}