{
  "type": "Feature",
  "properties": {
    "gn:admin1_code":"01",
    "gn:asciiname":"Merovce",
    "gn:country_code":"SK",
    "gn:dem":168,
    "gn:feature_class":"P",
    "gn:feature_code":"PPL",
    "gn:name":"Merovce",
    "gn:population":0,
    "gn:timezone":"Europe/Bratislava",
    "iso:country":"SK",
    "name:hun_x_preferred":[
        "Mere"
    ],
    "name:slk_x_preferred":[
        "Merovce"
    ],
    "wof:name":"Merovce",
    "wof:placetype":"locality"
},
  "geometry": {"coordinates":[18.89812,48.1674],"type":"Point"}
}