{
  "type": "Feature",
  "properties": {
    "gn:admin1_code":"04",
    "gn:asciiname":"Trhyna",
    "gn:country_code":"SK",
    "gn:dem":131,
    "gn:feature_class":"P",
    "gn:feature_code":"PPL",
    "gn:name":"Trhy\u0148a",
    "gn:population":0,
    "gn:timezone":"Europe/Bratislava",
    "iso:country":"SK",
    "name:und_x_variant":[
        "Trgy\u0148a",
        "Trhy\u0148a"
    ],
    "wof:name":"Trhyna",
    "wof:placetype":"locality"
},
  "geometry": {"coordinates":[18.71608,48.0622],"type":"Point"}
}