{
  "type": "Feature",
  "properties": {
    "gn:admin1_code":"08",
    "gn:asciiname":"Vrchovany",
    "gn:country_code":"SK",
    "gn:dem":841,
    "gn:feature_class":"P",
    "gn:feature_code":"PPL",
    "gn:name":"Vrchovany",
    "gn:population":0,
    "gn:timezone":"Europe/Bratislava",
    "iso:country":"SK",
    "name:azb_x_preferred":[
        "\u0648\u0631\u062e\u0648\u0648\u0627\u0646\u06cc"
    ],
    "name:ces_x_preferred":[
        "Vrchovany"
    ],
    "name:deu_x_preferred":[
        "Vrchovany"
    ],
    "name:eus_x_preferred":[
        "Vrchovany"
    ],
    "name:fas_x_preferred":[
        "\u0648\u0631\u062e\u0648\u0648\u0627\u0646\u06cc"
    ],
    "name:fra_x_preferred":[
        "Vrchovany"
    ],
    "name:hun_x_preferred":[
        "Vrchovany"
    ],
    "name:ita_x_preferred":[
        "Vrchovany"
    ],
    "name:msa_x_preferred":[
        "Vrchovany"
    ],
    "name:nld_x_preferred":[
        "Vrchovany"
    ],
    "name:por_x_preferred":[
        "Vrchovany"
    ],
    "name:slk_x_preferred":[
        "Vrchovany"
    ],
    "name:spa_x_preferred":[
        "Vrchovany"
    ],
    "name:srp_x_preferred":[
        "\u0412\u0440\u0445\u043e\u0432\u0430\u043d\u0438"
    ],
    "name:vie_x_preferred":[
        "Vrchovany"
    ],
    "wof:name":"Vrchovany",
    "wof:placetype":"locality"
},
  "geometry": {"coordinates":[18.54621,48.94697],"type":"Point"}
}