{
  "type": "Feature",
  "properties": {
    "gn:admin1_code":"08",
    "gn:asciiname":"Vrchovany",
    "gn:country_code":"SK",
    "gn:dem":841,
    "gn:feature_class":"P",
    "gn:feature_code":"PPL",
    "gn:name":"Vrchovany",
    "gn:population":0,
    "gn:timezone":"Europe/Bratislava",
    "iso:country":"SK",
    "wof:name":"Vrchovany",
    "wof:placetype":"locality"
},
  "geometry": {"coordinates":[18.54621,48.94697],"type":"Point"}
}