{
  "type": "Feature",
  "properties": {
    "gn:admin1_code":"01",
    "gn:asciiname":"Medovarce",
    "gn:country_code":"SK",
    "gn:dem":180,
    "gn:feature_class":"P",
    "gn:feature_code":"PPL",
    "gn:name":"Medovarce",
    "gn:population":0,
    "gn:timezone":"Europe/Bratislava",
    "iso:country":"SK",
    "wof:name":"Medovarce",
    "wof:placetype":"locality"
},
  "geometry": {"coordinates":[19.00255,48.23472],"type":"Point"}
}