{
  "type": "Feature",
  "properties": {
    "gn:admin1_code":"01",
    "gn:asciiname":"Medovarce",
    "gn:country_code":"SK",
    "gn:dem":180,
    "gn:feature_class":"P",
    "gn:feature_code":"PPL",
    "gn:name":"Medovarce",
    "gn:population":0,
    "gn:timezone":"Europe/Bratislava",
    "iso:country":"SK",
    "name:cat_x_preferred":[
        "Medovarce"
    ],
    "name:epo_x_preferred":[
        "Medovarce"
    ],
    "name:eus_x_preferred":[
        "Medovarce"
    ],
    "name:fra_x_preferred":[
        "Medovarce"
    ],
    "name:hun_x_preferred":[
        "M\u00e9znevel\u0151"
    ],
    "name:ita_x_preferred":[
        "Medovarce"
    ],
    "name:msa_x_preferred":[
        "Medovarce"
    ],
    "name:nld_x_preferred":[
        "Medovarce"
    ],
    "name:pol_x_preferred":[
        "Medovarce"
    ],
    "name:ron_x_preferred":[
        "Medovarce"
    ],
    "name:slk_x_preferred":[
        "Medovarce"
    ],
    "name:spa_x_preferred":[
        "Medovarce"
    ],
    "name:srp_x_preferred":[
        "\u041c\u0435\u0434\u043e\u0432\u0430\u0440\u0446\u0435"
    ],
    "name:ukr_x_preferred":[
        "\u041c\u0435\u0434\u043e\u0432\u0430\u0440\u0446\u0435"
    ],
    "name:war_x_preferred":[
        "Medovarce"
    ],
    "wof:name":"Medovarce",
    "wof:placetype":"locality"
},
  "geometry": {"coordinates":[19.00255,48.23472],"type":"Point"}
}