{
  "type": "Feature",
  "properties": {
    "gn:admin1_code":"05",
    "gn:asciiname":"Snakov",
    "gn:country_code":"SK",
    "gn:dem":453,
    "gn:feature_class":"P",
    "gn:feature_code":"PPL",
    "gn:name":"Snakov",
    "gn:population":0,
    "gn:timezone":"Europe/Bratislava",
    "iso:country":"SK",
    "name:cat_x_preferred":[
        "Snakov"
    ],
    "name:ces_x_preferred":[
        "Snakov"
    ],
    "name:epo_x_preferred":[
        "Snakov"
    ],
    "name:eus_x_preferred":[
        "Snakov"
    ],
    "name:fra_x_preferred":[
        "Snakov"
    ],
    "name:hun_x_preferred":[
        "Sz\u00e1nk\u00f3"
    ],
    "name:ita_x_preferred":[
        "Snakov"
    ],
    "name:msa_x_preferred":[
        "Snakov"
    ],
    "name:nld_x_preferred":[
        "Snakov"
    ],
    "name:pol_x_preferred":[
        "Snakov"
    ],
    "name:ron_x_preferred":[
        "Snakov"
    ],
    "name:rue_x_preferred":[
        "\u0421\u043d\u0430\u043a\u0456\u0432"
    ],
    "name:slk_x_preferred":[
        "Snakov"
    ],
    "name:spa_x_preferred":[
        "Snakov"
    ],
    "name:srp_x_preferred":[
        "\u0421\u043d\u0430\u043a\u043e\u0432"
    ],
    "name:ukr_x_preferred":[
        "\u0421\u043d\u0430\u043a\u0456\u0432"
    ],
    "name:war_x_preferred":[
        "Snakov"
    ],
    "wof:name":"Snakov",
    "wof:placetype":"locality"
},
  "geometry": {"coordinates":[21.05373,49.32469],"type":"Point"}
}