{
  "type": "Feature",
  "properties": {
    "gn:admin1_code":"04",
    "gn:asciiname":"Lelasi",
    "gn:country_code":"SK",
    "gn:dem":417,
    "gn:feature_class":"P",
    "gn:feature_code":"PPL",
    "gn:name":"Lela\u0161i",
    "gn:population":0,
    "gn:timezone":"Europe/Bratislava",
    "iso:country":"SK",
    "wof:name":"Lelasi",
    "wof:placetype":"locality"
},
  "geometry": {"coordinates":[17.95,48.93333],"type":"Point"}
}