{
  "type": "Feature",
  "properties": {
    "gn:admin1_code":"07",
    "gn:asciiname":"Sovikovsky Dvor",
    "gn:country_code":"SK",
    "gn:dem":189,
    "gn:feature_class":"P",
    "gn:feature_code":"PPL",
    "gn:name":"Sov\u00edkovsk\u00fd Dvor",
    "gn:population":0,
    "gn:timezone":"Europe/Bratislava",
    "iso:country":"SK",
    "wof:name":"Sovikovsky Dvor",
    "wof:placetype":"locality"
},
  "geometry": {"coordinates":[17.15,48.73333],"type":"Point"}
}