{
  "type": "Feature",
  "properties": {
    "gn:admin1_code":"03",
    "gn:asciiname":"Stefanovce",
    "gn:country_code":"SK",
    "gn:dem":821,
    "gn:feature_class":"P",
    "gn:feature_code":"PPL",
    "gn:name":"\u0160tefanovce",
    "gn:population":0,
    "gn:timezone":"Europe/Bratislava",
    "iso:country":"SK",
    "wof:name":"Stefanovce",
    "wof:placetype":"locality"
},
  "geometry": {"coordinates":[20.38333,48.86667],"type":"Point"}
}