{
  "type": "Feature",
  "properties": {
    "gn:country":"SK",
    "gn:fcode":"PPL",
    "gn:population":0,
    "iso:country":"SK",
    "qs_pg:aaroncc":"SK",
    "qs_pg:gn_country":"SK",
    "qs_pg:gn_fcode":"PPL",
    "qs_pg:gn_pop":0,
    "qs_pg:name":"Vel\u0315k\u00e1 Poloma",
    "qs_pg:name_adm0":"Slovensk\u00e1",
    "qs_pg:name_adm1":"Kosicky",
    "qs_pg:photos":27,
    "qs_pg:photos_1k":5,
    "qs_pg:photos_9k":1,
    "qs_pg:photos_9r":2,
    "qs_pg:photos_all":27,
    "qs_pg:photos_sr":2,
    "qs_pg:pop_sr":0,
    "qs_pg:qs_pg_placetype":"locality",
    "qs_pg:qs_pg_placetype_gp":"Town",
    "qs_pg:woe_adm0":23424877,
    "woe:adm0_id":23424877,
    "woe:name_adm0":"Slovensk\u00e1",
    "woe:name_adm1":"Kosicky",
    "woe:placetype":"Town",
    "wof:name":"Vel\u0315k\u00e1 Poloma",
    "wof:placetype":"locality"
},
  "geometry": {"coordinates":[20.48333,48.71667],"type":"Point"}
}