{
  "type": "Feature",
  "properties": {
    "gn:admin1_code":"01",
    "gn:asciiname":"Repiste",
    "gn:country_code":"SK",
    "gn:dem":508,
    "gn:feature_class":"P",
    "gn:feature_code":"PPL",
    "gn:name":"Repi\u0161te",
    "gn:population":0,
    "gn:timezone":"Europe/Bratislava",
    "iso:country":"SK",
    "name:cat_x_preferred":[
        "Repi\u0161te"
    ],
    "name:ces_x_preferred":[
        "Repi\u0161te"
    ],
    "name:deu_x_preferred":[
        "Repi\u0161te"
    ],
    "name:epo_x_preferred":[
        "Repi\u0161te"
    ],
    "name:eus_x_preferred":[
        "Repi\u0161te"
    ],
    "name:hun_x_preferred":[
        "Repistye"
    ],
    "name:ita_x_preferred":[
        "Repi\u0161te"
    ],
    "name:msa_x_preferred":[
        "Repi\u0161te"
    ],
    "name:nld_x_preferred":[
        "Repi\u0161te"
    ],
    "name:pol_x_preferred":[
        "Repi\u0161te"
    ],
    "name:slk_x_preferred":[
        "Repi\u0161te"
    ],
    "name:spa_x_preferred":[
        "Repi\u0161te"
    ],
    "name:srp_x_preferred":[
        "\u0420\u0435\u043f\u0438\u0448\u0442\u0435"
    ],
    "name:ukr_x_preferred":[
        "\u0420\u0435\u043f\u0456\u0448\u0442\u0435"
    ],
    "name:und_x_variant":[
        "Repi\u0161te"
    ],
    "name:war_x_preferred":[
        "Repi\u0161te"
    ],
    "wof:name":"Repiste",
    "wof:placetype":"locality"
},
  "geometry": {"coordinates":[18.84653,48.51564000000001],"type":"Point"}
}