{
  "type": "Feature",
  "properties": {
    "gn:admin1_code":"01",
    "gn:asciiname":"Zahorce",
    "gn:country_code":"SK",
    "gn:dem":149,
    "gn:feature_class":"P",
    "gn:feature_code":"PPL",
    "gn:name":"Z\u00e1horce",
    "gn:population":0,
    "gn:timezone":"Europe/Bratislava",
    "iso:country":"SK",
    "name:und_x_variant":[
        "Z\u00e1horce"
    ],
    "wof:name":"Zahorce",
    "wof:placetype":"locality"
},
  "geometry": {"coordinates":[19.34012,48.11163],"type":"Point"}
}