{
  "type": "Feature",
  "properties": {
    "gn:admin1_code":"05",
    "gn:asciiname":"Kelcanky",
    "gn:country_code":"SK",
    "gn:dem":235,
    "gn:feature_class":"P",
    "gn:feature_code":"PPL",
    "gn:name":"Kel\u010danky",
    "gn:population":0,
    "gn:timezone":"Europe/Bratislava",
    "iso:country":"SK",
    "wof:name":"Kelcanky",
    "wof:placetype":"locality"
},
  "geometry": {"coordinates":[21.71659,49.03098],"type":"Point"}
}