{
  "type": "Feature",
  "properties": {
    "gn:admin1_code":"04",
    "gn:asciiname":"Mala Mana",
    "gn:country_code":"SK",
    "gn:dem":130,
    "gn:feature_class":"P",
    "gn:feature_code":"PPL",
    "gn:name":"Mal\u00e1 Ma\u0148a",
    "gn:population":0,
    "gn:timezone":"Europe/Bratislava",
    "iso:country":"SK",
    "name:und_x_variant":[
        "Kis-M\u00e1nya",
        "Mal\u00e1 Ma\u0148a"
    ],
    "wof:name":"Mala Mana",
    "wof:placetype":"locality"
},
  "geometry": {"coordinates":[18.26453,48.1452],"type":"Point"}
}