{
  "type": "Feature",
  "properties": {
    "gn:admin1_code":"04",
    "gn:asciiname":"Rakovec",
    "gn:country_code":"SK",
    "gn:dem":371,
    "gn:feature_class":"P",
    "gn:feature_code":"PPL",
    "gn:name":"Rakovec",
    "gn:population":0,
    "gn:timezone":"Europe/Bratislava",
    "iso:country":"SK",
    "wof:name":"Rakovec",
    "wof:placetype":"locality"
},
  "geometry": {"coordinates":[18.36688,48.79273],"type":"Point"}
}