{
  "type": "Feature",
  "properties": {
    "gn:admin1_code":"04",
    "gn:asciiname":"Rakovec",
    "gn:country_code":"SK",
    "gn:dem":371,
    "gn:feature_class":"P",
    "gn:feature_code":"PPL",
    "gn:name":"Rakovec",
    "gn:population":0,
    "gn:timezone":"Europe/Bratislava",
    "iso:country":"SK",
    "name:bos_x_preferred":[
        "Rakovec"
    ],
    "name:bul_x_preferred":[
        "\u0420\u0430\u043a\u043e\u0432\u0435\u0446"
    ],
    "name:ceb_x_preferred":[
        "Rakovec"
    ],
    "name:ces_x_preferred":[
        "Rakovec"
    ],
    "name:deu_x_preferred":[
        "Rakowez"
    ],
    "name:fra_x_preferred":[
        "Rakovec"
    ],
    "name:hrv_x_preferred":[
        "Rakovec"
    ],
    "name:hun_x_preferred":[
        "Rakovec"
    ],
    "name:nld_x_preferred":[
        "Rakovec"
    ],
    "name:rus_x_preferred":[
        "\u0420\u0430\u043a\u043e\u0432\u0435\u0446"
    ],
    "name:slk_x_preferred":[
        "Rakovec"
    ],
    "name:slv_x_preferred":[
        "Rakovec"
    ],
    "name:srp_x_preferred":[
        "\u0420\u0430\u043a\u043e\u0432\u0435\u0446"
    ],
    "name:swe_x_preferred":[
        "Rakovec"
    ],
    "name:ukr_x_preferred":[
        "\u0420\u0430\u043a\u043e\u0432\u0435\u0446\u044c"
    ],
    "wof:name":"Rakovec",
    "wof:placetype":"locality"
},
  "geometry": {"coordinates":[18.36688,48.79273],"type":"Point"}
}