{
  "type": "Feature",
  "properties": {
    "gn:admin1_code":"04",
    "gn:asciiname":"Durisove Stale",
    "gn:country_code":"SK",
    "gn:dem":316,
    "gn:feature_class":"P",
    "gn:feature_code":"PPL",
    "gn:name":"Duri\u0161ove \u0160t\u00e1le",
    "gn:population":0,
    "gn:timezone":"Europe/Bratislava",
    "iso:country":"SK",
    "wof:name":"Durisove Stale",
    "wof:placetype":"locality"
},
  "geometry": {"coordinates":[18.4999,48.61856],"type":"Point"}
}