{
  "type": "Feature",
  "properties": {
    "iso:country":"SK",
    "name:bos_x_preferred":[
        "Ra\u010da"
    ],
    "name:eng_x_variant":[
        "Ra\u010da"
    ],
    "name:fra_x_preferred":[
        "Ra\u010da"
    ],
    "name:hbs_x_preferred":[
        "Ra\u010da"
    ],
    "name:ita_x_preferred":[
        "Ra\u010da"
    ],
    "name:msa_x_preferred":[
        "Ra\u010da"
    ],
    "name:nld_x_preferred":[
        "Ra\u010da"
    ],
    "name:pnb_x_preferred":[
        "\u0631\u0627\u0686\u0627"
    ],
    "name:slk_x_preferred":[
        "Ra\u010da"
    ],
    "name:slv_x_preferred":[
        "Ra\u010da"
    ],
    "name:spa_x_preferred":[
        "Ra\u010da"
    ],
    "name:srp_x_preferred":[
        "\u0420\u0430\u0447\u0430"
    ],
    "name:tur_x_preferred":[
        "Ra\u010da"
    ],
    "name:und_x_colloquial":[
        "Raca",
        "Racistorf",
        "Recse"
    ],
    "name:und_x_variant":[
        "Ratzersdorf",
        "Ra\u010di\u0161torf",
        "R\u00e9cse"
    ],
    "qs:gn_adm0_cc":"SK",
    "qs:gn_local":3060972,
    "qs:local_max":14839,
    "qs:local_sum":27271,
    "qs:localhoods":23,
    "qs:name":"Ra\u010da",
    "qs:name_adm0":"Slovensk\u00e1",
    "qs:name_adm1":"Bratislavsky",
    "qs:name_adm2":"Bratislava",
    "qs:name_lau":"Bratislava III",
    "qs:name_local":"Bratislava",
    "qs:photo_max":98,
    "qs:photo_sum":262,
    "qs:placetype":"Suburb",
    "qs:quad_count":29,
    "qs:woe_adm0":23424877,
    "qs:woe_adm1":20070505,
    "qs:woe_adm2":29399347,
    "qs:woe_lau":29402283,
    "qs:woe_local":818717,
    "qs:woe_ver":"7.10.0",
    "wd:wordcount":113,
    "wof:lang":[
        "unk"
    ],
    "wof:name":"Ra\u010da",
    "wof:placetype":"neighbourhood"
},
  "geometry": {"coordinates":[17.151989,48.211524],"type":"Point"}
}