{
  "type": "Feature",
  "properties": {
    "gn:admin1_code":"00",
    "gn:asciiname":"Dolne Orechove",
    "gn:country_code":"SK",
    "gn:dem":210,
    "gn:feature_class":"P",
    "gn:feature_code":"PPL",
    "gn:name":"Doln\u00e9 Orechov\u00e9",
    "gn:population":0,
    "gn:timezone":"Europe/Bratislava",
    "iso:country":"SK",
    "wof:name":"Dolne Orechove",
    "wof:placetype":"locality"
},
  "geometry": {"coordinates":[18.03869,48.90321],"type":"Point"}
}