{
  "type": "Feature",
  "properties": {
    "gn:admin1_code":"05",
    "gn:asciiname":"Podskalka",
    "gn:country_code":"SK",
    "gn:dem":209,
    "gn:feature_class":"P",
    "gn:feature_code":"PPL",
    "gn:name":"Podskalka",
    "gn:population":0,
    "gn:timezone":"Europe/Bratislava",
    "iso:country":"SK",
    "wof:name":"Podskalka",
    "wof:placetype":"locality"
},
  "geometry": {"coordinates":[21.93034,48.90981],"type":"Point"}
}