{
  "type": "Feature",
  "properties": {
    "gn:admin1_code":"04",
    "gn:asciiname":"Vlckovia",
    "gn:country_code":"SK",
    "gn:dem":396,
    "gn:feature_class":"P",
    "gn:feature_code":"PPL",
    "gn:name":"Vl\u010dkovia",
    "gn:population":0,
    "gn:timezone":"Europe/Bratislava",
    "iso:country":"SK",
    "wof:name":"Vlckovia",
    "wof:placetype":"locality"
},
  "geometry": {"coordinates":[17.59707000000001,48.76244000000001],"type":"Point"}
}