{
  "type": "Feature",
  "properties": {
    "gn:country":"SK",
    "gn:fcode":"PPL",
    "gn:population":0,
    "iso:country":"SK",
    "name:ara_x_preferred":[
        "\u062a\u0648\u0631\u062a\u0634\u064a\u0646\u0633\u0643\u0649 \u062a\u064a\u0628\u0644\u064a\u062a\u0633\u0649"
    ],
    "name:ces_x_preferred":[
        "Tur\u010dianske Teplice"
    ],
    "name:deu_x_preferred":[
        "Tur\u010dianske Teplice"
    ],
    "name:eng_x_preferred":[
        "Tur\u010dianske Teplice"
    ],
    "name:fas_x_preferred":[
        "\u062a\u0648\u0631\u0686\u06cc\u0627\u0646\u0633\u06a9\u0647 \u062a\u067e\u0644\u06cc\u062a\u0633\u0647"
    ],
    "name:hbs_x_preferred":[
        "Tur\u010djanske Tjeplice"
    ],
    "name:hun_x_preferred":[
        "Stubnyaf\u00fcrd\u0151"
    ],
    "name:lav_x_preferred":[
        "Tur\u010danske Teplice"
    ],
    "name:pol_x_preferred":[
        "Tur\u010dianske Teplice"
    ],
    "name:ron_x_preferred":[
        "Tur\u010dianske Teplice"
    ],
    "name:rus_x_preferred":[
        "\u0422\u0443\u0440\u0447\u044c\u044f\u043d\u0441\u043a\u0435-\u0422\u0435\u043f\u043b\u0438\u0446\u0435"
    ],
    "name:slk_x_preferred":[
        "Tur\u010dianske Teplice"
    ],
    "name:srp_x_preferred":[
        "\u0422\u0443\u0440\u0447\u0458\u0430\u043d\u0441\u043a\u0435 \u0422\u0458\u0435\u043f\u043b\u0438\u0446\u0435"
    ],
    "name:und_x_variant":[
        "\u0160tubnianske Teplice"
    ],
    "name:zho_x_preferred":[
        "\u5716\u723e\u9322\u65af\u51f1\u7279\u666e\u5229\u91c7"
    ],
    "qs_pg:aaroncc":"SK",
    "qs_pg:gn_country":"SK",
    "qs_pg:gn_fcode":"PPL",
    "qs_pg:gn_pop":0,
    "qs_pg:name":"Turcianske Teplice",
    "qs_pg:name_adm0":"Slovensk\u00e1",
    "qs_pg:name_adm1":"Zilinsky",
    "qs_pg:photos":1,
    "qs_pg:photos_1k":1,
    "qs_pg:photos_9k":1,
    "qs_pg:photos_9r":1,
    "qs_pg:photos_all":1,
    "qs_pg:photos_sr":1,
    "qs_pg:pop_sr":0,
    "qs_pg:qs_pg_placetype":"localadmin",
    "qs_pg:qs_pg_placetype_gp":"LocalAdmin",
    "qs_pg:woe_adm0":23424877,
    "woe:adm0_id":23424877,
    "woe:name_adm0":"Slovensk\u00e1",
    "woe:name_adm1":"Zilinsky",
    "woe:placetype":"LocalAdmin",
    "wof:name":"Turcianske Teplice",
    "wof:placetype":"localadmin"
},
  "geometry": {"coordinates":[18.86048,48.86226],"type":"Point"}
}