{
  "type": "Feature",
  "properties": {
    "gn:admin1_code":"03",
    "gn:asciiname":"Banovce nad Ondavou",
    "gn:country_code":"SK",
    "gn:dem":115,
    "gn:feature_class":"P",
    "gn:feature_code":"PPL",
    "gn:name":"B\u00e1novce nad Ondavou",
    "gn:population":0,
    "gn:timezone":"Europe/Bratislava",
    "iso:country":"SK",
    "name:und_x_variant":[
        "B\u00e1novce nad Ondavou"
    ],
    "wof:name":"Banovce nad Ondavou",
    "wof:placetype":"locality"
},
  "geometry": {"coordinates":[21.81241,48.68316],"type":"Point"}
}