{
  "type": "Feature",
  "properties": {
    "gn:admin1_code":"03",
    "gn:asciiname":"Banovce nad Ondavou",
    "gn:country_code":"SK",
    "gn:dem":115,
    "gn:feature_class":"P",
    "gn:feature_code":"PPL",
    "gn:name":"B\u00e1novce nad Ondavou",
    "gn:population":0,
    "gn:timezone":"Europe/Bratislava",
    "iso:country":"SK",
    "name:cat_x_preferred":[
        "B\u00e1novce nad Ondavou"
    ],
    "name:ces_x_preferred":[
        "B\u00e1novce nad Ondavou"
    ],
    "name:deu_x_preferred":[
        "B\u00e1novce nad Ondavou"
    ],
    "name:epo_x_preferred":[
        "B\u00e1novce nad Ondavou"
    ],
    "name:eus_x_preferred":[
        "B\u00e1novce nad Ondavou"
    ],
    "name:fra_x_preferred":[
        "B\u00e1novce nad Ondavou"
    ],
    "name:hun_x_preferred":[
        "B\u00e1n\u00f3c"
    ],
    "name:ita_x_preferred":[
        "B\u00e1novce nad Ondavou"
    ],
    "name:msa_x_preferred":[
        "B\u00e1novce nad Ondavou"
    ],
    "name:nld_x_preferred":[
        "B\u00e1novce nad Ondavou"
    ],
    "name:pol_x_preferred":[
        "B\u00e1novce nad Ondavou"
    ],
    "name:ron_x_preferred":[
        "B\u00e1novce nad Ondavou"
    ],
    "name:slk_x_preferred":[
        "B\u00e1novce nad Ondavou"
    ],
    "name:spa_x_preferred":[
        "B\u00e1novce nad Ondavou"
    ],
    "name:srp_x_preferred":[
        "\u0411\u0430\u043d\u043e\u0432\u0446\u0435 \u043d\u0430 \u041e\u043d\u0434\u0430\u0432\u0438"
    ],
    "name:ukr_x_preferred":[
        "\u0411\u0430\u043d\u043e\u0432\u0446\u0435-\u043d\u0430\u0434-\u041e\u043d\u0434\u0430\u0432\u043e\u044e"
    ],
    "name:war_x_preferred":[
        "B\u00e1novce nad Ondavou"
    ],
    "wof:name":"Banovce nad Ondavou",
    "wof:placetype":"locality"
},
  "geometry": {"coordinates":[21.81241,48.68316],"type":"Point"}
}