{
  "type": "Feature",
  "properties": {
    "gn:admin1_code":"05",
    "gn:asciiname":"Jakusovce",
    "gn:country_code":"SK",
    "gn:dem":273,
    "gn:feature_class":"P",
    "gn:feature_code":"PPL",
    "gn:name":"Jaku\u0161ovce",
    "gn:population":0,
    "gn:timezone":"Europe/Bratislava",
    "iso:country":"SK",
    "name:und_x_variant":[
        "Jaku\u0161ovce"
    ],
    "wof:name":"Jakusovce",
    "wof:placetype":"locality"
},
  "geometry": {"coordinates":[21.74982,49.15799000000001],"type":"Point"}
}