{
  "type": "Feature",
  "properties": {
    "gn:admin1_code":"05",
    "gn:asciiname":"Jakusovce",
    "gn:country_code":"SK",
    "gn:dem":273,
    "gn:feature_class":"P",
    "gn:feature_code":"PPL",
    "gn:name":"Jaku\u0161ovce",
    "gn:population":0,
    "gn:timezone":"Europe/Bratislava",
    "iso:country":"SK",
    "name:cat_x_preferred":[
        "Jaku\u0161ovce"
    ],
    "name:ces_x_preferred":[
        "Jaku\u0161ovce"
    ],
    "name:epo_x_preferred":[
        "Jaku\u0161ovce"
    ],
    "name:eus_x_preferred":[
        "Jaku\u0161ovce"
    ],
    "name:fra_x_preferred":[
        "Jaku\u0161ovce"
    ],
    "name:hun_x_preferred":[
        "Jakabv\u00f6lgye"
    ],
    "name:ita_x_preferred":[
        "Jaku\u0161ovce"
    ],
    "name:msa_x_preferred":[
        "Jaku\u0161ovce"
    ],
    "name:nld_x_preferred":[
        "Jaku\u0161ovce"
    ],
    "name:pol_x_preferred":[
        "Jaku\u0161ovce"
    ],
    "name:ron_x_preferred":[
        "Jaku\u0161ovce"
    ],
    "name:rue_x_preferred":[
        "\u042f\u043a\u0443\u0448\u0456\u0432\u0446\u0457"
    ],
    "name:slk_x_preferred":[
        "Jaku\u0161ovce"
    ],
    "name:spa_x_preferred":[
        "Jaku\u0161ovce"
    ],
    "name:srp_x_preferred":[
        "\u0408\u0430\u043a\u0443\u0448\u043e\u0432\u0446\u0435"
    ],
    "name:ukr_x_preferred":[
        "\u042f\u043a\u0443\u0448\u0456\u0432\u0446\u0456"
    ],
    "name:war_x_preferred":[
        "Jaku\u0161ovce"
    ],
    "wof:name":"Jakusovce",
    "wof:placetype":"locality"
},
  "geometry": {"coordinates":[21.74982,49.15799000000001],"type":"Point"}
}