{
  "type": "Feature",
  "properties": {
    "gn:admin1_code":"04",
    "gn:asciiname":"Kovacova",
    "gn:country_code":"SK",
    "gn:dem":172,
    "gn:feature_class":"P",
    "gn:feature_code":"PPL",
    "gn:name":"Kov\u00e1\u010dov\u00e1",
    "gn:population":0,
    "gn:timezone":"Europe/Bratislava",
    "iso:country":"SK",
    "name:und_x_variant":[
        "Dvor Kov\u00e1\u010dou\u00e1",
        "Kov\u00e1\u010dov\u00e1"
    ],
    "wof:name":"Kovacova",
    "wof:placetype":"locality"
},
  "geometry": {"coordinates":[18.35465,48.20888],"type":"Point"}
}