{
  "type": "Feature",
  "properties": {
    "gn:admin1_code":"04",
    "gn:asciiname":"Hadovce",
    "gn:country_code":"SK",
    "gn:dem":107,
    "gn:feature_class":"P",
    "gn:feature_code":"PPL",
    "gn:name":"Hadovce",
    "gn:population":0,
    "gn:timezone":"Europe/Bratislava",
    "iso:country":"SK",
    "name:hun_x_preferred":[
        "Gad\u00f3c"
    ],
    "name:und_x_variant":[
        "Gad\u00f3cpuszta",
        "Hadovce"
    ],
    "wof:name":"Hadovce",
    "wof:placetype":"locality"
},
  "geometry": {"coordinates":[18.0794,47.78486],"type":"Point"}
}