{
  "type": "Feature",
  "properties": {
    "gn:country":"SK",
    "gn:fcode":"PPL",
    "gn:population":0,
    "iso:country":"SK",
    "name:ces_x_preferred":[
        "Nov\u00fd Smokovec"
    ],
    "name:che_x_preferred":[
        "\u041d\u043e\u0432\u0438\u0439 \u0421\u043c\u043e\u043a\u043e\u0432\u0435\u0446\u044c"
    ],
    "name:deu_x_preferred":[
        "Nov\u00fd Smokovec"
    ],
    "name:eng_x_preferred":[
        "Nov\u00fd Smokovec"
    ],
    "name:epo_x_preferred":[
        "Nov\u00fd Smokovec"
    ],
    "name:fra_x_preferred":[
        "Nov\u00fd Smokovec"
    ],
    "name:hun_x_preferred":[
        "\u00dajt\u00e1traf\u00fcred"
    ],
    "name:jpn_x_preferred":[
        "\u30ce\u30f4\u30a3\u30fc\u30fb\u30b9\u30e2\u30b3\u30f4\u30a7\u30c4"
    ],
    "name:nan_x_preferred":[
        "Nov\u00fd Smokovec"
    ],
    "name:pol_x_preferred":[
        "Nowy Smokowiec"
    ],
    "name:slk_x_preferred":[
        "Nov\u00fd Smokovec"
    ],
    "name:tat_x_preferred":[
        "\u041d\u043e\u0432\u0438\u0439 \u0421\u043c\u043e\u043a\u043e\u0432\u0435\u0446\u044c"
    ],
    "name:ukr_x_preferred":[
        "\u041d\u043e\u0432\u0438\u0439 \u0421\u043c\u043e\u043a\u043e\u0432\u0435\u0446\u044c"
    ],
    "name:und_x_variant":[
        "Nov\u00fd Szmeks"
    ],
    "qs_pg:aaroncc":"SK",
    "qs_pg:gn_country":"SK",
    "qs_pg:gn_fcode":"PPL",
    "qs_pg:gn_pop":0,
    "qs_pg:name":"Nov\u00fd Smokovec",
    "qs_pg:name_adm0":"Slovensk\u00e1",
    "qs_pg:name_adm1":"Presovsky",
    "qs_pg:photos":41,
    "qs_pg:photos_1k":8,
    "qs_pg:photos_9k":1,
    "qs_pg:photos_9r":2,
    "qs_pg:photos_all":41,
    "qs_pg:photos_sr":2,
    "qs_pg:pop_sr":0,
    "qs_pg:qs_pg_placetype":"locality",
    "qs_pg:qs_pg_placetype_gp":"Town",
    "qs_pg:woe_adm0":23424877,
    "woe:adm0_id":23424877,
    "woe:name_adm0":"Slovensk\u00e1",
    "woe:name_adm1":"Presovsky",
    "woe:placetype":"Town",
    "wof:name":"Nov\u00fd Smokovec",
    "wof:placetype":"locality"
},
  "geometry": {"coordinates":[20.20861,49.13432],"type":"Point"}
}