{
  "type": "Feature",
  "properties": {
    "gn:admin1_code":"04",
    "gn:asciiname":"Fackov",
    "gn:country_code":"SK",
    "gn:dem":541,
    "gn:feature_class":"P",
    "gn:feature_code":"PPL",
    "gn:name":"Fa\u010dkov",
    "gn:population":0,
    "gn:timezone":"Europe/Bratislava",
    "iso:country":"SK",
    "name:cat_x_preferred":[
        "Fa\u010dkov"
    ],
    "name:ces_x_preferred":[
        "Fa\u010dkov"
    ],
    "name:deu_x_preferred":[
        "Fa\u010dkov"
    ],
    "name:epo_x_preferred":[
        "Fa\u010dkov"
    ],
    "name:eus_x_preferred":[
        "Fa\u010dkov"
    ],
    "name:fra_x_preferred":[
        "Fa\u010dkov"
    ],
    "name:hun_x_preferred":[
        "Facsk\u00f3"
    ],
    "name:ita_x_preferred":[
        "Fa\u010dkov"
    ],
    "name:msa_x_preferred":[
        "Fa\u010dkov"
    ],
    "name:nld_x_preferred":[
        "Fa\u010dkov"
    ],
    "name:pol_x_preferred":[
        "Fa\u010dkov"
    ],
    "name:ron_x_preferred":[
        "Fa\u010dkov"
    ],
    "name:slk_x_preferred":[
        "Fa\u010dkov"
    ],
    "name:spa_x_preferred":[
        "Fa\u010dkov"
    ],
    "name:srp_x_preferred":[
        "\u0424\u0430\u0447\u043a\u043e\u0432"
    ],
    "name:war_x_preferred":[
        "Fa\u010dkov"
    ],
    "wof:name":"Fackov",
    "wof:placetype":"locality"
},
  "geometry": {"coordinates":[18.60257,49.01061],"type":"Point"}
}