{
  "type": "Feature",
  "properties": {
    "gn:admin1_code":"04",
    "gn:asciiname":"Fackov",
    "gn:country_code":"SK",
    "gn:dem":541,
    "gn:feature_class":"P",
    "gn:feature_code":"PPL",
    "gn:name":"Fa\u010dkov",
    "gn:population":0,
    "gn:timezone":"Europe/Bratislava",
    "iso:country":"SK",
    "name:und_x_variant":[
        "Fa\u010dkov"
    ],
    "wof:name":"Fackov",
    "wof:placetype":"locality"
},
  "geometry": {"coordinates":[18.60257,49.01061],"type":"Point"}
}