{
  "type": "Feature",
  "properties": {
    "gn:admin1_code":"01",
    "gn:asciiname":"Babinec",
    "gn:country_code":"SK",
    "gn:dem":423,
    "gn:feature_class":"P",
    "gn:feature_code":"PPL",
    "gn:name":"Bab\u00ednec",
    "gn:population":0,
    "gn:timezone":"Europe/Bratislava",
    "iso:country":"SK",
    "name:cat_x_preferred":[
        "Babinec"
    ],
    "name:ces_x_preferred":[
        "Babinec"
    ],
    "name:epo_x_preferred":[
        "Babinec"
    ],
    "name:eus_x_preferred":[
        "Babinec"
    ],
    "name:fra_x_preferred":[
        "Babinec"
    ],
    "name:hun_x_preferred":[
        "Babar\u00e9t"
    ],
    "name:ita_x_preferred":[
        "Babinec"
    ],
    "name:msa_x_preferred":[
        "Babinec"
    ],
    "name:nld_x_preferred":[
        "Babinec"
    ],
    "name:pol_x_preferred":[
        "Babinec"
    ],
    "name:ron_x_preferred":[
        "Babinec"
    ],
    "name:slk_x_preferred":[
        "Babinec"
    ],
    "name:spa_x_preferred":[
        "Babinec"
    ],
    "name:srp_x_preferred":[
        "\u0411\u0430\u0431\u0438\u045a\u0435\u0446"
    ],
    "name:ukr_x_preferred":[
        "\u0411\u0430\u0431\u0456\u043d\u0435\u0446"
    ],
    "name:und_x_variant":[
        "Bab\u00ednec"
    ],
    "name:war_x_preferred":[
        "Babinec"
    ],
    "wof:name":"Babinec",
    "wof:placetype":"locality"
},
  "geometry": {"coordinates":[20.00485,48.51222],"type":"Point"}
}