{
  "type": "Feature",
  "properties": {
    "gn:admin1_code":"01",
    "gn:asciiname":"Babinec",
    "gn:country_code":"SK",
    "gn:dem":423,
    "gn:feature_class":"P",
    "gn:feature_code":"PPL",
    "gn:name":"Bab\u00ednec",
    "gn:population":0,
    "gn:timezone":"Europe/Bratislava",
    "iso:country":"SK",
    "name:und_x_variant":[
        "Bab\u00ednec"
    ],
    "wof:name":"Babinec",
    "wof:placetype":"locality"
},
  "geometry": {"coordinates":[20.00485,48.51222],"type":"Point"}
}