{
  "type": "Feature",
  "properties": {
    "gn:admin1_code":"04",
    "gn:asciiname":"Kamenicka",
    "gn:country_code":"SK",
    "gn:dem":180,
    "gn:feature_class":"P",
    "gn:feature_code":"PPL",
    "gn:name":"Kamenick\u00e1",
    "gn:population":0,
    "gn:timezone":"Europe/Bratislava",
    "iso:country":"SK",
    "name:und_x_variant":[
        "Kamenick\u00e1 Pusta",
        "Kamenick\u00e1"
    ],
    "wof:name":"Kamenicka",
    "wof:placetype":"locality"
},
  "geometry": {"coordinates":[18.7107,47.85534000000001],"type":"Point"}
}