{
  "type": "Feature",
  "properties": {
    "gn:gn_country":"SK",
    "gn:gn_fcode":"PPL",
    "gn:gn_pop":0,
    "gn:population":930,
    "iso:country":"SK",
    "name:cat_x_preferred":[
        "Kru\u0161etnica"
    ],
    "name:ceb_x_preferred":[
        "Kru\u0161etnica"
    ],
    "name:ces_x_preferred":[
        "Kru\u0161etnica"
    ],
    "name:deu_x_preferred":[
        "Kru\u0161etnica"
    ],
    "name:eng_x_preferred":[
        "Kru\u0161etnica"
    ],
    "name:epo_x_preferred":[
        "Kru\u0161etnica"
    ],
    "name:eus_x_preferred":[
        "Kru\u0161etnica"
    ],
    "name:fra_x_preferred":[
        "Kru\u0161etnica"
    ],
    "name:hun_x_preferred":[
        "Krusetnica"
    ],
    "name:ita_x_preferred":[
        "Kru\u0161etnica"
    ],
    "name:msa_x_preferred":[
        "Kru\u0161etnica"
    ],
    "name:nan_x_preferred":[
        "Kru\u0161etnica"
    ],
    "name:nld_x_preferred":[
        "Kru\u0161etnica"
    ],
    "name:pol_x_preferred":[
        "Kruszetnica"
    ],
    "name:ron_x_preferred":[
        "Kru\u0161etnica"
    ],
    "name:rus_x_preferred":[
        "\u041a\u0440\u0443\u0448\u0435\u0442\u043d\u0438\u0446\u0430"
    ],
    "name:slk_x_preferred":[
        "Kru\u0161etnica"
    ],
    "name:spa_x_preferred":[
        "Kru\u0161etnica"
    ],
    "name:srp_x_preferred":[
        "\u041a\u0440\u0443\u0448\u0435\u0442\u045a\u0438\u0446\u0430"
    ],
    "name:war_x_preferred":[
        "Kru\u0161etnica"
    ],
    "qs_pg:aaroncc":"SK",
    "qs_pg:gn_country":"SK",
    "qs_pg:gn_fcode":"PPL",
    "qs_pg:gn_pop":0,
    "qs_pg:name":"Kru\u0161etnica",
    "qs_pg:name_adm0":"Slovensk\u00e1",
    "qs_pg:name_adm1":"Zilinsky",
    "qs_pg:photos_9r":0,
    "qs_pg:photos_sr":0,
    "qs_pg:pop_sr":0,
    "qs_pg:qs_pg_placetype":"locality",
    "qs_pg:qs_pg_placetype_gp":"Town",
    "qs_pg:woe_adm0":23424877,
    "woe:adm0_id":23424877,
    "woe:name_adm0":"Slovensk\u00e1",
    "woe:name_adm1":"Zilinsky",
    "woe:placetype":"Town",
    "wof:name":"Kru\u0161etnica",
    "wof:placetype":"locality",
    "wof:population":930
},
  "geometry": {"coordinates":[19.33876,49.37523],"type":"Point"}
}