{
  "type": "Feature",
  "properties": {
    "gn:admin1_code":"01",
    "gn:asciiname":"Svata Turen",
    "gn:country_code":"SK",
    "gn:dem":294,
    "gn:feature_class":"P",
    "gn:feature_code":"PPL",
    "gn:name":"Sv\u00e4t\u00e1 T\u00fare\u0148",
    "gn:population":0,
    "gn:timezone":"Europe/Bratislava",
    "iso:country":"SK",
    "name:und_x_variant":[
        "Dvor Sv\u00e4t\u00e1 T\u00fare\u0148",
        "Sv\u00e4t\u00e1 T\u00fare\u0148"
    ],
    "wof:name":"Svata Turen",
    "wof:placetype":"locality"
},
  "geometry": {"coordinates":[19.91667,48.43333],"type":"Point"}
}