{
  "type": "Feature",
  "properties": {
    "gn:admin1_code":"01",
    "gn:asciiname":"Neporadza",
    "gn:country_code":"SK",
    "gn:dem":213,
    "gn:feature_class":"P",
    "gn:feature_code":"PPL",
    "gn:name":"Neporadza",
    "gn:population":0,
    "gn:timezone":"Europe/Bratislava",
    "iso:country":"SK",
    "name:cat_x_preferred":[
        "Neporadza"
    ],
    "name:ces_x_preferred":[
        "Neporadza"
    ],
    "name:epo_x_preferred":[
        "Neporadza"
    ],
    "name:eus_x_preferred":[
        "Neporadza"
    ],
    "name:hun_x_preferred":[
        "Napr\u00e1gy"
    ],
    "name:ita_x_preferred":[
        "Neporadza"
    ],
    "name:msa_x_preferred":[
        "Neporadza"
    ],
    "name:nld_x_preferred":[
        "Neporadza"
    ],
    "name:pol_x_preferred":[
        "Neporadza"
    ],
    "name:ron_x_preferred":[
        "Neporadza"
    ],
    "name:slk_x_preferred":[
        "Neporadza"
    ],
    "name:spa_x_preferred":[
        "Neporadza"
    ],
    "name:srp_x_preferred":[
        "\u040a\u0435\u043f\u043e\u0440\u0430\u0434\u0437\u0430"
    ],
    "name:ukr_x_preferred":[
        "\u041d\u0435\u043f\u043e\u0440\u0430\u0434\u0437\u0430"
    ],
    "name:und_x_variant":[
        "Napra\u010f",
        "Neporadza"
    ],
    "name:war_x_preferred":[
        "Neporadza"
    ],
    "wof:name":"Neporadza",
    "wof:placetype":"locality"
},
  "geometry": {"coordinates":[20.39139,48.36217],"type":"Point"}
}