{
  "type": "Feature",
  "properties": {
    "gn:admin1_code":"01",
    "gn:asciiname":"Neporadza",
    "gn:country_code":"SK",
    "gn:dem":213,
    "gn:feature_class":"P",
    "gn:feature_code":"PPL",
    "gn:name":"Neporadza",
    "gn:population":0,
    "gn:timezone":"Europe/Bratislava",
    "iso:country":"SK",
    "name:und_x_variant":[
        "Napra\u010f",
        "Neporadza"
    ],
    "wof:name":"Neporadza",
    "wof:placetype":"locality"
},
  "geometry": {"coordinates":[20.39139,48.36217],"type":"Point"}
}