{
  "type": "Feature",
  "properties": {
    "gn:admin1_code":"05",
    "gn:asciiname":"Kral'ova Studna",
    "gn:country_code":"SK",
    "gn:dem":717,
    "gn:feature_class":"P",
    "gn:feature_code":"PPL",
    "gn:name":"Kr\u00e1\u013eova Stud\u0148a",
    "gn:population":0,
    "gn:timezone":"Europe/Bratislava",
    "iso:country":"SK",
    "wof:name":"Kral'ova Studna",
    "wof:placetype":"locality"
},
  "geometry": {"coordinates":[21.01667,49.33333],"type":"Point"}
}