{
  "type": "Feature",
  "properties": {
    "gn:admin1_code":"07",
    "gn:asciiname":"Fajnoraci",
    "gn:country_code":"SK",
    "gn:dem":248,
    "gn:feature_class":"P",
    "gn:feature_code":"PPL",
    "gn:name":"Fajnor\u00e1ci",
    "gn:population":0,
    "gn:timezone":"Europe/Bratislava",
    "iso:country":"SK",
    "wof:name":"Fajnoraci",
    "wof:placetype":"locality"
},
  "geometry": {"coordinates":[17.6372,48.64516],"type":"Point"}
}