{
  "type": "Feature",
  "properties": {
    "gn:admin1_code":"07",
    "gn:asciiname":"Sarkanovska samota",
    "gn:country_code":"SK",
    "gn:dem":112,
    "gn:feature_class":"P",
    "gn:feature_code":"PPL",
    "gn:name":"\u0160arkanovsk\u00e1 samota",
    "gn:population":0,
    "gn:timezone":"Europe/Bratislava",
    "iso:country":"SK",
    "name:hun_x_preferred":[
        "S\u00e1rk\u00e1nypuszta"
    ],
    "name:und_x_variant":[
        "\u0160arkanovsk\u00e1 Pusta"
    ],
    "wof:name":"Sarkanovska samota",
    "wof:placetype":"locality"
},
  "geometry": {"coordinates":[17.70842,47.87675],"type":"Point"}
}