{
  "type": "Feature",
  "properties": {
    "gn:admin1_code":"01",
    "gn:asciiname":"Stiavnicke Bane",
    "gn:country_code":"SK",
    "gn:dem":769,
    "gn:feature_class":"P",
    "gn:feature_code":"PPL",
    "gn:name":"\u0160tiavnick\u00e9 Bane",
    "gn:population":0,
    "gn:timezone":"Europe/Bratislava",
    "iso:country":"SK",
    "name:und_x_variant":[
        "Piarg",
        "\u0160tiavnick\u00e9 Bane"
    ],
    "wof:name":"Stiavnicke Bane",
    "wof:placetype":"locality"
},
  "geometry": {"coordinates":[18.85553,48.43935],"type":"Point"}
}