{
  "type": "Feature",
  "properties": {
    "gn:admin1_code":"05",
    "gn:asciiname":"Koskovce",
    "gn:country_code":"SK",
    "gn:dem":187,
    "gn:feature_class":"P",
    "gn:feature_code":"PPL",
    "gn:name":"Ko\u0161kovce",
    "gn:population":0,
    "gn:timezone":"Europe/Bratislava",
    "iso:country":"SK",
    "name:und_x_variant":[
        "Ko\u0161kovce"
    ],
    "wof:name":"Koskovce",
    "wof:placetype":"locality"
},
  "geometry": {"coordinates":[21.95472,49.04726],"type":"Point"}
}