{
  "type": "Feature",
  "properties": {
    "gn:admin1_code":"05",
    "gn:asciiname":"Koskovce",
    "gn:country_code":"SK",
    "gn:dem":187,
    "gn:feature_class":"P",
    "gn:feature_code":"PPL",
    "gn:name":"Ko\u0161kovce",
    "gn:population":0,
    "gn:timezone":"Europe/Bratislava",
    "iso:country":"SK",
    "name:cat_x_preferred":[
        "Ko\u0161kovce"
    ],
    "name:ces_x_preferred":[
        "Ko\u0161kovce"
    ],
    "name:epo_x_preferred":[
        "Ko\u0161kovce"
    ],
    "name:eus_x_preferred":[
        "Ko\u0161kovce"
    ],
    "name:fra_x_preferred":[
        "Ko\u0161kovce"
    ],
    "name:hun_x_preferred":[
        "Kosk\u00f3c"
    ],
    "name:ita_x_preferred":[
        "Ko\u0161kovce"
    ],
    "name:msa_x_preferred":[
        "Ko\u0161kovce"
    ],
    "name:nld_x_preferred":[
        "Ko\u0161kovce"
    ],
    "name:pol_x_preferred":[
        "Ko\u0161kovce"
    ],
    "name:ron_x_preferred":[
        "Ko\u0161kovce"
    ],
    "name:slk_x_preferred":[
        "Ko\u0161kovce"
    ],
    "name:spa_x_preferred":[
        "Ko\u0161kovce"
    ],
    "name:srp_x_preferred":[
        "\u041a\u043e\u0448\u043a\u043e\u0432\u0446\u0435"
    ],
    "name:ukr_x_preferred":[
        "\u041a\u043e\u0448\u043a\u043e\u0432\u0446\u0435"
    ],
    "name:war_x_preferred":[
        "Ko\u0161kovce"
    ],
    "wof:name":"Koskovce",
    "wof:placetype":"locality"
},
  "geometry": {"coordinates":[21.95472,49.04726],"type":"Point"}
}