{
  "type": "Feature",
  "properties": {
    "gn:admin1_code":"04",
    "gn:asciiname":"Zigov Olvar",
    "gn:country_code":"SK",
    "gn:dem":293,
    "gn:feature_class":"P",
    "gn:feature_code":"PPL",
    "gn:name":"\u017digov Olv\u00e1r",
    "gn:population":0,
    "gn:timezone":"Europe/Bratislava",
    "iso:country":"SK",
    "wof:name":"Zigov Olvar",
    "wof:placetype":"locality"
},
  "geometry": {"coordinates":[19.00214,48.13268],"type":"Point"}
}