{
  "type": "Feature",
  "properties": {
    "gn:admin1_code":"01",
    "gn:asciiname":"Rapovce",
    "gn:country_code":"SK",
    "gn:dem":171,
    "gn:feature_class":"P",
    "gn:feature_code":"PPL",
    "gn:name":"Rapovce",
    "gn:population":0,
    "gn:timezone":"Europe/Bratislava",
    "iso:country":"SK",
    "name:cat_x_preferred":[
        "Rapovce"
    ],
    "name:deu_x_preferred":[
        "Rapovce"
    ],
    "name:epo_x_preferred":[
        "Rapovce"
    ],
    "name:eus_x_preferred":[
        "Rapovce"
    ],
    "name:fra_x_preferred":[
        "Rapovce"
    ],
    "name:hun_x_preferred":[
        "Rapp"
    ],
    "name:ita_x_preferred":[
        "Rapovce"
    ],
    "name:msa_x_preferred":[
        "Rapovce"
    ],
    "name:nld_x_preferred":[
        "Rapovce"
    ],
    "name:pol_x_preferred":[
        "Rapovce"
    ],
    "name:ron_x_preferred":[
        "Rapovce"
    ],
    "name:slk_x_preferred":[
        "Rapovce"
    ],
    "name:spa_x_preferred":[
        "Rapovce"
    ],
    "name:srp_x_preferred":[
        "\u0420\u0430\u043f\u043e\u0432\u0446\u0435"
    ],
    "name:ukr_x_preferred":[
        "\u0420\u0430\u043f\u043e\u0432\u0446\u0435"
    ],
    "name:und_x_variant":[
        "Rapp",
        "Rapovce"
    ],
    "name:war_x_preferred":[
        "Rapovce"
    ],
    "wof:name":"Rapovce",
    "wof:placetype":"locality"
},
  "geometry": {"coordinates":[19.68154,48.27388],"type":"Point"}
}