{
  "type": "Feature",
  "properties": {
    "gn:admin1_code":"01",
    "gn:asciiname":"Rapovce",
    "gn:country_code":"SK",
    "gn:dem":171,
    "gn:feature_class":"P",
    "gn:feature_code":"PPL",
    "gn:name":"Rapovce",
    "gn:population":0,
    "gn:timezone":"Europe/Bratislava",
    "iso:country":"SK",
    "name:und_x_variant":[
        "Rapp",
        "Rapovce"
    ],
    "wof:name":"Rapovce",
    "wof:placetype":"locality"
},
  "geometry": {"coordinates":[19.68154,48.27388],"type":"Point"}
}