{
  "type": "Feature",
  "properties": {
    "gn:admin1_code":"04",
    "gn:asciiname":"Dvor Nandin",
    "gn:country_code":"SK",
    "gn:dem":190,
    "gn:feature_class":"P",
    "gn:feature_code":"PPL",
    "gn:name":"Dvor Nandin",
    "gn:population":0,
    "gn:timezone":"Europe/Bratislava",
    "iso:country":"SK",
    "wof:name":"Dvor Nandin",
    "wof:placetype":"locality"
},
  "geometry": {"coordinates":[17.93332999999999,48.31667],"type":"Point"}
}