{
  "type": "Feature",
  "properties": {
    "gn:admin1_code":"01",
    "gn:asciiname":"Dacov Lom",
    "gn:country_code":"SK",
    "gn:dem":484,
    "gn:feature_class":"P",
    "gn:feature_code":"PPL",
    "gn:name":"Da\u010dov Lom",
    "gn:population":0,
    "gn:timezone":"Europe/Bratislava",
    "iso:country":"SK",
    "name:und_x_variant":[
        "Da\u010dov Lom"
    ],
    "wof:name":"Dacov Lom",
    "wof:placetype":"locality"
},
  "geometry": {"coordinates":[19.2499,48.3225],"type":"Point"}
}