{
  "type": "Feature",
  "properties": {
    "iso:country":"SK",
    "qs_pg:aaroncc":"SK",
    "qs_pg:name":"Krahule",
    "qs_pg:name_adm0":"Slovensk\u00e1",
    "qs_pg:name_adm1":"Banskobystricky",
    "qs_pg:photos":28,
    "qs_pg:photos_1k":6,
    "qs_pg:photos_9k":1,
    "qs_pg:photos_9r":3,
    "qs_pg:photos_all":91,
    "qs_pg:photos_sr":2,
    "qs_pg:pop_sr":0,
    "qs_pg:qs_pg_placetype":"localadmin",
    "qs_pg:qs_pg_placetype_gp":"LocalAdmin",
    "qs_pg:woe_adm0":23424877,
    "woe:adm0_id":23424877,
    "woe:name_adm0":"Slovensk\u00e1",
    "woe:name_adm1":"Banskobystricky",
    "woe:placetype":"LocalAdmin",
    "wof:name":"Krahule",
    "wof:placetype":"localadmin"
},
  "geometry": {"coordinates":[18.942972,48.72563],"type":"Point"}
}