{
  "type": "Feature",
  "properties": {
    "gn:admin1_code":"08",
    "gn:asciiname":"Strazov",
    "gn:country_code":"SK",
    "gn:dem":326,
    "gn:feature_class":"P",
    "gn:feature_code":"PPL",
    "gn:name":"Str\u00e1\u017eov",
    "gn:population":0,
    "gn:timezone":"Europe/Bratislava",
    "iso:country":"SK",
    "wof:name":"Strazov",
    "wof:placetype":"locality"
},
  "geometry": {"coordinates":[18.70429,49.23537],"type":"Point"}
}