{
  "type": "Feature",
  "properties": {
    "gn:admin1_code":"04",
    "gn:asciiname":"Kopanica Dolina",
    "gn:country_code":"SK",
    "gn:dem":339,
    "gn:feature_class":"P",
    "gn:feature_code":"PPL",
    "gn:name":"Kopanica Dolina",
    "gn:population":0,
    "gn:timezone":"Europe/Bratislava",
    "iso:country":"SK",
    "wof:name":"Kopanica Dolina",
    "wof:placetype":"locality"
},
  "geometry": {"coordinates":[18.00553,48.633],"type":"Point"}
}