{
  "type": "Feature",
  "properties": {
    "iso:country":"SK",
    "name:cat_x_preferred":[
        "Rovinka"
    ],
    "name:ces_x_preferred":[
        "Rovinka"
    ],
    "name:deu_x_preferred":[
        "Rovinka"
    ],
    "name:epo_x_preferred":[
        "Rovinka"
    ],
    "name:eus_x_preferred":[
        "Rovinka"
    ],
    "name:fra_x_preferred":[
        "Rovinka"
    ],
    "name:hun_x_preferred":[
        "Cs\u00f6lle"
    ],
    "name:ita_x_preferred":[
        "Rovinka"
    ],
    "name:msa_x_preferred":[
        "Rovinka"
    ],
    "name:nld_x_preferred":[
        "Rovinka"
    ],
    "name:por_x_preferred":[
        "Rovinka"
    ],
    "name:ron_x_preferred":[
        "Rovinka"
    ],
    "name:slk_x_preferred":[
        "Rovinka"
    ],
    "name:spa_x_preferred":[
        "Rovinka"
    ],
    "name:srp_x_preferred":[
        "\u0420\u043e\u0432\u0438\u043d\u043a\u0430"
    ],
    "name:war_x_preferred":[
        "Rovinka"
    ],
    "qs_pg:aaroncc":"SK",
    "qs_pg:name":"Rovinka",
    "qs_pg:name_adm0":"Slovensk\u00e1",
    "qs_pg:name_adm1":"Bratislavsky",
    "qs_pg:photos":19,
    "qs_pg:photos_1k":4,
    "qs_pg:photos_9k":1,
    "qs_pg:photos_9r":2,
    "qs_pg:photos_all":34,
    "qs_pg:photos_sr":1,
    "qs_pg:pop_sr":0,
    "qs_pg:qs_pg_placetype":"localadmin",
    "qs_pg:qs_pg_placetype_gp":"LocalAdmin",
    "qs_pg:woe_adm0":23424877,
    "woe:adm0_id":23424877,
    "woe:name_adm0":"Slovensk\u00e1",
    "woe:name_adm1":"Bratislavsky",
    "woe:placetype":"LocalAdmin",
    "wof:name":"Rovinka",
    "wof:placetype":"localadmin"
},
  "geometry": {"coordinates":[17.223794,48.105511],"type":"Point"}
}