{
  "type": "Feature",
  "properties": {
    "gn:admin1_code":"01",
    "gn:asciiname":"Radvan",
    "gn:country_code":"SK",
    "gn:dem":346,
    "gn:feature_class":"P",
    "gn:feature_code":"PPL",
    "gn:name":"Radva\u0148",
    "gn:population":0,
    "gn:timezone":"Europe/Bratislava",
    "iso:country":"SK",
    "name:und_x_variant":[
        "Radva\u0148 nad Hronom",
        "Radva\u0148"
    ],
    "wof:name":"Radvan",
    "wof:placetype":"locality"
},
  "geometry": {"coordinates":[19.13442,48.72241],"type":"Point"}
}