{
  "type": "Feature",
  "properties": {
    "gn:admin1_code":"04",
    "gn:asciiname":"Vel'ke Hoste",
    "gn:country_code":"SK",
    "gn:dem":242,
    "gn:feature_class":"P",
    "gn:feature_code":"PPL",
    "gn:name":"Ve\u013ek\u00e9 Hoste",
    "gn:population":0,
    "gn:timezone":"Europe/Bratislava",
    "iso:country":"SK",
    "name:cat_x_preferred":[
        "Ve\u013ek\u00e9 Hoste"
    ],
    "name:ces_x_preferred":[
        "Ve\u013ek\u00e9 Hoste"
    ],
    "name:epo_x_preferred":[
        "Ve\u013ek\u00e9 Hoste"
    ],
    "name:eus_x_preferred":[
        "Ve\u013ek\u00e9 Hoste"
    ],
    "name:fra_x_preferred":[
        "Ve\u013ek\u00e9 Hoste"
    ],
    "name:hun_x_preferred":[
        "Nagyvend\u00e9g"
    ],
    "name:ita_x_preferred":[
        "Ve\u013ek\u00e9 Hoste"
    ],
    "name:msa_x_preferred":[
        "Ve\u013ek\u00e9 Hoste"
    ],
    "name:nld_x_preferred":[
        "Ve\u013ek\u00e9 Hoste"
    ],
    "name:ron_x_preferred":[
        "Ve\u013ek\u00e9 Hoste"
    ],
    "name:slk_x_preferred":[
        "Ve\u013ek\u00e9 Hoste"
    ],
    "name:spa_x_preferred":[
        "Ve\u013ek\u00e9 Hoste"
    ],
    "name:srp_x_preferred":[
        "\u0412\u0435\u0459\u043a\u0435 \u0425\u043e\u0441\u0442\u0458\u0435"
    ],
    "name:tgl_x_preferred":[
        "Ve\u013ek\u00e9 Hoste"
    ],
    "name:ukr_x_preferred":[
        "\u0412\u0435\u043b\u044c\u043a\u0435 \u0413\u043e\u0441\u0442\u0435"
    ],
    "name:war_x_preferred":[
        "Ve\u013ek\u00e9 Hoste"
    ],
    "wof:name":"Vel'ke Hoste",
    "wof:placetype":"locality"
},
  "geometry": {"coordinates":[18.15761,48.68095],"type":"Point"}
}