{
  "type": "Feature",
  "properties": {
    "gn:admin1_code":"03",
    "gn:asciiname":"Budulov",
    "gn:country_code":"SK",
    "gn:dem":196,
    "gn:feature_class":"P",
    "gn:feature_code":"PPL",
    "gn:name":"Budulov",
    "gn:population":0,
    "gn:timezone":"Europe/Bratislava",
    "iso:country":"SK",
    "name:hun_x_preferred":[
        "Bodoll\u00f3"
    ],
    "name:und_x_variant":[
        "Bodolov",
        "Budulov"
    ],
    "wof:name":"Budulov",
    "wof:placetype":"locality"
},
  "geometry": {"coordinates":[20.99235,48.58823],"type":"Point"}
}