{
  "type": "Feature",
  "properties": {
    "gn:admin1_code":"03",
    "gn:asciiname":"Vel'ke Pol'e",
    "gn:country_code":"SK",
    "gn:dem":154,
    "gn:feature_class":"P",
    "gn:feature_code":"PPL",
    "gn:name":"Ve\u013ek\u00e9 Po\u013ee",
    "gn:population":0,
    "gn:timezone":"Europe/Bratislava",
    "iso:country":"SK",
    "name:und_x_variant":[
        "Ve\u013ek\u00e9 Po\u013eo",
        "Ve\u013ek\u00e9 Po\u013ee"
    ],
    "wof:name":"Vel'ke Pol'e",
    "wof:placetype":"locality"
},
  "geometry": {"coordinates":[21.64291,48.66201],"type":"Point"}
}