{
  "type": "Feature",
  "properties": {
    "gn:admin1_code":"05",
    "gn:asciiname":"Spisske Hanusovce",
    "gn:country_code":"SK",
    "gn:dem":609,
    "gn:feature_class":"P",
    "gn:feature_code":"PPL",
    "gn:name":"Spi\u0161sk\u00e9 Hanu\u0161ovce",
    "gn:population":0,
    "gn:timezone":"Europe/Bratislava",
    "iso:country":"SK",
    "name:cat_x_preferred":[
        "Spi\u0161sk\u00e9 Hanu\u0161ovce"
    ],
    "name:deu_x_preferred":[
        "Spi\u0161sk\u00e9 Hanu\u0161ovce"
    ],
    "name:epo_x_preferred":[
        "Spi\u0161sk\u00e9 Hanu\u0161ovce"
    ],
    "name:eus_x_preferred":[
        "Spi\u0161sk\u00e9 Hanu\u0161ovce"
    ],
    "name:fra_x_preferred":[
        "Spi\u0161sk\u00e9 Hanu\u0161ovce"
    ],
    "name:hun_x_preferred":[
        "Hanusfalva"
    ],
    "name:ita_x_preferred":[
        "Spi\u0161sk\u00e9 Hanu\u0161ovce"
    ],
    "name:msa_x_preferred":[
        "Spi\u0161sk\u00e9 Hanu\u0161ovce"
    ],
    "name:nld_x_preferred":[
        "Spi\u0161sk\u00e9 Hanu\u0161ovce"
    ],
    "name:pol_x_preferred":[
        "Hanuszowce"
    ],
    "name:ron_x_preferred":[
        "Spi\u0161sk\u00e9 Hanu\u0161ovce"
    ],
    "name:rue_x_preferred":[
        "\u0421\u043f\u0456\u0441\u044c\u043a\u0435 \u0413\u0430\u043d\u0443\u0448\u043e\u0432\u0446\u0435"
    ],
    "name:slk_x_preferred":[
        "Spi\u0161sk\u00e9 Hanu\u0161ovce"
    ],
    "name:spa_x_preferred":[
        "Spi\u0161sk\u00e9 Hanu\u0161ovce"
    ],
    "name:srp_x_preferred":[
        "\u0421\u043f\u0438\u0448\u043a\u0435 \u0425\u0430\u043d\u0443\u0448\u043e\u0432\u0446\u0435"
    ],
    "name:ukr_x_preferred":[
        "\u0421\u043f\u0438\u0441\u044c\u043a\u0456 \u0413\u0430\u043d\u0443\u0448\u0456\u0432\u0446\u0456"
    ],
    "name:war_x_preferred":[
        "Spi\u0161sk\u00e9 Hanu\u0161ovce"
    ],
    "wof:name":"Spisske Hanusovce",
    "wof:placetype":"locality"
},
  "geometry": {"coordinates":[20.34476,49.33101],"type":"Point"}
}