{
  "type": "Feature",
  "properties": {
    "gn:admin1_code":"05",
    "gn:asciiname":"Spisske Hanusovce",
    "gn:country_code":"SK",
    "gn:dem":609,
    "gn:feature_class":"P",
    "gn:feature_code":"PPL",
    "gn:name":"Spi\u0161sk\u00e9 Hanu\u0161ovce",
    "gn:population":0,
    "gn:timezone":"Europe/Bratislava",
    "iso:country":"SK",
    "name:und_x_variant":[
        "Spi\u0161sk\u00e9 Hanu\u0161ovce"
    ],
    "wof:name":"Spisske Hanusovce",
    "wof:placetype":"locality"
},
  "geometry": {"coordinates":[20.34476,49.33101],"type":"Point"}
}