{
  "type": "Feature",
  "properties": {
    "gn:admin1_code":"04",
    "gn:asciiname":"Dolny Vinodol",
    "gn:country_code":"SK",
    "gn:dem":128,
    "gn:feature_class":"P",
    "gn:feature_code":"PPL",
    "gn:name":"Doln\u00fd Vinodol",
    "gn:population":0,
    "gn:timezone":"Europe/Bratislava",
    "iso:country":"SK",
    "name:und_x_variant":[
        "S\u00edle\u0161",
        "Doln\u00ed S\u00edle\u0161",
        "Doln\u00fd Vinodol"
    ],
    "wof:name":"Dolny Vinodol",
    "wof:placetype":"locality"
},
  "geometry": {"coordinates":[18.21148,48.18006],"type":"Point"}
}