{
  "type": "Feature",
  "properties": {
    "gn:admin1_code":"05",
    "gn:asciiname":"Ruska Kajna",
    "gn:country_code":"SK",
    "gn:dem":209,
    "gn:feature_class":"P",
    "gn:feature_code":"PPL",
    "gn:name":"Rusk\u00e1 Kaj\u0148a",
    "gn:population":0,
    "gn:timezone":"Europe/Bratislava",
    "iso:country":"SK",
    "name:cat_x_preferred":[
        "Rusk\u00e1 Kaj\u0148a"
    ],
    "name:epo_x_preferred":[
        "Rusk\u00e1 Kaj\u0148a"
    ],
    "name:eus_x_preferred":[
        "Rusk\u00e1 Kaj\u0148a"
    ],
    "name:fra_x_preferred":[
        "Rusk\u00e1 Kaj\u0148a"
    ],
    "name:hun_x_preferred":[
        "Oroszk\u00e1nya"
    ],
    "name:ita_x_preferred":[
        "Rusk\u00e1 Kaj\u0148a"
    ],
    "name:msa_x_preferred":[
        "Rusk\u00e1 Kaj\u0148a"
    ],
    "name:nld_x_preferred":[
        "Rusk\u00e1 Kaj\u0148a"
    ],
    "name:pol_x_preferred":[
        "Rusk\u00e1 Kaj\u0148a"
    ],
    "name:ron_x_preferred":[
        "Rusk\u00e1 Kaj\u0148a"
    ],
    "name:rue_x_preferred":[
        "\u0420\u0443\u0441\u044c\u043a\u0430 \u041a\u0430\u0439\u043d\u044f"
    ],
    "name:slk_x_preferred":[
        "Rusk\u00e1 Kaj\u0148a"
    ],
    "name:spa_x_preferred":[
        "Rusk\u00e1 Kaj\u0148a"
    ],
    "name:srp_x_preferred":[
        "\u0420\u0443\u0441\u043a\u0430 \u041a\u0430\u0458\u045a\u0430"
    ],
    "name:ukr_x_preferred":[
        "\u0420\u0443\u0441\u044c\u043a\u0430 \u041a\u0430\u0439\u043d\u044f"
    ],
    "name:und_x_variant":[
        "Kajna Ruska"
    ],
    "name:war_x_preferred":[
        "Rusk\u00e1 Kaj\u0148a"
    ],
    "wof:name":"Ruska Kajna",
    "wof:placetype":"locality"
},
  "geometry": {"coordinates":[21.83969,49.1197],"type":"Point"}
}