{
  "type": "Feature",
  "properties": {
    "gn:admin1_code":"05",
    "gn:asciiname":"Ruska Kajna",
    "gn:country_code":"SK",
    "gn:dem":209,
    "gn:feature_class":"P",
    "gn:feature_code":"PPL",
    "gn:name":"Rusk\u00e1 Kaj\u0148a",
    "gn:population":0,
    "gn:timezone":"Europe/Bratislava",
    "iso:country":"SK",
    "name:und_x_variant":[
        "Kajna Ruska",
        "Rusk\u00e1 Kaj\u0148a"
    ],
    "wof:name":"Ruska Kajna",
    "wof:placetype":"locality"
},
  "geometry": {"coordinates":[21.83969,49.1197],"type":"Point"}
}