{
  "type": "Feature",
  "properties": {
    "gn:admin1_code":"08",
    "gn:asciiname":"Kotrcina Lucka",
    "gn:country_code":"SK",
    "gn:dem":460,
    "gn:feature_class":"P",
    "gn:feature_code":"PPL",
    "gn:name":"Kotr\u010din\u00e1 L\u00fa\u010dka",
    "gn:population":0,
    "gn:timezone":"Europe/Bratislava",
    "iso:country":"SK",
    "name:cat_x_preferred":[
        "Kotr\u010din\u00e1 L\u00fa\u010dka"
    ],
    "name:ces_x_preferred":[
        "Kotr\u010din\u00e1 L\u00fa\u010dka"
    ],
    "name:deu_x_preferred":[
        "Kotr\u010din\u00e1 L\u00fa\u010dka"
    ],
    "name:epo_x_preferred":[
        "Kotr\u010din\u00e1 L\u00fa\u010dka"
    ],
    "name:eus_x_preferred":[
        "Kotr\u010din\u00e1 L\u00fa\u010dka"
    ],
    "name:fra_x_preferred":[
        "Kotr\u010din\u00e1 L\u00fa\u010dka"
    ],
    "name:hun_x_preferred":[
        "Kasz\u00e1sr\u00e9t"
    ],
    "name:ita_x_preferred":[
        "Kotr\u010din\u00e1 L\u00fa\u010dka"
    ],
    "name:msa_x_preferred":[
        "Kotr\u010din\u00e1 L\u00fa\u010dka"
    ],
    "name:nld_x_preferred":[
        "Kotr\u010din\u00e1 L\u00fa\u010dka"
    ],
    "name:pol_x_preferred":[
        "Kotr\u010din\u00e1 L\u00fa\u010dka"
    ],
    "name:ron_x_preferred":[
        "Kotr\u010din\u00e1 L\u00fa\u010dka"
    ],
    "name:slk_x_preferred":[
        "Kotr\u010din\u00e1 L\u00fa\u010dka"
    ],
    "name:spa_x_preferred":[
        "Kotr\u010din\u00e1 L\u00fa\u010dka"
    ],
    "name:srp_x_preferred":[
        "\u041a\u043e\u0442\u0440\u0447\u0438\u043d\u0430 \u041b\u0443\u0447\u043a\u0430"
    ],
    "name:und_x_variant":[
        "Kotr\u010din\u00e1 L\u00fa\u010dka"
    ],
    "name:war_x_preferred":[
        "Kotr\u010din\u00e1 L\u00fa\u010dka"
    ],
    "wof:name":"Kotrcina Lucka",
    "wof:placetype":"locality"
},
  "geometry": {"coordinates":[18.83897,49.2503],"type":"Point"}
}