{
  "type": "Feature",
  "properties": {
    "gn:admin1_code":"08",
    "gn:asciiname":"Kotrcina Lucka",
    "gn:country_code":"SK",
    "gn:dem":460,
    "gn:feature_class":"P",
    "gn:feature_code":"PPL",
    "gn:name":"Kotr\u010din\u00e1 L\u00fa\u010dka",
    "gn:population":0,
    "gn:timezone":"Europe/Bratislava",
    "iso:country":"SK",
    "name:und_x_variant":[
        "Kotr\u010din\u00e1 L\u00fa\u010dka"
    ],
    "wof:name":"Kotrcina Lucka",
    "wof:placetype":"locality"
},
  "geometry": {"coordinates":[18.83897,49.2503],"type":"Point"}
}