{
  "type": "Feature",
  "properties": {
    "gn:admin1_code":"07",
    "gn:asciiname":"Margit",
    "gn:country_code":"SK",
    "gn:dem":146,
    "gn:feature_class":"P",
    "gn:feature_code":"PPL",
    "gn:name":"Margit",
    "gn:population":0,
    "gn:timezone":"Europe/Bratislava",
    "iso:country":"SK",
    "name:bre_x_preferred":[
        "Margit"
    ],
    "name:dan_x_preferred":[
        "Margit"
    ],
    "name:deu_x_preferred":[
        "Margit"
    ],
    "name:fin_x_preferred":[
        "Margit"
    ],
    "name:fra_x_preferred":[
        "Margit"
    ],
    "name:hun_x_preferred":[
        "Margit"
    ],
    "name:isl_x_preferred":[
        "Margit"
    ],
    "name:jpn_x_preferred":[
        "\u30de\u30eb\u30ae\u30c8"
    ],
    "name:nno_x_preferred":[
        "Margit"
    ],
    "name:nor_x_preferred":[
        "Margit"
    ],
    "name:slv_x_preferred":[
        "Margit"
    ],
    "name:swe_x_preferred":[
        "Margit"
    ],
    "name:und_x_variant":[
        "Dvor Margit"
    ],
    "wof:name":"Margit",
    "wof:placetype":"locality"
},
  "geometry": {"coordinates":[17.51667,48.33333],"type":"Point"}
}