{
  "type": "Feature",
  "properties": {
    "gn:admin1_code":"01",
    "gn:asciiname":"Savol'",
    "gn:country_code":"SK",
    "gn:dem":198,
    "gn:feature_class":"P",
    "gn:feature_code":"PPL",
    "gn:name":"\u0160\u00e1vol\u2019",
    "gn:population":0,
    "gn:timezone":"Europe/Bratislava",
    "iso:country":"SK",
    "name:und_x_variant":[
        "S\u00e1voly",
        "\u0160\u00e1vol\u2019"
    ],
    "wof:name":"Savol'",
    "wof:placetype":"locality"
},
  "geometry": {"coordinates":[19.82661,48.30461],"type":"Point"}
}