{
  "type": "Feature",
  "properties": {
    "gn:admin1_code":"04",
    "gn:asciiname":"Biskupice",
    "gn:country_code":"SK",
    "gn:dem":194,
    "gn:feature_class":"P",
    "gn:feature_code":"PPL",
    "gn:name":"Biskupice",
    "gn:population":0,
    "gn:timezone":"Europe/Bratislava",
    "iso:country":"SK",
    "name:ceb_x_preferred":[
        "Biskupice"
    ],
    "name:ces_x_preferred":[
        "Biskupice"
    ],
    "name:deu_x_preferred":[
        "Biskupice"
    ],
    "name:epo_x_preferred":[
        "Biskupice"
    ],
    "name:fra_x_preferred":[
        "Biskupice"
    ],
    "name:hun_x_preferred":[
        "Biskupice"
    ],
    "name:ita_x_preferred":[
        "Biskupice"
    ],
    "name:nld_x_preferred":[
        "Biskupice"
    ],
    "name:pol_x_preferred":[
        "Biskupice"
    ],
    "name:rus_x_preferred":[
        "\u0411\u0438\u0441\u043a\u0443\u043f\u0438\u0446\u0435"
    ],
    "name:slk_x_preferred":[
        "Biskupice"
    ],
    "name:spa_x_preferred":[
        "Biskupice"
    ],
    "name:srp_x_preferred":[
        "\u0411\u0438\u0441\u043a\u0443\u043f\u0438\u0446\u0435"
    ],
    "name:swe_x_preferred":[
        "Biskupice"
    ],
    "name:ukr_x_preferred":[
        "\u0411\u0456\u0441\u043a\u0443\u043f\u0456\u0446\u0435"
    ],
    "wof:name":"Biskupice",
    "wof:placetype":"locality"
},
  "geometry": {"coordinates":[18.24257,48.70976],"type":"Point"}
}