{
  "type": "Feature",
  "properties": {
    "gn:admin1_code":"04",
    "gn:asciiname":"Biskupice",
    "gn:country_code":"SK",
    "gn:dem":194,
    "gn:feature_class":"P",
    "gn:feature_code":"PPL",
    "gn:name":"Biskupice",
    "gn:population":0,
    "gn:timezone":"Europe/Bratislava",
    "iso:country":"SK",
    "wof:name":"Biskupice",
    "wof:placetype":"locality"
},
  "geometry": {"coordinates":[18.24257,48.70976],"type":"Point"}
}