{
  "type": "Feature",
  "properties": {
    "gn:admin1_code":"07",
    "gn:asciiname":"Prekazka",
    "gn:country_code":"SK",
    "gn:dem":242,
    "gn:feature_class":"P",
    "gn:feature_code":"PPL",
    "gn:name":"Prek\u00e1\u017eka",
    "gn:population":0,
    "gn:timezone":"Europe/Bratislava",
    "iso:country":"SK",
    "wof:name":"Prekazka",
    "wof:placetype":"locality"
},
  "geometry": {"coordinates":[17.50514,48.53503],"type":"Point"}
}