{
  "type": "Feature",
  "properties": {
    "gn:admin1_code":"04",
    "gn:asciiname":"Striebornica",
    "gn:country_code":"SK",
    "gn:dem":287,
    "gn:feature_class":"P",
    "gn:feature_code":"PPL",
    "gn:name":"Striebornica",
    "gn:population":0,
    "gn:timezone":"Europe/Bratislava",
    "iso:country":"SK",
    "wof:name":"Striebornica",
    "wof:placetype":"locality"
},
  "geometry": {"coordinates":[18.34893,48.75083],"type":"Point"}
}