{
  "type": "Feature",
  "properties": {
    "gn:admin1_code":"08",
    "gn:asciiname":"Kriva",
    "gn:country_code":"SK",
    "gn:dem":547,
    "gn:feature_class":"P",
    "gn:feature_code":"PPL",
    "gn:name":"Kriv\u00e1",
    "gn:population":0,
    "gn:timezone":"Europe/Bratislava",
    "iso:country":"SK",
    "name:bos_x_preferred":[
        "Kriv\u00e1"
    ],
    "name:cat_x_preferred":[
        "Kriv\u00e1"
    ],
    "name:ces_x_preferred":[
        "Kriv\u00e1"
    ],
    "name:deu_x_preferred":[
        "Kriv\u00e1"
    ],
    "name:epo_x_preferred":[
        "Kriv\u00e1"
    ],
    "name:eus_x_preferred":[
        "Kriv\u00e1"
    ],
    "name:fra_x_preferred":[
        "Kriv\u00e1"
    ],
    "name:hun_x_preferred":[
        "Kriva"
    ],
    "name:ita_x_preferred":[
        "Kriv\u00e1"
    ],
    "name:msa_x_preferred":[
        "Kriv\u00e1"
    ],
    "name:nld_x_preferred":[
        "Kriv\u00e1"
    ],
    "name:pol_x_preferred":[
        "Kriv\u00e1"
    ],
    "name:ron_x_preferred":[
        "Kriv\u00e1"
    ],
    "name:slk_x_preferred":[
        "Kriv\u00e1"
    ],
    "name:spa_x_preferred":[
        "Kriv\u00e1"
    ],
    "name:srp_x_preferred":[
        "\u041a\u0440\u0438\u0432\u0430"
    ],
    "name:ukr_x_preferred":[
        "\u041a\u0440\u0456\u0432\u0430"
    ],
    "name:war_x_preferred":[
        "Kriv\u00e1"
    ],
    "wof:name":"Kriva",
    "wof:placetype":"locality"
},
  "geometry": {"coordinates":[19.4798,49.28349],"type":"Point"}
}