{
  "type": "Feature",
  "properties": {
    "gn:admin1_code":"08",
    "gn:asciiname":"Kriva",
    "gn:country_code":"SK",
    "gn:dem":547,
    "gn:feature_class":"P",
    "gn:feature_code":"PPL",
    "gn:name":"Kriv\u00e1",
    "gn:population":0,
    "gn:timezone":"Europe/Bratislava",
    "iso:country":"SK",
    "name:und_x_variant":[
        "Kriv\u00e1"
    ],
    "wof:name":"Kriva",
    "wof:placetype":"locality"
},
  "geometry": {"coordinates":[19.4798,49.28349],"type":"Point"}
}