{
  "type": "Feature",
  "properties": {
    "gn:admin1_code":"04",
    "gn:asciiname":"Vyskovce nad Ipl'om",
    "gn:country_code":"SK",
    "gn:dem":123,
    "gn:feature_class":"P",
    "gn:feature_code":"PPL",
    "gn:name":"Vy\u0161kovce nad Ip\u013eom",
    "gn:population":0,
    "gn:timezone":"Europe/Bratislava",
    "iso:country":"SK",
    "name:cat_x_preferred":[
        "Vy\u0161kovce nad Ip\u013eom"
    ],
    "name:deu_x_preferred":[
        "Vy\u0161kovce nad Ip\u013eom"
    ],
    "name:epo_x_preferred":[
        "Vy\u0161kovce nad Ip\u013eom"
    ],
    "name:eus_x_preferred":[
        "Vy\u0161kovce nad Ip\u013eom"
    ],
    "name:fra_x_preferred":[
        "Vy\u0161kovce nad Ip\u013eom"
    ],
    "name:hun_x_historical":[
        "Visk",
        "Hontvisk"
    ],
    "name:hun_x_preferred":[
        "Ipolyvisk"
    ],
    "name:hun_x_variant":[
        "Visk",
        "Hontvisk"
    ],
    "name:ita_x_preferred":[
        "Vy\u0161kovce nad Ip\u013eom"
    ],
    "name:msa_x_preferred":[
        "Vy\u0161kovce nad Ip\u013eom"
    ],
    "name:nld_x_preferred":[
        "Vy\u0161kovce nad Ip\u013eom"
    ],
    "name:pol_x_preferred":[
        "Vy\u0161kovce nad Ip\u013eom"
    ],
    "name:ron_x_preferred":[
        "Vy\u0161kovce nad Ip\u013eom"
    ],
    "name:slk_x_preferred":[
        "Vy\u0161kovce nad Ip\u013eom"
    ],
    "name:spa_x_preferred":[
        "Vy\u0161kovce nad Ip\u013eom"
    ],
    "name:srp_x_preferred":[
        "\u0412\u0438\u0448\u043a\u043e\u0432\u0446\u0435 \u043d\u0430 \u0418\u043f\u0435\u0459\u0443"
    ],
    "name:war_x_preferred":[
        "Vy\u0161kovce nad Ip\u013eom"
    ],
    "wof:name":"Vyskovce nad Ipl'om",
    "wof:placetype":"locality"
},
  "geometry": {"coordinates":[18.86778,48.05575],"type":"Point"}
}