{
  "type": "Feature",
  "properties": {
    "gn:admin1_code":"04",
    "gn:asciiname":"Adamovce",
    "gn:country_code":"SK",
    "gn:dem":195,
    "gn:feature_class":"P",
    "gn:feature_code":"PPL",
    "gn:name":"Adamovce",
    "gn:population":0,
    "gn:timezone":"Europe/Bratislava",
    "iso:country":"SK",
    "wof:name":"Adamovce",
    "wof:placetype":"locality"
},
  "geometry": {"coordinates":[17.92778999999999,48.849],"type":"Point"}
}