{
  "type": "Feature",
  "properties": {
    "gn:admin1_code":"05",
    "gn:asciiname":"Beloveza",
    "gn:country_code":"SK",
    "gn:dem":298,
    "gn:feature_class":"P",
    "gn:feature_code":"PPL",
    "gn:name":"Belove\u017ea",
    "gn:population":0,
    "gn:timezone":"Europe/Bratislava",
    "iso:country":"SK",
    "name:cat_x_preferred":[
        "Belove\u017ea"
    ],
    "name:ces_x_preferred":[
        "Belove\u017ea"
    ],
    "name:deu_x_preferred":[
        "Belove\u017ea"
    ],
    "name:epo_x_preferred":[
        "Belove\u017ea"
    ],
    "name:eus_x_preferred":[
        "Belove\u017ea"
    ],
    "name:fra_x_preferred":[
        "Belove\u017ea"
    ],
    "name:hun_x_preferred":[
        "B\u00e9lav\u00e9zse"
    ],
    "name:ita_x_preferred":[
        "Belove\u017ea"
    ],
    "name:msa_x_preferred":[
        "Belove\u017ea"
    ],
    "name:nld_x_preferred":[
        "Belove\u017ea"
    ],
    "name:pol_x_preferred":[
        "Belove\u017ea"
    ],
    "name:ron_x_preferred":[
        "Belove\u017ea"
    ],
    "name:rue_x_preferred":[
        "\u0411\u0456\u043b\u043e\u0432\u0435\u0436\u0430"
    ],
    "name:slk_x_preferred":[
        "Belove\u017ea"
    ],
    "name:spa_x_preferred":[
        "Belove\u017ea"
    ],
    "name:srp_x_preferred":[
        "\u0411\u0435\u043b\u043e\u0432\u0435\u0436\u0430"
    ],
    "name:ukr_x_preferred":[
        "\u0411\u0456\u043b\u043e\u0432\u0435\u0436\u0430"
    ],
    "name:und_x_variant":[
        "Belove\u017ea"
    ],
    "name:war_x_preferred":[
        "Belove\u017ea"
    ],
    "wof:name":"Beloveza",
    "wof:placetype":"locality"
},
  "geometry": {"coordinates":[21.3683,49.29600000000001],"type":"Point"}
}