{
  "type": "Feature",
  "properties": {
    "gn:admin1_code":"05",
    "gn:asciiname":"Beloveza",
    "gn:country_code":"SK",
    "gn:dem":298,
    "gn:feature_class":"P",
    "gn:feature_code":"PPL",
    "gn:name":"Belove\u017ea",
    "gn:population":0,
    "gn:timezone":"Europe/Bratislava",
    "iso:country":"SK",
    "name:und_x_variant":[
        "Belove\u017ea"
    ],
    "wof:name":"Beloveza",
    "wof:placetype":"locality"
},
  "geometry": {"coordinates":[21.3683,49.29600000000001],"type":"Point"}
}