{
  "type": "Feature",
  "properties": {
    "gn:admin1_code":"05",
    "gn:asciiname":"Majerovce",
    "gn:country_code":"SK",
    "gn:dem":128,
    "gn:feature_class":"P",
    "gn:feature_code":"PPL",
    "gn:name":"Majerovce",
    "gn:population":0,
    "gn:timezone":"Europe/Bratislava",
    "iso:country":"SK",
    "name:cat_x_preferred":[
        "Majerovce"
    ],
    "name:ces_x_preferred":[
        "Majerovce"
    ],
    "name:deu_x_preferred":[
        "Majerovce"
    ],
    "name:epo_x_preferred":[
        "Majerovce"
    ],
    "name:eus_x_preferred":[
        "Majerovce"
    ],
    "name:fra_x_preferred":[
        "Majerovce"
    ],
    "name:hun_x_preferred":[
        "Majoros"
    ],
    "name:ita_x_preferred":[
        "Majerovce"
    ],
    "name:msa_x_preferred":[
        "Majerovce"
    ],
    "name:nld_x_preferred":[
        "Majerovce"
    ],
    "name:pol_x_preferred":[
        "Majerovce"
    ],
    "name:ron_x_preferred":[
        "Majerovce"
    ],
    "name:slk_x_preferred":[
        "Majerovce"
    ],
    "name:spa_x_preferred":[
        "Majerovce"
    ],
    "name:srp_x_preferred":[
        "\u041c\u0430\u0458\u0435\u0440\u043e\u0432\u0446\u0435"
    ],
    "name:ukr_x_preferred":[
        "\u041c\u0430\u0454\u0440\u043e\u0432\u0446\u0435"
    ],
    "name:war_x_preferred":[
        "Majerovce"
    ],
    "wof:name":"Majerovce",
    "wof:placetype":"locality"
},
  "geometry": {"coordinates":[21.71718,48.89173],"type":"Point"}
}