{
  "type": "Feature",
  "properties": {
    "gn:admin1_code":"05",
    "gn:asciiname":"Majerovce",
    "gn:country_code":"SK",
    "gn:dem":128,
    "gn:feature_class":"P",
    "gn:feature_code":"PPL",
    "gn:name":"Majerovce",
    "gn:population":0,
    "gn:timezone":"Europe/Bratislava",
    "iso:country":"SK",
    "wof:name":"Majerovce",
    "wof:placetype":"locality"
},
  "geometry": {"coordinates":[21.71718,48.89173],"type":"Point"}
}