{
  "type": "Feature",
  "properties": {
    "gn:admin1_code":"01",
    "gn:asciiname":"Licince",
    "gn:country_code":"SK",
    "gn:dem":210,
    "gn:feature_class":"P",
    "gn:feature_code":"PPL",
    "gn:name":"Licince",
    "gn:population":0,
    "gn:timezone":"Europe/Bratislava",
    "iso:country":"SK",
    "name:cat_x_preferred":[
        "Licince"
    ],
    "name:deu_x_preferred":[
        "Licince"
    ],
    "name:epo_x_preferred":[
        "Licince"
    ],
    "name:eus_x_preferred":[
        "Licince"
    ],
    "name:fra_x_preferred":[
        "Licince"
    ],
    "name:hun_x_preferred":[
        "Lice"
    ],
    "name:ita_x_preferred":[
        "Licince"
    ],
    "name:msa_x_preferred":[
        "Licince"
    ],
    "name:nld_x_preferred":[
        "Licince"
    ],
    "name:pol_x_preferred":[
        "Licince"
    ],
    "name:ron_x_preferred":[
        "Licince"
    ],
    "name:slk_x_preferred":[
        "Licince"
    ],
    "name:spa_x_preferred":[
        "Licince"
    ],
    "name:srp_x_preferred":[
        "\u041b\u0438\u0446\u0438\u043d\u0446\u0435"
    ],
    "name:ukr_x_preferred":[
        "\u041b\u0456\u0446\u0456\u043d\u0446\u0435"
    ],
    "name:war_x_preferred":[
        "Licince"
    ],
    "wof:name":"Licince",
    "wof:placetype":"locality"
},
  "geometry": {"coordinates":[20.29806,48.53943],"type":"Point"}
}