{
  "type": "Feature",
  "properties": {
    "gn:admin1_code":"01",
    "gn:asciiname":"Licince",
    "gn:country_code":"SK",
    "gn:dem":210,
    "gn:feature_class":"P",
    "gn:feature_code":"PPL",
    "gn:name":"Licince",
    "gn:population":0,
    "gn:timezone":"Europe/Bratislava",
    "iso:country":"SK",
    "wof:name":"Licince",
    "wof:placetype":"locality"
},
  "geometry": {"coordinates":[20.29806,48.53943],"type":"Point"}
}