{
  "type": "Feature",
  "properties": {
    "gn:admin1_code":"05",
    "gn:asciiname":"Rokycany",
    "gn:country_code":"SK",
    "gn:dem":309,
    "gn:feature_class":"P",
    "gn:feature_code":"PPL",
    "gn:name":"Rokycany",
    "gn:population":0,
    "gn:timezone":"Europe/Bratislava",
    "iso:country":"SK",
    "name:cat_x_preferred":[
        "Rokycany"
    ],
    "name:ces_x_preferred":[
        "Rokycany"
    ],
    "name:deu_x_preferred":[
        "Rokycany"
    ],
    "name:epo_x_preferred":[
        "Rokycany"
    ],
    "name:eus_x_preferred":[
        "Rokycany"
    ],
    "name:hun_x_preferred":[
        "Berki"
    ],
    "name:ita_x_preferred":[
        "Rokycany"
    ],
    "name:msa_x_preferred":[
        "Rokycany"
    ],
    "name:nld_x_preferred":[
        "Rokycany"
    ],
    "name:pol_x_preferred":[
        "Rokycany"
    ],
    "name:ron_x_preferred":[
        "Rokycany"
    ],
    "name:rue_x_preferred":[
        "\u0420\u043e\u043a\u0456\u0446\u0430\u043d\u0456"
    ],
    "name:slk_x_preferred":[
        "Rokycany"
    ],
    "name:spa_x_preferred":[
        "Rokycany"
    ],
    "name:srp_x_preferred":[
        "\u0420\u043e\u043a\u0438\u0446\u0430\u043d\u0438"
    ],
    "name:ukr_x_preferred":[
        "\u0420\u043e\u043a\u0438\u0446\u0430\u043d\u0438"
    ],
    "name:war_x_preferred":[
        "Rokycany"
    ],
    "wof:name":"Rokycany",
    "wof:placetype":"locality"
},
  "geometry": {"coordinates":[21.14199,48.96106],"type":"Point"}
}