{
  "type": "Feature",
  "properties": {
    "gn:admin1_code":"05",
    "gn:asciiname":"Rokycany",
    "gn:country_code":"SK",
    "gn:dem":309,
    "gn:feature_class":"P",
    "gn:feature_code":"PPL",
    "gn:name":"Rokycany",
    "gn:population":0,
    "gn:timezone":"Europe/Bratislava",
    "iso:country":"SK",
    "wof:name":"Rokycany",
    "wof:placetype":"locality"
},
  "geometry": {"coordinates":[21.14199,48.96106],"type":"Point"}
}