{
  "type": "Feature",
  "properties": {
    "gn:admin1_code":"01",
    "gn:asciiname":"Lackov",
    "gn:country_code":"SK",
    "gn:dem":486,
    "gn:feature_class":"P",
    "gn:feature_code":"PPL",
    "gn:name":"Lackov",
    "gn:population":0,
    "gn:timezone":"Europe/Bratislava",
    "iso:country":"SK",
    "name:cat_x_preferred":[
        "Lackov"
    ],
    "name:ces_x_preferred":[
        "Lackov"
    ],
    "name:epo_x_preferred":[
        "Lackov"
    ],
    "name:eus_x_preferred":[
        "Lackov"
    ],
    "name:fra_x_preferred":[
        "Lackov"
    ],
    "name:hun_x_preferred":[
        "L\u00e1szl\u00f3d"
    ],
    "name:ita_x_preferred":[
        "Lackov"
    ],
    "name:msa_x_preferred":[
        "Lackov"
    ],
    "name:nld_x_preferred":[
        "Lackov"
    ],
    "name:pol_x_preferred":[
        "Lackov"
    ],
    "name:ron_x_preferred":[
        "Lackov"
    ],
    "name:slk_x_preferred":[
        "Lackov"
    ],
    "name:spa_x_preferred":[
        "Lackov"
    ],
    "name:srp_x_preferred":[
        "\u041b\u0430\u0446\u043a\u043e\u0432"
    ],
    "name:ukr_x_preferred":[
        "\u041b\u0430\u0446\u043a\u043e\u0432"
    ],
    "name:war_x_preferred":[
        "Lackov"
    ],
    "wof:name":"Lackov",
    "wof:placetype":"locality"
},
  "geometry": {"coordinates":[19.18686,48.32144],"type":"Point"}
}