{
  "type": "Feature",
  "properties": {
    "gn:admin1_code":"04",
    "gn:asciiname":"Zabi Potok",
    "gn:country_code":"SK",
    "gn:dem":420,
    "gn:feature_class":"P",
    "gn:feature_code":"PPL",
    "gn:name":"\u017dab\u00ed Potok",
    "gn:population":0,
    "gn:timezone":"Europe/Bratislava",
    "iso:country":"SK",
    "wof:name":"Zabi Potok",
    "wof:placetype":"locality"
},
  "geometry": {"coordinates":[17.41667,48.78333],"type":"Point"}
}