{
  "type": "Feature",
  "properties": {
    "gn:admin1_code":"01",
    "gn:asciiname":"Skubin",
    "gn:country_code":"SK",
    "gn:dem":414,
    "gn:feature_class":"P",
    "gn:feature_code":"PPL",
    "gn:name":"Skub\u00edn",
    "gn:population":0,
    "gn:timezone":"Europe/Bratislava",
    "iso:country":"SK",
    "wof:name":"Skubin",
    "wof:placetype":"locality"
},
  "geometry": {"coordinates":[19.10452,48.73762],"type":"Point"}
}