{
  "type": "Feature",
  "properties": {
    "gn:admin1_code":"01",
    "gn:asciiname":"Horne Zahorany",
    "gn:country_code":"SK",
    "gn:dem":464,
    "gn:feature_class":"P",
    "gn:feature_code":"PPL",
    "gn:name":"Horn\u00e9 Zahorany",
    "gn:population":0,
    "gn:timezone":"Europe/Bratislava",
    "iso:country":"SK",
    "name:cat_x_preferred":[
        "Horn\u00e9 Zahorany"
    ],
    "name:epo_x_preferred":[
        "Horn\u00e9 Zahorany"
    ],
    "name:eus_x_preferred":[
        "Horn\u00e9 Zahorany"
    ],
    "name:fra_x_preferred":[
        "Horn\u00e9 Zahorany"
    ],
    "name:hun_x_preferred":[
        "T\u00f3thegymeg"
    ],
    "name:ita_x_preferred":[
        "Horn\u00e9 Zahorany"
    ],
    "name:msa_x_preferred":[
        "Horn\u00e9 Zahorany"
    ],
    "name:nld_x_preferred":[
        "Horn\u00e9 Zahorany"
    ],
    "name:pol_x_preferred":[
        "Horn\u00e9 Zahorany"
    ],
    "name:ron_x_preferred":[
        "Horn\u00e9 Zahorany"
    ],
    "name:slk_x_preferred":[
        "Horn\u00e9 Zahorany"
    ],
    "name:spa_x_preferred":[
        "Horn\u00e9 Zahorany"
    ],
    "name:srp_x_preferred":[
        "\u0425\u043e\u0440\u045a\u0435 \u0417\u0430\u0445\u043e\u0440\u0430\u043d\u0438"
    ],
    "name:ukr_x_preferred":[
        "\u0413\u043e\u0440\u043d\u0435 \u0417\u0430\u0433\u043e\u0440\u0430\u043d\u0438"
    ],
    "name:und_x_variant":[
        "Slovensk\u00e9 Zahorany",
        "Horn\u00e9 Zahorany"
    ],
    "name:war_x_preferred":[
        "Horn\u00e9 Zahorany"
    ],
    "wof:name":"Horne Zahorany",
    "wof:placetype":"locality"
},
  "geometry": {"coordinates":[20.00845,48.46146],"type":"Point"}
}