{
  "type": "Feature",
  "properties": {
    "gn:admin1_code":"01",
    "gn:asciiname":"Horne Zahorany",
    "gn:country_code":"SK",
    "gn:dem":464,
    "gn:feature_class":"P",
    "gn:feature_code":"PPL",
    "gn:name":"Horn\u00e9 Zahorany",
    "gn:population":0,
    "gn:timezone":"Europe/Bratislava",
    "iso:country":"SK",
    "name:und_x_variant":[
        "Slovensk\u00e9 Zahorany",
        "Horn\u00e9 Zahorany"
    ],
    "wof:name":"Horne Zahorany",
    "wof:placetype":"locality"
},
  "geometry": {"coordinates":[20.00845,48.46146],"type":"Point"}
}