{
  "type": "Feature",
  "properties": {
    "gn:admin1_code":"03",
    "gn:asciiname":"Tiba",
    "gn:country_code":"SK",
    "gn:dem":220,
    "gn:feature_class":"P",
    "gn:feature_code":"PPL",
    "gn:name":"Tiba",
    "gn:population":0,
    "gn:timezone":"Europe/Bratislava",
    "iso:country":"SK",
    "name:ceb_x_preferred":[
        "Tiba"
    ],
    "name:deu_x_preferred":[
        "Tiba"
    ],
    "name:swe_x_preferred":[
        "Tiba"
    ],
    "wof:name":"Tiba",
    "wof:placetype":"locality"
},
  "geometry": {"coordinates":[20.37503,48.51035],"type":"Point"}
}