{
  "type": "Feature",
  "properties": {
    "gn:asciiname":"Kastiel' a Dvor St'avnik",
    "gn:country_code":"SK",
    "gn:dem":557,
    "gn:feature_class":"P",
    "gn:feature_code":"PPL",
    "gn:name":"Ka\u0161tie\u013e a Dvor S\u0165avn\u00edk",
    "gn:population":0,
    "gn:timezone":"Europe/Bratislava",
    "iso:country":"SK",
    "wof:name":"Kastiel' a Dvor St'avnik",
    "wof:placetype":"locality"
},
  "geometry": {"coordinates":[20.3805,48.98822],"type":"Point"}
}