{
  "type": "Feature",
  "properties": {
    "gn:admin1_code":"08",
    "gn:asciiname":"Zbynov",
    "gn:country_code":"SK",
    "gn:dem":426,
    "gn:feature_class":"P",
    "gn:feature_code":"PPL",
    "gn:name":"Zby\u0148ov",
    "gn:population":0,
    "gn:timezone":"Europe/Bratislava",
    "iso:country":"SK",
    "name:cat_x_preferred":[
        "Zby\u0148ov"
    ],
    "name:ces_x_preferred":[
        "Zby\u0148ov"
    ],
    "name:deu_x_preferred":[
        "Zby\u0148ov"
    ],
    "name:epo_x_preferred":[
        "Zby\u0148ov"
    ],
    "name:eus_x_preferred":[
        "Zby\u0148ov"
    ],
    "name:fra_x_preferred":[
        "Zby\u0148ov"
    ],
    "name:hun_x_preferred":[
        "Zeb\u00e9ny"
    ],
    "name:ita_x_preferred":[
        "Zby\u0148ov"
    ],
    "name:msa_x_preferred":[
        "Zby\u0148ov"
    ],
    "name:nld_x_preferred":[
        "Zby\u0148ov"
    ],
    "name:pol_x_preferred":[
        "Zby\u0148ov"
    ],
    "name:ron_x_preferred":[
        "Zby\u0148ov"
    ],
    "name:slk_x_preferred":[
        "Zby\u0148ov"
    ],
    "name:spa_x_preferred":[
        "Zby\u0148ov"
    ],
    "name:srp_x_preferred":[
        "\u0417\u0431\u0438\u045a\u043e\u0432"
    ],
    "name:war_x_preferred":[
        "Zby\u0148ov"
    ],
    "wof:name":"Zbynov",
    "wof:placetype":"locality"
},
  "geometry": {"coordinates":[18.64867000000001,49.12081],"type":"Point"}
}