{
  "type": "Feature",
  "properties": {
    "gn:admin1_code":"08",
    "gn:asciiname":"Zbynov",
    "gn:country_code":"SK",
    "gn:dem":426,
    "gn:feature_class":"P",
    "gn:feature_code":"PPL",
    "gn:name":"Zby\u0148ov",
    "gn:population":0,
    "gn:timezone":"Europe/Bratislava",
    "iso:country":"SK",
    "name:und_x_variant":[
        "Zby\u0148ov"
    ],
    "wof:name":"Zbynov",
    "wof:placetype":"locality"
},
  "geometry": {"coordinates":[18.64867000000001,49.12081],"type":"Point"}
}