{
  "type": "Feature",
  "properties": {
    "gn:admin1_code":"04",
    "gn:asciiname":"Cierna Lehota",
    "gn:country_code":"SK",
    "gn:dem":389,
    "gn:feature_class":"P",
    "gn:feature_code":"PPL",
    "gn:name":"\u010cierna Lehota",
    "gn:population":0,
    "gn:timezone":"Europe/Bratislava",
    "iso:country":"SK",
    "wof:name":"Cierna Lehota",
    "wof:placetype":"locality"
},
  "geometry": {"coordinates":[18.33157000000001,48.865],"type":"Point"}
}