{
  "type": "Feature",
  "properties": {
    "gn:admin1_code":"04",
    "gn:asciiname":"Cuklasovce",
    "gn:country_code":"SK",
    "gn:dem":252,
    "gn:feature_class":"P",
    "gn:feature_code":"PPL",
    "gn:name":"\u010cuklasovce",
    "gn:population":0,
    "gn:timezone":"Europe/Bratislava",
    "iso:country":"SK",
    "wof:name":"Cuklasovce",
    "wof:placetype":"locality"
},
  "geometry": {"coordinates":[18.1401,48.73918],"type":"Point"}
}