{
  "type": "Feature",
  "properties": {
    "gn:admin1_code":"04",
    "gn:asciiname":"Zitna",
    "gn:country_code":"SK",
    "gn:dem":274,
    "gn:feature_class":"P",
    "gn:feature_code":"PPL",
    "gn:name":"\u017ditn\u00e1",
    "gn:population":0,
    "gn:timezone":"Europe/Bratislava",
    "iso:country":"SK",
    "name:vie_x_preferred":[
        "Zitna"
    ],
    "wof:name":"Zitna",
    "wof:placetype":"locality"
},
  "geometry": {"coordinates":[18.35058,48.76631],"type":"Point"}
}