{
  "type": "Feature",
  "properties": {
    "gn:admin1_code":"01",
    "gn:asciiname":"Nevol'ne",
    "gn:country_code":"SK",
    "gn:dem":696,
    "gn:feature_class":"P",
    "gn:feature_code":"PPL",
    "gn:name":"Nevo\u013en\u00e9",
    "gn:population":0,
    "gn:timezone":"Europe/Bratislava",
    "iso:country":"SK",
    "name:und_x_variant":[
        "Nevo\u013en\u00e9"
    ],
    "wof:name":"Nevol'ne",
    "wof:placetype":"locality"
},
  "geometry": {"coordinates":[18.94393,48.67083],"type":"Point"}
}