{
  "type": "Feature",
  "properties": {
    "gn:admin1_code":"01",
    "gn:asciiname":"Nevol'ne",
    "gn:country_code":"SK",
    "gn:dem":696,
    "gn:feature_class":"P",
    "gn:feature_code":"PPL",
    "gn:name":"Nevo\u013en\u00e9",
    "gn:population":0,
    "gn:timezone":"Europe/Bratislava",
    "iso:country":"SK",
    "name:cat_x_preferred":[
        "Nevo\u013en\u00e9"
    ],
    "name:ces_x_preferred":[
        "Nevo\u013en\u00e9"
    ],
    "name:deu_x_preferred":[
        "Nevo\u013en\u00e9"
    ],
    "name:epo_x_preferred":[
        "Nevo\u013en\u00e9"
    ],
    "name:eus_x_preferred":[
        "Nevo\u013en\u00e9"
    ],
    "name:fra_x_preferred":[
        "Nevo\u013en\u00e9"
    ],
    "name:hun_x_preferred":[
        "Torm\u00e1skert"
    ],
    "name:ita_x_preferred":[
        "Nevo\u013en\u00e9"
    ],
    "name:msa_x_preferred":[
        "Nevo\u013en\u00e9"
    ],
    "name:nld_x_preferred":[
        "Nevo\u013en\u00e9"
    ],
    "name:pol_x_preferred":[
        "Nevo\u013en\u00e9"
    ],
    "name:ron_x_preferred":[
        "Nevo\u013en\u00e9"
    ],
    "name:slk_x_preferred":[
        "Nevo\u013en\u00e9"
    ],
    "name:spa_x_preferred":[
        "Nevo\u013en\u00e9"
    ],
    "name:srp_x_preferred":[
        "\u040a\u0435\u0432\u043e\u0459\u045a\u0435"
    ],
    "name:ukr_x_preferred":[
        "\u041d\u0435\u0432\u043e\u043b\u044c\u043d\u0435"
    ],
    "name:und_x_variant":[
        "Nevo\u013en\u00e9"
    ],
    "name:war_x_preferred":[
        "Nevo\u013en\u00e9"
    ],
    "wof:name":"Nevol'ne",
    "wof:placetype":"locality"
},
  "geometry": {"coordinates":[18.94393,48.67083],"type":"Point"}
}