{
  "type": "Feature",
  "properties": {
    "gn:admin1_code":"04",
    "gn:asciiname":"Cibajka",
    "gn:country_code":"SK",
    "gn:dem":218,
    "gn:feature_class":"P",
    "gn:feature_code":"PPL",
    "gn:name":"Cibajka",
    "gn:population":0,
    "gn:timezone":"Europe/Bratislava",
    "iso:country":"SK",
    "wof:name":"Cibajka",
    "wof:placetype":"locality"
},
  "geometry": {"coordinates":[18.31667,48.55],"type":"Point"}
}