{
  "type": "Feature",
  "properties": {
    "gn:admin1_code":"01",
    "gn:asciiname":"Budikovany",
    "gn:country_code":"SK",
    "gn:dem":227,
    "gn:feature_class":"P",
    "gn:feature_code":"PPL",
    "gn:name":"Budikovany",
    "gn:population":0,
    "gn:timezone":"Europe/Bratislava",
    "iso:country":"SK",
    "name:cat_x_preferred":[
        "Budikovany"
    ],
    "name:ces_x_preferred":[
        "Budikovany"
    ],
    "name:epo_x_preferred":[
        "Budikovany"
    ],
    "name:eus_x_preferred":[
        "Budikovany"
    ],
    "name:fra_x_preferred":[
        "Budikovany"
    ],
    "name:hun_x_preferred":[
        "Bugyikfala"
    ],
    "name:ita_x_preferred":[
        "Budikovany"
    ],
    "name:msa_x_preferred":[
        "Budikovany"
    ],
    "name:nld_x_preferred":[
        "Budikovany"
    ],
    "name:pol_x_preferred":[
        "Budikovany"
    ],
    "name:ron_x_preferred":[
        "Budikovany"
    ],
    "name:slk_x_preferred":[
        "Budikovany"
    ],
    "name:spa_x_preferred":[
        "Budikovany"
    ],
    "name:srp_x_preferred":[
        "\u0411\u0443\u0434\u0438\u043a\u043e\u0432\u0430\u043d\u0438"
    ],
    "name:ukr_x_preferred":[
        "\u0411\u0443\u0434\u0456\u043a\u043e\u0432\u0430\u043d\u0438"
    ],
    "name:war_x_preferred":[
        "Budikovany"
    ],
    "wof:name":"Budikovany",
    "wof:placetype":"locality"
},
  "geometry": {"coordinates":[20.08824,48.48842],"type":"Point"}
}