{
  "type": "Feature",
  "properties": {
    "gn:admin1_code":"03",
    "gn:asciiname":"Frantiskov Dvor",
    "gn:country_code":"SK",
    "gn:dem":238,
    "gn:feature_class":"P",
    "gn:feature_code":"PPL",
    "gn:name":"Franti\u0161kov Dvor",
    "gn:population":0,
    "gn:timezone":"Europe/Bratislava",
    "iso:country":"SK",
    "name:und_x_variant":[
        "Ferenc Tanya",
        "Franti\u0161kov Dvor"
    ],
    "wof:name":"Frantiskov Dvor",
    "wof:placetype":"locality"
},
  "geometry": {"coordinates":[21.13932,48.61276],"type":"Point"}
}