{
  "type": "Feature",
  "properties": {
    "gn:admin1_code":"05",
    "gn:asciiname":"Hubosovce",
    "gn:country_code":"SK",
    "gn:dem":355,
    "gn:feature_class":"P",
    "gn:feature_code":"PPL",
    "gn:name":"Hubo\u0161ovce",
    "gn:population":0,
    "gn:timezone":"Europe/Bratislava",
    "iso:country":"SK",
    "name:und_x_variant":[
        "Gombo\u0161ovce",
        "Hubo\u0161ovce"
    ],
    "wof:name":"Hubosovce",
    "wof:placetype":"locality"
},
  "geometry": {"coordinates":[21.20545,49.09644],"type":"Point"}
}