{
  "type": "Feature",
  "properties": {
    "gn:country":"SK",
    "gn:fcode":"PPL",
    "gn:population":0,
    "iso:country":"SK",
    "name:cat_x_preferred":[
        "Jasov\u00e1"
    ],
    "name:ces_x_preferred":[
        "Jasov\u00e1"
    ],
    "name:che_x_preferred":[
        "\u042f\u0441\u043e\u0432\u0430"
    ],
    "name:deu_x_preferred":[
        "Jasov\u00e1"
    ],
    "name:eng_x_preferred":[
        "Jasov\u00e1"
    ],
    "name:epo_x_preferred":[
        "Jasov\u00e1"
    ],
    "name:eus_x_preferred":[
        "Jasov\u00e1"
    ],
    "name:fra_x_preferred":[
        "Jasov\u00e1"
    ],
    "name:gle_x_preferred":[
        "Jasov\u00e1"
    ],
    "name:hun_x_preferred":[
        "J\u00e1szfalu"
    ],
    "name:ita_x_preferred":[
        "Jasov\u00e1"
    ],
    "name:msa_x_preferred":[
        "Jasov\u00e1"
    ],
    "name:nld_x_preferred":[
        "Jasov\u00e1"
    ],
    "name:pol_x_preferred":[
        "Nadbanske"
    ],
    "name:pol_x_variant":[
        "Jasov\u00e1"
    ],
    "name:por_x_preferred":[
        "Jasov\u00e1"
    ],
    "name:ron_x_preferred":[
        "Jasov\u00e1"
    ],
    "name:slk_x_preferred":[
        "Jasov\u00e1"
    ],
    "name:spa_x_preferred":[
        "Jasov\u00e1"
    ],
    "name:srp_x_preferred":[
        "\u0408\u0430\u0441\u043e\u0432\u0430"
    ],
    "name:tat_x_preferred":[
        "\u042f\u0441\u043e\u0432\u0430"
    ],
    "name:ukr_x_preferred":[
        "\u042f\u0441\u043e\u0432\u0430"
    ],
    "name:war_x_preferred":[
        "Jasov\u00e1"
    ],
    "qs_pg:aaroncc":"SK",
    "qs_pg:gn_country":"SK",
    "qs_pg:gn_fcode":"PPL",
    "qs_pg:gn_pop":0,
    "qs_pg:name":"J\u00e1sov\u00e1",
    "qs_pg:name_adm0":"Slovensk\u00e1",
    "qs_pg:name_adm1":"Nitriansky",
    "qs_pg:photos_9r":0,
    "qs_pg:photos_sr":0,
    "qs_pg:pop_sr":0,
    "qs_pg:qs_pg_placetype":"locality",
    "qs_pg:qs_pg_placetype_gp":"Town",
    "qs_pg:woe_adm0":23424877,
    "woe:adm0_id":23424877,
    "woe:name_adm0":"Slovensk\u00e1",
    "woe:name_adm1":"Nitriansky",
    "woe:placetype":"Town",
    "wof:name":"J\u00e1sov\u00e1",
    "wof:placetype":"locality"
},
  "geometry": {"coordinates":[18.39712,47.989],"type":"Point"}
}