{
  "type": "Feature",
  "properties": {
    "gn:admin1_code":"05",
    "gn:asciiname":"Vysny Hrabovec",
    "gn:country_code":"SK",
    "gn:dem":180,
    "gn:feature_class":"P",
    "gn:feature_code":"PPL",
    "gn:name":"Vy\u0161n\u00fd Hrabovec",
    "gn:population":0,
    "gn:timezone":"Europe/Bratislava",
    "iso:country":"SK",
    "name:cat_x_preferred":[
        "Vy\u0161n\u00fd Hrabovec"
    ],
    "name:ces_x_preferred":[
        "Vy\u0161n\u00fd Hrabovec"
    ],
    "name:epo_x_preferred":[
        "Vy\u0161n\u00fd Hrabovec"
    ],
    "name:eus_x_preferred":[
        "Vy\u0161n\u00fd Hrabovec"
    ],
    "name:fra_x_preferred":[
        "Vy\u0161n\u00fd Hrabovec"
    ],
    "name:hun_x_preferred":[
        "Kisgyerty\u00e1nos"
    ],
    "name:ita_x_preferred":[
        "Vy\u0161n\u00fd Hrabovec"
    ],
    "name:msa_x_preferred":[
        "Vy\u0161n\u00fd Hrabovec"
    ],
    "name:nld_x_preferred":[
        "Vy\u0161n\u00fd Hrabovec"
    ],
    "name:pol_x_preferred":[
        "Vy\u0161n\u00fd Hrabovec"
    ],
    "name:ron_x_preferred":[
        "Vy\u0161n\u00fd Hrabovec"
    ],
    "name:rue_x_preferred":[
        "\u0412\u044b\u0448\u043d\u0457\u0439 \u0413\u0440\u0430\u0431\u043e\u0432\u0435\u0446\u044c"
    ],
    "name:slk_x_preferred":[
        "Vy\u0161n\u00fd Hrabovec"
    ],
    "name:spa_x_preferred":[
        "Vy\u0161n\u00fd Hrabovec"
    ],
    "name:srp_x_preferred":[
        "\u0412\u0438\u0448\u043d\u0438 \u0425\u0440\u0430\u0431\u043e\u0432\u0435\u0446"
    ],
    "name:ukr_x_preferred":[
        "\u0412\u0438\u0448\u043d\u0456\u0439 \u0413\u0440\u0430\u0431\u043e\u0432\u0435\u0446\u044c"
    ],
    "name:war_x_preferred":[
        "Vy\u0161n\u00fd Hrabovec"
    ],
    "wof:name":"Vysny Hrabovec",
    "wof:placetype":"locality"
},
  "geometry": {"coordinates":[21.68771,49.08924],"type":"Point"}
}