{
  "type": "Feature",
  "properties": {
    "gn:admin1_code":"05",
    "gn:asciiname":"Vysny Hrabovec",
    "gn:country_code":"SK",
    "gn:dem":180,
    "gn:feature_class":"P",
    "gn:feature_code":"PPL",
    "gn:name":"Vy\u0161n\u00fd Hrabovec",
    "gn:population":0,
    "gn:timezone":"Europe/Bratislava",
    "iso:country":"SK",
    "name:und_x_variant":[
        "Vy\u0161n\u00fd Hrabovec"
    ],
    "wof:name":"Vysny Hrabovec",
    "wof:placetype":"locality"
},
  "geometry": {"coordinates":[21.68771,49.08924],"type":"Point"}
}