{
  "type": "Feature",
  "properties": {
    "gn:admin1_code":"04",
    "gn:asciiname":"Pustatina Rozmarin",
    "gn:country_code":"SK",
    "gn:dem":185,
    "gn:feature_class":"P",
    "gn:feature_code":"PPL",
    "gn:name":"Pustatina Rozmar\u00edn",
    "gn:population":0,
    "gn:timezone":"Europe/Bratislava",
    "iso:country":"SK",
    "wof:name":"Pustatina Rozmarin",
    "wof:placetype":"locality"
},
  "geometry": {"coordinates":[18.75421,48.00659],"type":"Point"}
}