{
  "type": "Feature",
  "properties": {
    "gn:admin1_code":"08",
    "gn:asciiname":"Suja",
    "gn:country_code":"SK",
    "gn:dem":467,
    "gn:feature_class":"P",
    "gn:feature_code":"PPL",
    "gn:name":"\u0160uja",
    "gn:population":0,
    "gn:timezone":"Europe/Bratislava",
    "iso:country":"SK",
    "name:und_x_variant":[
        "\u0160uja"
    ],
    "wof:name":"Suja",
    "wof:placetype":"locality"
},
  "geometry": {"coordinates":[18.62874,49.06943],"type":"Point"}
}