{
  "type": "Feature",
  "properties": {
    "gn:admin1_code":"08",
    "gn:asciiname":"Suja",
    "gn:country_code":"SK",
    "gn:dem":467,
    "gn:feature_class":"P",
    "gn:feature_code":"PPL",
    "gn:name":"\u0160uja",
    "gn:population":0,
    "gn:timezone":"Europe/Bratislava",
    "iso:country":"SK",
    "name:cat_x_preferred":[
        "\u0160uja"
    ],
    "name:ces_x_preferred":[
        "\u0160uja"
    ],
    "name:deu_x_preferred":[
        "\u0160uja"
    ],
    "name:epo_x_preferred":[
        "\u0160uja"
    ],
    "name:eus_x_preferred":[
        "\u0160uja"
    ],
    "name:fra_x_preferred":[
        "\u0160uja"
    ],
    "name:hun_x_preferred":[
        "Suja"
    ],
    "name:ita_x_preferred":[
        "\u0160uja"
    ],
    "name:msa_x_preferred":[
        "\u0160uja"
    ],
    "name:nld_x_preferred":[
        "\u0160uja"
    ],
    "name:pol_x_preferred":[
        "\u0160uja"
    ],
    "name:ron_x_preferred":[
        "\u0160uja"
    ],
    "name:slk_x_preferred":[
        "\u0160uja"
    ],
    "name:spa_x_preferred":[
        "\u0160uja"
    ],
    "name:srp_x_preferred":[
        "\u0428\u0443\u0458\u0430"
    ],
    "name:war_x_preferred":[
        "\u0160uja"
    ],
    "wof:name":"Suja",
    "wof:placetype":"locality"
},
  "geometry": {"coordinates":[18.62874,49.06943],"type":"Point"}
}