{
  "type": "Feature",
  "properties": {
    "gn:admin1_code":"03",
    "gn:asciiname":"Nadabula",
    "gn:country_code":"SK",
    "gn:dem":294,
    "gn:feature_class":"P",
    "gn:feature_code":"PPL",
    "gn:name":"Nadabula",
    "gn:population":0,
    "gn:timezone":"Europe/Bratislava",
    "iso:country":"SK",
    "wof:name":"Nadabula",
    "wof:placetype":"locality"
},
  "geometry": {"coordinates":[20.51853,48.67775],"type":"Point"}
}