{
  "type": "Feature",
  "properties": {
    "gn:gn_country":"SK",
    "gn:gn_fcode":"PPL",
    "gn:gn_pop":0,
    "iso:country":"SK",
    "name:cat_x_preferred":[
        "Nov\u00fd \u017divot"
    ],
    "name:deu_x_preferred":[
        "Nov\u00fd \u017divot"
    ],
    "name:eng_x_preferred":[
        "Nov\u00fd \u017divot"
    ],
    "name:epo_x_preferred":[
        "Nov\u00fd \u017divot"
    ],
    "name:fra_x_preferred":[
        "Nov\u00fd \u017divot"
    ],
    "name:hun_x_preferred":[
        "Ill\u00e9sh\u00e1za"
    ],
    "name:ita_x_preferred":[
        "Nov\u00fd \u017divot"
    ],
    "name:msa_x_preferred":[
        "Nov\u00fd \u017divot"
    ],
    "name:nan_x_preferred":[
        "Nov\u00fd \u017divot"
    ],
    "name:nld_x_preferred":[
        "Nov\u00fd \u017divot"
    ],
    "name:por_x_preferred":[
        "Nov\u00fd \u017divot"
    ],
    "name:slk_x_preferred":[
        "Nov\u00fd \u017divot"
    ],
    "name:srp_x_preferred":[
        "\u041d\u043e\u0432\u0438 \u0416\u0438\u0432\u043e\u0442"
    ],
    "name:unk_x_variant":[
        "Ill\u00e9sh\u00e1za"
    ],
    "name:war_x_preferred":[
        "Nov\u00fd \u017divot"
    ],
    "qs_pg:aaroncc":"SK",
    "qs_pg:gn_country":"SK",
    "qs_pg:gn_fcode":"PPL",
    "qs_pg:gn_pop":0,
    "qs_pg:name":"Eli\u00e1\u0161ovce",
    "qs_pg:name_adm0":"Slovensk\u00e1",
    "qs_pg:name_adm1":"Trnavsky",
    "qs_pg:photos_9r":0,
    "qs_pg:photos_sr":0,
    "qs_pg:pop_sr":0,
    "qs_pg:qs_pg_placetype":"locality",
    "qs_pg:qs_pg_placetype_gp":"Town",
    "qs_pg:woe_adm0":23424877,
    "woe:adm0_id":23424877,
    "woe:name_adm0":"Slovensk\u00e1",
    "woe:name_adm1":"Trnavsky",
    "woe:placetype":"Town",
    "wof:name":"Eli\u00e1\u0161ovce",
    "wof:placetype":"locality"
},
  "geometry": {"coordinates":[17.46708,48.12305],"type":"Point"}
}