{
  "type": "Feature",
  "properties": {
    "gn:admin1_code":"08",
    "gn:asciiname":"Lavkovo",
    "gn:country_code":"SK",
    "gn:dem":596,
    "gn:feature_class":"P",
    "gn:feature_code":"PPL",
    "gn:name":"Lavkovo",
    "gn:population":0,
    "gn:timezone":"Europe/Bratislava",
    "iso:country":"SK",
    "wof:name":"Lavkovo",
    "wof:placetype":"locality"
},
  "geometry": {"coordinates":[19.55,49.38333],"type":"Point"}
}