{
  "type": "Feature",
  "properties": {
    "gn:admin1_code":"04",
    "gn:asciiname":"Gurinovce",
    "gn:country_code":"SK",
    "gn:dem":371,
    "gn:feature_class":"P",
    "gn:feature_code":"PPL",
    "gn:name":"Gurinovce",
    "gn:population":0,
    "gn:timezone":"Europe/Bratislava",
    "iso:country":"SK",
    "wof:name":"Gurinovce",
    "wof:placetype":"locality"
},
  "geometry": {"coordinates":[18.24453,49.19366],"type":"Point"}
}