{
  "type": "Feature",
  "properties": {
    "gn:admin1_code":"03",
    "gn:asciiname":"Ochtina",
    "gn:country_code":"SK",
    "gn:dem":333,
    "gn:feature_class":"P",
    "gn:feature_code":"PPL",
    "gn:name":"Ochtin\u00e1",
    "gn:population":0,
    "gn:timezone":"Europe/Bratislava",
    "iso:country":"SK",
    "name:cat_x_preferred":[
        "Ochtin\u00e1"
    ],
    "name:ces_x_preferred":[
        "Ochtin\u00e1"
    ],
    "name:deu_x_preferred":[
        "Ochtin\u00e1"
    ],
    "name:epo_x_preferred":[
        "Ochtin\u00e1"
    ],
    "name:eus_x_preferred":[
        "Ochtin\u00e1"
    ],
    "name:fra_x_preferred":[
        "Ochtin\u00e1"
    ],
    "name:hun_x_preferred":[
        "Martonh\u00e1za"
    ],
    "name:ita_x_preferred":[
        "Ochtin\u00e1"
    ],
    "name:msa_x_preferred":[
        "Ochtin\u00e1"
    ],
    "name:nld_x_preferred":[
        "Ochtin\u00e1"
    ],
    "name:pol_x_preferred":[
        "Ochtyna"
    ],
    "name:ron_x_preferred":[
        "Ochtin\u00e1"
    ],
    "name:slk_x_preferred":[
        "Ochtin\u00e1"
    ],
    "name:spa_x_preferred":[
        "Ochtin\u00e1"
    ],
    "name:srp_x_preferred":[
        "\u041e\u0445\u0442\u0438\u043d\u0430"
    ],
    "name:ukr_x_preferred":[
        "\u041e\u0445\u0442\u0456\u043d\u0430"
    ],
    "name:und_x_variant":[
        "Ochtin\u00e1"
    ],
    "name:war_x_preferred":[
        "Ochtin\u00e1"
    ],
    "wof:name":"Ochtina",
    "wof:placetype":"locality"
},
  "geometry": {"coordinates":[20.32745,48.68413],"type":"Point"}
}