{
  "type": "Feature",
  "properties": {
    "gn:admin1_code":"04",
    "gn:asciiname":"Zemiansky Kvasov",
    "gn:country_code":"SK",
    "gn:dem":343,
    "gn:feature_class":"P",
    "gn:feature_code":"PPL",
    "gn:name":"Zemiansky Kva\u0161ov",
    "gn:population":0,
    "gn:timezone":"Europe/Bratislava",
    "iso:country":"SK",
    "name:hun_x_preferred":[
        "Nemeskvass\u00f3"
    ],
    "name:hun_x_variant":[
        "Kvass\u00f3",
        "Nemes-Kvass\u00f3",
        "Nemeskv\u00e1so"
    ],
    "name:und_x_variant":[
        "Zemiansky Kva\u0161ov"
    ],
    "wof:name":"Zemiansky Kvasov",
    "wof:placetype":"locality"
},
  "geometry": {"coordinates":[18.47816,49.08575],"type":"Point"}
}