{
  "type": "Feature",
  "properties": {
    "gn:admin1_code":"04",
    "gn:asciiname":"Hostina",
    "gn:country_code":"SK",
    "gn:dem":410,
    "gn:feature_class":"P",
    "gn:feature_code":"PPL",
    "gn:name":"Ho\u0161tin\u00e1",
    "gn:population":0,
    "gn:timezone":"Europe/Bratislava",
    "iso:country":"SK",
    "wof:name":"Hostina",
    "wof:placetype":"locality"
},
  "geometry": {"coordinates":[18.33285,49.16715],"type":"Point"}
}