{
  "type": "Feature",
  "properties": {
    "gn:admin1_code":"04",
    "gn:asciiname":"Velcice",
    "gn:country_code":"SK",
    "gn:dem":223,
    "gn:feature_class":"P",
    "gn:feature_code":"PPL",
    "gn:name":"Vel\u010dice",
    "gn:population":0,
    "gn:timezone":"Europe/Bratislava",
    "iso:country":"SK",
    "name:und_x_variant":[
        "Vel\u010dice"
    ],
    "wof:name":"Velcice",
    "wof:placetype":"locality"
},
  "geometry": {"coordinates":[18.30393,48.41432],"type":"Point"}
}