{
  "type": "Feature",
  "properties": {
    "gn:admin1_code":"04",
    "gn:asciiname":"Velcice",
    "gn:country_code":"SK",
    "gn:dem":223,
    "gn:feature_class":"P",
    "gn:feature_code":"PPL",
    "gn:name":"Vel\u010dice",
    "gn:population":0,
    "gn:timezone":"Europe/Bratislava",
    "iso:country":"SK",
    "name:cat_x_preferred":[
        "Vel\u010dice"
    ],
    "name:ces_x_preferred":[
        "Vel\u010dice"
    ],
    "name:deu_x_preferred":[
        "Vel\u010dice"
    ],
    "name:epo_x_preferred":[
        "Vel\u010dice"
    ],
    "name:eus_x_preferred":[
        "Vel\u010dice"
    ],
    "name:fra_x_preferred":[
        "Vel\u010dice"
    ],
    "name:hun_x_preferred":[
        "Vels\u00e9c"
    ],
    "name:ita_x_preferred":[
        "Vel\u010dice"
    ],
    "name:msa_x_preferred":[
        "Vel\u010dice"
    ],
    "name:nld_x_preferred":[
        "Vel\u010dice"
    ],
    "name:ron_x_preferred":[
        "Vel\u010dice"
    ],
    "name:slk_x_preferred":[
        "Vel\u010dice"
    ],
    "name:spa_x_preferred":[
        "Vel\u010dice"
    ],
    "name:srp_x_preferred":[
        "\u0412\u0435\u043b\u0447\u0438\u0446\u0435"
    ],
    "name:ukr_x_preferred":[
        "\u0412\u0435\u043b\u0447\u0456\u0446\u0435"
    ],
    "name:war_x_preferred":[
        "Vel\u010dice"
    ],
    "wof:name":"Velcice",
    "wof:placetype":"locality"
},
  "geometry": {"coordinates":[18.30393,48.41432],"type":"Point"}
}