{
  "type": "Feature",
  "properties": {
    "gn:admin1_code":"00",
    "gn:asciiname":"Trebule",
    "gn:country_code":"SK",
    "gn:dem":865,
    "gn:feature_class":"P",
    "gn:feature_code":"PPL",
    "gn:name":"Trebule",
    "gn:population":0,
    "gn:timezone":"Europe/Bratislava",
    "iso:country":"SK",
    "wof:name":"Trebule",
    "wof:placetype":"locality"
},
  "geometry": {"coordinates":[18.42556,49.34217],"type":"Point"}
}