{
  "type": "Feature",
  "properties": {
    "gn:gn_country":"SK",
    "gn:gn_fcode":"PPL",
    "gn:gn_pop":0,
    "iso:country":"SK",
    "name:cat_x_preferred":[
        "Horn\u00e1 \u0160tub\u0148a"
    ],
    "name:ces_x_preferred":[
        "Horn\u00e1 \u0160tub\u0148a"
    ],
    "name:deu_x_preferred":[
        "Ober-Stuben"
    ],
    "name:deu_x_variant":[
        "Horn\u00e1 \u0160tub\u0148a"
    ],
    "name:eng_x_preferred":[
        "Horn\u00e1 \u0160tub\u0148a"
    ],
    "name:epo_x_preferred":[
        "Horn\u00e1 \u0160tub\u0148a"
    ],
    "name:fra_x_preferred":[
        "Horn\u00e1 \u0160tub\u0148a"
    ],
    "name:hun_x_preferred":[
        "Fels\u0151stubnya"
    ],
    "name:ita_x_preferred":[
        "Horn\u00e1 \u0160tub\u0148a"
    ],
    "name:msa_x_preferred":[
        "Horn\u00e1 \u0160tub\u0148a"
    ],
    "name:nld_x_preferred":[
        "Horn\u00e1 \u0160tub\u0148a"
    ],
    "name:pol_x_preferred":[
        "Horn\u00e1 \u0160tub\u0148a"
    ],
    "name:slk_x_preferred":[
        "Horn\u00e1 \u0160tub\u0148a"
    ],
    "name:srp_x_preferred":[
        "\u0425\u043e\u0440\u043d\u0430 \u0428\u0442\u0443\u0431\u045a\u0430"
    ],
    "name:unk_x_variant":[
        "Hornia Stub\u0148a"
    ],
    "name:war_x_preferred":[
        "Horn\u00e1 \u0160tub\u0148a"
    ],
    "qs_pg:aaroncc":"SK",
    "qs_pg:gn_country":"SK",
    "qs_pg:gn_fcode":"PPL",
    "qs_pg:gn_pop":0,
    "qs_pg:name":"Horna Stubna",
    "qs_pg:name_adm0":"Slovensk\u00e1",
    "qs_pg:name_adm1":"Zilinsky",
    "qs_pg:photos_9k":1,
    "qs_pg:photos_9r":4,
    "qs_pg:photos_all":184,
    "qs_pg:photos_sr":0,
    "qs_pg:pop_sr":0,
    "qs_pg:qs_pg_placetype":"locality",
    "qs_pg:qs_pg_placetype_gp":"Town",
    "qs_pg:woe_adm0":23424877,
    "woe:adm0_id":23424877,
    "woe:name_adm0":"Slovensk\u00e1",
    "woe:name_adm1":"Zilinsky",
    "woe:placetype":"Town",
    "wof:name":"Horna Stubna",
    "wof:placetype":"locality"
},
  "geometry": {"coordinates":[18.88462,48.82505],"type":"Point"}
}