{
  "type": "Feature",
  "properties": {
    "gn:asciiname":"Studienka",
    "gn:country_code":"SK",
    "gn:dem":108,
    "gn:feature_class":"P",
    "gn:feature_code":"PPLL",
    "gn:name":"Studienka",
    "gn:population":0,
    "gn:timezone":"Europe/Bratislava",
    "iso:country":"SK",
    "wof:name":"Studienka",
    "wof:placetype":"locality"
},
  "geometry": {"coordinates":[17.88918,47.97464],"type":"Point"}
}