{
  "type": "Feature",
  "properties": {
    "gn:asciiname":"Studienka",
    "gn:country_code":"SK",
    "gn:dem":108,
    "gn:feature_class":"P",
    "gn:feature_code":"PPLL",
    "gn:name":"Studienka",
    "gn:population":0,
    "gn:timezone":"Europe/Bratislava",
    "iso:country":"SK",
    "name:cat_x_preferred":[
        "Studienka"
    ],
    "name:ces_x_preferred":[
        "Studienka"
    ],
    "name:deu_x_preferred":[
        "Studienka"
    ],
    "name:epo_x_preferred":[
        "Studienka"
    ],
    "name:eus_x_preferred":[
        "Studienka"
    ],
    "name:fra_x_preferred":[
        "Studienka"
    ],
    "name:hun_x_preferred":[
        "Szentistv\u00e1nk\u00fat"
    ],
    "name:ita_x_preferred":[
        "Studienka"
    ],
    "name:msa_x_preferred":[
        "Studienka"
    ],
    "name:nld_x_preferred":[
        "Studienka"
    ],
    "name:por_x_preferred":[
        "Studienka"
    ],
    "name:ron_x_preferred":[
        "Studienka"
    ],
    "name:slk_x_preferred":[
        "Studienka"
    ],
    "name:spa_x_preferred":[
        "Studienka"
    ],
    "name:srp_x_preferred":[
        "\u0421\u0442\u0443\u0434\u0458\u0435\u043d\u043a\u0430"
    ],
    "name:war_x_preferred":[
        "Studienka"
    ],
    "wof:name":"Studienka",
    "wof:placetype":"locality"
},
  "geometry": {"coordinates":[17.88918,47.97464],"type":"Point"}
}