{
  "type": "Feature",
  "properties": {
    "gn:population":4402,
    "iso:country":"SK",
    "name:ara_x_preferred":[
        "\u0646\u0648\u0641\u0627\u0643\u064a"
    ],
    "name:arz_x_preferred":[
        "\u0646\u0648\u0641\u0627\u0643\u0649"
    ],
    "name:ast_x_preferred":[
        "Nov\u00e1ky"
    ],
    "name:cat_x_preferred":[
        "Nov\u00e1ky"
    ],
    "name:ceb_x_preferred":[
        "Nov\u00e1ky"
    ],
    "name:ces_x_preferred":[
        "Nov\u00e1ky"
    ],
    "name:dan_x_preferred":[
        "Nov\u00e1ky"
    ],
    "name:deu_x_preferred":[
        "Nov\u00e1ky"
    ],
    "name:eng_x_preferred":[
        "Nov\u00e1ky"
    ],
    "name:epo_x_preferred":[
        "Nov\u00e1ky"
    ],
    "name:est_x_preferred":[
        "Nov\u00e1ky"
    ],
    "name:eus_x_preferred":[
        "Nov\u00e1ky"
    ],
    "name:fas_x_preferred":[
        "\u0646\u0648\u0627\u06a9\u06cc"
    ],
    "name:fra_x_preferred":[
        "Nov\u00e1ky"
    ],
    "name:gle_x_preferred":[
        "Nov\u00e1ky"
    ],
    "name:heb_x_preferred":[
        "\u05e0\u05d5\u05d1\u05e7\u05d9"
    ],
    "name:hrv_x_preferred":[
        "Nov\u00e1ky"
    ],
    "name:hun_x_preferred":[
        "Nyitranov\u00e1k"
    ],
    "name:ita_x_preferred":[
        "Nov\u00e1ky"
    ],
    "name:lav_x_preferred":[
        "Nov\u0101ki"
    ],
    "name:msa_x_preferred":[
        "Nov\u00e1ky"
    ],
    "name:nan_x_preferred":[
        "Nov\u00e1ky"
    ],
    "name:nld_x_preferred":[
        "Nov\u00e1ky"
    ],
    "name:pol_x_preferred":[
        "Nov\u00e1ky"
    ],
    "name:por_x_preferred":[
        "Nov\u00e1ky"
    ],
    "name:ron_x_preferred":[
        "Nov\u00e1ky"
    ],
    "name:rus_x_preferred":[
        "\u041d\u043e\u0432\u0430\u043a\u0438"
    ],
    "name:slk_x_preferred":[
        "Nov\u00e1ky"
    ],
    "name:spa_x_preferred":[
        "Nov\u00e1ky"
    ],
    "name:srp_x_preferred":[
        "\u041d\u043e\u0432\u0430\u043a\u0438"
    ],
    "name:tat_x_preferred":[
        "\u041d\u043e\u0432\u0430\u043a\u0438"
    ],
    "name:tur_x_preferred":[
        "Nov\u00e1ky"
    ],
    "name:ukr_x_preferred":[
        "\u041d\u043e\u0432\u0430\u043a\u0438"
    ],
    "name:und_x_variant":[
        "Navaky"
    ],
    "name:urd_x_preferred":[
        "\u0646\u0648\u0627\u06a9\u06d2"
    ],
    "name:war_x_preferred":[
        "Nov\u00e1ky"
    ],
    "name:zho_x_preferred":[
        "\u8afe\u74e6\u57fa"
    ],
    "qs:a0":"Slovensko",
    "qs:a1":"*Trenciansky kraj",
    "qs:a1r":"0",
    "qs:a2":"Prievidza",
    "qs:adm0":"Slovensko",
    "qs:la_lc":"*",
    "qs:level":"locality",
    "qs:loc":"Nov\u00e1ky",
    "qs:loc_alt":"Novaky",
    "qs:pop":0,
    "qs:type":"buffered point",
    "wd:wordcount":217,
    "wof:name":"Nov\u00e1ky",
    "wof:placetype":"locality",
    "wof:population":4402
},
  "geometry": {"coordinates":[18.556938,48.728993],"type":"Point"}
}