{
  "type": "Feature",
  "properties": {
    "gn:admin1_code":"03",
    "gn:asciiname":"Krivost'any",
    "gn:country_code":"SK",
    "gn:dem":143,
    "gn:feature_class":"P",
    "gn:feature_code":"PPL",
    "gn:name":"Krivo\u0161\u0165any",
    "gn:population":0,
    "gn:timezone":"Europe/Bratislava",
    "iso:country":"SK",
    "wof:name":"Krivost'any",
    "wof:placetype":"locality"
},
  "geometry": {"coordinates":[21.85246,48.88051],"type":"Point"}
}