{
  "type": "Feature",
  "properties": {
    "gn:admin1_code":"01",
    "gn:asciiname":"Nizna Kalosa",
    "gn:country_code":"SK",
    "gn:dem":184,
    "gn:feature_class":"P",
    "gn:feature_code":"PPL",
    "gn:name":"Ni\u017en\u00e1 Kalo\u0161a",
    "gn:population":0,
    "gn:timezone":"Europe/Bratislava",
    "iso:country":"SK",
    "name:und_x_variant":[
        "Als\u00f3-K\u00e1losa",
        "Ni\u017en\u00ed K\u00e1lo\u0161a",
        "Ni\u017enia K\u00e1lo\u0161a",
        "Ni\u017en\u00e1 Kalo\u0161a"
    ],
    "wof:name":"Nizna Kalosa",
    "wof:placetype":"locality"
},
  "geometry": {"coordinates":[20.22525,48.42287],"type":"Point"}
}