{
  "type": "Feature",
  "properties": {
    "gn:admin1_code":"04",
    "gn:asciiname":"Betlehem",
    "gn:country_code":"SK",
    "gn:dem":366,
    "gn:feature_class":"P",
    "gn:feature_code":"PPL",
    "gn:name":"Betlehem",
    "gn:population":0,
    "gn:timezone":"Europe/Bratislava",
    "iso:country":"SK",
    "name:und_x_variant":[
        "Dvor Betlehem",
        "Betlehem"
    ],
    "wof:name":"Betlehem",
    "wof:placetype":"locality"
},
  "geometry": {"coordinates":[18.61667000000001,48.71667],"type":"Point"}
}