{
  "type": "Feature",
  "properties": {
    "gn:admin1_code":"03",
    "gn:asciiname":"Svinica",
    "gn:country_code":"SK",
    "gn:dem":256,
    "gn:feature_class":"P",
    "gn:feature_code":"PPL",
    "gn:name":"Svinica",
    "gn:population":0,
    "gn:timezone":"Europe/Bratislava",
    "iso:country":"SK",
    "name:cat_x_preferred":[
        "Svinica"
    ],
    "name:deu_x_preferred":[
        "Svinica"
    ],
    "name:epo_x_preferred":[
        "Svinica"
    ],
    "name:eus_x_preferred":[
        "Svinica"
    ],
    "name:hun_x_preferred":[
        "Pet\u0151szinye"
    ],
    "name:ita_x_preferred":[
        "Svinica"
    ],
    "name:msa_x_preferred":[
        "Svinica"
    ],
    "name:nld_x_preferred":[
        "Svinica"
    ],
    "name:pol_x_preferred":[
        "Svinica"
    ],
    "name:ron_x_preferred":[
        "Svinica"
    ],
    "name:slk_x_preferred":[
        "Svinica"
    ],
    "name:spa_x_preferred":[
        "Svinica"
    ],
    "name:srp_x_preferred":[
        "\u0421\u0432\u0438\u045a\u0438\u0446\u0430"
    ],
    "name:ukr_x_preferred":[
        "\u0421\u0432\u0456\u043d\u0438\u0446\u044f"
    ],
    "name:war_x_preferred":[
        "Svinica"
    ],
    "wof:name":"Svinica",
    "wof:placetype":"locality"
},
  "geometry": {"coordinates":[21.46633,48.73482],"type":"Point"}
}