{
  "type": "Feature",
  "properties": {
    "gn:admin1_code":"03",
    "gn:asciiname":"Svinica",
    "gn:country_code":"SK",
    "gn:dem":256,
    "gn:feature_class":"P",
    "gn:feature_code":"PPL",
    "gn:name":"Svinica",
    "gn:population":0,
    "gn:timezone":"Europe/Bratislava",
    "iso:country":"SK",
    "wof:name":"Svinica",
    "wof:placetype":"locality"
},
  "geometry": {"coordinates":[21.46633,48.73482],"type":"Point"}
}