{
  "type": "Feature",
  "properties": {
    "gn:admin1_code":"05",
    "gn:asciiname":"Potocky",
    "gn:country_code":"SK",
    "gn:dem":257,
    "gn:feature_class":"P",
    "gn:feature_code":"PPL",
    "gn:name":"Pot\u00f4\u010dky",
    "gn:population":0,
    "gn:timezone":"Europe/Bratislava",
    "iso:country":"SK",
    "name:cat_x_preferred":[
        "Pot\u00f4\u010dky"
    ],
    "name:ces_x_preferred":[
        "Pot\u00f4\u010dky"
    ],
    "name:epo_x_preferred":[
        "Pot\u00f4\u010dky"
    ],
    "name:eus_x_preferred":[
        "Pot\u00f4\u010dky"
    ],
    "name:fra_x_preferred":[
        "Pot\u00f4\u010dky"
    ],
    "name:hun_x_preferred":[
        "\u00c9rfalu"
    ],
    "name:ita_x_preferred":[
        "Pot\u00f4\u010dky"
    ],
    "name:msa_x_preferred":[
        "Pot\u00f4\u010dky"
    ],
    "name:nld_x_preferred":[
        "Pot\u00f4\u010dky"
    ],
    "name:pol_x_preferred":[
        "Pot\u00f4\u010dky"
    ],
    "name:ron_x_preferred":[
        "Pot\u00f4\u010dky"
    ],
    "name:rue_x_preferred":[
        "\u041f\u043e\u0442\u0456\u0447\u043a\u044b"
    ],
    "name:slk_x_preferred":[
        "Pot\u00f4\u010dky"
    ],
    "name:spa_x_preferred":[
        "Pot\u00f4\u010dky"
    ],
    "name:srp_x_preferred":[
        "\u041f\u043e\u0442\u043e\u0447\u043a\u0438"
    ],
    "name:ukr_x_preferred":[
        "\u041f\u043e\u0442\u0456\u0447\u043a\u0438"
    ],
    "name:und_x_variant":[
        "Pot\u00f4\u010dky"
    ],
    "name:war_x_preferred":[
        "Pot\u00f4\u010dky"
    ],
    "wof:name":"Potocky",
    "wof:placetype":"locality"
},
  "geometry": {"coordinates":[21.71621,49.20951],"type":"Point"}
}