{
  "type": "Feature",
  "properties": {
    "gn:admin1_code":"05",
    "gn:asciiname":"Potocky",
    "gn:country_code":"SK",
    "gn:dem":257,
    "gn:feature_class":"P",
    "gn:feature_code":"PPL",
    "gn:name":"Pot\u00f4\u010dky",
    "gn:population":0,
    "gn:timezone":"Europe/Bratislava",
    "iso:country":"SK",
    "name:und_x_variant":[
        "Pot\u00f4\u010dky"
    ],
    "wof:name":"Potocky",
    "wof:placetype":"locality"
},
  "geometry": {"coordinates":[21.71621,49.20951],"type":"Point"}
}