{
  "type": "Feature",
  "properties": {
    "gn:gn_country":"SK",
    "gn:gn_fcode":"PPL",
    "gn:gn_pop":0,
    "iso:country":"SK",
    "name:cat_x_preferred":[
        "Obi\u0161ovce"
    ],
    "name:ces_x_preferred":[
        "Obi\u0161ovce"
    ],
    "name:deu_x_preferred":[
        "Obi\u0161ovce"
    ],
    "name:eng_x_preferred":[
        "Obi\u0161ovce"
    ],
    "name:epo_x_preferred":[
        "Obi\u0161ovce"
    ],
    "name:eus_x_preferred":[
        "Obi\u0161ovce"
    ],
    "name:fra_x_preferred":[
        "Obi\u0161ovce"
    ],
    "name:hun_x_preferred":[
        "Abos"
    ],
    "name:ita_x_preferred":[
        "Obi\u0161ovce"
    ],
    "name:msa_x_preferred":[
        "Obi\u0161ovce"
    ],
    "name:nan_x_preferred":[
        "Obi\u0161ovce"
    ],
    "name:nld_x_preferred":[
        "Obi\u0161ovce"
    ],
    "name:pol_x_preferred":[
        "Obi\u0161ovce"
    ],
    "name:ron_x_preferred":[
        "Obi\u0161ovce"
    ],
    "name:slk_x_preferred":[
        "Obi\u0161ovce"
    ],
    "name:spa_x_preferred":[
        "Obi\u0161ovce"
    ],
    "name:srp_x_preferred":[
        "\u041e\u0431\u0438\u0448\u043e\u0432\u0446\u0435"
    ],
    "name:ukr_x_preferred":[
        "\u041e\u0431\u0456\u0448\u043e\u0432\u0446\u0435"
    ],
    "name:unk_x_variant":[
        "Oby\u0161ovce"
    ],
    "name:war_x_preferred":[
        "Obi\u0161ovce"
    ],
    "name:war_x_variant":[
        "Rusk\u00e1"
    ],
    "qs_pg:aaroncc":"SK",
    "qs_pg:gn_country":"SK",
    "qs_pg:gn_fcode":"PPL",
    "qs_pg:gn_pop":0,
    "qs_pg:name":"Obi\u0161ovce",
    "qs_pg:name_adm0":"Slovensk\u00e1",
    "qs_pg:name_adm1":"Kosicky",
    "qs_pg:photos_9k":1,
    "qs_pg:photos_9r":1,
    "qs_pg:photos_all":1,
    "qs_pg:photos_sr":0,
    "qs_pg:pop_sr":0,
    "qs_pg:qs_pg_placetype":"locality",
    "qs_pg:qs_pg_placetype_gp":"Town",
    "qs_pg:woe_adm0":23424877,
    "woe:adm0_id":23424877,
    "woe:name_adm0":"Slovensk\u00e1",
    "woe:name_adm1":"Kosicky",
    "woe:placetype":"Town",
    "wof:name":"Obi\u0161ovce",
    "wof:placetype":"locality"
},
  "geometry": {"coordinates":[21.24008,48.86199],"type":"Point"}
}