{
  "type": "Feature",
  "properties": {
    "gn:admin1_code":"03",
    "gn:asciiname":"Silicka Jablonica",
    "gn:country_code":"SK",
    "gn:dem":239,
    "gn:feature_class":"P",
    "gn:feature_code":"PPL",
    "gn:name":"Silick\u00e1 Jablonica",
    "gn:population":0,
    "gn:timezone":"Europe/Bratislava",
    "iso:country":"SK",
    "name:und_x_variant":[
        "Jablonica",
        "Jablonca",
        "Silick\u00e1 Jablonica"
    ],
    "wof:name":"Silicka Jablonica",
    "wof:placetype":"locality"
},
  "geometry": {"coordinates":[20.60861,48.55826],"type":"Point"}
}