{
  "type": "Feature",
  "properties": {
    "gn:admin1_code":"03",
    "gn:asciiname":"Silicka Jablonica",
    "gn:country_code":"SK",
    "gn:dem":239,
    "gn:feature_class":"P",
    "gn:feature_code":"PPL",
    "gn:name":"Silick\u00e1 Jablonica",
    "gn:population":0,
    "gn:timezone":"Europe/Bratislava",
    "iso:country":"SK",
    "name:cat_x_preferred":[
        "Silick\u00e1 Jablonica"
    ],
    "name:epo_x_preferred":[
        "Silick\u00e1 Jablonica"
    ],
    "name:eus_x_preferred":[
        "Silick\u00e1 Jablonica"
    ],
    "name:fra_x_preferred":[
        "Silick\u00e1 Jablonica"
    ],
    "name:hun_x_preferred":[
        "Jablonca"
    ],
    "name:ita_x_preferred":[
        "Silick\u00e1 Jablonica"
    ],
    "name:msa_x_preferred":[
        "Silick\u00e1 Jablonica"
    ],
    "name:nld_x_preferred":[
        "Silick\u00e1 Jablonica"
    ],
    "name:pol_x_preferred":[
        "Silick\u00e1 Jablonica"
    ],
    "name:ron_x_preferred":[
        "Silick\u00e1 Jablonica"
    ],
    "name:slk_x_preferred":[
        "Silick\u00e1 Jablonica"
    ],
    "name:spa_x_preferred":[
        "Silick\u00e1 Jablonica"
    ],
    "name:srp_x_preferred":[
        "\u0421\u0438\u043b\u0438\u0446\u043a\u0430 \u0408\u0430\u0431\u043b\u043e\u045a\u0438\u0446\u0430"
    ],
    "name:ukr_x_preferred":[
        "\u0421\u0456\u043b\u0456\u0446\u043a\u0430 \u042f\u0431\u043b\u043e\u043d\u0456\u0446\u0430"
    ],
    "name:und_x_variant":[
        "Jablonica",
        "Jablonca",
        "Silick\u00e1 Jablonica"
    ],
    "name:war_x_preferred":[
        "Silick\u00e1 Jablonica"
    ],
    "wof:name":"Silicka Jablonica",
    "wof:placetype":"locality"
},
  "geometry": {"coordinates":[20.60861,48.55826],"type":"Point"}
}