{
  "type": "Feature",
  "properties": {
    "gn:admin1_code":"05",
    "gn:asciiname":"Sukov",
    "gn:country_code":"SK",
    "gn:dem":291,
    "gn:feature_class":"P",
    "gn:feature_code":"PPL",
    "gn:name":"Sukov",
    "gn:population":0,
    "gn:timezone":"Europe/Bratislava",
    "iso:country":"SK",
    "wof:name":"Sukov",
    "wof:placetype":"locality"
},
  "geometry": {"coordinates":[21.87455,49.21908],"type":"Point"}
}