{
  "type": "Feature",
  "properties": {
    "gn:admin1_code":"03",
    "gn:asciiname":"Strazne",
    "gn:country_code":"SK",
    "gn:dem":99,
    "gn:feature_class":"P",
    "gn:feature_code":"PPL",
    "gn:name":"Str\u00e1\u017en\u00e9",
    "gn:population":0,
    "gn:timezone":"Europe/Bratislava",
    "iso:country":"SK",
    "name:und_x_variant":[
        "\u00d6r\u00f6s",
        "Str\u00e1\u017en\u00e9"
    ],
    "wof:name":"Strazne",
    "wof:placetype":"locality"
},
  "geometry": {"coordinates":[21.86659,48.36587],"type":"Point"}
}