{
  "type": "Feature",
  "properties": {
    "gn:admin1_code":"01",
    "gn:asciiname":"Nikelberg",
    "gn:country_code":"SK",
    "gn:dem":370,
    "gn:feature_class":"P",
    "gn:feature_code":"PPL",
    "gn:name":"Nikelberg",
    "gn:population":0,
    "gn:timezone":"Europe/Bratislava",
    "iso:country":"SK",
    "name:und_x_variant":[
        "Niklberg",
        "Nikelberg"
    ],
    "wof:name":"Nikelberg",
    "wof:placetype":"locality"
},
  "geometry": {"coordinates":[19.06667,48.38333],"type":"Point"}
}