{
  "type": "Feature",
  "properties": {
    "gn:admin1_code":"04",
    "gn:asciiname":"Nedasovce",
    "gn:country_code":"SK",
    "gn:dem":206,
    "gn:feature_class":"P",
    "gn:feature_code":"PPL",
    "gn:name":"Neda\u0161ovce",
    "gn:population":0,
    "gn:timezone":"Europe/Bratislava",
    "iso:country":"SK",
    "name:und_x_variant":[
        "Neda\u0161ovce"
    ],
    "wof:name":"Nedasovce",
    "wof:placetype":"locality"
},
  "geometry": {"coordinates":[18.3139,48.66948],"type":"Point"}
}