{
  "type": "Feature",
  "properties": {
    "gn:admin1_code":"05",
    "gn:asciiname":"Osikov",
    "gn:country_code":"SK",
    "gn:dem":373,
    "gn:feature_class":"P",
    "gn:feature_code":"PPL",
    "gn:name":"Osikov",
    "gn:population":0,
    "gn:timezone":"Europe/Bratislava",
    "iso:country":"SK",
    "name:cat_x_preferred":[
        "Osikov"
    ],
    "name:ces_x_preferred":[
        "Osikov"
    ],
    "name:deu_x_preferred":[
        "Osikov"
    ],
    "name:epo_x_preferred":[
        "Osikov"
    ],
    "name:eus_x_preferred":[
        "Osikov"
    ],
    "name:fra_x_preferred":[
        "Osikov"
    ],
    "name:hun_x_preferred":[
        "Oszik\u00f3"
    ],
    "name:ita_x_preferred":[
        "Osikov"
    ],
    "name:msa_x_preferred":[
        "Osikov"
    ],
    "name:nld_x_preferred":[
        "Osikov"
    ],
    "name:pol_x_preferred":[
        "Osikov"
    ],
    "name:ron_x_preferred":[
        "Osikov"
    ],
    "name:rue_x_preferred":[
        "\u041e\u0441\u0456\u043a\u043e\u0432"
    ],
    "name:slk_x_preferred":[
        "Osikov"
    ],
    "name:spa_x_preferred":[
        "Osikov"
    ],
    "name:srp_x_preferred":[
        "\u041e\u0441\u0438\u043a\u043e\u0432"
    ],
    "name:ukr_x_preferred":[
        "\u041e\u0441\u0456\u043a\u043e\u0432"
    ],
    "name:war_x_preferred":[
        "Osikov"
    ],
    "wof:name":"Osikov",
    "wof:placetype":"locality"
},
  "geometry": {"coordinates":[21.26211,49.17463],"type":"Point"}
}