{
  "type": "Feature",
  "properties": {
    "gn:admin1_code":"05",
    "gn:asciiname":"Osikov",
    "gn:country_code":"SK",
    "gn:dem":373,
    "gn:feature_class":"P",
    "gn:feature_code":"PPL",
    "gn:name":"Osikov",
    "gn:population":0,
    "gn:timezone":"Europe/Bratislava",
    "iso:country":"SK",
    "wof:name":"Osikov",
    "wof:placetype":"locality"
},
  "geometry": {"coordinates":[21.26211,49.17463],"type":"Point"}
}