{
  "type": "Feature",
  "properties": {
    "gn:admin1_code":"04",
    "gn:asciiname":"Male Kozmalovce",
    "gn:country_code":"SK",
    "gn:dem":172,
    "gn:feature_class":"P",
    "gn:feature_code":"PPL",
    "gn:name":"Mal\u00e9 Kozm\u00e1lovce",
    "gn:population":0,
    "gn:timezone":"Europe/Bratislava",
    "iso:country":"SK",
    "name:cat_x_preferred":[
        "Mal\u00e9 Kozm\u00e1lovce"
    ],
    "name:epo_x_preferred":[
        "Mal\u00e9 Kozm\u00e1lovce"
    ],
    "name:eus_x_preferred":[
        "Mal\u00e9 Kozm\u00e1lovce"
    ],
    "name:fra_x_preferred":[
        "Mal\u00e9 Kozm\u00e1lovce"
    ],
    "name:hun_x_preferred":[
        "Kiskoszm\u00e1ly"
    ],
    "name:ita_x_preferred":[
        "Mal\u00e9 Kozm\u00e1lovce"
    ],
    "name:msa_x_preferred":[
        "Mal\u00e9 Kozm\u00e1lovce"
    ],
    "name:nld_x_preferred":[
        "Mal\u00e9 Kozm\u00e1lovce"
    ],
    "name:pol_x_preferred":[
        "Mal\u00e9 Kozm\u00e1lovce"
    ],
    "name:ron_x_preferred":[
        "Mal\u00e9 Kozm\u00e1lovce"
    ],
    "name:slk_x_preferred":[
        "Mal\u00e9 Kozm\u00e1lovce"
    ],
    "name:spa_x_preferred":[
        "Mal\u00e9 Kozm\u00e1lovce"
    ],
    "name:srp_x_preferred":[
        "\u041c\u0430\u0459\u0435 \u041a\u043e\u0437\u043c\u0430\u043b\u043e\u0432\u0446\u0435"
    ],
    "name:und_x_variant":[
        "Kis-Koszm\u00e1ly",
        "Mal\u00e9 Kozm\u00e1lovce"
    ],
    "name:war_x_preferred":[
        "Mal\u00e9 Kozm\u00e1lovce"
    ],
    "wof:name":"Male Kozmalovce",
    "wof:placetype":"locality"
},
  "geometry": {"coordinates":[18.51155,48.27375],"type":"Point"}
}