{
  "type": "Feature",
  "properties": {
    "gn:admin1_code":"04",
    "gn:asciiname":"Male Kozmalovce",
    "gn:country_code":"SK",
    "gn:dem":172,
    "gn:feature_class":"P",
    "gn:feature_code":"PPL",
    "gn:name":"Mal\u00e9 Kozm\u00e1lovce",
    "gn:population":0,
    "gn:timezone":"Europe/Bratislava",
    "iso:country":"SK",
    "name:und_x_variant":[
        "Kis-Koszm\u00e1ly",
        "Mal\u00e9 Kozm\u00e1lovce"
    ],
    "wof:name":"Male Kozmalovce",
    "wof:placetype":"locality"
},
  "geometry": {"coordinates":[18.51155,48.27375],"type":"Point"}
}