{
  "type": "Feature",
  "properties": {
    "gn:admin1_code":"03",
    "gn:asciiname":"Pavlovo",
    "gn:country_code":"SK",
    "gn:dem":99,
    "gn:feature_class":"P",
    "gn:feature_code":"PPL",
    "gn:name":"Pavlovo",
    "gn:population":0,
    "gn:timezone":"Europe/Bratislava",
    "iso:country":"SK",
    "name:und_x_variant":[
        "P\u00e1lf\u00f6lde",
        "Pavlovo"
    ],
    "wof:name":"Pavlovo",
    "wof:placetype":"locality"
},
  "geometry": {"coordinates":[21.83648,48.43901],"type":"Point"}
}