{
  "type": "Feature",
  "properties": {
    "gn:admin1_code":"04",
    "gn:asciiname":"Vieska",
    "gn:country_code":"SK",
    "gn:dem":244,
    "gn:feature_class":"P",
    "gn:feature_code":"PPL",
    "gn:name":"Vieska",
    "gn:population":0,
    "gn:timezone":"Europe/Bratislava",
    "iso:country":"SK",
    "wof:name":"Vieska",
    "wof:placetype":"locality"
},
  "geometry": {"coordinates":[18.51412,48.67109],"type":"Point"}
}