{
  "type": "Feature",
  "properties": {
    "gn:admin1_code":"03",
    "gn:asciiname":"Betlenovce",
    "gn:country_code":"SK",
    "gn:dem":105,
    "gn:feature_class":"P",
    "gn:feature_code":"PPL",
    "gn:name":"Betlenovce",
    "gn:population":0,
    "gn:timezone":"Europe/Bratislava",
    "iso:country":"SK",
    "wof:name":"Betlenovce",
    "wof:placetype":"locality"
},
  "geometry": {"coordinates":[21.90455,48.71931],"type":"Point"}
}