{
  "type": "Feature",
  "properties": {
    "gn:admin1_code":"08",
    "gn:asciiname":"Kycerka",
    "gn:country_code":"SK",
    "gn:dem":651,
    "gn:feature_class":"P",
    "gn:feature_code":"PPL",
    "gn:name":"K\u00fd\u010derka",
    "gn:population":0,
    "gn:timezone":"Europe/Bratislava",
    "iso:country":"SK",
    "wof:name":"Kycerka",
    "wof:placetype":"locality"
},
  "geometry": {"coordinates":[18.61558,49.37588],"type":"Point"}
}