{
  "type": "Feature",
  "properties": {
    "gn:admin1_code":"04",
    "gn:asciiname":"Diel",
    "gn:country_code":"SK",
    "gn:dem":300,
    "gn:feature_class":"P",
    "gn:feature_code":"PPL",
    "gn:name":"Diel",
    "gn:population":0,
    "gn:timezone":"Europe/Bratislava",
    "iso:country":"SK",
    "wof:name":"Diel",
    "wof:placetype":"locality"
},
  "geometry": {"coordinates":[18.43236,48.58358],"type":"Point"}
}