{
  "type": "Feature",
  "properties": {
    "gn:admin1_code":"07",
    "gn:asciiname":"Siposovske Kracany",
    "gn:country_code":"SK",
    "gn:dem":116,
    "gn:feature_class":"P",
    "gn:feature_code":"PPL",
    "gn:name":"\u0160\u00edpo\u0161ovsk\u00e9 Kra\u010dany",
    "gn:population":0,
    "gn:timezone":"Europe/Bratislava",
    "iso:country":"SK",
    "name:und_x_variant":[
        "S\u00edpos-Karcsa",
        "\u0160\u00edpo\u0161ovsk\u00e9 Kra\u010dany"
    ],
    "wof:name":"Siposovske Kracany",
    "wof:placetype":"locality"
},
  "geometry": {"coordinates":[17.58269,47.96981],"type":"Point"}
}