{
  "type": "Feature",
  "properties": {
    "gn:admin1_code":"06",
    "gn:admin2_code":"303.0",
    "gn:asciiname":"Brestovec",
    "gn:cc2":"SK",
    "gn:country_code":"SK",
    "gn:dem":389,
    "gn:feature_class":"P",
    "gn:feature_code":"PPL",
    "gn:name":"Brestovec",
    "gn:population":0,
    "gn:timezone":"Europe/Bratislava",
    "iso:country":"SK",
    "wof:name":"Brestovec",
    "wof:placetype":"locality"
},
  "geometry": {"coordinates":[17.56628,48.79409],"type":"Point"}
}