{
  "type": "Feature",
  "properties": {
    "gn:admin1_code":"06",
    "gn:admin2_code":"303.0",
    "gn:asciiname":"Brestovec",
    "gn:cc2":"SK",
    "gn:country_code":"SK",
    "gn:dem":389,
    "gn:feature_class":"P",
    "gn:feature_code":"PPL",
    "gn:name":"Brestovec",
    "gn:population":0,
    "gn:timezone":"Europe/Bratislava",
    "iso:country":"SK",
    "name:cat_x_preferred":[
        "Brestovec"
    ],
    "name:ces_x_preferred":[
        "Brestovec"
    ],
    "name:deu_x_preferred":[
        "Brestovec"
    ],
    "name:epo_x_preferred":[
        "Brestovec"
    ],
    "name:eus_x_preferred":[
        "Brestovec"
    ],
    "name:hun_x_preferred":[
        "Brez\u00f3v\u00f6lgy"
    ],
    "name:ita_x_preferred":[
        "Brestovec"
    ],
    "name:msa_x_preferred":[
        "Brestovec"
    ],
    "name:nld_x_preferred":[
        "Brestovec"
    ],
    "name:ron_x_preferred":[
        "Brestove\u021b"
    ],
    "name:slk_x_preferred":[
        "Brestovec"
    ],
    "name:spa_x_preferred":[
        "Brestovec"
    ],
    "name:srp_x_preferred":[
        "\u0411\u0440\u0435\u0441\u0442\u043e\u0432\u0435\u0446"
    ],
    "name:war_x_preferred":[
        "Brestovec"
    ],
    "wof:name":"Brestovec",
    "wof:placetype":"locality"
},
  "geometry": {"coordinates":[17.56628,48.79409],"type":"Point"}
}