{
  "type": "Feature",
  "properties": {
    "gn:country":"SK",
    "gn:fcode":"PPL",
    "gn:population":0,
    "iso:country":"SK",
    "name:cat_x_preferred":[
        "Smrd\u00e1ky"
    ],
    "name:ces_x_preferred":[
        "Smrd\u00e1ky"
    ],
    "name:deu_x_preferred":[
        "Smrd\u00e1ky"
    ],
    "name:eng_x_preferred":[
        "Smrd\u00e1ky"
    ],
    "name:epo_x_preferred":[
        "Smrd\u00e1ky"
    ],
    "name:eus_x_preferred":[
        "Vel\u0315k\u00e9 Kapu\u0161any"
    ],
    "name:eus_x_variant":[
        "Smrd\u00e1ky"
    ],
    "name:fra_x_preferred":[
        "Smrd\u00e1ky"
    ],
    "name:hun_x_preferred":[
        "B\u00fcd\u00f6sk\u0151"
    ],
    "name:ita_x_preferred":[
        "Smrd\u00e1ky"
    ],
    "name:msa_x_preferred":[
        "Smrd\u00e1ky"
    ],
    "name:nan_x_preferred":[
        "Smrd\u00e1ky"
    ],
    "name:nld_x_preferred":[
        "Smrd\u00e1ky"
    ],
    "name:por_x_preferred":[
        "Smrd\u00e1ky"
    ],
    "name:ron_x_preferred":[
        "Smrd\u00e1ky"
    ],
    "name:slk_x_preferred":[
        "Smrd\u00e1ky"
    ],
    "name:spa_x_preferred":[
        "Smrd\u00e1ky"
    ],
    "name:srp_x_preferred":[
        "\u0421\u043c\u0440\u0434\u0430\u043a\u0438"
    ],
    "name:war_x_preferred":[
        "Smrd\u00e1ky"
    ],
    "qs_pg:aaroncc":"SK",
    "qs_pg:gn_country":"SK",
    "qs_pg:gn_fcode":"PPL",
    "qs_pg:gn_pop":0,
    "qs_pg:name":"Smrd\u00e1ky",
    "qs_pg:name_adm0":"Slovensk\u00e1",
    "qs_pg:name_adm1":"Trnavsky",
    "qs_pg:photos":26,
    "qs_pg:photos_1k":5,
    "qs_pg:photos_9k":1,
    "qs_pg:photos_9r":2,
    "qs_pg:photos_all":26,
    "qs_pg:photos_sr":2,
    "qs_pg:pop_sr":0,
    "qs_pg:qs_pg_placetype":"locality",
    "qs_pg:qs_pg_placetype_gp":"Town",
    "qs_pg:woe_adm0":23424877,
    "woe:adm0_id":23424877,
    "woe:name_adm0":"Slovensk\u00e1",
    "woe:name_adm1":"Trnavsky",
    "woe:placetype":"Town",
    "wof:name":"Smrd\u00e1ky",
    "wof:placetype":"locality"
},
  "geometry": {"coordinates":[17.30235,48.72234],"type":"Point"}
}