{
  "type": "Feature",
  "properties": {
    "gn:admin1_code":"08",
    "gn:asciiname":"Vysny Kubin",
    "gn:country_code":"SK",
    "gn:dem":523,
    "gn:feature_class":"P",
    "gn:feature_code":"PPL",
    "gn:name":"Vy\u0161n\u00fd Kub\u00edn",
    "gn:population":0,
    "gn:timezone":"Europe/Bratislava",
    "iso:country":"SK",
    "name:und_x_variant":[
        "Horn\u00ed Kub\u00edn",
        "Vy\u0161n\u00ed Kub\u00edn",
        "Vy\u0161n\u00fd Kub\u00edn"
    ],
    "wof:name":"Vysny Kubin",
    "wof:placetype":"locality"
},
  "geometry": {"coordinates":[19.31702,49.18436],"type":"Point"}
}