{
  "type": "Feature",
  "properties": {
    "gn:admin1_code":"08",
    "gn:asciiname":"Vysny Kubin",
    "gn:country_code":"SK",
    "gn:dem":523,
    "gn:feature_class":"P",
    "gn:feature_code":"PPL",
    "gn:name":"Vy\u0161n\u00fd Kub\u00edn",
    "gn:population":0,
    "gn:timezone":"Europe/Bratislava",
    "iso:country":"SK",
    "name:cat_x_preferred":[
        "Vy\u0161n\u00fd Kub\u00edn"
    ],
    "name:ces_x_preferred":[
        "Vy\u0161n\u00fd Kub\u00edn"
    ],
    "name:deu_x_preferred":[
        "Vy\u0161n\u00fd Kub\u00edn"
    ],
    "name:epo_x_preferred":[
        "Vy\u0161n\u00fd Kub\u00edn"
    ],
    "name:eus_x_preferred":[
        "Vy\u0161n\u00fd Kub\u00edn"
    ],
    "name:fra_x_preferred":[
        "Vy\u0161n\u00fd Kub\u00edn"
    ],
    "name:hun_x_preferred":[
        "Fels\u0151kubin"
    ],
    "name:ita_x_preferred":[
        "Vy\u0161n\u00fd Kub\u00edn"
    ],
    "name:msa_x_preferred":[
        "Vy\u0161n\u00fd Kub\u00edn"
    ],
    "name:nld_x_preferred":[
        "Vy\u0161n\u00fd Kub\u00edn"
    ],
    "name:pol_x_preferred":[
        "Vy\u0161n\u00fd Kub\u00edn"
    ],
    "name:ron_x_preferred":[
        "Vy\u0161n\u00fd Kub\u00edn"
    ],
    "name:slk_x_preferred":[
        "Vy\u0161n\u00fd Kub\u00edn"
    ],
    "name:spa_x_preferred":[
        "Vy\u0161n\u00fd Kub\u00edn"
    ],
    "name:srp_x_preferred":[
        "\u0412\u0438\u0448\u043d\u0438 \u041a\u0443\u0431\u0438\u043d"
    ],
    "name:ukr_x_preferred":[
        "\u0412\u0438\u0448\u043d\u0438 \u041a\u0443\u0431\u0456\u043d"
    ],
    "name:und_x_variant":[
        "Horn\u00ed Kub\u00edn",
        "Vy\u0161n\u00ed Kub\u00edn"
    ],
    "name:war_x_preferred":[
        "Vy\u0161n\u00fd Kub\u00edn"
    ],
    "wof:name":"Vysny Kubin",
    "wof:placetype":"locality"
},
  "geometry": {"coordinates":[19.31702,49.18436],"type":"Point"}
}