{
  "type": "Feature",
  "properties": {
    "gn:gn_country":"SK",
    "gn:gn_fcode":"PPL",
    "gn:gn_pop":0,
    "iso:country":"SK",
    "name:cat_x_preferred":[
        "Se\u010dianky"
    ],
    "name:epo_x_preferred":[
        "Se\u010dianky"
    ],
    "name:eus_x_preferred":[
        "Se\u010dianky"
    ],
    "name:fra_x_preferred":[
        "Se\u010dianky"
    ],
    "name:hun_x_preferred":[
        "Ipolysz\u00e9cs\u00e9nyke"
    ],
    "name:ita_x_preferred":[
        "Se\u010dianky"
    ],
    "name:msa_x_preferred":[
        "Se\u010dianky"
    ],
    "name:nld_x_preferred":[
        "Se\u010dianky"
    ],
    "name:pol_x_preferred":[
        "Se\u010dianky"
    ],
    "name:ron_x_preferred":[
        "Se\u010dianky"
    ],
    "name:slk_x_preferred":[
        "Se\u010dianky"
    ],
    "name:spa_x_preferred":[
        "Se\u010dianky"
    ],
    "name:srp_x_preferred":[
        "\u0421\u0435\u0447\u0458\u0430\u043d\u043a\u0438"
    ],
    "name:ukr_x_preferred":[
        "\u0421\u0435\u0447'\u044f\u043d\u043a\u0438"
    ],
    "name:unk_x_variant":[
        "Sz\u00e9cs\u00e9nke"
    ],
    "name:war_x_preferred":[
        "Se\u010dianky"
    ],
    "qs_pg:aaroncc":"SK",
    "qs_pg:gn_country":"SK",
    "qs_pg:gn_fcode":"PPL",
    "qs_pg:gn_pop":0,
    "qs_pg:name":"Se\u010dianky",
    "qs_pg:name_adm0":"Slovensk\u00e1",
    "qs_pg:name_adm1":"Banskobystricky",
    "qs_pg:photos_9r":0,
    "qs_pg:photos_sr":0,
    "qs_pg:pop_sr":0,
    "qs_pg:qs_pg_placetype":"locality",
    "qs_pg:qs_pg_placetype_gp":"Town",
    "qs_pg:woe_adm0":23424877,
    "woe:adm0_id":23424877,
    "woe:name_adm0":"Slovensk\u00e1",
    "woe:name_adm1":"Banskobystricky",
    "woe:placetype":"Town",
    "wof:name":"Se\u010dianky",
    "wof:placetype":"locality"
},
  "geometry": {"coordinates":[19.07959,48.09511],"type":"Point"}
}