{
  "type": "Feature",
  "properties": {
    "iso:country":"SK",
    "qs_pg:aaroncc":"SK",
    "qs_pg:name":"Prievidza",
    "qs_pg:name_adm0":"Slovensk\u00e1",
    "qs_pg:name_adm1":"Trenciansky",
    "qs_pg:photos":2,
    "qs_pg:photos_1k":1,
    "qs_pg:photos_9k":2,
    "qs_pg:photos_9r":5,
    "qs_pg:photos_all":430,
    "qs_pg:photos_sr":1,
    "qs_pg:pop_sr":0,
    "qs_pg:qs_pg_placetype":"localadmin",
    "qs_pg:qs_pg_placetype_gp":"LocalAdmin",
    "qs_pg:woe_adm0":23424877,
    "woe:adm0_id":23424877,
    "woe:name_adm0":"Slovensk\u00e1",
    "woe:name_adm1":"Trenciansky",
    "woe:placetype":"LocalAdmin",
    "wof:name":"Prievidza",
    "wof:placetype":"localadmin"
},
  "geometry": {"coordinates":[18.600583,48.774469],"type":"Point"}
}