{
  "type": "Feature",
  "properties": {
    "gn:admin1_code":"05",
    "gn:asciiname":"Lucina",
    "gn:country_code":"SK",
    "gn:dem":511,
    "gn:feature_class":"P",
    "gn:feature_code":"PPL",
    "gn:name":"L\u00fa\u010dina",
    "gn:population":0,
    "gn:timezone":"Europe/Bratislava",
    "iso:country":"SK",
    "name:und_x_variant":[
        "Huviz",
        "L\u00fa\u010dina"
    ],
    "wof:name":"Lucina",
    "wof:placetype":"locality"
},
  "geometry": {"coordinates":[21.43118,48.89315],"type":"Point"}
}