{
  "type": "Feature",
  "properties": {
    "gn:admin1_code":"05",
    "gn:asciiname":"Lucina",
    "gn:country_code":"SK",
    "gn:dem":511,
    "gn:feature_class":"P",
    "gn:feature_code":"PPL",
    "gn:name":"L\u00fa\u010dina",
    "gn:population":0,
    "gn:timezone":"Europe/Bratislava",
    "iso:country":"SK",
    "name:cat_x_preferred":[
        "L\u00fa\u010dina"
    ],
    "name:ces_x_preferred":[
        "L\u00fa\u010dina"
    ],
    "name:epo_x_preferred":[
        "L\u00fa\u010dina"
    ],
    "name:eus_x_preferred":[
        "L\u00fa\u010dina"
    ],
    "name:fra_x_preferred":[
        "L\u00fa\u010dina"
    ],
    "name:hun_x_preferred":[
        "H\u00fcv\u00e9sz"
    ],
    "name:ita_x_preferred":[
        "L\u00fa\u010dina"
    ],
    "name:msa_x_preferred":[
        "L\u00fa\u010dina"
    ],
    "name:nld_x_preferred":[
        "L\u00fa\u010dina"
    ],
    "name:pol_x_preferred":[
        "L\u00fa\u010dina"
    ],
    "name:ron_x_preferred":[
        "L\u00fa\u010dina"
    ],
    "name:rue_x_preferred":[
        "\u041b\u0443\u0447\u0456\u043d\u0430"
    ],
    "name:slk_x_preferred":[
        "L\u00fa\u010dina"
    ],
    "name:spa_x_preferred":[
        "L\u00fa\u010dina"
    ],
    "name:srp_x_preferred":[
        "\u041b\u0443\u0447\u0438\u043d\u0430"
    ],
    "name:ukr_x_preferred":[
        "\u041b\u0443\u0447\u0438\u043d\u0430"
    ],
    "name:und_x_variant":[
        "Huviz",
        "L\u00fa\u010dina"
    ],
    "name:war_x_preferred":[
        "L\u00fa\u010dina"
    ],
    "wof:name":"Lucina",
    "wof:placetype":"locality"
},
  "geometry": {"coordinates":[21.43118,48.89315],"type":"Point"}
}