{
  "type": "Feature",
  "properties": {
    "gn:admin1_code":"08",
    "gn:asciiname":"Maly Cepcin",
    "gn:country_code":"SK",
    "gn:dem":464,
    "gn:feature_class":"P",
    "gn:feature_code":"PPL",
    "gn:name":"Mal\u00fd \u010cep\u010d\u00edn",
    "gn:population":0,
    "gn:timezone":"Europe/Bratislava",
    "iso:country":"SK",
    "name:cat_x_preferred":[
        "Mal\u00fd \u010cep\u010d\u00edn"
    ],
    "name:ces_x_preferred":[
        "Mal\u00fd \u010cep\u010d\u00edn"
    ],
    "name:epo_x_preferred":[
        "Mal\u00fd \u010cep\u010d\u00edn"
    ],
    "name:eus_x_preferred":[
        "Mal\u00fd \u010cep\u010d\u00edn"
    ],
    "name:fra_x_preferred":[
        "Mal\u00fd \u010cep\u010d\u00edn"
    ],
    "name:hun_x_preferred":[
        "Kiscsepcs\u00e9ny"
    ],
    "name:ita_x_preferred":[
        "Mal\u00fd \u010cep\u010d\u00edn"
    ],
    "name:msa_x_preferred":[
        "Mal\u00fd \u010cep\u010d\u00edn"
    ],
    "name:nld_x_preferred":[
        "Mal\u00fd \u010cep\u010d\u00edn"
    ],
    "name:pol_x_preferred":[
        "Mal\u00fd \u010cep\u010d\u00edn"
    ],
    "name:ron_x_preferred":[
        "Mal\u00fd \u010cep\u010d\u00edn"
    ],
    "name:slk_x_preferred":[
        "Mal\u00fd \u010cep\u010d\u00edn"
    ],
    "name:spa_x_preferred":[
        "Mal\u00fd \u010cep\u010d\u00edn"
    ],
    "name:srp_x_preferred":[
        "\u041c\u0430\u043b\u0438 \u0427\u0435\u043f\u0447\u0438\u043d"
    ],
    "name:und_x_variant":[
        "Mal\u00fd \u010cep\u010d\u00edn"
    ],
    "name:war_x_preferred":[
        "Mal\u00fd \u010cep\u010d\u00edn"
    ],
    "wof:name":"Maly Cepcin",
    "wof:placetype":"locality"
},
  "geometry": {"coordinates":[18.83931,48.90293],"type":"Point"}
}