{
  "type": "Feature",
  "properties": {
    "gn:admin1_code":"08",
    "gn:asciiname":"Maly Cepcin",
    "gn:country_code":"SK",
    "gn:dem":464,
    "gn:feature_class":"P",
    "gn:feature_code":"PPL",
    "gn:name":"Mal\u00fd \u010cep\u010d\u00edn",
    "gn:population":0,
    "gn:timezone":"Europe/Bratislava",
    "iso:country":"SK",
    "name:und_x_variant":[
        "Mal\u00fd \u010cep\u010d\u00edn"
    ],
    "wof:name":"Maly Cepcin",
    "wof:placetype":"locality"
},
  "geometry": {"coordinates":[18.83931,48.90293],"type":"Point"}
}