{
  "type": "Feature",
  "properties": {
    "iso:country":"SK",
    "name:cat_x_preferred":[
        "Hamuliakovo"
    ],
    "name:ces_x_preferred":[
        "Hamuliakovo"
    ],
    "name:deu_x_preferred":[
        "Hamuliakovo"
    ],
    "name:epo_x_preferred":[
        "Hamuliakovo"
    ],
    "name:eus_x_preferred":[
        "Hamuliakovo"
    ],
    "name:fra_x_preferred":[
        "Hamuliakovo"
    ],
    "name:hun_x_preferred":[
        "Gutor"
    ],
    "name:ita_x_preferred":[
        "Hamuliakovo"
    ],
    "name:msa_x_preferred":[
        "Hamuliakovo"
    ],
    "name:nld_x_preferred":[
        "Hamuliakovo"
    ],
    "name:por_x_preferred":[
        "Hamuliakovo"
    ],
    "name:ron_x_preferred":[
        "Hamuliakovo"
    ],
    "name:slk_x_preferred":[
        "Hamuliakovo"
    ],
    "name:spa_x_preferred":[
        "Hamuliakovo"
    ],
    "name:srp_x_preferred":[
        "\u0425\u0430\u043c\u0443\u0459\u0430\u043a\u043e\u0432\u043e"
    ],
    "name:war_x_preferred":[
        "Hamuliakovo"
    ],
    "qs_pg:aaroncc":"SK",
    "qs_pg:name":"Hamuliakovo",
    "qs_pg:name_adm0":"Slovensk\u00e1",
    "qs_pg:name_adm1":"Bratislavsky",
    "qs_pg:photos":1,
    "qs_pg:photos_1k":1,
    "qs_pg:photos_9k":1,
    "qs_pg:photos_9r":2,
    "qs_pg:photos_all":31,
    "qs_pg:photos_sr":1,
    "qs_pg:pop_sr":0,
    "qs_pg:qs_pg_placetype":"localadmin",
    "qs_pg:qs_pg_placetype_gp":"LocalAdmin",
    "qs_pg:woe_adm0":23424877,
    "woe:adm0_id":23424877,
    "woe:name_adm0":"Slovensk\u00e1",
    "woe:name_adm1":"Bratislavsky",
    "woe:placetype":"LocalAdmin",
    "wof:name":"Hamuliakovo",
    "wof:placetype":"localadmin"
},
  "geometry": {"coordinates":[17.226101,48.030772],"type":"Point"}
}