{
  "type": "Feature",
  "properties": {
    "gn:admin1_code":"05",
    "gn:asciiname":"Chmel'ova",
    "gn:country_code":"SK",
    "gn:dem":368,
    "gn:feature_class":"P",
    "gn:feature_code":"PPL",
    "gn:name":"Chme\u013eov\u00e1",
    "gn:population":0,
    "gn:timezone":"Europe/Bratislava",
    "iso:country":"SK",
    "name:und_x_variant":[
        "Komlo\u0161a",
        "Chme\u013eov\u00e1"
    ],
    "wof:name":"Chmel'ova",
    "wof:placetype":"locality"
},
  "geometry": {"coordinates":[21.29885,49.39998],"type":"Point"}
}