{
  "type": "Feature",
  "properties": {
    "gn:gn_country":"SK",
    "gn:gn_fcode":"PPL",
    "gn:gn_pop":0,
    "iso:country":"SK",
    "name:cat_x_preferred":[
        "Ni\u017en\u00fd Slavkov"
    ],
    "name:ces_x_preferred":[
        "Ni\u017en\u00fd Slavkov"
    ],
    "name:deu_x_preferred":[
        "Ni\u017en\u00fd Slavkov"
    ],
    "name:eng_x_preferred":[
        "Ni\u017en\u00fd Slavkov"
    ],
    "name:epo_x_preferred":[
        "Ni\u017en\u00fd Slavkov"
    ],
    "name:eus_x_preferred":[
        "Ni\u017en\u00fd Slavkov"
    ],
    "name:fra_x_preferred":[
        "Ni\u017en\u00fd Slavkov"
    ],
    "name:hun_x_preferred":[
        "Als\u00f3szal\u00f3k"
    ],
    "name:ita_x_preferred":[
        "Ni\u017en\u00fd Slavkov"
    ],
    "name:msa_x_preferred":[
        "Ni\u017en\u00fd Slavkov"
    ],
    "name:nan_x_preferred":[
        "Ni\u017en\u00fd Slavkov"
    ],
    "name:nld_x_preferred":[
        "Ni\u017en\u00fd Slavkov"
    ],
    "name:pol_x_preferred":[
        "Ni\u017en\u00fd Slavkov"
    ],
    "name:ron_x_preferred":[
        "Ni\u017en\u00fd Slavkov"
    ],
    "name:slk_x_preferred":[
        "Ni\u017en\u00fd Slavkov"
    ],
    "name:spa_x_preferred":[
        "Ni\u017en\u00fd Slavkov"
    ],
    "name:srp_x_preferred":[
        "\u040a\u0438\u0436\u043d\u0438 \u0421\u043b\u0430\u0432\u043a\u043e\u0432"
    ],
    "name:ukr_x_preferred":[
        "\u041d\u0438\u0436\u043d\u0456\u0439 \u0421\u043b\u0430\u0432\u043a\u043e\u0432"
    ],
    "name:unk_x_variant":[
        "Ni\u017en\u00ed Slavkov"
    ],
    "name:war_x_preferred":[
        "Ni\u017en\u00fd Slavkov"
    ],
    "qs_pg:aaroncc":"SK",
    "qs_pg:gn_country":"SK",
    "qs_pg:gn_fcode":"PPL",
    "qs_pg:gn_pop":0,
    "qs_pg:name":"Ni\u017en\u00fd Slavkov",
    "qs_pg:name_adm0":"Slovensk\u00e1",
    "qs_pg:name_adm1":"Presovsky",
    "qs_pg:photos_9r":0,
    "qs_pg:photos_sr":0,
    "qs_pg:pop_sr":0,
    "qs_pg:qs_pg_placetype":"locality",
    "qs_pg:qs_pg_placetype_gp":"Town",
    "qs_pg:woe_adm0":23424877,
    "woe:adm0_id":23424877,
    "woe:name_adm0":"Slovensk\u00e1",
    "woe:name_adm1":"Presovsky",
    "woe:placetype":"Town",
    "wof:name":"Ni\u017en\u00fd Slavkov",
    "wof:placetype":"locality"
},
  "geometry": {"coordinates":[20.85054,49.10233],"type":"Point"}
}