{
  "type": "Feature",
  "properties": {
    "gn:admin1_code":"01",
    "gn:asciiname":"Vel'ka Romhan",
    "gn:country_code":"SK",
    "gn:dem":226,
    "gn:feature_class":"P",
    "gn:feature_code":"PPL",
    "gn:name":"Ve\u013ek\u00e1 Romh\u00e1\u0148",
    "gn:population":0,
    "gn:timezone":"Europe/Bratislava",
    "iso:country":"SK",
    "wof:name":"Vel'ka Romhan",
    "wof:placetype":"locality"
},
  "geometry": {"coordinates":[19.71667,48.21667],"type":"Point"}
}