{
  "type": "Feature",
  "properties": {
    "gn:admin1_code":"04",
    "gn:asciiname":"Janov Dvor",
    "gn:country_code":"SK",
    "gn:dem":114,
    "gn:feature_class":"P",
    "gn:feature_code":"PPL",
    "gn:name":"Janov Dvor",
    "gn:population":0,
    "gn:timezone":"Europe/Bratislava",
    "iso:country":"SK",
    "wof:name":"Janov Dvor",
    "wof:placetype":"locality"
},
  "geometry": {"coordinates":[18.16813,47.95843],"type":"Point"}
}