{
  "type": "Feature",
  "properties": {
    "gn:admin1_code":"07",
    "gn:asciiname":"Pastuchov",
    "gn:country_code":"SK",
    "gn:dem":206,
    "gn:feature_class":"P",
    "gn:feature_code":"PPL",
    "gn:name":"Pastuchov",
    "gn:population":0,
    "gn:timezone":"Europe/Bratislava",
    "iso:country":"SK",
    "name:cat_x_preferred":[
        "Pastuchov"
    ],
    "name:ces_x_preferred":[
        "Pastuchov"
    ],
    "name:deu_x_preferred":[
        "Pastuchov"
    ],
    "name:epo_x_preferred":[
        "Pastuchov"
    ],
    "name:eus_x_preferred":[
        "Pastuchov"
    ],
    "name:fra_x_preferred":[
        "Pastuchov"
    ],
    "name:hun_x_preferred":[
        "Nyitrap\u00e1szt\u00f3"
    ],
    "name:ita_x_preferred":[
        "Pastuchov"
    ],
    "name:msa_x_preferred":[
        "Pastuchov"
    ],
    "name:nld_x_preferred":[
        "Pastuchov"
    ],
    "name:ron_x_preferred":[
        "Pastuchov"
    ],
    "name:slk_x_preferred":[
        "Pastuchov"
    ],
    "name:spa_x_preferred":[
        "Pastuchov"
    ],
    "name:srp_x_preferred":[
        "\u041f\u0430\u0441\u0442\u0443\u0445\u043e\u0432"
    ],
    "name:ukr_x_preferred":[
        "\u041f\u0430\u0441\u0442\u0443\u0445\u043e\u0432"
    ],
    "name:war_x_preferred":[
        "Pastuchov"
    ],
    "wof:name":"Pastuchov",
    "wof:placetype":"locality"
},
  "geometry": {"coordinates":[17.87812000000001,48.42627],"type":"Point"}
}