{
  "type": "Feature",
  "properties": {
    "gn:admin1_code":"07",
    "gn:asciiname":"Pastuchov",
    "gn:country_code":"SK",
    "gn:dem":206,
    "gn:feature_class":"P",
    "gn:feature_code":"PPL",
    "gn:name":"Pastuchov",
    "gn:population":0,
    "gn:timezone":"Europe/Bratislava",
    "iso:country":"SK",
    "wof:name":"Pastuchov",
    "wof:placetype":"locality"
},
  "geometry": {"coordinates":[17.87812000000001,48.42627],"type":"Point"}
}