{
  "type": "Feature",
  "properties": {
    "gn:admin1_code":"05",
    "gn:asciiname":"Bujakov",
    "gn:country_code":"SK",
    "gn:dem":364,
    "gn:feature_class":"P",
    "gn:feature_code":"PPL",
    "gn:name":"Bujakov",
    "gn:population":0,
    "gn:timezone":"Europe/Bratislava",
    "iso:country":"SK",
    "wof:name":"Bujakov",
    "wof:placetype":"locality"
},
  "geometry": {"coordinates":[21.11014,48.97841],"type":"Point"}
}