{
  "type": "Feature",
  "properties": {
    "gn:admin1_code":"05",
    "gn:asciiname":"Buclovany",
    "gn:country_code":"SK",
    "gn:dem":232,
    "gn:feature_class":"P",
    "gn:feature_code":"PPL",
    "gn:name":"Buclovany",
    "gn:population":0,
    "gn:timezone":"Europe/Bratislava",
    "iso:country":"SK",
    "name:und_x_variant":[
        "Bucloviany",
        "Buclovany"
    ],
    "wof:name":"Buclovany",
    "wof:placetype":"locality"
},
  "geometry": {"coordinates":[21.36517000000001,49.1553],"type":"Point"}
}