{
  "type": "Feature",
  "properties": {
    "gn:admin1_code":"01",
    "gn:asciiname":"Poloma",
    "gn:country_code":"SK",
    "gn:dem":387,
    "gn:feature_class":"P",
    "gn:feature_code":"PPL",
    "gn:name":"Poloma",
    "gn:population":0,
    "gn:timezone":"Europe/Bratislava",
    "iso:country":"SK",
    "wof:name":"Poloma",
    "wof:placetype":"locality"
},
  "geometry": {"coordinates":[19.10522000000001,48.41832],"type":"Point"}
}