{
  "type": "Feature",
  "properties": {
    "gn:admin1_code":"01",
    "gn:asciiname":"Poloma",
    "gn:country_code":"SK",
    "gn:dem":387,
    "gn:feature_class":"P",
    "gn:feature_code":"PPL",
    "gn:name":"Poloma",
    "gn:population":0,
    "gn:timezone":"Europe/Bratislava",
    "iso:country":"SK",
    "name:cat_x_preferred":[
        "Poloma"
    ],
    "name:ces_x_preferred":[
        "Poloma"
    ],
    "name:deu_x_preferred":[
        "Poloma"
    ],
    "name:epo_x_preferred":[
        "Poloma"
    ],
    "name:eus_x_preferred":[
        "Poloma"
    ],
    "name:hun_x_preferred":[
        "Polony"
    ],
    "name:ita_x_preferred":[
        "Poloma"
    ],
    "name:msa_x_preferred":[
        "Poloma"
    ],
    "name:nld_x_preferred":[
        "Poloma"
    ],
    "name:pol_x_preferred":[
        "Poloma"
    ],
    "name:por_x_preferred":[
        "Poloma"
    ],
    "name:ron_x_preferred":[
        "Poloma"
    ],
    "name:slk_x_preferred":[
        "Poloma"
    ],
    "name:spa_x_preferred":[
        "Poloma"
    ],
    "name:srp_x_preferred":[
        "\u041f\u043e\u043b\u043e\u043c\u0430"
    ],
    "name:ukr_x_preferred":[
        "\u041f\u043e\u043b\u043e\u043c\u0430"
    ],
    "name:war_x_preferred":[
        "Poloma"
    ],
    "wof:name":"Poloma",
    "wof:placetype":"locality"
},
  "geometry": {"coordinates":[19.10522000000001,48.41832],"type":"Point"}
}