{
  "type": "Feature",
  "properties": {
    "gn:admin1_code":"01",
    "gn:asciiname":"Konci Diel",
    "gn:country_code":"SK",
    "gn:dem":672,
    "gn:feature_class":"P",
    "gn:feature_code":"PPL",
    "gn:name":"Kon\u010di Diel",
    "gn:population":0,
    "gn:timezone":"Europe/Bratislava",
    "iso:country":"SK",
    "wof:name":"Konci Diel",
    "wof:placetype":"locality"
},
  "geometry": {"coordinates":[19.55,48.51667],"type":"Point"}
}