{
  "type": "Feature",
  "properties": {
    "gn:admin1_code":"04",
    "gn:asciiname":"Pusta Potok",
    "gn:country_code":"SK",
    "gn:dem":154,
    "gn:feature_class":"P",
    "gn:feature_code":"PPL",
    "gn:name":"Pusta Potok",
    "gn:population":0,
    "gn:timezone":"Europe/Bratislava",
    "iso:country":"SK",
    "wof:name":"Pusta Potok",
    "wof:placetype":"locality"
},
  "geometry": {"coordinates":[18.84256,48.13486],"type":"Point"}
}