{
  "type": "Feature",
  "properties": {
    "gn:admin1_code":"04",
    "gn:asciiname":"Praznovce",
    "gn:country_code":"SK",
    "gn:dem":165,
    "gn:feature_class":"P",
    "gn:feature_code":"PPL",
    "gn:name":"Praznovce",
    "gn:population":0,
    "gn:timezone":"Europe/Bratislava",
    "iso:country":"SK",
    "wof:name":"Praznovce",
    "wof:placetype":"locality"
},
  "geometry": {"coordinates":[18.21026,48.5667],"type":"Point"}
}