{
  "type": "Feature",
  "properties": {
    "gn:admin1_code":"04",
    "gn:asciiname":"Praznovce",
    "gn:country_code":"SK",
    "gn:dem":165,
    "gn:feature_class":"P",
    "gn:feature_code":"PPL",
    "gn:name":"Praznovce",
    "gn:population":0,
    "gn:timezone":"Europe/Bratislava",
    "iso:country":"SK",
    "name:cat_x_preferred":[
        "Pr\u00e1znovce"
    ],
    "name:ces_x_preferred":[
        "Pr\u00e1znovce"
    ],
    "name:deu_x_preferred":[
        "Pr\u00e1znovce"
    ],
    "name:epo_x_preferred":[
        "Pr\u00e1znovce"
    ],
    "name:eus_x_preferred":[
        "Pr\u00e1znovce"
    ],
    "name:fra_x_preferred":[
        "Pr\u00e1znovce"
    ],
    "name:hun_x_preferred":[
        "Pr\u00e1zn\u00f3c"
    ],
    "name:ita_x_preferred":[
        "Pr\u00e1znovce"
    ],
    "name:msa_x_preferred":[
        "Pr\u00e1znovce"
    ],
    "name:nld_x_preferred":[
        "Pr\u00e1znovce"
    ],
    "name:ron_x_preferred":[
        "Pr\u00e1znovce"
    ],
    "name:slk_x_preferred":[
        "Pr\u00e1znovce"
    ],
    "name:spa_x_preferred":[
        "Pr\u00e1znovce"
    ],
    "name:srp_x_preferred":[
        "\u041f\u0440\u0430\u0437\u043d\u043e\u0432\u0446\u0435"
    ],
    "name:war_x_preferred":[
        "Pr\u00e1znovce"
    ],
    "wof:name":"Praznovce",
    "wof:placetype":"locality"
},
  "geometry": {"coordinates":[18.21026,48.5667],"type":"Point"}
}