{
  "type": "Feature",
  "properties": {
    "gn:admin1_code":"01",
    "gn:asciiname":"Jazero",
    "gn:country_code":"SK",
    "gn:dem":239,
    "gn:feature_class":"P",
    "gn:feature_code":"PPL",
    "gn:name":"Jazero",
    "gn:population":0,
    "gn:timezone":"Europe/Bratislava",
    "iso:country":"SK",
    "wof:name":"Jazero",
    "wof:placetype":"locality"
},
  "geometry": {"coordinates":[19.46325,48.27889],"type":"Point"}
}