{
  "type": "Feature",
  "properties": {
    "gn:admin1_code":"04",
    "gn:asciiname":"Max",
    "gn:country_code":"SK",
    "gn:dem":748,
    "gn:feature_class":"P",
    "gn:feature_code":"PPL",
    "gn:name":"Max",
    "gn:population":0,
    "gn:timezone":"Europe/Bratislava",
    "iso:country":"SK",
    "name:bos_x_preferred":[
        "Max"
    ],
    "name:cat_x_preferred":[
        "Max"
    ],
    "name:ces_x_preferred":[
        "Max"
    ],
    "name:dan_x_preferred":[
        "Max"
    ],
    "name:deu_x_preferred":[
        "Max"
    ],
    "name:fas_x_preferred":[
        "\u0645\u06a9\u0633"
    ],
    "name:fin_x_preferred":[
        "Max"
    ],
    "name:fra_x_preferred":[
        "Max"
    ],
    "name:fry_x_preferred":[
        "Max"
    ],
    "name:heb_x_preferred":[
        "Max"
    ],
    "name:hrv_x_preferred":[
        "Max"
    ],
    "name:ind_x_preferred":[
        "Max"
    ],
    "name:jpn_x_preferred":[
        "\u30de\u30c3\u30af\u30b9"
    ],
    "name:nld_x_preferred":[
        "Max"
    ],
    "name:pol_x_preferred":[
        "Max"
    ],
    "name:por_x_preferred":[
        "Max"
    ],
    "name:ron_x_preferred":[
        "Max"
    ],
    "name:rus_x_preferred":[
        "\u041c\u0430\u043a\u0441"
    ],
    "name:spa_x_preferred":[
        "Max"
    ],
    "name:srp_x_preferred":[
        "\u041c\u0430\u043a\u0441"
    ],
    "name:swe_x_preferred":[
        "Max"
    ],
    "name:tur_x_preferred":[
        "Max"
    ],
    "name:ukr_x_preferred":[
        "\u041c\u0430\u043a\u0441"
    ],
    "name:vie_x_preferred":[
        "Max"
    ],
    "name:zho_x_preferred":[
        "Max"
    ],
    "wof:name":"Max",
    "wof:placetype":"locality"
},
  "geometry": {"coordinates":[18.55,48.56667],"type":"Point"}
}