{
  "type": "Feature",
  "properties": {
    "gn:admin1_code":"04",
    "gn:asciiname":"Max",
    "gn:country_code":"SK",
    "gn:dem":748,
    "gn:feature_class":"P",
    "gn:feature_code":"PPL",
    "gn:name":"Max",
    "gn:population":0,
    "gn:timezone":"Europe/Bratislava",
    "iso:country":"SK",
    "wof:name":"Max",
    "wof:placetype":"locality"
},
  "geometry": {"coordinates":[18.55,48.56667],"type":"Point"}
}