{
  "type": "Feature",
  "properties": {
    "gn:admin1_code":"02",
    "gn:asciiname":"Nova Ves pri Dunaji",
    "gn:country_code":"SK",
    "gn:dem":126,
    "gn:feature_class":"P",
    "gn:feature_code":"PPL",
    "gn:name":"Nov\u00e1 Ves pri Dunaji",
    "gn:population":0,
    "gn:timezone":"Europe/Bratislava",
    "iso:country":"SK",
    "name:hun_x_preferred":[
        "Duna\u00fajfalu"
    ],
    "name:hun_x_variant":[
        "Duna-\u00dajfalu"
    ],
    "name:und_x_variant":[
        "Nov\u00e1 Ves pri Dunaji"
    ],
    "wof:name":"Nova Ves pri Dunaji",
    "wof:placetype":"locality"
},
  "geometry": {"coordinates":[17.35629,48.1861],"type":"Point"}
}