{
  "type": "Feature",
  "properties": {
    "gn:admin1_code":"04",
    "gn:asciiname":"Nitrianska Streda",
    "gn:country_code":"SK",
    "gn:dem":166,
    "gn:feature_class":"P",
    "gn:feature_code":"PPL",
    "gn:name":"Nitrianska Streda",
    "gn:population":0,
    "gn:timezone":"Europe/Bratislava",
    "iso:country":"SK",
    "name:cat_x_preferred":[
        "Nitrianska Streda"
    ],
    "name:ceb_x_preferred":[
        "Nitrianska Streda"
    ],
    "name:ces_x_preferred":[
        "Nitrianska Streda"
    ],
    "name:deu_x_preferred":[
        "Nitrianska Streda"
    ],
    "name:epo_x_preferred":[
        "Nitrianska Streda"
    ],
    "name:eus_x_preferred":[
        "Nitrianska Streda"
    ],
    "name:fra_x_preferred":[
        "Nitrianska Streda"
    ],
    "name:hun_x_preferred":[
        "Nyitraszerdahely"
    ],
    "name:ita_x_preferred":[
        "Nitrianska Streda"
    ],
    "name:msa_x_preferred":[
        "Nitrianska Streda"
    ],
    "name:nld_x_preferred":[
        "Nitrianska Streda"
    ],
    "name:ron_x_preferred":[
        "Nitrianska Streda"
    ],
    "name:slk_x_preferred":[
        "Nitrianska Streda"
    ],
    "name:spa_x_preferred":[
        "Nitrianska Streda"
    ],
    "name:srp_x_preferred":[
        "\u040a\u0438\u0442\u0440\u0430\u043d\u0441\u043a\u0430 \u0421\u0442\u0440\u0435\u0434\u0430"
    ],
    "name:war_x_preferred":[
        "Nitrianska Streda"
    ],
    "wof:name":"Nitrianska Streda",
    "wof:placetype":"locality"
},
  "geometry": {"coordinates":[18.17514,48.51783],"type":"Point"}
}