{
  "type": "Feature",
  "properties": {
    "gn:country":"SK",
    "gn:fcode":"PPL",
    "gn:population":0,
    "iso:country":"SK",
    "name:cat_x_preferred":[
        "Betlanovce"
    ],
    "name:ces_x_preferred":[
        "Betlanovce"
    ],
    "name:deu_x_preferred":[
        "Betlanovce"
    ],
    "name:eng_x_preferred":[
        "Betlanovce"
    ],
    "name:epo_x_preferred":[
        "Betlanovce"
    ],
    "name:eus_x_preferred":[
        "Betlanovce"
    ],
    "name:fra_x_preferred":[
        "Betlanovce"
    ],
    "name:hun_x_preferred":[
        "Betlenfalva"
    ],
    "name:ita_x_preferred":[
        "Betlanovce"
    ],
    "name:msa_x_preferred":[
        "Betlanovce"
    ],
    "name:nan_x_preferred":[
        "Betlanovce"
    ],
    "name:nld_x_preferred":[
        "Betlanovce"
    ],
    "name:pol_x_preferred":[
        "Betlanovce"
    ],
    "name:ron_x_preferred":[
        "Betlanovce"
    ],
    "name:slk_x_preferred":[
        "Betlanovce"
    ],
    "name:spa_x_preferred":[
        "Betlanovce"
    ],
    "name:srp_x_preferred":[
        "\u0411\u0435\u0442\u043b\u0430\u043d\u043e\u0432\u0446\u0435"
    ],
    "name:ukr_x_preferred":[
        "\u0411\u0435\u0442\u043b\u0430\u043d\u043e\u0432\u0446\u0435"
    ],
    "name:war_x_preferred":[
        "Betlanovce"
    ],
    "qs_pg:aaroncc":"SK",
    "qs_pg:gn_country":"SK",
    "qs_pg:gn_fcode":"PPL",
    "qs_pg:gn_pop":0,
    "qs_pg:name":"Betlanovce",
    "qs_pg:name_adm0":"Slovensk\u00e1",
    "qs_pg:name_adm1":"Kosicky",
    "qs_pg:photos_9r":0,
    "qs_pg:photos_sr":0,
    "qs_pg:pop_sr":0,
    "qs_pg:qs_pg_placetype":"locality",
    "qs_pg:qs_pg_placetype_gp":"Town",
    "qs_pg:woe_adm0":23424877,
    "woe:adm0_id":23424877,
    "woe:name_adm0":"Slovensk\u00e1",
    "woe:name_adm1":"Kosicky",
    "woe:placetype":"Town",
    "wof:name":"Betlanovce",
    "wof:placetype":"locality"
},
  "geometry": {"coordinates":[20.38977,48.98117],"type":"Point"}
}