{
  "type": "Feature",
  "properties": {
    "gn:admin1_code":"07",
    "gn:asciiname":"Rastice",
    "gn:country_code":"SK",
    "gn:dem":123,
    "gn:feature_class":"P",
    "gn:feature_code":"PPL",
    "gn:name":"Rastice",
    "gn:population":0,
    "gn:timezone":"Europe/Bratislava",
    "iso:country":"SK",
    "name:und_x_variant":[
        "Ve\u013ek\u00fd Mager",
        "Nagy-Magyar",
        "Rastice"
    ],
    "wof:name":"Rastice",
    "wof:placetype":"locality"
},
  "geometry": {"coordinates":[17.41667,48.11667],"type":"Point"}
}