{
  "type": "Feature",
  "properties": {
    "gn:admin1_code":"05",
    "gn:asciiname":"Posa",
    "gn:country_code":"SK",
    "gn:dem":129,
    "gn:feature_class":"P",
    "gn:feature_code":"PPL",
    "gn:name":"Po\u0161a",
    "gn:population":0,
    "gn:timezone":"Europe/Bratislava",
    "iso:country":"SK",
    "name:und_x_variant":[
        "Po\u0161a"
    ],
    "wof:name":"Posa",
    "wof:placetype":"locality"
},
  "geometry": {"coordinates":[21.75977,48.83921],"type":"Point"}
}