{
  "type": "Feature",
  "properties": {
    "gn:admin1_code":"05",
    "gn:asciiname":"Posa",
    "gn:country_code":"SK",
    "gn:dem":129,
    "gn:feature_class":"P",
    "gn:feature_code":"PPL",
    "gn:name":"Po\u0161a",
    "gn:population":0,
    "gn:timezone":"Europe/Bratislava",
    "iso:country":"SK",
    "name:cat_x_preferred":[
        "Po\u0161a"
    ],
    "name:ces_x_preferred":[
        "Po\u0161a"
    ],
    "name:deu_x_preferred":[
        "Po\u0161a"
    ],
    "name:epo_x_preferred":[
        "Po\u0161a"
    ],
    "name:eus_x_preferred":[
        "Po\u0161a"
    ],
    "name:fra_x_preferred":[
        "Po\u0161a"
    ],
    "name:hun_x_preferred":[
        "P\u00f3sa"
    ],
    "name:ita_x_preferred":[
        "Po\u0161a"
    ],
    "name:msa_x_preferred":[
        "Po\u0161a"
    ],
    "name:nld_x_preferred":[
        "Po\u0161a"
    ],
    "name:pol_x_preferred":[
        "Po\u0161a"
    ],
    "name:ron_x_preferred":[
        "Po\u0161a"
    ],
    "name:rus_x_preferred":[
        "\u041f\u043e\u0448\u0430"
    ],
    "name:slk_x_preferred":[
        "Po\u0161a"
    ],
    "name:spa_x_preferred":[
        "Po\u0161a"
    ],
    "name:srp_x_preferred":[
        "\u041f\u043e\u0448\u0430"
    ],
    "name:ukr_x_preferred":[
        "\u041f\u043e\u0448\u0430"
    ],
    "name:war_x_preferred":[
        "Po\u0161a"
    ],
    "wof:name":"Posa",
    "wof:placetype":"locality"
},
  "geometry": {"coordinates":[21.75977,48.83921],"type":"Point"}
}