{
  "type": "Feature",
  "properties": {
    "iso:country":"SK",
    "qs_pg:aaroncc":"SK",
    "qs_pg:name":"Liptovsky Peter",
    "qs_pg:name_adm0":"Slovensk\u00e1",
    "qs_pg:name_adm1":"Zilinsky",
    "qs_pg:photos":184,
    "qs_pg:photos_1k":37,
    "qs_pg:photos_9k":1,
    "qs_pg:photos_9r":4,
    "qs_pg:photos_all":184,
    "qs_pg:photos_sr":4,
    "qs_pg:pop_sr":0,
    "qs_pg:qs_pg_placetype":"localadmin",
    "qs_pg:qs_pg_placetype_gp":"LocalAdmin",
    "qs_pg:woe_adm0":23424877,
    "woe:adm0_id":23424877,
    "woe:name_adm0":"Slovensk\u00e1",
    "woe:name_adm1":"Zilinsky",
    "woe:placetype":"LocalAdmin",
    "wof:name":"Liptovsky Peter",
    "wof:placetype":"localadmin"
},
  "geometry": {"coordinates":[19.732131,49.05632],"type":"Point"}
}