{
  "type": "Feature",
  "properties": {
    "gn:admin1_code":"08",
    "gn:asciiname":"Zavodie",
    "gn:country_code":"SK",
    "gn:dem":677,
    "gn:feature_class":"P",
    "gn:feature_code":"PPL",
    "gn:name":"Z\u00e1vodie",
    "gn:population":0,
    "gn:timezone":"Europe/Bratislava",
    "iso:country":"SK",
    "wof:name":"Zavodie",
    "wof:placetype":"locality"
},
  "geometry": {"coordinates":[18.95,49.43333],"type":"Point"}
}