{
  "type": "Feature",
  "properties": {
    "gn:admin1_code":"04",
    "gn:asciiname":"Vrbany",
    "gn:country_code":"SK",
    "gn:dem":268,
    "gn:feature_class":"P",
    "gn:feature_code":"PPL",
    "gn:name":"Vrbany",
    "gn:population":0,
    "gn:timezone":"Europe/Bratislava",
    "iso:country":"SK",
    "wof:name":"Vrbany",
    "wof:placetype":"locality"
},
  "geometry": {"coordinates":[18.50256,48.74846],"type":"Point"}
}