{
  "type": "Feature",
  "properties": {
    "gn:admin1_code":"03",
    "gn:asciiname":"Ostrov",
    "gn:country_code":"SK",
    "gn:dem":106,
    "gn:feature_class":"P",
    "gn:feature_code":"PPL",
    "gn:name":"Ostrov",
    "gn:population":0,
    "gn:timezone":"Europe/Bratislava",
    "iso:country":"SK",
    "name:cat_x_preferred":[
        "Ostrov"
    ],
    "name:ces_x_preferred":[
        "Ostrov"
    ],
    "name:epo_x_preferred":[
        "Ostrov"
    ],
    "name:eus_x_preferred":[
        "Ostrov"
    ],
    "name:hun_x_preferred":[
        "\u00c9les"
    ],
    "name:ita_x_preferred":[
        "Ostrov"
    ],
    "name:msa_x_preferred":[
        "Ostrov"
    ],
    "name:nld_x_preferred":[
        "Ostrov"
    ],
    "name:pol_x_preferred":[
        "Ostrov"
    ],
    "name:ron_x_preferred":[
        "Ostrov"
    ],
    "name:rue_x_preferred":[
        "\u041e\u0441\u0442\u0440\u043e\u0432"
    ],
    "name:slk_x_preferred":[
        "Ostrov"
    ],
    "name:spa_x_preferred":[
        "Ostrov"
    ],
    "name:srp_x_preferred":[
        "\u041e\u0441\u0442\u0440\u043e\u0432"
    ],
    "name:ukr_x_preferred":[
        "\u041e\u0441\u0442\u0440\u043e\u0432"
    ],
    "name:war_x_preferred":[
        "Ostrov"
    ],
    "wof:name":"Ostrov",
    "wof:placetype":"locality"
},
  "geometry": {"coordinates":[22.1635,48.71829],"type":"Point"}
}