{
  "type": "Feature",
  "properties": {
    "gn:admin1_code":"01",
    "gn:asciiname":"Tauszova Samota",
    "gn:country_code":"SK",
    "gn:dem":190,
    "gn:feature_class":"P",
    "gn:feature_code":"PPL",
    "gn:name":"Tauszova Samota",
    "gn:population":0,
    "gn:timezone":"Europe/Bratislava",
    "iso:country":"SK",
    "wof:name":"Tauszova Samota",
    "wof:placetype":"locality"
},
  "geometry": {"coordinates":[19.65,48.35],"type":"Point"}
}