{
  "type": "Feature",
  "properties": {
    "gn:admin1_code":"05",
    "gn:asciiname":"Jedlinka",
    "gn:country_code":"SK",
    "gn:dem":408,
    "gn:feature_class":"P",
    "gn:feature_code":"PPL",
    "gn:name":"Jedlinka",
    "gn:population":0,
    "gn:timezone":"Europe/Bratislava",
    "iso:country":"SK",
    "name:cat_x_preferred":[
        "Jedlinka"
    ],
    "name:ces_x_preferred":[
        "Jedlinka"
    ],
    "name:deu_x_preferred":[
        "Jedlinka"
    ],
    "name:epo_x_preferred":[
        "Jedlinka"
    ],
    "name:eus_x_preferred":[
        "Jedlinka"
    ],
    "name:fra_x_preferred":[
        "Jedlinka"
    ],
    "name:hun_x_preferred":[
        "Bor\u00f3k\u00e1s"
    ],
    "name:ita_x_preferred":[
        "Jedlinka"
    ],
    "name:msa_x_preferred":[
        "Jedlinka"
    ],
    "name:nld_x_preferred":[
        "Jedlinka"
    ],
    "name:pol_x_preferred":[
        "Jedlinka"
    ],
    "name:ron_x_preferred":[
        "Jedlinka"
    ],
    "name:rue_x_preferred":[
        "\u042f\u043b\u0438\u043d\u043a\u044b"
    ],
    "name:slk_x_preferred":[
        "Jedlinka"
    ],
    "name:spa_x_preferred":[
        "Jedlinka"
    ],
    "name:srp_x_preferred":[
        "\u0408\u0435\u0434\u043b\u0438\u043d\u043a\u0430"
    ],
    "name:ukr_x_preferred":[
        "\u042f\u043b\u0438\u043d\u043a\u0430"
    ],
    "name:war_x_preferred":[
        "Jedlinka"
    ],
    "wof:name":"Jedlinka",
    "wof:placetype":"locality"
},
  "geometry": {"coordinates":[21.37009,49.39927],"type":"Point"}
}