{
  "type": "Feature",
  "properties": {
    "gn:admin1_code":"08",
    "gn:asciiname":"Polgrun",
    "gn:country_code":"SK",
    "gn:dem":503,
    "gn:feature_class":"P",
    "gn:feature_code":"PPL",
    "gn:name":"Polgr\u00fa\u0148",
    "gn:population":0,
    "gn:timezone":"Europe/Bratislava",
    "iso:country":"SK",
    "wof:name":"Polgrun",
    "wof:placetype":"locality"
},
  "geometry": {"coordinates":[18.66672,49.44485],"type":"Point"}
}