{
  "type": "Feature",
  "properties": {
    "gn:admin1_code":"04",
    "gn:asciiname":"Male Bielice",
    "gn:country_code":"SK",
    "gn:dem":183,
    "gn:feature_class":"P",
    "gn:feature_code":"PPL",
    "gn:name":"Mal\u00e9 Bielice",
    "gn:population":0,
    "gn:timezone":"Europe/Bratislava",
    "iso:country":"SK",
    "name:und_x_variant":[
        "Mal\u00e9 Bielice"
    ],
    "wof:name":"Male Bielice",
    "wof:placetype":"locality"
},
  "geometry": {"coordinates":[18.33171,48.63117],"type":"Point"}
}