{
  "type": "Feature",
  "properties": {
    "gn:gn_country":"SK",
    "gn:gn_fcode":"PPL",
    "gn:gn_pop":0,
    "iso:country":"SK",
    "name:cat_x_preferred":[
        "\u0160enkvice"
    ],
    "name:ces_x_preferred":[
        "\u0160enkvice"
    ],
    "name:deu_x_preferred":[
        "\u0160enkvice"
    ],
    "name:eng_x_preferred":[
        "\u0160enkvice"
    ],
    "name:epo_x_preferred":[
        "\u0160enkvice"
    ],
    "name:est_x_preferred":[
        "\u0160enkvice"
    ],
    "name:eus_x_preferred":[
        "\u0160enkvice"
    ],
    "name:fra_x_preferred":[
        "\u0160enkvice"
    ],
    "name:hun_x_preferred":[
        "Nagysenk\u0151c"
    ],
    "name:hun_x_variant":[
        "Senk\u0151c"
    ],
    "name:ita_x_preferred":[
        "\u0160enkvice"
    ],
    "name:msa_x_preferred":[
        "\u0160enkvice"
    ],
    "name:nan_x_preferred":[
        "\u0160enkvice"
    ],
    "name:nld_x_preferred":[
        "\u0160enkvice"
    ],
    "name:por_x_preferred":[
        "\u0160enkvice"
    ],
    "name:ron_x_preferred":[
        "\u0160enkvice"
    ],
    "name:slk_x_preferred":[
        "\u0160enkvice"
    ],
    "name:spa_x_preferred":[
        "\u0160enkvice"
    ],
    "name:srp_x_preferred":[
        "\u0428\u0435\u043d\u043a\u0432\u0438\u0446\u0435"
    ],
    "name:unk_x_variant":[
        "\u0160enkvice"
    ],
    "name:war_x_preferred":[
        "\u0160enkvice"
    ],
    "qs_pg:aaroncc":"SK",
    "qs_pg:gn_country":"SK",
    "qs_pg:gn_fcode":"PPL",
    "qs_pg:gn_pop":0,
    "qs_pg:name":"Vel\u0315k\u00e9 \u010can\u00edkovce",
    "qs_pg:name_adm0":"Slovensk\u00e1",
    "qs_pg:name_adm1":"Bratislavsky",
    "qs_pg:photos_9k":1,
    "qs_pg:photos_9r":1,
    "qs_pg:photos_all":1,
    "qs_pg:photos_sr":0,
    "qs_pg:pop_sr":0,
    "qs_pg:qs_pg_placetype":"locality",
    "qs_pg:qs_pg_placetype_gp":"Town",
    "qs_pg:woe_adm0":23424877,
    "woe:adm0_id":23424877,
    "woe:name_adm0":"Slovensk\u00e1",
    "woe:name_adm1":"Bratislavsky",
    "woe:placetype":"Town",
    "wof:name":"Vel\u0315k\u00e9 \u010can\u00edkovce",
    "wof:placetype":"locality"
},
  "geometry": {"coordinates":[17.34959,48.29817],"type":"Point"}
}