{
  "type": "Feature",
  "properties": {
    "gn:admin1_code":"01",
    "gn:asciiname":"Glabusovce",
    "gn:country_code":"SK",
    "gn:dem":177,
    "gn:feature_class":"P",
    "gn:feature_code":"PPL",
    "gn:name":"Glabu\u0161ovce",
    "gn:population":0,
    "gn:timezone":"Europe/Bratislava",
    "iso:country":"SK",
    "name:cat_x_preferred":[
        "Glabu\u0161ovce"
    ],
    "name:epo_x_preferred":[
        "Glabu\u0161ovce"
    ],
    "name:eus_x_preferred":[
        "Glabu\u0161ovce"
    ],
    "name:fra_x_preferred":[
        "Glabu\u0161ovce"
    ],
    "name:hun_x_preferred":[
        "Gal\u00e1bocs"
    ],
    "name:ita_x_preferred":[
        "Glabu\u0161ovce"
    ],
    "name:msa_x_preferred":[
        "Glabu\u0161ovce"
    ],
    "name:nld_x_preferred":[
        "Glabu\u0161ovce"
    ],
    "name:pol_x_preferred":[
        "Glabu\u0161ovce"
    ],
    "name:ron_x_preferred":[
        "Glabu\u0161ovce"
    ],
    "name:slk_x_preferred":[
        "Glabu\u0161ovce"
    ],
    "name:spa_x_preferred":[
        "Glabu\u0161ovce"
    ],
    "name:srp_x_preferred":[
        "\u0413\u043b\u0430\u0431\u0443\u0448\u043e\u0432\u0446\u0435"
    ],
    "name:ukr_x_preferred":[
        "\u0490\u043b\u0430\u0431\u0443\u0448\u043e\u0432\u0446\u0435"
    ],
    "name:war_x_preferred":[
        "Glabu\u0161ovce"
    ],
    "wof:name":"Glabusovce",
    "wof:placetype":"locality"
},
  "geometry": {"coordinates":[19.45831,48.15538],"type":"Point"}
}