{
  "type": "Feature",
  "properties": {
    "gn:admin1_code":"04",
    "gn:asciiname":"Podvazie",
    "gn:country_code":"SK",
    "gn:dem":239,
    "gn:feature_class":"P",
    "gn:feature_code":"PPL",
    "gn:name":"Podva\u017eie",
    "gn:population":0,
    "gn:timezone":"Europe/Bratislava",
    "iso:country":"SK",
    "wof:name":"Podvazie",
    "wof:placetype":"locality"
},
  "geometry": {"coordinates":[18.22428,49.01293],"type":"Point"}
}