{
  "type": "Feature",
  "properties": {
    "gn:admin1_code":"05",
    "gn:asciiname":"Harakovce",
    "gn:country_code":"SK",
    "gn:dem":603,
    "gn:feature_class":"P",
    "gn:feature_code":"PPL",
    "gn:name":"Harakovce",
    "gn:population":0,
    "gn:timezone":"Europe/Bratislava",
    "iso:country":"SK",
    "name:cat_x_preferred":[
        "Harakovce"
    ],
    "name:ces_x_preferred":[
        "Harakovce"
    ],
    "name:deu_x_preferred":[
        "Harakovce"
    ],
    "name:epo_x_preferred":[
        "Harakovce"
    ],
    "name:eus_x_preferred":[
        "Harakovce"
    ],
    "name:fra_x_preferred":[
        "Harakovce"
    ],
    "name:hun_x_preferred":[
        "Harak\u00f3c"
    ],
    "name:ita_x_preferred":[
        "Harakovce"
    ],
    "name:msa_x_preferred":[
        "Harakovce"
    ],
    "name:nld_x_preferred":[
        "Harakovce"
    ],
    "name:pol_x_preferred":[
        "Harakovce"
    ],
    "name:ron_x_preferred":[
        "Harakovce"
    ],
    "name:slk_x_preferred":[
        "Harakovce"
    ],
    "name:spa_x_preferred":[
        "Harakovce"
    ],
    "name:srp_x_preferred":[
        "\u0425\u0430\u0440\u0430\u043a\u043e\u0432\u0446\u0435"
    ],
    "name:ukr_x_preferred":[
        "\u0413\u0430\u0440\u0430\u043a\u043e\u0432\u0446\u0435"
    ],
    "name:war_x_preferred":[
        "Harakovce"
    ],
    "wof:name":"Harakovce",
    "wof:placetype":"locality"
},
  "geometry": {"coordinates":[20.84677000000001,48.9978],"type":"Point"}
}