{
  "type": "Feature",
  "properties": {
    "gn:admin1_code":"05",
    "gn:asciiname":"Harakovce",
    "gn:country_code":"SK",
    "gn:dem":603,
    "gn:feature_class":"P",
    "gn:feature_code":"PPL",
    "gn:name":"Harakovce",
    "gn:population":0,
    "gn:timezone":"Europe/Bratislava",
    "iso:country":"SK",
    "wof:name":"Harakovce",
    "wof:placetype":"locality"
},
  "geometry": {"coordinates":[20.84677000000001,48.9978],"type":"Point"}
}