{
  "type": "Feature",
  "properties": {
    "gn:admin1_code":"04",
    "gn:asciiname":"Podkylava",
    "gn:country_code":"SK",
    "gn:dem":235,
    "gn:feature_class":"P",
    "gn:feature_code":"PPL",
    "gn:name":"Podkylava",
    "gn:population":0,
    "gn:timezone":"Europe/Bratislava",
    "iso:country":"SK",
    "wof:name":"Podkylava",
    "wof:placetype":"locality"
},
  "geometry": {"coordinates":[17.66636,48.67873],"type":"Point"}
}