{
  "type": "Feature",
  "properties": {
    "gn:admin1_code":"04",
    "gn:asciiname":"Podkylava",
    "gn:country_code":"SK",
    "gn:dem":235,
    "gn:feature_class":"P",
    "gn:feature_code":"PPL",
    "gn:name":"Podkylava",
    "gn:population":0,
    "gn:timezone":"Europe/Bratislava",
    "iso:country":"SK",
    "name:cat_x_preferred":[
        "Podkylava"
    ],
    "name:ces_x_preferred":[
        "Podkylava"
    ],
    "name:deu_x_preferred":[
        "Podkylava"
    ],
    "name:epo_x_preferred":[
        "Podkylava"
    ],
    "name:eus_x_preferred":[
        "Podkylava"
    ],
    "name:fra_x_preferred":[
        "Podkylava"
    ],
    "name:hun_x_preferred":[
        "Szakad\u00e9k"
    ],
    "name:ita_x_preferred":[
        "Podkylava"
    ],
    "name:msa_x_preferred":[
        "Podkylava"
    ],
    "name:nld_x_preferred":[
        "Podkylava"
    ],
    "name:ron_x_preferred":[
        "Podkylava"
    ],
    "name:slk_x_preferred":[
        "Podkylava"
    ],
    "name:spa_x_preferred":[
        "Podkylava"
    ],
    "name:srp_x_preferred":[
        "\u041f\u043e\u0434\u043a\u0438\u043b\u0430\u0432\u0430"
    ],
    "name:war_x_preferred":[
        "Podkylava"
    ],
    "wof:name":"Podkylava",
    "wof:placetype":"locality"
},
  "geometry": {"coordinates":[17.66636,48.67873],"type":"Point"}
}