{
  "type": "Feature",
  "properties": {
    "gn:admin1_code":"01",
    "gn:asciiname":"Drienovo",
    "gn:country_code":"SK",
    "gn:dem":370,
    "gn:feature_class":"P",
    "gn:feature_code":"PPL",
    "gn:name":"Drienovo",
    "gn:population":0,
    "gn:timezone":"Europe/Bratislava",
    "iso:country":"SK",
    "name:cat_x_preferred":[
        "Drienovo"
    ],
    "name:epo_x_preferred":[
        "Drienovo"
    ],
    "name:eus_x_preferred":[
        "Drienovo"
    ],
    "name:fra_x_preferred":[
        "Drienovo"
    ],
    "name:hun_x_preferred":[
        "Cs\u00e1br\u00e1gsomos"
    ],
    "name:ita_x_preferred":[
        "Drienovo"
    ],
    "name:msa_x_preferred":[
        "Drienovo"
    ],
    "name:nld_x_preferred":[
        "Drienovo"
    ],
    "name:pol_x_preferred":[
        "Drienovo"
    ],
    "name:ron_x_preferred":[
        "Drienovo"
    ],
    "name:slk_x_preferred":[
        "Drienovo"
    ],
    "name:spa_x_preferred":[
        "Drienovo"
    ],
    "name:srp_x_preferred":[
        "\u0414\u0440\u0458\u0435\u043d\u043e\u0432\u043e"
    ],
    "name:ukr_x_preferred":[
        "\u0414\u0440'\u0454\u043d\u043e\u0432\u043e"
    ],
    "name:war_x_preferred":[
        "Drienovo"
    ],
    "wof:name":"Drienovo",
    "wof:placetype":"locality"
},
  "geometry": {"coordinates":[19.06256,48.23029],"type":"Point"}
}