{
  "type": "Feature",
  "properties": {
    "gn:admin1_code":"01",
    "gn:asciiname":"Drienovo",
    "gn:country_code":"SK",
    "gn:dem":370,
    "gn:feature_class":"P",
    "gn:feature_code":"PPL",
    "gn:name":"Drienovo",
    "gn:population":0,
    "gn:timezone":"Europe/Bratislava",
    "iso:country":"SK",
    "wof:name":"Drienovo",
    "wof:placetype":"locality"
},
  "geometry": {"coordinates":[19.06256,48.23029],"type":"Point"}
}