{
  "type": "Feature",
  "properties": {
    "gn:admin1_code":"07",
    "gn:asciiname":"Mocidlany",
    "gn:country_code":"SK",
    "gn:dem":208,
    "gn:feature_class":"P",
    "gn:feature_code":"PPL",
    "gn:name":"Mo\u010didlany",
    "gn:population":0,
    "gn:timezone":"Europe/Bratislava",
    "iso:country":"SK",
    "wof:name":"Mocidlany",
    "wof:placetype":"locality"
},
  "geometry": {"coordinates":[17.21566,48.77922],"type":"Point"}
}