{
  "type": "Feature",
  "properties": {
    "gn:admin1_code":"05",
    "gn:asciiname":"Mala Domasa",
    "gn:country_code":"SK",
    "gn:dem":135,
    "gn:feature_class":"P",
    "gn:feature_code":"PPL",
    "gn:name":"Mal\u00e1 Doma\u0161a",
    "gn:population":0,
    "gn:timezone":"Europe/Bratislava",
    "iso:country":"SK",
    "name:cat_x_preferred":[
        "Mal\u00e1 Doma\u0161a"
    ],
    "name:ces_x_preferred":[
        "Mal\u00e1 Doma\u0161a"
    ],
    "name:deu_x_preferred":[
        "Mal\u00e1 Doma\u0161a"
    ],
    "name:epo_x_preferred":[
        "Mal\u00e1 Doma\u0161a"
    ],
    "name:eus_x_preferred":[
        "Mal\u00e1 Doma\u0161a"
    ],
    "name:fra_x_preferred":[
        "Mal\u00e1 Doma\u0161a"
    ],
    "name:hun_x_preferred":[
        "Kisdom\u00e1sa"
    ],
    "name:ita_x_preferred":[
        "Mal\u00e1 Doma\u0161a"
    ],
    "name:msa_x_preferred":[
        "Mal\u00e1 Doma\u0161a"
    ],
    "name:nld_x_preferred":[
        "Mal\u00e1 Doma\u0161a"
    ],
    "name:pol_x_preferred":[
        "Mal\u00e1 Doma\u0161a"
    ],
    "name:ron_x_preferred":[
        "Mal\u00e1 Doma\u0161a"
    ],
    "name:slk_x_preferred":[
        "Mal\u00e1 Doma\u0161a"
    ],
    "name:spa_x_preferred":[
        "Mal\u00e1 Doma\u0161a"
    ],
    "name:srp_x_preferred":[
        "\u041c\u0430\u043b\u0430 \u0414\u043e\u043c\u0430\u0448\u0430"
    ],
    "name:ukr_x_preferred":[
        "\u041c\u0430\u043b\u0430 \u0414\u043e\u043c\u0430\u0448\u0430"
    ],
    "name:und_x_variant":[
        "Mal\u00e1 Doma\u0161a"
    ],
    "name:war_x_preferred":[
        "Mal\u00e1 Doma\u0161a"
    ],
    "wof:name":"Mala Domasa",
    "wof:placetype":"locality"
},
  "geometry": {"coordinates":[21.71107,48.97107000000001],"type":"Point"}
}