{
  "type": "Feature",
  "properties": {
    "gn:admin1_code":"08",
    "gn:asciiname":"Vasil'ov",
    "gn:country_code":"SK",
    "gn:dem":653,
    "gn:feature_class":"P",
    "gn:feature_code":"PPL",
    "gn:name":"Vasi\u013eov",
    "gn:population":0,
    "gn:timezone":"Europe/Bratislava",
    "iso:country":"SK",
    "name:cat_x_preferred":[
        "Vasi\u013eov"
    ],
    "name:ces_x_preferred":[
        "Vasi\u013eov"
    ],
    "name:deu_x_preferred":[
        "Vasi\u013eov"
    ],
    "name:epo_x_preferred":[
        "Vasi\u013eov"
    ],
    "name:eus_x_preferred":[
        "Vasi\u013eov"
    ],
    "name:fra_x_preferred":[
        "Vasi\u013eov"
    ],
    "name:hun_x_preferred":[
        "Vaszil\u00f3"
    ],
    "name:ita_x_preferred":[
        "Vasi\u013eov"
    ],
    "name:msa_x_preferred":[
        "Vasi\u013eov"
    ],
    "name:nld_x_preferred":[
        "Vasi\u013eov"
    ],
    "name:pol_x_preferred":[
        "Wasyl\u00f3w"
    ],
    "name:ron_x_preferred":[
        "Vasi\u013eov"
    ],
    "name:slk_x_preferred":[
        "Vasi\u013eov"
    ],
    "name:spa_x_preferred":[
        "Vasi\u013eov"
    ],
    "name:srp_x_preferred":[
        "\u0412\u0430\u0441\u0438\u0459\u043e\u0432"
    ],
    "name:und_x_variant":[
        "Vasi\u013eov"
    ],
    "name:war_x_preferred":[
        "Vasi\u013eov"
    ],
    "wof:name":"Vasil'ov",
    "wof:placetype":"locality"
},
  "geometry": {"coordinates":[19.38498,49.35017],"type":"Point"}
}