{
  "type": "Feature",
  "properties": {
    "gn:admin1_code":"05",
    "gn:asciiname":"Valaskovce",
    "gn:country_code":"SK",
    "gn:dem":690,
    "gn:feature_class":"P",
    "gn:feature_code":"PPL",
    "gn:name":"Vala\u0161kovce",
    "gn:population":0,
    "gn:timezone":"Europe/Bratislava",
    "iso:country":"SK",
    "name:und_x_variant":[
        "Vala\u0161kovce"
    ],
    "wof:name":"Valaskovce",
    "wof:placetype":"locality"
},
  "geometry": {"coordinates":[22.10974,48.92511],"type":"Point"}
}