{
  "type": "Feature",
  "properties": {
    "gn:admin1_code":"05",
    "gn:asciiname":"Valaskovce",
    "gn:country_code":"SK",
    "gn:dem":690,
    "gn:feature_class":"P",
    "gn:feature_code":"PPL",
    "gn:name":"Vala\u0161kovce",
    "gn:population":0,
    "gn:timezone":"Europe/Bratislava",
    "iso:country":"SK",
    "name:cat_x_preferred":[
        "Vala\u0161kovce"
    ],
    "name:deu_x_preferred":[
        "Vala\u0161kovce"
    ],
    "name:eus_x_preferred":[
        "Vala\u0161kovce"
    ],
    "name:fra_x_preferred":[
        "Vala\u0161kovce"
    ],
    "name:hun_x_preferred":[
        "P\u00e1sztorhegy"
    ],
    "name:ita_x_preferred":[
        "Vala\u0161kovce"
    ],
    "name:jpn_x_preferred":[
        "\u30f4\u30a1\u30e9\u30b7\u30e5\u30b3\u30d5\u30c4\u30a7"
    ],
    "name:msa_x_preferred":[
        "Vala\u0161kovce"
    ],
    "name:nld_x_preferred":[
        "Vala\u0161kovce"
    ],
    "name:pol_x_preferred":[
        "Vala\u0161kovce"
    ],
    "name:ron_x_preferred":[
        "Vala\u0161kovce"
    ],
    "name:slk_x_preferred":[
        "Vala\u0161kovce"
    ],
    "name:ukr_x_preferred":[
        "\u0412\u0430\u043b\u0430\u0448\u043a\u043e\u0432\u0446\u0435"
    ],
    "name:und_x_variant":[
        "Vala\u0161kovce"
    ],
    "name:war_x_preferred":[
        "Vala\u0161kovce"
    ],
    "wof:name":"Valaskovce",
    "wof:placetype":"locality"
},
  "geometry": {"coordinates":[22.10974,48.92511],"type":"Point"}
}