{
  "type": "Feature",
  "properties": {
    "gn:admin1_code":"08",
    "gn:asciiname":"Hlinik",
    "gn:country_code":"SK",
    "gn:dem":582,
    "gn:feature_class":"P",
    "gn:feature_code":"PPL",
    "gn:name":"Hlin\u00edk",
    "gn:population":0,
    "gn:timezone":"Europe/Bratislava",
    "iso:country":"SK",
    "wof:name":"Hlinik",
    "wof:placetype":"locality"
},
  "geometry": {"coordinates":[19.48881,49.12203],"type":"Point"}
}