{
  "type": "Feature",
  "properties": {
    "gn:admin1_code":"05",
    "gn:asciiname":"Pakostov",
    "gn:country_code":"SK",
    "gn:dem":189,
    "gn:feature_class":"P",
    "gn:feature_code":"PPL",
    "gn:name":"Pakostov",
    "gn:population":0,
    "gn:timezone":"Europe/Bratislava",
    "iso:country":"SK",
    "name:cat_x_preferred":[
        "Pakostov"
    ],
    "name:ces_x_preferred":[
        "Pakostov"
    ],
    "name:epo_x_preferred":[
        "Pakostov"
    ],
    "name:eus_x_preferred":[
        "Pakostov"
    ],
    "name:fra_x_preferred":[
        "Pakostov"
    ],
    "name:hun_x_preferred":[
        "Zempl\u00e9np\u00e1lhegy"
    ],
    "name:ita_x_preferred":[
        "Pakostov"
    ],
    "name:msa_x_preferred":[
        "Pakostov"
    ],
    "name:nld_x_preferred":[
        "Pakostov"
    ],
    "name:pol_x_preferred":[
        "Pakostov"
    ],
    "name:ron_x_preferred":[
        "Pakostov"
    ],
    "name:rue_x_preferred":[
        "\u041f\u0430\u043a\u043e\u0441\u0442\u0456\u0432"
    ],
    "name:slk_x_preferred":[
        "Pakostov"
    ],
    "name:spa_x_preferred":[
        "Pakostov"
    ],
    "name:srp_x_preferred":[
        "\u041f\u0430\u043a\u043e\u0441\u0442\u043e\u0432"
    ],
    "name:ukr_x_preferred":[
        "\u041f\u0430\u043a\u043e\u0441\u0442\u043e\u0432"
    ],
    "name:war_x_preferred":[
        "Pakostov"
    ],
    "wof:name":"Pakostov",
    "wof:placetype":"locality"
},
  "geometry": {"coordinates":[21.82466,49.09237],"type":"Point"}
}