{
  "type": "Feature",
  "properties": {
    "gn:country":"SK",
    "gn:fcode":"PPL",
    "gn:population":0,
    "iso:country":"SK",
    "name:cat_x_preferred":[
        "Rokytov"
    ],
    "name:ces_x_preferred":[
        "Rokytov"
    ],
    "name:che_x_preferred":[
        "\u0420\u043e\u043a\u0438\u0442\u043e\u0432"
    ],
    "name:deu_x_preferred":[
        "Rokytov"
    ],
    "name:eng_x_preferred":[
        "Rokytov"
    ],
    "name:epo_x_preferred":[
        "Rokytov"
    ],
    "name:eus_x_preferred":[
        "Rokytov"
    ],
    "name:fra_x_preferred":[
        "Rokytov"
    ],
    "name:gle_x_preferred":[
        "Rokytov"
    ],
    "name:hun_x_preferred":[
        "Rokit\u00f3"
    ],
    "name:ita_x_preferred":[
        "Rokytov"
    ],
    "name:msa_x_preferred":[
        "Rokytov"
    ],
    "name:nan_x_preferred":[
        "Rokytov"
    ],
    "name:nld_x_preferred":[
        "Rokytov"
    ],
    "name:pol_x_preferred":[
        "Rokytov"
    ],
    "name:por_x_preferred":[
        "Rokytov"
    ],
    "name:ron_x_preferred":[
        "Rokytov"
    ],
    "name:rue_x_preferred":[
        "\u0420\u043e\u043a\u0438\u0442\u043e\u0432"
    ],
    "name:rus_x_preferred":[
        "\u0420\u043e\u043a\u0438\u0442\u043e\u0432"
    ],
    "name:slk_x_preferred":[
        "Rokytov"
    ],
    "name:spa_x_preferred":[
        "Rokytov"
    ],
    "name:srp_x_preferred":[
        "\u0420\u043e\u043a\u0438\u0442\u043e\u0432"
    ],
    "name:tat_x_preferred":[
        "\u0420\u043e\u043a\u0438\u0442\u043e\u0432"
    ],
    "name:ukr_x_preferred":[
        "\u0420\u043e\u043a\u0438\u0442\u043e\u0432"
    ],
    "name:war_x_preferred":[
        "Rokytov"
    ],
    "name:war_x_variant":[
        "Tuh\u00e1r"
    ],
    "qs_pg:aaroncc":"SK",
    "qs_pg:gn_country":"SK",
    "qs_pg:gn_fcode":"PPL",
    "qs_pg:gn_pop":0,
    "qs_pg:name":"Rokytov",
    "qs_pg:name_adm0":"Slovensk\u00e1",
    "qs_pg:name_adm1":"Presovsky",
    "qs_pg:photos_9r":0,
    "qs_pg:photos_sr":0,
    "qs_pg:pop_sr":0,
    "qs_pg:qs_pg_placetype":"locality",
    "qs_pg:qs_pg_placetype_gp":"Town",
    "qs_pg:woe_adm0":23424877,
    "woe:adm0_id":23424877,
    "woe:name_adm0":"Slovensk\u00e1",
    "woe:name_adm1":"Presovsky",
    "woe:placetype":"Town",
    "wof:name":"Rokytov",
    "wof:placetype":"locality"
},
  "geometry": {"coordinates":[21.19011,49.31815],"type":"Point"}
}