{
  "type": "Feature",
  "properties": {
    "gn:admin1_code":"05",
    "gn:asciiname":"Mocarmany",
    "gn:country_code":"SK",
    "gn:dem":241,
    "gn:feature_class":"P",
    "gn:feature_code":"PPL",
    "gn:name":"Mo\u010darmany",
    "gn:population":0,
    "gn:timezone":"Europe/Bratislava",
    "iso:country":"SK",
    "wof:name":"Mocarmany",
    "wof:placetype":"locality"
},
  "geometry": {"coordinates":[21.25966,48.91201],"type":"Point"}
}