{
  "type": "Feature",
  "properties": {
    "gn:admin1_code":"08",
    "gn:asciiname":"Svaty d'ur",
    "gn:country_code":"SK",
    "gn:dem":439,
    "gn:feature_class":"P",
    "gn:feature_code":"PPL",
    "gn:name":"Sv\u00e4t\u00fd \u010fur",
    "gn:population":0,
    "gn:timezone":"Europe/Bratislava",
    "iso:country":"SK",
    "wof:name":"Svaty d'ur",
    "wof:placetype":"locality"
},
  "geometry": {"coordinates":[18.85,48.95],"type":"Point"}
}