{
  "type": "Feature",
  "properties": {
    "gn:admin1_code":"07",
    "gn:asciiname":"Cakany",
    "gn:country_code":"SK",
    "gn:dem":125,
    "gn:feature_class":"P",
    "gn:feature_code":"PPL",
    "gn:name":"\u010cakany",
    "gn:population":0,
    "gn:timezone":"Europe/Bratislava",
    "iso:country":"SK",
    "name:cat_x_preferred":[
        "\u010cakany"
    ],
    "name:ces_x_preferred":[
        "\u010cakany"
    ],
    "name:deu_x_preferred":[
        "\u010cakany"
    ],
    "name:epo_x_preferred":[
        "\u010cakany"
    ],
    "name:eus_x_preferred":[
        "\u010cakany"
    ],
    "name:fra_x_preferred":[
        "\u010cakany"
    ],
    "name:hun_x_preferred":[
        "Pozsonycs\u00e1k\u00e1ny"
    ],
    "name:ita_x_preferred":[
        "\u010cakany"
    ],
    "name:msa_x_preferred":[
        "\u010cakany"
    ],
    "name:nld_x_preferred":[
        "\u010cakany"
    ],
    "name:por_x_preferred":[
        "\u010cakany"
    ],
    "name:ron_x_preferred":[
        "\u010cakany"
    ],
    "name:slk_x_preferred":[
        "\u010cakany"
    ],
    "name:spa_x_preferred":[
        "\u010cakany"
    ],
    "name:srp_x_preferred":[
        "\u0427\u0430\u043a\u0430\u043d\u0438"
    ],
    "name:ukr_x_preferred":[
        "\u0427\u0430\u043a\u0430\u043d\u0438"
    ],
    "name:und_x_variant":[
        "Czakany"
    ],
    "name:war_x_preferred":[
        "\u010cakany"
    ],
    "wof:name":"Cakany",
    "wof:placetype":"locality"
},
  "geometry": {"coordinates":[17.36617,48.118],"type":"Point"}
}