{
  "type": "Feature",
  "properties": {
    "gn:admin1_code":"07",
    "gn:asciiname":"Cakany",
    "gn:country_code":"SK",
    "gn:dem":125,
    "gn:feature_class":"P",
    "gn:feature_code":"PPL",
    "gn:name":"\u010cakany",
    "gn:population":0,
    "gn:timezone":"Europe/Bratislava",
    "iso:country":"SK",
    "name:hun_x_preferred":[
        "Pozsonycs\u00e1k\u00e1ny"
    ],
    "name:und_x_variant":[
        "Czakany",
        "\u010cakany"
    ],
    "wof:name":"Cakany",
    "wof:placetype":"locality"
},
  "geometry": {"coordinates":[17.36617,48.118],"type":"Point"}
}