{
  "type": "Feature",
  "properties": {
    "gn:admin1_code":"05",
    "gn:asciiname":"Makovce",
    "gn:country_code":"SK",
    "gn:dem":255,
    "gn:feature_class":"P",
    "gn:feature_code":"PPL",
    "gn:name":"Makovce",
    "gn:population":0,
    "gn:timezone":"Europe/Bratislava",
    "iso:country":"SK",
    "name:cat_x_preferred":[
        "Makovce"
    ],
    "name:ces_x_preferred":[
        "Makovce"
    ],
    "name:epo_x_preferred":[
        "Makovce"
    ],
    "name:eus_x_preferred":[
        "Makovce"
    ],
    "name:fra_x_preferred":[
        "Makovce"
    ],
    "name:hun_x_preferred":[
        "M\u00e1kos"
    ],
    "name:ita_x_preferred":[
        "Makovce"
    ],
    "name:msa_x_preferred":[
        "Makovce"
    ],
    "name:nld_x_preferred":[
        "Makovce"
    ],
    "name:pol_x_preferred":[
        "Makovce"
    ],
    "name:ron_x_preferred":[
        "Makovce"
    ],
    "name:rue_x_preferred":[
        "\u041c\u0430\u043a\u0456\u0432\u0446\u0457"
    ],
    "name:slk_x_preferred":[
        "Makovce"
    ],
    "name:spa_x_preferred":[
        "Makovce"
    ],
    "name:srp_x_preferred":[
        "\u041c\u0430\u043a\u043e\u0432\u0446\u0435"
    ],
    "name:ukr_x_preferred":[
        "\u041c\u0430\u043a\u043e\u0432\u0435\u0446\u044c"
    ],
    "name:und_x_variant":[
        "Makovec"
    ],
    "name:war_x_preferred":[
        "Makovce"
    ],
    "wof:name":"Makovce",
    "wof:placetype":"locality"
},
  "geometry": {"coordinates":[21.7524,49.25815],"type":"Point"}
}