{
  "type": "Feature",
  "properties": {
    "gn:admin1_code":"05",
    "gn:asciiname":"Makovce",
    "gn:country_code":"SK",
    "gn:dem":255,
    "gn:feature_class":"P",
    "gn:feature_code":"PPL",
    "gn:name":"Makovce",
    "gn:population":0,
    "gn:timezone":"Europe/Bratislava",
    "iso:country":"SK",
    "name:und_x_variant":[
        "Makovec",
        "Makovce"
    ],
    "wof:name":"Makovce",
    "wof:placetype":"locality"
},
  "geometry": {"coordinates":[21.7524,49.25815],"type":"Point"}
}