{
  "type": "Feature",
  "properties": {
    "gn:gn_country":"SK",
    "gn:gn_fcode":"PPL",
    "gn:gn_pop":0,
    "iso:country":"SK",
    "name:cat_x_preferred":[
        "Ni\u017en\u00e1 Polianka"
    ],
    "name:cze_x_preferred":[
        "Ni\u017en\u00e1 Polianka"
    ],
    "name:dut_x_preferred":[
        "Ni\u017en\u00e1 Polianka"
    ],
    "name:eng_x_preferred":[
        "Ni\u017en\u00e1 Polianka"
    ],
    "name:epo_x_preferred":[
        "Ni\u017en\u00e1 Polianka"
    ],
    "name:fre_x_preferred":[
        "Ni\u017en\u00e1 Polianka"
    ],
    "name:ger_x_preferred":[
        "Ni\u017en\u00e1 Polianka"
    ],
    "name:hun_x_preferred":[
        "Als\u00f3pagony"
    ],
    "name:ita_x_preferred":[
        "Ni\u017en\u00e1 Polianka"
    ],
    "name:may_x_preferred":[
        "Ni\u017en\u00e1 Polianka"
    ],
    "name:nan_x_preferred":[
        "Ni\u017en\u00e1 Polianka"
    ],
    "name:pol_x_preferred":[
        "Ni\u017en\u00e1 Polianka"
    ],
    "name:rue_x_preferred":[
        "\u041d\u0438\u0436\u043d\u044f \u041f\u043e\u043b\u044f\u043d\u043a\u0430"
    ],
    "name:slo_x_preferred":[
        "Ni\u017en\u00e1 Polianka"
    ],
    "name:srp_x_preferred":[
        "\u040a\u0438\u0436\u043d\u0430 \u041f\u043e\u0459\u0430\u043d\u043a\u0430"
    ],
    "name:ukr_x_preferred":[
        "\u041d\u0438\u0436\u043d\u044f \u041f\u043e\u043b\u044f\u043d\u043a\u0430"
    ],
    "name:unk_x_variant":[
        "Ni\u017en\u00e1 Po\u013eanka"
    ],
    "name:war_x_preferred":[
        "Ni\u017en\u00e1 Polianka"
    ],
    "qs_pg:aaroncc":"SK",
    "qs_pg:gn_country":"SK",
    "qs_pg:gn_fcode":"PPL",
    "qs_pg:gn_pop":0,
    "qs_pg:name":"Ni\u017en\u00e1 Polianka",
    "qs_pg:name_adm0":"Slovensk\u00e1",
    "qs_pg:name_adm1":"Presovsky",
    "qs_pg:photos_9k":1,
    "qs_pg:photos_9r":1,
    "qs_pg:photos_all":1,
    "qs_pg:photos_sr":0,
    "qs_pg:pop_sr":0,
    "qs_pg:qs_pg_placetype":"locality",
    "qs_pg:qs_pg_placetype_gp":"Town",
    "qs_pg:woe_adm0":23424877,
    "woe:adm0_id":23424877,
    "woe:name_adm0":"Slovensk\u00e1",
    "woe:name_adm1":"Presovsky",
    "woe:placetype":"Town",
    "wof:name":"Ni\u017en\u00e1 Polianka",
    "wof:placetype":"locality"
},
  "geometry": {"coordinates":[21.40144,49.40431],"type":"Point"}
}