{
  "type": "Feature",
  "properties": {
    "gn:admin1_code":"05",
    "gn:asciiname":"Sandal",
    "gn:country_code":"SK",
    "gn:dem":259,
    "gn:feature_class":"P",
    "gn:feature_code":"PPL",
    "gn:name":"\u0160andal",
    "gn:population":0,
    "gn:timezone":"Europe/Bratislava",
    "iso:country":"SK",
    "name:cat_x_preferred":[
        "\u0160andal"
    ],
    "name:ces_x_preferred":[
        "\u0160andal"
    ],
    "name:epo_x_preferred":[
        "\u0160andal"
    ],
    "name:eus_x_preferred":[
        "\u0160andal"
    ],
    "name:fra_x_preferred":[
        "\u0160andal"
    ],
    "name:hun_x_preferred":[
        "Sandal"
    ],
    "name:ita_x_preferred":[
        "\u0160andal"
    ],
    "name:msa_x_preferred":[
        "\u0160andal"
    ],
    "name:nld_x_preferred":[
        "\u0160andal"
    ],
    "name:pol_x_preferred":[
        "\u0160andal"
    ],
    "name:ron_x_preferred":[
        "\u0160andal"
    ],
    "name:rue_x_preferred":[
        "\u0428\u0430\u043d\u0434\u0430\u043b"
    ],
    "name:slk_x_preferred":[
        "\u0160andal"
    ],
    "name:spa_x_preferred":[
        "\u0160andal"
    ],
    "name:srp_x_preferred":[
        "\u0428\u0430\u043d\u0434\u0430\u043b"
    ],
    "name:ukr_x_preferred":[
        "\u0428\u0430\u043d\u0434\u0430\u043b"
    ],
    "name:und_x_variant":[
        "\u0160andal"
    ],
    "name:war_x_preferred":[
        "\u0160andal"
    ],
    "wof:name":"Sandal",
    "wof:placetype":"locality"
},
  "geometry": {"coordinates":[21.61734,49.18691],"type":"Point"}
}