{
  "type": "Feature",
  "properties": {
    "gn:admin1_code":"05",
    "gn:asciiname":"Sandal",
    "gn:country_code":"SK",
    "gn:dem":259,
    "gn:feature_class":"P",
    "gn:feature_code":"PPL",
    "gn:name":"\u0160andal",
    "gn:population":0,
    "gn:timezone":"Europe/Bratislava",
    "iso:country":"SK",
    "name:und_x_variant":[
        "\u0160andal"
    ],
    "wof:name":"Sandal",
    "wof:placetype":"locality"
},
  "geometry": {"coordinates":[21.61734,49.18691],"type":"Point"}
}