{
  "type": "Feature",
  "properties": {
    "gn:admin1_code":"01",
    "gn:asciiname":"Male Straciny",
    "gn:country_code":"SK",
    "gn:dem":202,
    "gn:feature_class":"P",
    "gn:feature_code":"PPL",
    "gn:name":"Mal\u00e9 Straciny",
    "gn:population":0,
    "gn:timezone":"Europe/Bratislava",
    "iso:country":"SK",
    "name:cat_x_preferred":[
        "Mal\u00e9 Straciny"
    ],
    "name:epo_x_preferred":[
        "Mal\u00e9 Straciny"
    ],
    "name:eus_x_preferred":[
        "Mal\u00e9 Straciny"
    ],
    "name:fra_x_preferred":[
        "Mal\u00e9 Straciny"
    ],
    "name:hun_x_preferred":[
        "Kishalom"
    ],
    "name:ita_x_preferred":[
        "Mal\u00e9 Straciny"
    ],
    "name:msa_x_preferred":[
        "Mal\u00e9 Straciny"
    ],
    "name:nld_x_preferred":[
        "Mal\u00e9 Straciny"
    ],
    "name:pol_x_preferred":[
        "Mal\u00e9 Straciny"
    ],
    "name:ron_x_preferred":[
        "Mal\u00e9 Straciny"
    ],
    "name:slk_x_preferred":[
        "Mal\u00e9 Straciny"
    ],
    "name:spa_x_preferred":[
        "Mal\u00e9 Straciny"
    ],
    "name:srp_x_preferred":[
        "\u041c\u0430\u0459\u0435 \u0421\u0442\u0440\u0430\u0446\u0438\u043d\u0438"
    ],
    "name:ukr_x_preferred":[
        "\u041c\u0430\u043b\u0435 \u0421\u0442\u0440\u0430\u0446\u0456\u043d\u0438"
    ],
    "name:war_x_preferred":[
        "Mal\u00e9 Straciny"
    ],
    "wof:name":"Male Straciny",
    "wof:placetype":"locality"
},
  "geometry": {"coordinates":[19.41509,48.20981],"type":"Point"}
}