{
  "type": "Feature",
  "properties": {
    "gn:admin1_code":"01",
    "gn:asciiname":"Male Straciny",
    "gn:country_code":"SK",
    "gn:dem":202,
    "gn:feature_class":"P",
    "gn:feature_code":"PPL",
    "gn:name":"Mal\u00e9 Straciny",
    "gn:population":0,
    "gn:timezone":"Europe/Bratislava",
    "iso:country":"SK",
    "name:und_x_variant":[
        "Mal\u00e9 Straciny"
    ],
    "wof:name":"Male Straciny",
    "wof:placetype":"locality"
},
  "geometry": {"coordinates":[19.41509,48.20981],"type":"Point"}
}