{
  "type": "Feature",
  "properties": {
    "gn:admin1_code":"05",
    "gn:asciiname":"Cabov",
    "gn:country_code":"SK",
    "gn:dem":200,
    "gn:feature_class":"P",
    "gn:feature_code":"PPL",
    "gn:name":"Cabov",
    "gn:population":0,
    "gn:timezone":"Europe/Bratislava",
    "iso:country":"SK",
    "wof:name":"Cabov",
    "wof:placetype":"locality"
},
  "geometry": {"coordinates":[21.64945,48.80255],"type":"Point"}
}