{
  "type": "Feature",
  "properties": {
    "gn:admin1_code":"05",
    "gn:asciiname":"Cabov",
    "gn:country_code":"SK",
    "gn:dem":200,
    "gn:feature_class":"P",
    "gn:feature_code":"PPL",
    "gn:name":"Cabov",
    "gn:population":0,
    "gn:timezone":"Europe/Bratislava",
    "iso:country":"SK",
    "name:cat_x_preferred":[
        "Cabov"
    ],
    "name:ces_x_preferred":[
        "Cabov"
    ],
    "name:epo_x_preferred":[
        "Cabov"
    ],
    "name:eus_x_preferred":[
        "Cabov"
    ],
    "name:fra_x_preferred":[
        "Cabov"
    ],
    "name:hun_x_preferred":[
        "Cs\u00e1b\u00f3c"
    ],
    "name:ita_x_preferred":[
        "Cabov"
    ],
    "name:msa_x_preferred":[
        "Cabov"
    ],
    "name:nld_x_preferred":[
        "Cabov"
    ],
    "name:pol_x_preferred":[
        "Cabov"
    ],
    "name:ron_x_preferred":[
        "Cabov"
    ],
    "name:slk_x_preferred":[
        "Cabov"
    ],
    "name:spa_x_preferred":[
        "Cabov"
    ],
    "name:srp_x_preferred":[
        "\u0426\u0430\u0431\u043e\u0432"
    ],
    "name:ukr_x_preferred":[
        "\u0426\u0430\u0431\u043e\u0432"
    ],
    "name:war_x_preferred":[
        "Cabov"
    ],
    "wof:name":"Cabov",
    "wof:placetype":"locality"
},
  "geometry": {"coordinates":[21.64945,48.80255],"type":"Point"}
}