{
  "type": "Feature",
  "properties": {
    "gn:admin1_code":"01",
    "gn:asciiname":"Horne Strhare",
    "gn:country_code":"SK",
    "gn:dem":241,
    "gn:feature_class":"P",
    "gn:feature_code":"PPL",
    "gn:name":"Horn\u00e9 Strh\u00e1re",
    "gn:population":0,
    "gn:timezone":"Europe/Bratislava",
    "iso:country":"SK",
    "name:und_x_variant":[
        "Horn\u00ed Strh\u00e1ry",
        "Hornie Strh\u00e1ry",
        "Horn\u00e9 Strh\u00e1re"
    ],
    "wof:name":"Horne Strhare",
    "wof:placetype":"locality"
},
  "geometry": {"coordinates":[19.36276,48.27017],"type":"Point"}
}