{
  "type": "Feature",
  "properties": {
    "gn:gn_country":"SK",
    "gn:gn_fcode":"PPL",
    "gn:gn_pop":0,
    "iso:country":"SK",
    "name:cat_x_preferred":[
        "Drienica"
    ],
    "name:cze_x_preferred":[
        "Drienica"
    ],
    "name:dut_x_preferred":[
        "Drienica"
    ],
    "name:eng_x_preferred":[
        "Drienica"
    ],
    "name:epo_x_preferred":[
        "Drienica"
    ],
    "name:fre_x_preferred":[
        "Drienica"
    ],
    "name:hun_x_preferred":[
        "Fels\u0151som"
    ],
    "name:ita_x_preferred":[
        "Drienica"
    ],
    "name:may_x_preferred":[
        "Drienica"
    ],
    "name:pol_x_preferred":[
        "Drienica"
    ],
    "name:rue_x_preferred":[
        "\u0414\u0440\u0454\u043d\u0456\u0446\u044f"
    ],
    "name:slo_x_preferred":[
        "Drienica"
    ],
    "name:srp_x_preferred":[
        "\u0414\u0440\u0458\u0435\u045a\u0438\u0446\u0430"
    ],
    "name:ukr_x_preferred":[
        "\u0414\u0440'\u0454\u043d\u0438\u0446\u044f"
    ],
    "name:unk_x_variant":[
        "\u0160oma"
    ],
    "name:war_x_preferred":[
        "Drienica"
    ],
    "qs_pg:aaroncc":"SK",
    "qs_pg:gn_country":"SK",
    "qs_pg:gn_fcode":"PPL",
    "qs_pg:gn_pop":0,
    "qs_pg:name":"Drienica",
    "qs_pg:name_adm0":"Slovensk\u00e1",
    "qs_pg:name_adm1":"Presovsky",
    "qs_pg:photos_9r":0,
    "qs_pg:photos_sr":0,
    "qs_pg:pop_sr":0,
    "qs_pg:qs_pg_placetype":"locality",
    "qs_pg:qs_pg_placetype_gp":"Town",
    "qs_pg:woe_adm0":23424877,
    "woe:adm0_id":23424877,
    "woe:name_adm0":"Slovensk\u00e1",
    "woe:name_adm1":"Presovsky",
    "woe:placetype":"Town",
    "wof:name":"Drienica",
    "wof:placetype":"locality"
},
  "geometry": {"coordinates":[21.11064,49.13113],"type":"Point"}
}