{
  "type": "Feature",
  "properties": {
    "gn:admin1_code":"01",
    "gn:asciiname":"Lovca",
    "gn:country_code":"SK",
    "gn:dem":242,
    "gn:feature_class":"P",
    "gn:feature_code":"PPL",
    "gn:name":"Lov\u010da",
    "gn:population":0,
    "gn:timezone":"Europe/Bratislava",
    "iso:country":"SK",
    "name:cat_x_preferred":[
        "Lov\u010da"
    ],
    "name:ces_x_preferred":[
        "Lov\u010da"
    ],
    "name:deu_x_preferred":[
        "Lov\u010da"
    ],
    "name:epo_x_preferred":[
        "Lov\u010da"
    ],
    "name:eus_x_preferred":[
        "Lov\u010da"
    ],
    "name:fra_x_preferred":[
        "Lov\u010da"
    ],
    "name:hun_x_preferred":[
        "Nagyl\u00f3csa"
    ],
    "name:ita_x_preferred":[
        "Lov\u010da"
    ],
    "name:msa_x_preferred":[
        "Lov\u010da"
    ],
    "name:nld_x_preferred":[
        "Lov\u010da"
    ],
    "name:pol_x_preferred":[
        "Lov\u010da"
    ],
    "name:ron_x_preferred":[
        "Lov\u010da"
    ],
    "name:slk_x_preferred":[
        "Lov\u010da"
    ],
    "name:spa_x_preferred":[
        "Lov\u010da"
    ],
    "name:srp_x_preferred":[
        "\u041b\u043e\u0432\u0447\u0430"
    ],
    "name:ukr_x_preferred":[
        "\u041b\u043e\u0432\u0447\u0430"
    ],
    "name:war_x_preferred":[
        "Lov\u010da"
    ],
    "wof:name":"Lovca",
    "wof:placetype":"locality"
},
  "geometry": {"coordinates":[18.81578,48.57169],"type":"Point"}
}