{
  "type": "Feature",
  "properties": {
    "gn:admin1_code":"01",
    "gn:asciiname":"Lovca",
    "gn:country_code":"SK",
    "gn:dem":242,
    "gn:feature_class":"P",
    "gn:feature_code":"PPL",
    "gn:name":"Lov\u010da",
    "gn:population":0,
    "gn:timezone":"Europe/Bratislava",
    "iso:country":"SK",
    "name:und_x_variant":[
        "Lov\u010da"
    ],
    "wof:name":"Lovca",
    "wof:placetype":"locality"
},
  "geometry": {"coordinates":[18.81578,48.57169],"type":"Point"}
}