{
  "type": "Feature",
  "properties": {
    "gn:admin1_code":"00",
    "gn:asciiname":"Certov",
    "gn:country_code":"SK",
    "gn:dem":517,
    "gn:feature_class":"P",
    "gn:feature_code":"PPL",
    "gn:name":"\u010certov",
    "gn:population":0,
    "gn:timezone":"Europe/Bratislava",
    "iso:country":"SK",
    "wof:name":"Certov",
    "wof:placetype":"locality"
},
  "geometry": {"coordinates":[18.21758,49.2756],"type":"Point"}
}