{
  "type": "Feature",
  "properties": {
    "gn:admin1_code":"05",
    "gn:asciiname":"Kremna",
    "gn:country_code":"SK",
    "gn:dem":589,
    "gn:feature_class":"P",
    "gn:feature_code":"PPL",
    "gn:name":"Kremn\u00e1",
    "gn:population":0,
    "gn:timezone":"Europe/Bratislava",
    "iso:country":"SK",
    "name:und_x_variant":[
        "Krempach",
        "Kremn\u00e1"
    ],
    "wof:name":"Kremna",
    "wof:placetype":"locality"
},
  "geometry": {"coordinates":[20.69965,49.35848],"type":"Point"}
}