{
  "type": "Feature",
  "properties": {
    "gn:admin1_code":"05",
    "gn:asciiname":"Kremna",
    "gn:country_code":"SK",
    "gn:dem":589,
    "gn:feature_class":"P",
    "gn:feature_code":"PPL",
    "gn:name":"Kremn\u00e1",
    "gn:population":0,
    "gn:timezone":"Europe/Bratislava",
    "iso:country":"SK",
    "name:cat_x_preferred":[
        "Kremn\u00e1"
    ],
    "name:ces_x_preferred":[
        "Kremn\u00e1"
    ],
    "name:deu_x_preferred":[
        "Kremn\u00e1"
    ],
    "name:epo_x_preferred":[
        "Kremn\u00e1"
    ],
    "name:eus_x_preferred":[
        "Kremn\u00e1"
    ],
    "name:fra_x_preferred":[
        "Kremn\u00e1"
    ],
    "name:hun_x_preferred":[
        "Lubl\u00f3korompa"
    ],
    "name:ita_x_preferred":[
        "Kremn\u00e1"
    ],
    "name:msa_x_preferred":[
        "Kremn\u00e1"
    ],
    "name:nld_x_preferred":[
        "Kremn\u00e1"
    ],
    "name:pol_x_preferred":[
        "Kremna"
    ],
    "name:ron_x_preferred":[
        "Kremn\u00e1"
    ],
    "name:rue_x_preferred":[
        "\u041a\u0440\u0435\u043c\u043d\u0430"
    ],
    "name:slk_x_preferred":[
        "Kremn\u00e1"
    ],
    "name:spa_x_preferred":[
        "Kremn\u00e1"
    ],
    "name:srp_x_preferred":[
        "\u041a\u0440\u0435\u043c\u043d\u0430"
    ],
    "name:ukr_x_preferred":[
        "\u041a\u0440\u0435\u043c\u043d\u0430"
    ],
    "name:und_x_variant":[
        "Krempach"
    ],
    "name:war_x_preferred":[
        "Kremn\u00e1"
    ],
    "wof:name":"Kremna",
    "wof:placetype":"locality"
},
  "geometry": {"coordinates":[20.69965,49.35848],"type":"Point"}
}