{
  "type": "Feature",
  "properties": {
    "gn:admin1_code":"05",
    "gn:asciiname":"Matejovce",
    "gn:country_code":"SK",
    "gn:dem":659,
    "gn:feature_class":"P",
    "gn:feature_code":"PPL",
    "gn:name":"Matejovce",
    "gn:population":0,
    "gn:timezone":"Europe/Bratislava",
    "iso:country":"SK",
    "name:deu_x_preferred":[
        "Matzdorf"
    ],
    "wof:name":"Matejovce",
    "wof:placetype":"locality"
},
  "geometry": {"coordinates":[20.32801,49.07991],"type":"Point"}
}