{
  "type": "Feature",
  "properties": {
    "gn:admin1_code":"04",
    "gn:asciiname":"Borcice",
    "gn:country_code":"SK",
    "gn:dem":226,
    "gn:feature_class":"P",
    "gn:feature_code":"PPL",
    "gn:name":"Bor\u010dice",
    "gn:population":0,
    "gn:timezone":"Europe/Bratislava",
    "iso:country":"SK",
    "name:cat_x_preferred":[
        "Bor\u010dice"
    ],
    "name:ces_x_preferred":[
        "Bor\u010dice"
    ],
    "name:deu_x_preferred":[
        "Bor\u010dice"
    ],
    "name:epo_x_preferred":[
        "Bor\u010dice"
    ],
    "name:eus_x_preferred":[
        "Bor\u010dice"
    ],
    "name:fra_x_preferred":[
        "Bor\u010dice"
    ],
    "name:hun_x_preferred":[
        "Borcsic"
    ],
    "name:ita_x_preferred":[
        "Bor\u010dice"
    ],
    "name:msa_x_preferred":[
        "Bor\u010dice"
    ],
    "name:nld_x_preferred":[
        "Bor\u010dice"
    ],
    "name:ron_x_preferred":[
        "Bor\u010dice"
    ],
    "name:slk_x_preferred":[
        "Bor\u010dice"
    ],
    "name:spa_x_preferred":[
        "Bor\u010dice"
    ],
    "name:srp_x_preferred":[
        "\u0411\u043e\u0440\u0447\u0438\u0446\u0435"
    ],
    "name:ukr_x_preferred":[
        "\u0411\u043e\u0440\u0447\u0438\u0446\u0435"
    ],
    "name:war_x_preferred":[
        "Bor\u010dice"
    ],
    "wof:name":"Borcice",
    "wof:placetype":"locality"
},
  "geometry": {"coordinates":[18.14148,48.97815],"type":"Point"}
}