{
  "type": "Feature",
  "properties": {
    "iso:country":"SK",
    "name:cat_x_preferred":[
        "Bertotovce"
    ],
    "name:ces_x_preferred":[
        "Bertotovce"
    ],
    "name:deu_x_preferred":[
        "Bertotovce"
    ],
    "name:epo_x_preferred":[
        "Bertotovce"
    ],
    "name:eus_x_preferred":[
        "Bertotovce"
    ],
    "name:fra_x_preferred":[
        "Bertotovce"
    ],
    "name:hun_x_preferred":[
        "Bert\u00f3t"
    ],
    "name:ita_x_preferred":[
        "Bertotovce"
    ],
    "name:msa_x_preferred":[
        "Bertotovce"
    ],
    "name:nld_x_preferred":[
        "Bertotovce"
    ],
    "name:pol_x_preferred":[
        "Bertotovce"
    ],
    "name:ron_x_preferred":[
        "Bertotovce"
    ],
    "name:rue_x_preferred":[
        "\u0411\u0435\u0440\u0442\u043e\u0442\u043e\u0432\u0446\u0435"
    ],
    "name:slk_x_preferred":[
        "Bertotovce"
    ],
    "name:spa_x_preferred":[
        "Bertotovce"
    ],
    "name:srp_x_preferred":[
        "\u0411\u0435\u0440\u0442\u043e\u0442\u043e\u0432\u0446\u0435"
    ],
    "name:ukr_x_preferred":[
        "\u0411\u0435\u0440\u0442\u043e\u0442\u043e\u0432\u0446\u0435"
    ],
    "name:war_x_preferred":[
        "Bertotovce"
    ],
    "qs_pg:aaroncc":"SK",
    "qs_pg:name":"Bertotovce",
    "qs_pg:name_adm0":"Slovensk\u00e1",
    "qs_pg:name_adm1":"Presovsky",
    "qs_pg:photos":5,
    "qs_pg:photos_1k":1,
    "qs_pg:photos_9k":1,
    "qs_pg:photos_9r":1,
    "qs_pg:photos_all":5,
    "qs_pg:photos_sr":1,
    "qs_pg:pop_sr":0,
    "qs_pg:qs_pg_placetype":"localadmin",
    "qs_pg:qs_pg_placetype_gp":"LocalAdmin",
    "qs_pg:woe_adm0":23424877,
    "woe:adm0_id":23424877,
    "woe:name_adm0":"Slovensk\u00e1",
    "woe:name_adm1":"Presovsky",
    "woe:placetype":"LocalAdmin",
    "wof:name":"Bertotovce",
    "wof:placetype":"localadmin"
},
  "geometry": {"coordinates":[21.02423,49.02158],"type":"Point"}
}