{
  "type": "Feature",
  "properties": {
    "gn:admin1_code":"03",
    "gn:asciiname":"Janik",
    "gn:country_code":"SK",
    "gn:dem":185,
    "gn:feature_class":"P",
    "gn:feature_code":"PPL",
    "gn:name":"Jan\u00edk",
    "gn:population":0,
    "gn:timezone":"Europe/Bratislava",
    "iso:country":"SK",
    "name:und_x_variant":[
        "J\u00e1nok",
        "Jan\u00edk"
    ],
    "wof:name":"Janik",
    "wof:placetype":"locality"
},
  "geometry": {"coordinates":[20.96882,48.55483],"type":"Point"}
}