{
  "type": "Feature",
  "properties": {
    "gn:admin1_code":"03",
    "gn:asciiname":"Janik",
    "gn:country_code":"SK",
    "gn:dem":185,
    "gn:feature_class":"P",
    "gn:feature_code":"PPL",
    "gn:name":"Jan\u00edk",
    "gn:population":0,
    "gn:timezone":"Europe/Bratislava",
    "iso:country":"SK",
    "name:cat_x_preferred":[
        "Jan\u00edk"
    ],
    "name:epo_x_preferred":[
        "Jan\u00edk"
    ],
    "name:eus_x_preferred":[
        "Jan\u00edk"
    ],
    "name:fra_x_preferred":[
        "Jan\u00edk"
    ],
    "name:hun_x_preferred":[
        "J\u00e1nok"
    ],
    "name:ita_x_preferred":[
        "Jan\u00edk"
    ],
    "name:msa_x_preferred":[
        "Jan\u00edk"
    ],
    "name:nld_x_preferred":[
        "Jan\u00edk"
    ],
    "name:pol_x_preferred":[
        "Jan\u00edk"
    ],
    "name:ron_x_preferred":[
        "Jan\u00edk"
    ],
    "name:slk_x_preferred":[
        "Jan\u00edk"
    ],
    "name:spa_x_preferred":[
        "Jan\u00edk"
    ],
    "name:srp_x_preferred":[
        "\u0408\u0430\u045a\u0438\u043a"
    ],
    "name:ukr_x_preferred":[
        "\u042f\u043d\u0456\u043a"
    ],
    "name:und_x_variant":[
        "J\u00e1nok",
        "Jan\u00edk"
    ],
    "name:war_x_preferred":[
        "Jan\u00edk"
    ],
    "wof:name":"Janik",
    "wof:placetype":"locality"
},
  "geometry": {"coordinates":[20.96882,48.55483],"type":"Point"}
}