{
  "type": "Feature",
  "properties": {
    "gn:admin1_code":"03",
    "gn:asciiname":"Herl'any",
    "gn:country_code":"SK",
    "gn:dem":376,
    "gn:feature_class":"P",
    "gn:feature_code":"PPL",
    "gn:name":"Her\u013eany",
    "gn:population":0,
    "gn:timezone":"Europe/Bratislava",
    "iso:country":"SK",
    "name:cat_x_preferred":[
        "Her\u013eany"
    ],
    "name:deu_x_preferred":[
        "Her\u013eany"
    ],
    "name:epo_x_preferred":[
        "Her\u013eany"
    ],
    "name:eus_x_preferred":[
        "Her\u013eany"
    ],
    "name:fra_x_preferred":[
        "Her\u013eany"
    ],
    "name:hun_x_preferred":[
        "R\u00e1nkf\u00fcred"
    ],
    "name:ita_x_preferred":[
        "Her\u013eany"
    ],
    "name:msa_x_preferred":[
        "Her\u013eany"
    ],
    "name:nld_x_preferred":[
        "Her\u013eany"
    ],
    "name:pol_x_preferred":[
        "Her\u013eany"
    ],
    "name:ron_x_preferred":[
        "Her\u013eany"
    ],
    "name:slk_x_preferred":[
        "Her\u013eany"
    ],
    "name:spa_x_preferred":[
        "Her\u013eany"
    ],
    "name:srp_x_preferred":[
        "\u0425\u0435\u0440\u0459\u0430\u043d\u0438"
    ],
    "name:ukr_x_preferred":[
        "\u0413\u0435\u0440\u043b\u044f\u043d\u0438"
    ],
    "name:und_x_variant":[
        "Her\u013eany"
    ],
    "name:war_x_preferred":[
        "Her\u013eany"
    ],
    "wof:name":"Herl'any",
    "wof:placetype":"locality"
},
  "geometry": {"coordinates":[21.47661,48.79975],"type":"Point"}
}