{
  "type": "Feature",
  "properties": {
    "gn:admin1_code":"03",
    "gn:asciiname":"Herl'any",
    "gn:country_code":"SK",
    "gn:dem":376,
    "gn:feature_class":"P",
    "gn:feature_code":"PPL",
    "gn:name":"Her\u013eany",
    "gn:population":0,
    "gn:timezone":"Europe/Bratislava",
    "iso:country":"SK",
    "name:und_x_variant":[
        "Her\u013eany"
    ],
    "wof:name":"Herl'any",
    "wof:placetype":"locality"
},
  "geometry": {"coordinates":[21.47661,48.79975],"type":"Point"}
}