{
  "type": "Feature",
  "properties": {
    "gn:admin1_code":"01",
    "gn:asciiname":"Horna Trnavka",
    "gn:country_code":"SK",
    "gn:dem":305,
    "gn:feature_class":"P",
    "gn:feature_code":"PPL",
    "gn:name":"Horn\u00e1 Trn\u00e1vka",
    "gn:population":0,
    "gn:timezone":"Europe/Bratislava",
    "iso:country":"SK",
    "wof:name":"Horna Trnavka",
    "wof:placetype":"locality"
},
  "geometry": {"coordinates":[18.75866,48.57904],"type":"Point"}
}