{
  "type": "Feature",
  "properties": {
    "gn:admin1_code":"02",
    "gn:asciiname":"Mast",
    "gn:country_code":"SK",
    "gn:dem":176,
    "gn:feature_class":"P",
    "gn:feature_code":"PPL",
    "gn:name":"M\u00e1st",
    "gn:population":0,
    "gn:timezone":"Europe/Bratislava",
    "iso:country":"SK",
    "wof:name":"Mast",
    "wof:placetype":"locality"
},
  "geometry": {"coordinates":[17.03053,48.26448],"type":"Point"}
}