{
  "type": "Feature",
  "properties": {
    "gn:admin1_code":"02",
    "gn:asciiname":"Mast",
    "gn:country_code":"SK",
    "gn:dem":176,
    "gn:feature_class":"P",
    "gn:feature_code":"PPL",
    "gn:name":"M\u00e1st",
    "gn:population":0,
    "gn:timezone":"Europe/Bratislava",
    "iso:country":"SK",
    "name:bul_x_preferred":[
        "\u041c\u0430\u0447\u0442\u0430"
    ],
    "name:ceb_x_preferred":[
        "Mast"
    ],
    "name:deu_x_preferred":[
        "Mast"
    ],
    "name:est_x_preferred":[
        "Mast"
    ],
    "name:fas_x_preferred":[
        "\u0645\u0633\u062a"
    ],
    "name:ita_x_preferred":[
        "Mast"
    ],
    "name:jpn_x_preferred":[
        "\u30de\u30b9\u30c8"
    ],
    "name:nld_x_preferred":[
        "Mast"
    ],
    "name:rus_x_preferred":[
        "\u041c\u0430\u0447\u0442\u0430"
    ],
    "name:ukr_x_preferred":[
        "\u0429\u043e\u0433\u043b\u0430"
    ],
    "wof:name":"Mast",
    "wof:placetype":"locality"
},
  "geometry": {"coordinates":[17.03053,48.26448],"type":"Point"}
}