{
  "type": "Feature",
  "properties": {
    "gn:admin1_code":"03",
    "gn:asciiname":"Trnavka",
    "gn:country_code":"SK",
    "gn:dem":181,
    "gn:feature_class":"P",
    "gn:feature_code":"PPL",
    "gn:name":"Trnavka",
    "gn:population":0,
    "gn:timezone":"Europe/Bratislava",
    "iso:country":"SK",
    "name:cat_x_preferred":[
        "Trn\u00e1vka"
    ],
    "name:ces_x_preferred":[
        "Trn\u00e1vka"
    ],
    "name:epo_x_preferred":[
        "Trn\u00e1vka"
    ],
    "name:eus_x_preferred":[
        "Trn\u00e1vka"
    ],
    "name:hun_x_preferred":[
        "Tarn\u00f3ka"
    ],
    "name:ita_x_preferred":[
        "Trn\u00e1vka"
    ],
    "name:msa_x_preferred":[
        "Trn\u00e1vka"
    ],
    "name:nld_x_preferred":[
        "Trn\u00e1vka"
    ],
    "name:pol_x_preferred":[
        "Trn\u00e1vka"
    ],
    "name:ron_x_preferred":[
        "Trn\u00e1vka"
    ],
    "name:rue_x_preferred":[
        "\u0422\u044b\u0440\u043d\u0430\u0432\u043a\u0430"
    ],
    "name:slk_x_preferred":[
        "Trn\u00e1vka"
    ],
    "name:spa_x_preferred":[
        "Trn\u00e1vka"
    ],
    "name:srp_x_preferred":[
        "\u0422\u0440\u043d\u0430\u0432\u043a\u0430"
    ],
    "name:ukr_x_preferred":[
        "\u0422\u0440\u043d\u0430\u0432\u043a\u0430"
    ],
    "name:und_x_variant":[
        "Ternavka",
        "Trnavka"
    ],
    "name:war_x_preferred":[
        "Trn\u00e1vka"
    ],
    "wof:name":"Trnavka",
    "wof:placetype":"locality"
},
  "geometry": {"coordinates":[21.6174,48.70694],"type":"Point"}
}