{
  "type": "Feature",
  "properties": {
    "gn:admin1_code":"08",
    "gn:asciiname":"Blatnicky Hrad",
    "gn:country_code":"SK",
    "gn:dem":560,
    "gn:feature_class":"P",
    "gn:feature_code":"PPL",
    "gn:name":"Blatnick\u00fd Hrad",
    "gn:population":0,
    "gn:timezone":"Europe/Bratislava",
    "iso:country":"SK",
    "wof:name":"Blatnicky Hrad",
    "wof:placetype":"locality"
},
  "geometry": {"coordinates":[18.94891,48.94727],"type":"Point"}
}