{
  "type": "Feature",
  "properties": {
    "gn:admin1_code":"01",
    "gn:asciiname":"Cert'azky",
    "gn:country_code":"SK",
    "gn:dem":688,
    "gn:feature_class":"P",
    "gn:feature_code":"PPL",
    "gn:name":"\u010cer\u0165a\u017eky",
    "gn:population":0,
    "gn:timezone":"Europe/Bratislava",
    "iso:country":"SK",
    "wof:name":"Cert'azky",
    "wof:placetype":"locality"
},
  "geometry": {"coordinates":[19.31027000000001,48.41202],"type":"Point"}
}