{
  "type": "Feature",
  "properties": {
    "gn:admin1_code":"05",
    "gn:asciiname":"Paseky",
    "gn:country_code":"SK",
    "gn:dem":190,
    "gn:feature_class":"P",
    "gn:feature_code":"PPL",
    "gn:name":"Paseky",
    "gn:population":0,
    "gn:timezone":"Europe/Bratislava",
    "iso:country":"SK",
    "name:und_x_variant":[
        "Dvor Paseky",
        "Paseky"
    ],
    "wof:name":"Paseky",
    "wof:placetype":"locality"
},
  "geometry": {"coordinates":[21.56926,48.97157],"type":"Point"}
}