{
  "type": "Feature",
  "properties": {
    "gn:admin1_code":"08",
    "gn:asciiname":"Vieska",
    "gn:country_code":"SK",
    "gn:dem":506,
    "gn:feature_class":"P",
    "gn:feature_code":"PPL",
    "gn:name":"Vieska",
    "gn:population":0,
    "gn:timezone":"Europe/Bratislava",
    "iso:country":"SK",
    "name:deu_x_preferred":[
        "Vieska"
    ],
    "name:epo_x_preferred":[
        "Vieska"
    ],
    "name:fra_x_preferred":[
        "Vieska"
    ],
    "name:hun_x_preferred":[
        "Vieska"
    ],
    "name:ita_x_preferred":[
        "Vieska"
    ],
    "name:nld_x_preferred":[
        "Vieska"
    ],
    "name:slk_x_preferred":[
        "Vieska"
    ],
    "name:srp_x_preferred":[
        "\u0412\u0458\u0435\u0441\u043a\u0430"
    ],
    "name:ukr_x_preferred":[
        "\u0412\u0454\u0441\u043a\u0430"
    ],
    "wof:name":"Vieska",
    "wof:placetype":"locality"
},
  "geometry": {"coordinates":[18.85,48.86667],"type":"Point"}
}