{
  "type": "Feature",
  "properties": {
    "gn:admin1_code":"07",
    "gn:asciiname":"Brezina",
    "gn:country_code":"SK",
    "gn:dem":317,
    "gn:feature_class":"P",
    "gn:feature_code":"PPL",
    "gn:name":"Brezina",
    "gn:population":0,
    "gn:timezone":"Europe/Bratislava",
    "iso:country":"SK",
    "name:ceb_x_preferred":[
        "Brezina"
    ],
    "name:ces_x_preferred":[
        "Brezina"
    ],
    "name:deu_x_preferred":[
        "Brezina"
    ],
    "name:epo_x_preferred":[
        "Brezina"
    ],
    "name:fra_x_preferred":[
        "Brezina"
    ],
    "name:hun_x_preferred":[
        "Brezina"
    ],
    "name:slk_x_preferred":[
        "Brezina"
    ],
    "name:spa_x_preferred":[
        "Brezina"
    ],
    "name:srp_x_preferred":[
        "\u0411\u0440\u0435\u0437\u0438\u043d\u0430"
    ],
    "name:swe_x_preferred":[
        "Brezina"
    ],
    "wof:name":"Brezina",
    "wof:placetype":"locality"
},
  "geometry": {"coordinates":[17.36904,48.52916],"type":"Point"}
}