{
  "type": "Feature",
  "properties": {
    "gn:admin1_code":"07",
    "gn:asciiname":"Brezina",
    "gn:country_code":"SK",
    "gn:dem":317,
    "gn:feature_class":"P",
    "gn:feature_code":"PPL",
    "gn:name":"Brezina",
    "gn:population":0,
    "gn:timezone":"Europe/Bratislava",
    "iso:country":"SK",
    "wof:name":"Brezina",
    "wof:placetype":"locality"
},
  "geometry": {"coordinates":[17.36904,48.52916],"type":"Point"}
}