{
  "type": "Feature",
  "properties": {
    "gn:admin1_code":"04",
    "gn:asciiname":"Upohlav",
    "gn:country_code":"SK",
    "gn:dem":333,
    "gn:feature_class":"P",
    "gn:feature_code":"PPL",
    "gn:name":"Upohlav",
    "gn:population":0,
    "gn:timezone":"Europe/Bratislava",
    "iso:country":"SK",
    "wof:name":"Upohlav",
    "wof:placetype":"locality"
},
  "geometry": {"coordinates":[18.37969,49.16223],"type":"Point"}
}