{
  "type": "Feature",
  "properties": {
    "gn:admin1_code":"08",
    "gn:asciiname":"Jastrabie",
    "gn:country_code":"SK",
    "gn:dem":602,
    "gn:feature_class":"P",
    "gn:feature_code":"PPL",
    "gn:name":"Jastrabie",
    "gn:population":0,
    "gn:timezone":"Europe/Bratislava",
    "iso:country":"SK",
    "wof:name":"Jastrabie",
    "wof:placetype":"locality"
},
  "geometry": {"coordinates":[18.71667,49.35],"type":"Point"}
}