{
  "type": "Feature",
  "properties": {
    "gn:admin1_code":"04",
    "gn:asciiname":"Branovo",
    "gn:country_code":"SK",
    "gn:dem":126,
    "gn:feature_class":"P",
    "gn:feature_code":"PPL",
    "gn:name":"Branovo",
    "gn:population":0,
    "gn:timezone":"Europe/Bratislava",
    "iso:country":"SK",
    "name:hun_x_preferred":[
        "Kisbaromlak"
    ],
    "name:und_x_variant":[
        "Baromlak"
    ],
    "wof:name":"Branovo",
    "wof:placetype":"locality"
},
  "geometry": {"coordinates":[18.30803,48.02323],"type":"Point"}
}