{
  "type": "Feature",
  "properties": {
    "gn:admin1_code":"04",
    "gn:asciiname":"Branovo",
    "gn:country_code":"SK",
    "gn:dem":126,
    "gn:feature_class":"P",
    "gn:feature_code":"PPL",
    "gn:name":"Branovo",
    "gn:population":0,
    "gn:timezone":"Europe/Bratislava",
    "iso:country":"SK",
    "name:cat_x_preferred":[
        "Branovo"
    ],
    "name:epo_x_preferred":[
        "Branovo"
    ],
    "name:eus_x_preferred":[
        "Branovo"
    ],
    "name:fra_x_preferred":[
        "Branovo"
    ],
    "name:hun_x_preferred":[
        "Kisbaromlak"
    ],
    "name:ita_x_preferred":[
        "Branovo"
    ],
    "name:msa_x_preferred":[
        "Branovo"
    ],
    "name:nld_x_preferred":[
        "Branovo"
    ],
    "name:ron_x_preferred":[
        "Branovo"
    ],
    "name:slk_x_preferred":[
        "Branovo"
    ],
    "name:spa_x_preferred":[
        "Branovo"
    ],
    "name:srp_x_preferred":[
        "\u0411\u0440\u0430\u043d\u043e\u0432\u043e"
    ],
    "name:und_x_variant":[
        "Baromlak"
    ],
    "name:war_x_preferred":[
        "Branovo"
    ],
    "wof:name":"Branovo",
    "wof:placetype":"locality"
},
  "geometry": {"coordinates":[18.30803,48.02323],"type":"Point"}
}