{
  "type": "Feature",
  "properties": {
    "gn:admin1_code":"05",
    "gn:asciiname":"Slatvina",
    "gn:country_code":"SK",
    "gn:dem":467,
    "gn:feature_class":"P",
    "gn:feature_code":"PPL",
    "gn:name":"Slatvina",
    "gn:population":0,
    "gn:timezone":"Europe/Bratislava",
    "iso:country":"SK",
    "name:cat_x_preferred":[
        "Slatvina"
    ],
    "name:ces_x_preferred":[
        "Slatvina"
    ],
    "name:deu_x_preferred":[
        "Slatvina"
    ],
    "name:epo_x_preferred":[
        "Slatvina"
    ],
    "name:eus_x_preferred":[
        "Slatvina"
    ],
    "name:fra_x_preferred":[
        "Slatvina"
    ],
    "name:hun_x_preferred":[
        "Szlatvin"
    ],
    "name:ita_x_preferred":[
        "Slatvina"
    ],
    "name:msa_x_preferred":[
        "Slatvina"
    ],
    "name:nld_x_preferred":[
        "Slatvina"
    ],
    "name:pol_x_preferred":[
        "Slatvina"
    ],
    "name:ron_x_preferred":[
        "Slatvina"
    ],
    "name:slk_x_preferred":[
        "Slatvina"
    ],
    "name:spa_x_preferred":[
        "Slatvina"
    ],
    "name:srp_x_preferred":[
        "\u0421\u043b\u0430\u0442\u0432\u0438\u043d\u0430"
    ],
    "name:ukr_x_preferred":[
        "\u0421\u043b\u0430\u0442\u0432\u0438\u043d\u0430"
    ],
    "name:war_x_preferred":[
        "Slatvina"
    ],
    "wof:name":"Slatvina",
    "wof:placetype":"locality"
},
  "geometry": {"coordinates":[20.84202,48.96228],"type":"Point"}
}