{
  "type": "Feature",
  "properties": {
    "gn:admin1_code":"05",
    "gn:asciiname":"Hrabovcik",
    "gn:country_code":"SK",
    "gn:dem":272,
    "gn:feature_class":"P",
    "gn:feature_code":"PPL",
    "gn:name":"Hrabov\u010d\u00edk",
    "gn:population":0,
    "gn:timezone":"Europe/Bratislava",
    "iso:country":"SK",
    "name:cat_x_preferred":[
        "Hrabov\u010d\u00edk"
    ],
    "name:epo_x_preferred":[
        "Hrabov\u010d\u00edk"
    ],
    "name:eus_x_preferred":[
        "Hrabov\u010d\u00edk"
    ],
    "name:fra_x_preferred":[
        "Hrabov\u010d\u00edk"
    ],
    "name:hun_x_preferred":[
        "Gyerty\u00e1npatak"
    ],
    "name:ita_x_preferred":[
        "Hrabov\u010d\u00edk"
    ],
    "name:msa_x_preferred":[
        "Hrabov\u010d\u00edk"
    ],
    "name:nld_x_preferred":[
        "Hrabov\u010d\u00edk"
    ],
    "name:pol_x_preferred":[
        "Hrabov\u010d\u00edk"
    ],
    "name:ron_x_preferred":[
        "Hrabov\u010d\u00edk"
    ],
    "name:rue_x_preferred":[
        "\u0413\u0440\u0430\u0431\u0456\u0432\u0447\u0456\u043a"
    ],
    "name:slk_x_preferred":[
        "Hrabov\u010d\u00edk"
    ],
    "name:spa_x_preferred":[
        "Hrabov\u010d\u00edk"
    ],
    "name:srp_x_preferred":[
        "\u0425\u0440\u0430\u0431\u043e\u0432\u0447\u0438\u043a"
    ],
    "name:ukr_x_preferred":[
        "\u0413\u0440\u0430\u0431\u043e\u0432\u0447\u0438\u043a"
    ],
    "name:und_x_variant":[
        "Hrabov\u010d\u00edk"
    ],
    "name:war_x_preferred":[
        "Hrabov\u010d\u00edk"
    ],
    "wof:name":"Hrabovcik",
    "wof:placetype":"locality"
},
  "geometry": {"coordinates":[21.5568,49.28043],"type":"Point"}
}