{
  "type": "Feature",
  "properties": {
    "gn:admin1_code":"05",
    "gn:asciiname":"Hrabovcik",
    "gn:country_code":"SK",
    "gn:dem":272,
    "gn:feature_class":"P",
    "gn:feature_code":"PPL",
    "gn:name":"Hrabov\u010d\u00edk",
    "gn:population":0,
    "gn:timezone":"Europe/Bratislava",
    "iso:country":"SK",
    "name:und_x_variant":[
        "Hrabov\u010d\u00edk"
    ],
    "wof:name":"Hrabovcik",
    "wof:placetype":"locality"
},
  "geometry": {"coordinates":[21.5568,49.28043],"type":"Point"}
}