{
  "type": "Feature",
  "properties": {
    "gn:admin1_code":"01",
    "gn:asciiname":"Pitelova",
    "gn:country_code":"SK",
    "gn:dem":452,
    "gn:feature_class":"P",
    "gn:feature_code":"PPL",
    "gn:name":"Pitelov\u00e1",
    "gn:population":0,
    "gn:timezone":"Europe/Bratislava",
    "iso:country":"SK",
    "name:und_x_variant":[
        "Pitelov\u00e1"
    ],
    "wof:name":"Pitelova",
    "wof:placetype":"locality"
},
  "geometry": {"coordinates":[18.92551,48.60298],"type":"Point"}
}