{
  "type": "Feature",
  "properties": {
    "gn:admin1_code":"01",
    "gn:asciiname":"Pitelova",
    "gn:country_code":"SK",
    "gn:dem":452,
    "gn:feature_class":"P",
    "gn:feature_code":"PPL",
    "gn:name":"Pitelov\u00e1",
    "gn:population":0,
    "gn:timezone":"Europe/Bratislava",
    "iso:country":"SK",
    "name:cat_x_preferred":[
        "Pitelov\u00e1"
    ],
    "name:ces_x_preferred":[
        "Pitelov\u00e1"
    ],
    "name:deu_x_preferred":[
        "Pitelov\u00e1"
    ],
    "name:epo_x_preferred":[
        "Pitelov\u00e1"
    ],
    "name:eus_x_preferred":[
        "Pitelov\u00e1"
    ],
    "name:fra_x_preferred":[
        "Pitelov\u00e1"
    ],
    "name:hun_x_preferred":[
        "Kiszelfalu"
    ],
    "name:ita_x_preferred":[
        "Pitelov\u00e1"
    ],
    "name:msa_x_preferred":[
        "Pitelov\u00e1"
    ],
    "name:nld_x_preferred":[
        "Pitelov\u00e1"
    ],
    "name:pol_x_preferred":[
        "Pitelov\u00e1"
    ],
    "name:ron_x_preferred":[
        "Pitelov\u00e1"
    ],
    "name:slk_x_preferred":[
        "Pitelov\u00e1"
    ],
    "name:spa_x_preferred":[
        "Pitelov\u00e1"
    ],
    "name:srp_x_preferred":[
        "\u041f\u0438\u0442\u0458\u0435\u043b\u043e\u0432\u0430"
    ],
    "name:ukr_x_preferred":[
        "\u041f\u0456\u0442\u0435\u043b\u043e\u0432\u0430"
    ],
    "name:war_x_preferred":[
        "Pitelov\u00e1"
    ],
    "wof:name":"Pitelova",
    "wof:placetype":"locality"
},
  "geometry": {"coordinates":[18.92551,48.60298],"type":"Point"}
}