{
  "type": "Feature",
  "properties": {
    "gn:admin1_code":"05",
    "gn:asciiname":"Hrabovec",
    "gn:country_code":"SK",
    "gn:dem":232,
    "gn:feature_class":"P",
    "gn:feature_code":"PPL",
    "gn:name":"Hrabovec",
    "gn:population":0,
    "gn:timezone":"Europe/Bratislava",
    "iso:country":"SK",
    "name:cat_x_preferred":[
        "Hrabovec"
    ],
    "name:ces_x_preferred":[
        "Hrabovec"
    ],
    "name:epo_x_preferred":[
        "Hrabovec"
    ],
    "name:eus_x_preferred":[
        "Hrabovec"
    ],
    "name:fra_x_preferred":[
        "Hrabovec"
    ],
    "name:hun_x_preferred":[
        "Rab\u00f3c"
    ],
    "name:ita_x_preferred":[
        "Hrabovec"
    ],
    "name:msa_x_preferred":[
        "Hrabovec"
    ],
    "name:nld_x_preferred":[
        "Hrabovec"
    ],
    "name:pol_x_preferred":[
        "Hrabovec"
    ],
    "name:ron_x_preferred":[
        "Hrabovec"
    ],
    "name:rue_x_preferred":[
        "\u0413\u0440\u0430\u0431\u043e\u0432\u0435\u0446\u044c"
    ],
    "name:slk_x_preferred":[
        "Hrabovec"
    ],
    "name:spa_x_preferred":[
        "Hrabovec"
    ],
    "name:srp_x_preferred":[
        "\u0425\u0440\u0430\u0431\u043e\u0432\u0435\u0446"
    ],
    "name:ukr_x_preferred":[
        "\u0413\u0440\u0430\u0431\u043e\u0432\u0435\u0446"
    ],
    "name:war_x_preferred":[
        "Hrabovec"
    ],
    "wof:name":"Hrabovec",
    "wof:placetype":"locality"
},
  "geometry": {"coordinates":[21.37897,49.27229000000001],"type":"Point"}
}