{
  "type": "Feature",
  "properties": {
    "gn:admin1_code":"01",
    "gn:asciiname":"Lukovistia",
    "gn:country_code":"SK",
    "gn:dem":357,
    "gn:feature_class":"P",
    "gn:feature_code":"PPL",
    "gn:name":"Lukovi\u0161tia",
    "gn:population":0,
    "gn:timezone":"Europe/Bratislava",
    "iso:country":"SK",
    "name:cat_x_preferred":[
        "Lukovi\u0161tia"
    ],
    "name:ces_x_preferred":[
        "Lukovi\u0161tia"
    ],
    "name:deu_x_preferred":[
        "Lukovi\u0161tia"
    ],
    "name:epo_x_preferred":[
        "Lukovi\u0161tia"
    ],
    "name:eus_x_preferred":[
        "Lukovi\u0161tia"
    ],
    "name:fra_x_preferred":[
        "Lukovi\u0161tia"
    ],
    "name:hun_x_preferred":[
        "K\u0151hegy"
    ],
    "name:ita_x_preferred":[
        "Lukovi\u0161tia"
    ],
    "name:msa_x_preferred":[
        "Lukovi\u0161tia"
    ],
    "name:nld_x_preferred":[
        "Lukovi\u0161tia"
    ],
    "name:pol_x_preferred":[
        "Lukovi\u0161tia"
    ],
    "name:ron_x_preferred":[
        "Lukovi\u0161tia"
    ],
    "name:slk_x_preferred":[
        "Lukovi\u0161tia"
    ],
    "name:spa_x_preferred":[
        "Lukovi\u0161tia"
    ],
    "name:srp_x_preferred":[
        "\u041b\u0443\u043a\u043e\u0432\u0438\u0448\u0442\u0458\u0430"
    ],
    "name:ukr_x_preferred":[
        "\u041b\u0443\u043a\u043e\u0432\u0456\u0448\u0442\u044c\u044f"
    ],
    "name:war_x_preferred":[
        "Lukovi\u0161tia"
    ],
    "wof:name":"Lukovistia",
    "wof:placetype":"locality"
},
  "geometry": {"coordinates":[20.02626,48.49181],"type":"Point"}
}