{
  "type": "Feature",
  "properties": {
    "gn:admin1_code":"01",
    "gn:asciiname":"Lukovistia",
    "gn:country_code":"SK",
    "gn:dem":357,
    "gn:feature_class":"P",
    "gn:feature_code":"PPL",
    "gn:name":"Lukovi\u0161tia",
    "gn:population":0,
    "gn:timezone":"Europe/Bratislava",
    "iso:country":"SK",
    "name:und_x_variant":[
        "Lukovi\u0161tia"
    ],
    "wof:name":"Lukovistia",
    "wof:placetype":"locality"
},
  "geometry": {"coordinates":[20.02626,48.49181],"type":"Point"}
}