{
  "type": "Feature",
  "properties": {
    "gn:admin1_code":"04",
    "gn:asciiname":"Csergo",
    "gn:country_code":"SK",
    "gn:dem":109,
    "gn:feature_class":"P",
    "gn:feature_code":"PPLL",
    "gn:name":"Cserg\u0151",
    "gn:population":0,
    "gn:timezone":"Europe/Bratislava",
    "iso:country":"SK",
    "name:hun_x_preferred":[
        "Cs\u00f6rg\u0151"
    ],
    "name:slk_x_preferred":[
        "\u010cergov"
    ],
    "wof:name":"Csergo",
    "wof:placetype":"locality"
},
  "geometry": {"coordinates":[18.01775,47.88769],"type":"Point"}
}