{
  "type": "Feature",
  "properties": {
    "gn:admin1_code":"01",
    "gn:asciiname":"Horne Terany",
    "gn:country_code":"SK",
    "gn:dem":147,
    "gn:feature_class":"P",
    "gn:feature_code":"PPL",
    "gn:name":"Horn\u00e9 Terany",
    "gn:population":0,
    "gn:timezone":"Europe/Bratislava",
    "iso:country":"SK",
    "name:hun_x_preferred":[
        "Fels\u0151ter\u00e9ny"
    ],
    "name:slk_x_historical":[
        "Horn\u00ed Terany",
        "Hornie Terany"
    ],
    "name:slk_x_preferred":[
        "Horn\u00e9 Terany"
    ],
    "name:slk_x_variant":[
        "Horn\u00ed Terany",
        "Hornie Terany"
    ],
    "wof:name":"Horne Terany",
    "wof:placetype":"locality"
},
  "geometry": {"coordinates":[18.89604,48.18334],"type":"Point"}
}