{
  "type": "Feature",
  "properties": {
    "gn:admin1_code":"01",
    "gn:asciiname":"Vrbovka",
    "gn:country_code":"SK",
    "gn:dem":147,
    "gn:feature_class":"P",
    "gn:feature_code":"PPL",
    "gn:name":"Vrbovka",
    "gn:population":0,
    "gn:timezone":"Europe/Bratislava",
    "iso:country":"SK",
    "name:cat_x_preferred":[
        "Vrbovka"
    ],
    "name:epo_x_preferred":[
        "Vrbovka"
    ],
    "name:eus_x_preferred":[
        "Vrbovka"
    ],
    "name:fra_x_preferred":[
        "Vrbovka"
    ],
    "name:hun_x_preferred":[
        "Ipolyvarb\u00f3"
    ],
    "name:ita_x_preferred":[
        "Vrbovka"
    ],
    "name:msa_x_preferred":[
        "Vrbovka"
    ],
    "name:nld_x_preferred":[
        "Vrbovka"
    ],
    "name:pol_x_preferred":[
        "Vrbovka"
    ],
    "name:ron_x_preferred":[
        "Vrbovka"
    ],
    "name:slk_x_preferred":[
        "Vrbovka"
    ],
    "name:spa_x_preferred":[
        "Vrbovka"
    ],
    "name:srp_x_preferred":[
        "\u0412\u0440\u0431\u043e\u0432\u043a\u0430"
    ],
    "name:ukr_x_preferred":[
        "\u0412\u0440\u0431\u043e\u0432\u043a\u0430"
    ],
    "name:und_x_variant":[
        "Varb\u00f3"
    ],
    "name:war_x_preferred":[
        "Vrbovka"
    ],
    "wof:name":"Vrbovka",
    "wof:placetype":"locality"
},
  "geometry": {"coordinates":[19.40872,48.09052],"type":"Point"}
}