{
  "type": "Feature",
  "properties": {
    "gn:admin1_code":"01",
    "gn:asciiname":"Vrbovka",
    "gn:country_code":"SK",
    "gn:dem":147,
    "gn:feature_class":"P",
    "gn:feature_code":"PPL",
    "gn:name":"Vrbovka",
    "gn:population":0,
    "gn:timezone":"Europe/Bratislava",
    "iso:country":"SK",
    "name:und_x_variant":[
        "Varb\u00f3",
        "Vrbovka"
    ],
    "wof:name":"Vrbovka",
    "wof:placetype":"locality"
},
  "geometry": {"coordinates":[19.40872,48.09052],"type":"Point"}
}