{
  "type": "Feature",
  "properties": {
    "gn:admin1_code":"04",
    "gn:asciiname":"Horny Kamenec",
    "gn:country_code":"SK",
    "gn:dem":382,
    "gn:feature_class":"P",
    "gn:feature_code":"PPL",
    "gn:name":"Horn\u00fd Kamenec",
    "gn:population":0,
    "gn:timezone":"Europe/Bratislava",
    "iso:country":"SK",
    "name:und_x_variant":[
        "Horn\u00ed Kamenec",
        "Horn\u00fd Kamenec"
    ],
    "wof:name":"Horny Kamenec",
    "wof:placetype":"locality"
},
  "geometry": {"coordinates":[18.56667,48.68333],"type":"Point"}
}