{
  "type": "Feature",
  "properties": {
    "gn:admin1_code":"05",
    "gn:asciiname":"Jablonov",
    "gn:country_code":"SK",
    "gn:dem":477,
    "gn:feature_class":"P",
    "gn:feature_code":"PPL",
    "gn:name":"Jablonov",
    "gn:population":0,
    "gn:timezone":"Europe/Bratislava",
    "iso:country":"SK",
    "name:cat_x_preferred":[
        "Jablonov"
    ],
    "name:ces_x_preferred":[
        "Jablonov"
    ],
    "name:deu_x_preferred":[
        "Jablonov"
    ],
    "name:epo_x_preferred":[
        "Jablonov"
    ],
    "name:eus_x_preferred":[
        "Jablonov"
    ],
    "name:fra_x_preferred":[
        "Jablonov"
    ],
    "name:hun_x_preferred":[
        "Szepesalm\u00e1s"
    ],
    "name:ita_x_preferred":[
        "Jablonov"
    ],
    "name:msa_x_preferred":[
        "Jablonov"
    ],
    "name:nld_x_preferred":[
        "Jablonov"
    ],
    "name:pol_x_preferred":[
        "Jablonov"
    ],
    "name:ron_x_preferred":[
        "Jablonov"
    ],
    "name:slk_x_preferred":[
        "Jablonov"
    ],
    "name:spa_x_preferred":[
        "Jablonov"
    ],
    "name:srp_x_preferred":[
        "\u0408\u0430\u0431\u043b\u043e\u043d\u043e\u0432"
    ],
    "name:ukr_x_preferred":[
        "\u042f\u0431\u043b\u043e\u043d\u043e\u0432"
    ],
    "name:war_x_preferred":[
        "Jablonov"
    ],
    "wof:name":"Jablonov",
    "wof:placetype":"locality"
},
  "geometry": {"coordinates":[20.72563,49.01655],"type":"Point"}
}