{
  "type": "Feature",
  "properties": {
    "gn:admin1_code":"05",
    "gn:asciiname":"Jablonov",
    "gn:country_code":"SK",
    "gn:dem":477,
    "gn:feature_class":"P",
    "gn:feature_code":"PPL",
    "gn:name":"Jablonov",
    "gn:population":0,
    "gn:timezone":"Europe/Bratislava",
    "iso:country":"SK",
    "wof:name":"Jablonov",
    "wof:placetype":"locality"
},
  "geometry": {"coordinates":[20.72563,49.01655],"type":"Point"}
}