{
  "type": "Feature",
  "properties": {
    "gn:admin1_code":"02",
    "gn:asciiname":"Nova Lipnica",
    "gn:country_code":"SK",
    "gn:dem":127,
    "gn:feature_class":"P",
    "gn:feature_code":"PPL",
    "gn:name":"Nov\u00e1 Lipnica",
    "gn:population":0,
    "gn:timezone":"Europe/Bratislava",
    "iso:country":"SK",
    "name:und_x_variant":[
        "Tartschendorf",
        "Torcs",
        "Nov\u00e1 Lipnica"
    ],
    "wof:name":"Nova Lipnica",
    "wof:placetype":"locality"
},
  "geometry": {"coordinates":[17.28212000000001,48.0775],"type":"Point"}
}