{
  "type": "Feature",
  "properties": {
    "gn:admin1_code":"08",
    "gn:asciiname":"Knazia",
    "gn:country_code":"SK",
    "gn:dem":483,
    "gn:feature_class":"P",
    "gn:feature_code":"PPL",
    "gn:name":"K\u0148a\u017eia",
    "gn:population":0,
    "gn:timezone":"Europe/Bratislava",
    "iso:country":"SK",
    "wof:name":"Knazia",
    "wof:placetype":"locality"
},
  "geometry": {"coordinates":[19.31834,49.23411],"type":"Point"}
}