{
  "type": "Feature",
  "properties": {
    "gn:admin1_code":"05",
    "gn:asciiname":"Bunde",
    "gn:country_code":"SK",
    "gn:dem":487,
    "gn:feature_class":"P",
    "gn:feature_code":"PPL",
    "gn:name":"Bunde",
    "gn:population":0,
    "gn:timezone":"Europe/Bratislava",
    "iso:country":"SK",
    "name:ceb_x_preferred":[
        "Bunde"
    ],
    "name:deu_x_preferred":[
        "Bunde"
    ],
    "name:fra_x_preferred":[
        "Bunde"
    ],
    "name:ind_x_preferred":[
        "Bunde"
    ],
    "name:nld_x_preferred":[
        "Bunde"
    ],
    "name:pol_x_preferred":[
        "Bunde"
    ],
    "name:swe_x_preferred":[
        "Bunde"
    ],
    "wof:name":"Bunde",
    "wof:placetype":"locality"
},
  "geometry": {"coordinates":[21.06029,49.02529000000001],"type":"Point"}
}