{
  "type": "Feature",
  "properties": {
    "gn:admin1_code":"00",
    "gn:asciiname":"Baska",
    "gn:country_code":"SK",
    "gn:dem":347,
    "gn:feature_class":"P",
    "gn:feature_code":"PPL",
    "gn:name":"Ba\u0161ka",
    "gn:population":0,
    "gn:timezone":"Europe/Bratislava",
    "iso:country":"SK",
    "name:hun_x_preferred":[
        "Baska"
    ],
    "wof:name":"Baska",
    "wof:placetype":"locality"
},
  "geometry": {"coordinates":[21.18396,48.70665],"type":"Point"}
}