{
  "type": "Feature",
  "properties": {
    "gn:admin1_code":"04",
    "gn:asciiname":"Halacovce",
    "gn:country_code":"SK",
    "gn:dem":233,
    "gn:feature_class":"P",
    "gn:feature_code":"PPL",
    "gn:name":"Hal\u00e1\u010dovce",
    "gn:population":0,
    "gn:timezone":"Europe/Bratislava",
    "iso:country":"SK",
    "name:und_x_variant":[
        "Hal\u00e1\u010dovce"
    ],
    "wof:name":"Halacovce",
    "wof:placetype":"locality"
},
  "geometry": {"coordinates":[18.19725,48.70205],"type":"Point"}
}