{
  "type": "Feature",
  "properties": {
    "gn:admin1_code":"04",
    "gn:asciiname":"Halacovce",
    "gn:country_code":"SK",
    "gn:dem":233,
    "gn:feature_class":"P",
    "gn:feature_code":"PPL",
    "gn:name":"Hal\u00e1\u010dovce",
    "gn:population":0,
    "gn:timezone":"Europe/Bratislava",
    "iso:country":"SK",
    "name:cat_x_preferred":[
        "Hal\u00e1\u010dovce"
    ],
    "name:ces_x_preferred":[
        "Hal\u00e1\u010dovce"
    ],
    "name:epo_x_preferred":[
        "Hal\u00e1\u010dovce"
    ],
    "name:eus_x_preferred":[
        "Hal\u00e1\u010dovce"
    ],
    "name:fra_x_preferred":[
        "Hal\u00e1\u010dovce"
    ],
    "name:hun_x_preferred":[
        "Hal\u00e1cs"
    ],
    "name:ita_x_preferred":[
        "Hal\u00e1\u010dovce"
    ],
    "name:msa_x_preferred":[
        "Hal\u00e1\u010dovce"
    ],
    "name:nld_x_preferred":[
        "Hal\u00e1\u010dovce"
    ],
    "name:ron_x_preferred":[
        "Hal\u00e1\u010dovce"
    ],
    "name:slk_x_preferred":[
        "Hal\u00e1\u010dovce"
    ],
    "name:spa_x_preferred":[
        "Hal\u00e1\u010dovce"
    ],
    "name:srp_x_preferred":[
        "\u0425\u0430\u043b\u0430\u0447\u043e\u0432\u0446\u0435"
    ],
    "name:tgl_x_preferred":[
        "Hal\u00e1\u010dovce"
    ],
    "name:ukr_x_preferred":[
        "\u0413\u0430\u043b\u0430\u0447\u043e\u0432\u0446\u0435"
    ],
    "name:und_x_variant":[
        "Hal\u00e1\u010dovce"
    ],
    "name:war_x_preferred":[
        "Hal\u00e1\u010dovce"
    ],
    "wof:name":"Halacovce",
    "wof:placetype":"locality"
},
  "geometry": {"coordinates":[18.19725,48.70205],"type":"Point"}
}