{
  "type": "Feature",
  "properties": {
    "gn:gn_country":"SK",
    "gn:gn_fcode":"PPL",
    "gn:gn_pop":247,
    "gn:population":247,
    "iso:country":"SK",
    "name:cat_x_preferred":[
        "Vy\u0161n\u00e9 Nemeck\u00e9"
    ],
    "name:cze_x_preferred":[
        "Vy\u0161n\u00e9 Nemeck\u00e9"
    ],
    "name:dut_x_preferred":[
        "Vy\u0161n\u00e9 Nemeck\u00e9"
    ],
    "name:eng_x_preferred":[
        "Vy\u0161n\u00e9 Nemeck\u00e9"
    ],
    "name:epo_x_preferred":[
        "Vy\u0161n\u00e9 Nemeck\u00e9"
    ],
    "name:fre_x_preferred":[
        "Vy\u0161n\u00e9 Nemeck\u00e9"
    ],
    "name:ger_x_preferred":[
        "Vy\u0161n\u00e9 Nemeck\u00e9"
    ],
    "name:hun_x_preferred":[
        "Fels\u0151n\u00e9meti"
    ],
    "name:ita_x_preferred":[
        "Vy\u0161n\u00e9 Nemeck\u00e9"
    ],
    "name:may_x_preferred":[
        "Vy\u0161n\u00e9 Nemeck\u00e9"
    ],
    "name:pol_x_preferred":[
        "Vy\u0161n\u00e9 Nemeck\u00e9"
    ],
    "name:rue_x_preferred":[
        "\u0412\u044b\u0448\u043d\u0454 \u041d\u0457\u043c\u0435\u0446\u044c\u043a\u0435"
    ],
    "name:slo_x_preferred":[
        "Vy\u0161n\u00e9 Nemeck\u00e9"
    ],
    "name:srp_x_preferred":[
        "\u0412\u0438\u0448\u045a\u0435 \u040a\u0435\u043c\u0435\u0446\u043a\u0435"
    ],
    "name:ukr_x_preferred":[
        "\u0412\u0438\u0448\u043d\u0454 \u041d\u0456\u043c\u0435\u0446\u044c\u043a\u0435"
    ],
    "name:war_x_preferred":[
        "Vy\u0161n\u00e9 Nemeck\u00e9"
    ],
    "qs_pg:aaroncc":"SK",
    "qs_pg:gn_country":"SK",
    "qs_pg:gn_fcode":"PPL",
    "qs_pg:gn_pop":247,
    "qs_pg:name":"Vy\u0161n\u00e9 Nemeck\u00e9",
    "qs_pg:name_adm0":"Slovensk\u00e1",
    "qs_pg:name_adm1":"Kosicky",
    "qs_pg:photos_9k":1,
    "qs_pg:photos_9r":1,
    "qs_pg:photos_all":3,
    "qs_pg:photos_sr":0,
    "qs_pg:pop_sr":2,
    "qs_pg:qs_pg_placetype":"locality",
    "qs_pg:qs_pg_placetype_gp":"Town",
    "qs_pg:woe_adm0":23424877,
    "woe:adm0_id":23424877,
    "woe:name_adm0":"Slovensk\u00e1",
    "woe:name_adm1":"Kosicky",
    "woe:placetype":"Town",
    "wof:name":"Vy\u0161n\u00e9 Nemeck\u00e9",
    "wof:placetype":"locality",
    "wof:population":247
},
  "geometry": {"coordinates":[22.26185,48.66077],"type":"Point"}
}