{
  "type": "Feature",
  "properties": {
    "gn:admin1_code":"08",
    "gn:asciiname":"Hladovka",
    "gn:country_code":"SK",
    "gn:dem":758,
    "gn:feature_class":"P",
    "gn:feature_code":"PPL",
    "gn:name":"Hladovka",
    "gn:population":0,
    "gn:timezone":"Europe/Bratislava",
    "iso:country":"SK",
    "name:und_x_variant":[
        "G\u0142odowka",
        "Hladovka"
    ],
    "wof:name":"Hladovka",
    "wof:placetype":"locality"
},
  "geometry": {"coordinates":[19.75741,49.36967],"type":"Point"}
}