{
  "type": "Feature",
  "properties": {
    "gn:admin1_code":"08",
    "gn:asciiname":"Hladovka",
    "gn:country_code":"SK",
    "gn:dem":758,
    "gn:feature_class":"P",
    "gn:feature_code":"PPL",
    "gn:name":"Hladovka",
    "gn:population":0,
    "gn:timezone":"Europe/Bratislava",
    "iso:country":"SK",
    "name:cat_x_preferred":[
        "Hladovka"
    ],
    "name:ces_x_preferred":[
        "Hladovka"
    ],
    "name:deu_x_preferred":[
        "Hladovka"
    ],
    "name:epo_x_preferred":[
        "Hladovka"
    ],
    "name:eus_x_preferred":[
        "Hladovka"
    ],
    "name:fra_x_preferred":[
        "Hladovka"
    ],
    "name:hun_x_preferred":[
        "Hladovka"
    ],
    "name:ita_x_preferred":[
        "Hladovka"
    ],
    "name:msa_x_preferred":[
        "Hladovka"
    ],
    "name:nld_x_preferred":[
        "Hladovka"
    ],
    "name:pol_x_preferred":[
        "G\u0142od\u00f3wka"
    ],
    "name:ron_x_preferred":[
        "Hladovka"
    ],
    "name:slk_x_preferred":[
        "Hladovka"
    ],
    "name:spa_x_preferred":[
        "Hladovka"
    ],
    "name:srp_x_preferred":[
        "\u0425\u043b\u0430\u0434\u043e\u0432\u043a\u0430"
    ],
    "name:und_x_variant":[
        "G\u0142odowka",
        "Hladovka"
    ],
    "name:war_x_preferred":[
        "Hladovka"
    ],
    "wof:name":"Hladovka",
    "wof:placetype":"locality"
},
  "geometry": {"coordinates":[19.75741,49.36967],"type":"Point"}
}