{
  "type": "Feature",
  "properties": {
    "gn:admin1_code":"05",
    "gn:asciiname":"Ortut'ova",
    "gn:country_code":"SK",
    "gn:dem":229,
    "gn:feature_class":"P",
    "gn:feature_code":"PPL",
    "gn:name":"Ortu\u0165ov\u00e1",
    "gn:population":0,
    "gn:timezone":"Europe/Bratislava",
    "iso:country":"SK",
    "name:und_x_variant":[
        "Ortu\u0165ov\u00e1"
    ],
    "wof:name":"Ortut'ova",
    "wof:placetype":"locality"
},
  "geometry": {"coordinates":[21.45673,49.26944],"type":"Point"}
}