{
  "type": "Feature",
  "properties": {
    "gn:admin1_code":"05",
    "gn:asciiname":"Ortut'ova",
    "gn:country_code":"SK",
    "gn:dem":229,
    "gn:feature_class":"P",
    "gn:feature_code":"PPL",
    "gn:name":"Ortu\u0165ov\u00e1",
    "gn:population":0,
    "gn:timezone":"Europe/Bratislava",
    "iso:country":"SK",
    "name:cat_x_preferred":[
        "Ortu\u0165ov\u00e1"
    ],
    "name:ces_x_preferred":[
        "Ortu\u0165ov\u00e1"
    ],
    "name:epo_x_preferred":[
        "Ortu\u0165ov\u00e1"
    ],
    "name:eus_x_preferred":[
        "Ortu\u0165ov\u00e1"
    ],
    "name:fra_x_preferred":[
        "Ortu\u0165ov\u00e1"
    ],
    "name:hun_x_preferred":[
        "Ortut\u00f3"
    ],
    "name:ita_x_preferred":[
        "Ortu\u0165ov\u00e1"
    ],
    "name:msa_x_preferred":[
        "Ortu\u0165ov\u00e1"
    ],
    "name:nld_x_preferred":[
        "Ortu\u0165ov\u00e1"
    ],
    "name:pol_x_preferred":[
        "Ortu\u0165ov\u00e1"
    ],
    "name:ron_x_preferred":[
        "Ortu\u0165ov\u00e1"
    ],
    "name:rue_x_preferred":[
        "\u041e\u0440\u0442\u0443\u0442\u043e\u0432\u0430"
    ],
    "name:slk_x_preferred":[
        "Ortu\u0165ov\u00e1"
    ],
    "name:spa_x_preferred":[
        "Ortu\u0165ov\u00e1"
    ],
    "name:srp_x_preferred":[
        "\u041e\u0440\u0442\u0443\u0442\u0458\u043e\u0432\u0430"
    ],
    "name:ukr_x_preferred":[
        "\u041e\u0440\u0442\u0443\u0442\u044c\u043e\u0432\u0430"
    ],
    "name:war_x_preferred":[
        "Ortu\u0165ov\u00e1"
    ],
    "wof:name":"Ortut'ova",
    "wof:placetype":"locality"
},
  "geometry": {"coordinates":[21.45673,49.26944],"type":"Point"}
}