{
  "type": "Feature",
  "properties": {
    "gn:admin1_code":"04",
    "gn:asciiname":"Nemcinany",
    "gn:country_code":"SK",
    "gn:dem":200,
    "gn:feature_class":"P",
    "gn:feature_code":"PPL",
    "gn:name":"Nem\u010di\u0148any",
    "gn:population":0,
    "gn:timezone":"Europe/Bratislava",
    "iso:country":"SK",
    "name:und_x_variant":[
        "Nem\u010di\u0148any"
    ],
    "wof:name":"Nemcinany",
    "wof:placetype":"locality"
},
  "geometry": {"coordinates":[18.45145,48.30867],"type":"Point"}
}