{
  "type": "Feature",
  "properties": {
    "gn:admin1_code":"04",
    "gn:asciiname":"Nemcinany",
    "gn:country_code":"SK",
    "gn:dem":200,
    "gn:feature_class":"P",
    "gn:feature_code":"PPL",
    "gn:name":"Nem\u010di\u0148any",
    "gn:population":0,
    "gn:timezone":"Europe/Bratislava",
    "iso:country":"SK",
    "name:cat_x_preferred":[
        "Nem\u010di\u0148any"
    ],
    "name:ces_x_preferred":[
        "Nem\u010di\u0148any"
    ],
    "name:epo_x_preferred":[
        "Nem\u010di\u0148any"
    ],
    "name:eus_x_preferred":[
        "Nem\u010di\u0148any"
    ],
    "name:fra_x_preferred":[
        "Nem\u010di\u0148any"
    ],
    "name:hun_x_preferred":[
        "Nemcs\u00e9ny"
    ],
    "name:ita_x_preferred":[
        "Nem\u010di\u0148any"
    ],
    "name:msa_x_preferred":[
        "Nem\u010di\u0148any"
    ],
    "name:nld_x_preferred":[
        "Nem\u010di\u0148any"
    ],
    "name:ron_x_preferred":[
        "Nem\u010di\u0148any"
    ],
    "name:slk_x_preferred":[
        "Nem\u010di\u0148any"
    ],
    "name:spa_x_preferred":[
        "Nem\u010di\u0148any"
    ],
    "name:srp_x_preferred":[
        "\u040a\u0435\u043c\u0447\u0438\u045a\u0430\u043d\u0438"
    ],
    "name:ukr_x_preferred":[
        "\u041d\u0435\u043c\u0447\u0456\u043d\u044f\u043d\u0438"
    ],
    "name:und_x_variant":[
        "Nem\u010di\u0148any"
    ],
    "name:war_x_preferred":[
        "Nem\u010di\u0148any"
    ],
    "wof:name":"Nemcinany",
    "wof:placetype":"locality"
},
  "geometry": {"coordinates":[18.45145,48.30867],"type":"Point"}
}