{
  "type": "Feature",
  "properties": {
    "gn:admin1_code":"01",
    "gn:asciiname":"Pila",
    "gn:country_code":"SK",
    "gn:dem":342,
    "gn:feature_class":"P",
    "gn:feature_code":"PPL",
    "gn:name":"P\u00edla",
    "gn:population":0,
    "gn:timezone":"Europe/Bratislava",
    "iso:country":"SK",
    "name:bos_x_preferred":[
        "Pila"
    ],
    "name:cat_x_preferred":[
        "Pila"
    ],
    "name:ceb_x_preferred":[
        "Pila"
    ],
    "name:ces_x_preferred":[
        "Pila"
    ],
    "name:dan_x_preferred":[
        "Pila"
    ],
    "name:deu_x_preferred":[
        "Pila"
    ],
    "name:epo_x_preferred":[
        "Pila"
    ],
    "name:fin_x_preferred":[
        "Pila"
    ],
    "name:fra_x_preferred":[
        "Pila"
    ],
    "name:glg_x_preferred":[
        "Pila"
    ],
    "name:hun_x_preferred":[
        "Pila"
    ],
    "name:hye_x_preferred":[
        "\u054a\u056b\u056c\u0561"
    ],
    "name:ita_x_preferred":[
        "Pila"
    ],
    "name:lat_x_preferred":[
        "Pila"
    ],
    "name:nld_x_preferred":[
        "Pila"
    ],
    "name:nor_x_preferred":[
        "Pila"
    ],
    "name:pol_x_preferred":[
        "Pila"
    ],
    "name:por_x_preferred":[
        "Pila"
    ],
    "name:rus_x_preferred":[
        "\u041f\u0438\u043b\u0430"
    ],
    "name:sco_x_preferred":[
        "Pila"
    ],
    "name:slv_x_preferred":[
        "Pila"
    ],
    "name:spa_x_preferred":[
        "Pila"
    ],
    "name:srp_x_preferred":[
        "\u041f\u0438\u043b\u0430"
    ],
    "name:swe_x_preferred":[
        "Pila"
    ],
    "name:ukr_x_preferred":[
        "\u041f\u0456\u043b\u0430"
    ],
    "name:war_x_preferred":[
        "Pila"
    ],
    "wof:name":"Pila",
    "wof:placetype":"locality"
},
  "geometry": {"coordinates":[19.50359,48.48348],"type":"Point"}
}