{
  "type": "Feature",
  "properties": {
    "gn:admin1_code":"01",
    "gn:asciiname":"Pila",
    "gn:country_code":"SK",
    "gn:dem":342,
    "gn:feature_class":"P",
    "gn:feature_code":"PPL",
    "gn:name":"P\u00edla",
    "gn:population":0,
    "gn:timezone":"Europe/Bratislava",
    "iso:country":"SK",
    "wof:name":"Pila",
    "wof:placetype":"locality"
},
  "geometry": {"coordinates":[19.50359,48.48348],"type":"Point"}
}