{
  "type": "Feature",
  "properties": {
    "gn:admin1_code":"03",
    "gn:asciiname":"Nizna Hutka",
    "gn:country_code":"SK",
    "gn:dem":182,
    "gn:feature_class":"P",
    "gn:feature_code":"PPL",
    "gn:name":"Ni\u017en\u00e1 Hutka",
    "gn:population":0,
    "gn:timezone":"Europe/Bratislava",
    "iso:country":"SK",
    "name:und_x_variant":[
        "Ni\u017en\u00e1 Hutka"
    ],
    "wof:name":"Nizna Hutka",
    "wof:placetype":"locality"
},
  "geometry": {"coordinates":[21.35941,48.65737],"type":"Point"}
}