{
  "type": "Feature",
  "properties": {
    "gn:admin1_code":"01",
    "gn:asciiname":"Dolne Sipice",
    "gn:country_code":"SK",
    "gn:dem":242,
    "gn:feature_class":"P",
    "gn:feature_code":"PPL",
    "gn:name":"Doln\u00e9 \u0160ipice",
    "gn:population":0,
    "gn:timezone":"Europe/Bratislava",
    "iso:country":"SK",
    "wof:name":"Dolne Sipice",
    "wof:placetype":"locality"
},
  "geometry": {"coordinates":[18.93333,48.23333],"type":"Point"}
}