{
  "type": "Feature",
  "properties": {
    "gn:asciiname":"Sastin-Straze",
    "gn:country_code":"SK",
    "gn:dem":169,
    "gn:elevation":"0.0",
    "gn:feature_class":"P",
    "gn:feature_code":"PPL",
    "gn:name":"\u0160a\u0161t\u00edn-Str\u00e1\u017ee",
    "gn:population":0,
    "gn:timezone":"Europe/Bratislava",
    "iso:country":"SK",
    "wof:name":"Sastin-Straze",
    "wof:placetype":"locality"
},
  "geometry": {"coordinates":[17.1453,48.63721],"type":"Point"}
}