{
  "type": "Feature",
  "properties": {
    "gn:admin1_code":"04",
    "gn:asciiname":"Obid",
    "gn:country_code":"SK",
    "gn:dem":118,
    "gn:feature_class":"P",
    "gn:feature_code":"PPL",
    "gn:name":"Obid",
    "gn:population":0,
    "gn:timezone":"Europe/Bratislava",
    "iso:country":"SK",
    "name:und_x_variant":[
        "Ebed",
        "Obid"
    ],
    "wof:name":"Obid",
    "wof:placetype":"locality"
},
  "geometry": {"coordinates":[18.6471,47.77804],"type":"Point"}
}