{
  "type": "Feature",
  "properties": {
    "gn:admin1_code":"04",
    "gn:asciiname":"Obid",
    "gn:country_code":"SK",
    "gn:dem":118,
    "gn:feature_class":"P",
    "gn:feature_code":"PPL",
    "gn:name":"Obid",
    "gn:population":0,
    "gn:timezone":"Europe/Bratislava",
    "iso:country":"SK",
    "name:cat_x_preferred":[
        "Obid"
    ],
    "name:deu_x_preferred":[
        "Obid"
    ],
    "name:epo_x_preferred":[
        "Obid"
    ],
    "name:eus_x_preferred":[
        "Obid"
    ],
    "name:fra_x_preferred":[
        "Obid"
    ],
    "name:hun_x_preferred":[
        "Ebed"
    ],
    "name:ita_x_preferred":[
        "Obid"
    ],
    "name:msa_x_preferred":[
        "Obid"
    ],
    "name:nld_x_preferred":[
        "Obid"
    ],
    "name:ron_x_preferred":[
        "Obid"
    ],
    "name:slk_x_preferred":[
        "Obid"
    ],
    "name:spa_x_preferred":[
        "Obid"
    ],
    "name:srp_x_preferred":[
        "\u041e\u0431\u0438\u0434"
    ],
    "name:und_x_variant":[
        "Ebed",
        "Obid"
    ],
    "name:war_x_preferred":[
        "Obid"
    ],
    "wof:name":"Obid",
    "wof:placetype":"locality"
},
  "geometry": {"coordinates":[18.6471,47.77804],"type":"Point"}
}