{
  "type": "Feature",
  "properties": {
    "gn:admin1_code":"01",
    "gn:asciiname":"Kraskovo",
    "gn:country_code":"SK",
    "gn:dem":408,
    "gn:feature_class":"P",
    "gn:feature_code":"PPL",
    "gn:name":"Kraskovo",
    "gn:population":0,
    "gn:timezone":"Europe/Bratislava",
    "iso:country":"SK",
    "name:cat_x_preferred":[
        "Kraskovo"
    ],
    "name:ceb_x_preferred":[
        "Kraskovo"
    ],
    "name:ces_x_preferred":[
        "Kraskovo"
    ],
    "name:deu_x_preferred":[
        "Kraskovo"
    ],
    "name:epo_x_preferred":[
        "Kraskovo"
    ],
    "name:eus_x_preferred":[
        "Kraskovo"
    ],
    "name:hun_x_preferred":[
        "Karaszk\u00f3"
    ],
    "name:ita_x_preferred":[
        "Kraskovo"
    ],
    "name:msa_x_preferred":[
        "Kraskovo"
    ],
    "name:nld_x_preferred":[
        "Kraskovo"
    ],
    "name:pol_x_preferred":[
        "Kraskovo"
    ],
    "name:ron_x_preferred":[
        "Kraskovo"
    ],
    "name:slk_x_preferred":[
        "Kraskovo"
    ],
    "name:spa_x_preferred":[
        "Kraskovo"
    ],
    "name:srp_x_preferred":[
        "\u041a\u0440\u0430\u0441\u043a\u043e\u0432\u043e"
    ],
    "name:ukr_x_preferred":[
        "\u041a\u0440\u0430\u0441\u043a\u043e\u0432\u043e"
    ],
    "name:war_x_preferred":[
        "Kraskovo"
    ],
    "wof:name":"Kraskovo",
    "wof:placetype":"locality"
},
  "geometry": {"coordinates":[19.98999,48.50121],"type":"Point"}
}