{
  "type": "Feature",
  "properties": {
    "gn:admin1_code":"01",
    "gn:asciiname":"Kraskovo",
    "gn:country_code":"SK",
    "gn:dem":408,
    "gn:feature_class":"P",
    "gn:feature_code":"PPL",
    "gn:name":"Kraskovo",
    "gn:population":0,
    "gn:timezone":"Europe/Bratislava",
    "iso:country":"SK",
    "wof:name":"Kraskovo",
    "wof:placetype":"locality"
},
  "geometry": {"coordinates":[19.98999,48.50121],"type":"Point"}
}