{
  "type": "Feature",
  "properties": {
    "gn:admin1_code":"03",
    "gn:asciiname":"Rudnianske Kupele",
    "gn:country_code":"SK",
    "gn:dem":463,
    "gn:feature_class":"P",
    "gn:feature_code":"PPL",
    "gn:name":"Rudnianske K\u00fapele",
    "gn:population":0,
    "gn:timezone":"Europe/Bratislava",
    "iso:country":"SK",
    "name:hun_x_preferred":[
        "Rudn\u00f3f\u00fcrd\u0151"
    ],
    "name:und_x_variant":[
        "K\u00fapele",
        "Rudnianske K\u00fapele"
    ],
    "wof:name":"Rudnianske Kupele",
    "wof:placetype":"locality"
},
  "geometry": {"coordinates":[21.03333,48.71667],"type":"Point"}
}