{
  "type": "Feature",
  "properties": {
    "gn:gn_country":"SK",
    "gn:gn_fcode":"PPL",
    "gn:gn_pop":0,
    "iso:country":"SK",
    "name:cat_x_preferred":[
        "Ve\u013ek\u00e9 Teriakovce"
    ],
    "name:deu_x_preferred":[
        "Ve\u013ek\u00e9 Teriakovce"
    ],
    "name:eng_x_preferred":[
        "Ve\u013ek\u00e9 Teriakovce"
    ],
    "name:epo_x_preferred":[
        "Ve\u013ek\u00e9 Teriakovce"
    ],
    "name:eus_x_preferred":[
        "Ve\u013ek\u00e9 Teriakovce"
    ],
    "name:fra_x_preferred":[
        "Ve\u013ek\u00e9 Teriakovce"
    ],
    "name:hun_x_preferred":[
        "Bakost\u00f6r\u00e9k"
    ],
    "name:ita_x_preferred":[
        "Ve\u013ek\u00e9 Teriakovce"
    ],
    "name:msa_x_preferred":[
        "Ve\u013ek\u00e9 Teriakovce"
    ],
    "name:nan_x_preferred":[
        "Ve\u013ek\u00e9 Teriakovce"
    ],
    "name:nld_x_preferred":[
        "Ve\u013ek\u00e9 Teriakovce"
    ],
    "name:pol_x_preferred":[
        "Ve\u013ek\u00e9 Teriakovce"
    ],
    "name:ron_x_preferred":[
        "Ve\u013ek\u00e9 Teriakovce"
    ],
    "name:slk_x_preferred":[
        "Ve\u013ek\u00e9 Teriakovce"
    ],
    "name:spa_x_preferred":[
        "Dol\u0315any"
    ],
    "name:spa_x_variant":[
        "Ve\u013ek\u00e9 Teriakovce"
    ],
    "name:srp_x_preferred":[
        "\u0412\u0435\u0459\u043a\u0435 \u0422\u0458\u0435\u0440\u0458\u0430\u043a\u043e\u0432\u0446\u0435"
    ],
    "name:ukr_x_preferred":[
        "\u0412\u0435\u043b\u044c\u043a\u0435 \u0422\u0435\u0440'\u044f\u043a\u043e\u0432\u0446\u0435"
    ],
    "name:unk_x_variant":[
        "Ve\u013ek\u00e9 Teriakovce"
    ],
    "name:war_x_preferred":[
        "Ve\u013ek\u00e9 Teriakovce"
    ],
    "qs_pg:aaroncc":"SK",
    "qs_pg:gn_country":"SK",
    "qs_pg:gn_fcode":"PPL",
    "qs_pg:gn_pop":0,
    "qs_pg:name":"Vel\u0315k\u00e9 Teriakovce",
    "qs_pg:name_adm0":"Slovensk\u00e1",
    "qs_pg:name_adm1":"Banskobystricky",
    "qs_pg:photos_9r":0,
    "qs_pg:photos_sr":0,
    "qs_pg:pop_sr":0,
    "qs_pg:qs_pg_placetype":"locality",
    "qs_pg:qs_pg_placetype_gp":"Town",
    "qs_pg:woe_adm0":23424877,
    "woe:adm0_id":23424877,
    "woe:name_adm0":"Slovensk\u00e1",
    "woe:name_adm1":"Banskobystricky",
    "woe:placetype":"Town",
    "wof:name":"Vel\u0315k\u00e9 Teriakovce",
    "wof:placetype":"locality"
},
  "geometry": {"coordinates":[19.96631,48.4332],"type":"Point"}
}