{
  "type": "Feature",
  "properties": {
    "gn:admin1_code":"07",
    "gn:asciiname":"Horne Suroviny",
    "gn:country_code":"SK",
    "gn:dem":212,
    "gn:feature_class":"P",
    "gn:feature_code":"PPL",
    "gn:name":"Horn\u00e9 Suroviny",
    "gn:population":0,
    "gn:timezone":"Europe/Bratislava",
    "iso:country":"SK",
    "name:und_x_variant":[
        "Dvor Horn\u00e9 Suroviny",
        "Horn\u00e9 Suroviny"
    ],
    "wof:name":"Horne Suroviny",
    "wof:placetype":"locality"
},
  "geometry": {"coordinates":[17.36685,48.65231],"type":"Point"}
}