{
  "type": "Feature",
  "properties": {
    "gn:admin1_code":"04",
    "gn:asciiname":"Zavada",
    "gn:country_code":"SK",
    "gn:dem":363,
    "gn:feature_class":"P",
    "gn:feature_code":"PPL",
    "gn:name":"Z\u00e1vada",
    "gn:population":0,
    "gn:timezone":"Europe/Bratislava",
    "iso:country":"SK",
    "wof:name":"Zavada",
    "wof:placetype":"locality"
},
  "geometry": {"coordinates":[18.35827,48.82359],"type":"Point"}
}