{
  "type": "Feature",
  "properties": {
    "gn:admin1_code":"04",
    "gn:asciiname":"Kopanica Dastinskeho",
    "gn:country_code":"SK",
    "gn:dem":345,
    "gn:feature_class":"P",
    "gn:feature_code":"PPL",
    "gn:name":"Kopanica Dastinsk\u00e9ho",
    "gn:population":0,
    "gn:timezone":"Europe/Bratislava",
    "iso:country":"SK",
    "wof:name":"Kopanica Dastinskeho",
    "wof:placetype":"locality"
},
  "geometry": {"coordinates":[17.97649,48.64348],"type":"Point"}
}