{
  "type": "Feature",
  "properties": {
    "gn:admin1_code":"04",
    "gn:asciiname":"Rohoznica",
    "gn:country_code":"SK",
    "gn:dem":173,
    "gn:feature_class":"P",
    "gn:feature_code":"PPL",
    "gn:name":"Roho\u017enica",
    "gn:population":0,
    "gn:timezone":"Europe/Bratislava",
    "iso:country":"SK",
    "name:hun_x_preferred":[
        "Kisgy\u00e9k\u00e9nyes"
    ],
    "name:und_x_variant":[
        "Dekene\u0161",
        "Roho\u017enica"
    ],
    "wof:name":"Rohoznica",
    "wof:placetype":"locality"
},
  "geometry": {"coordinates":[18.46468,48.21107],"type":"Point"}
}