{
  "type": "Feature",
  "properties": {
    "gn:admin1_code":"04",
    "gn:asciiname":"Hamry",
    "gn:country_code":"SK",
    "gn:dem":238,
    "gn:feature_class":"P",
    "gn:feature_code":"PPL",
    "gn:name":"H\u00e1mry",
    "gn:population":0,
    "gn:timezone":"Europe/Bratislava",
    "iso:country":"SK",
    "name:ces_x_preferred":[
        "Hamry"
    ],
    "name:deu_x_preferred":[
        "Hamry"
    ],
    "name:epo_x_preferred":[
        "Hamry"
    ],
    "name:fra_x_preferred":[
        "Hamry"
    ],
    "name:ita_x_preferred":[
        "Hamry"
    ],
    "name:nld_x_preferred":[
        "Hamry"
    ],
    "name:pol_x_preferred":[
        "Hamry"
    ],
    "name:slk_x_preferred":[
        "Hamry"
    ],
    "name:srp_x_preferred":[
        "\u0425\u0430\u043c\u0440\u0438"
    ],
    "wof:name":"Hamry",
    "wof:placetype":"locality"
},
  "geometry": {"coordinates":[18.0446,48.84699000000001],"type":"Point"}
}