{
  "type": "Feature",
  "properties": {
    "gn:admin1_code":"05",
    "gn:asciiname":"Olejnikov",
    "gn:country_code":"SK",
    "gn:dem":486,
    "gn:feature_class":"P",
    "gn:feature_code":"PPL",
    "gn:name":"Olejn\u00edkov",
    "gn:population":0,
    "gn:timezone":"Europe/Bratislava",
    "iso:country":"SK",
    "name:cat_x_preferred":[
        "Olejn\u00edkov"
    ],
    "name:ces_x_preferred":[
        "Olejn\u00edkov"
    ],
    "name:deu_x_preferred":[
        "Olejn\u00edkov"
    ],
    "name:epo_x_preferred":[
        "Olejn\u00edkov"
    ],
    "name:eus_x_preferred":[
        "Olejn\u00edkov"
    ],
    "name:fra_x_preferred":[
        "Olejn\u00edkov"
    ],
    "name:hun_x_preferred":[
        "Olajpatak"
    ],
    "name:ita_x_preferred":[
        "Olejn\u00edkov"
    ],
    "name:msa_x_preferred":[
        "Olejn\u00edkov"
    ],
    "name:nld_x_preferred":[
        "Olejn\u00edkov"
    ],
    "name:pol_x_preferred":[
        "Olejn\u00edkov"
    ],
    "name:ron_x_preferred":[
        "Olejn\u00edkov"
    ],
    "name:rue_x_preferred":[
        "\u041e\u043b\u0435\u043d\u0438\u043a\u0456\u0432"
    ],
    "name:slk_x_preferred":[
        "Olejn\u00edkov"
    ],
    "name:spa_x_preferred":[
        "Olejn\u00edkov"
    ],
    "name:srp_x_preferred":[
        "\u041e\u0459\u0435\u0458\u045a\u0438\u043a\u043e\u0432"
    ],
    "name:ukr_x_preferred":[
        "\u041e\u043b\u0435\u0439\u043d\u0438\u043a\u0456\u0432"
    ],
    "name:war_x_preferred":[
        "Olejn\u00edkov"
    ],
    "wof:name":"Olejnikov",
    "wof:placetype":"locality"
},
  "geometry": {"coordinates":[21.06516,49.18185],"type":"Point"}
}