{
  "type": "Feature",
  "properties": {
    "gn:admin1_code":"05",
    "gn:asciiname":"Olejnikov",
    "gn:country_code":"SK",
    "gn:dem":486,
    "gn:feature_class":"P",
    "gn:feature_code":"PPL",
    "gn:name":"Olejn\u00edkov",
    "gn:population":0,
    "gn:timezone":"Europe/Bratislava",
    "iso:country":"SK",
    "name:und_x_variant":[
        "Olejn\u00edkov"
    ],
    "wof:name":"Olejnikov",
    "wof:placetype":"locality"
},
  "geometry": {"coordinates":[21.06516,49.18185],"type":"Point"}
}