{
  "type": "Feature",
  "properties": {
    "gn:admin1_code":"03",
    "gn:asciiname":"Zbehnov",
    "gn:country_code":"SK",
    "gn:dem":168,
    "gn:feature_class":"P",
    "gn:feature_code":"PPL",
    "gn:name":"Zbeh\u0148ov",
    "gn:population":0,
    "gn:timezone":"Europe/Bratislava",
    "iso:country":"SK",
    "name:und_x_variant":[
        "Zbeh\u0148ov"
    ],
    "wof:name":"Zbehnov",
    "wof:placetype":"locality"
},
  "geometry": {"coordinates":[21.62972,48.68952],"type":"Point"}
}