{
  "type": "Feature",
  "properties": {
    "iso:country":"SK",
    "name:eng_x_preferred":[
        "Stary haj"
    ],
    "name:slk_x_preferred":[
        "Star\u00fd h\u00e1j"
    ],
    "wof:name":"Stary haj",
    "wof:placetype":"neighbourhood"
},
  "geometry": {"coordinates":[17.12537843893512,48.11311410553205],"type":"Point"}
}