{
  "type": "Feature",
  "properties": {
    "gn:admin1_code":"01",
    "gn:asciiname":"Uderina",
    "gn:country_code":"SK",
    "gn:dem":256,
    "gn:feature_class":"P",
    "gn:feature_code":"PPL",
    "gn:name":"Uderin\u00e1",
    "gn:population":0,
    "gn:timezone":"Europe/Bratislava",
    "iso:country":"SK",
    "wof:name":"Uderina",
    "wof:placetype":"locality"
},
  "geometry": {"coordinates":[19.60834,48.42107],"type":"Point"}
}