{
  "type": "Feature",
  "properties": {
    "gn:admin1_code":"03",
    "gn:asciiname":"Svetla",
    "gn:country_code":"SK",
    "gn:dem":226,
    "gn:feature_class":"P",
    "gn:feature_code":"PPL",
    "gn:name":"Svetl\u00e1",
    "gn:population":0,
    "gn:timezone":"Europe/Bratislava",
    "iso:country":"SK",
    "name:und_x_variant":[
        "Vil\u00e1go\u0161",
        "Svetl\u00e1"
    ],
    "wof:name":"Svetla",
    "wof:placetype":"locality"
},
  "geometry": {"coordinates":[21.25,48.68333],"type":"Point"}
}