{
  "type": "Feature",
  "properties": {
    "gn:admin1_code":"01",
    "gn:asciiname":"Mucin",
    "gn:country_code":"SK",
    "gn:dem":192,
    "gn:feature_class":"P",
    "gn:feature_code":"PPL",
    "gn:name":"Mu\u010d\u00edn",
    "gn:population":0,
    "gn:timezone":"Europe/Bratislava",
    "iso:country":"SK",
    "name:und_x_variant":[
        "Mu\u010d\u00edn"
    ],
    "wof:name":"Mucin",
    "wof:placetype":"locality"
},
  "geometry": {"coordinates":[19.70252,48.24425],"type":"Point"}
}