{
  "type": "Feature",
  "properties": {
    "gn:admin1_code":"01",
    "gn:asciiname":"Mucin",
    "gn:country_code":"SK",
    "gn:dem":192,
    "gn:feature_class":"P",
    "gn:feature_code":"PPL",
    "gn:name":"Mu\u010d\u00edn",
    "gn:population":0,
    "gn:timezone":"Europe/Bratislava",
    "iso:country":"SK",
    "name:cat_x_preferred":[
        "Mu\u010d\u00edn"
    ],
    "name:epo_x_preferred":[
        "Mu\u010d\u00edn"
    ],
    "name:eus_x_preferred":[
        "Mu\u010d\u00edn"
    ],
    "name:fra_x_preferred":[
        "Mu\u010d\u00edn"
    ],
    "name:hun_x_preferred":[
        "Mucs\u00e9ny"
    ],
    "name:ita_x_preferred":[
        "Mu\u010d\u00edn"
    ],
    "name:msa_x_preferred":[
        "Mu\u010d\u00edn"
    ],
    "name:nld_x_preferred":[
        "Mu\u010d\u00edn"
    ],
    "name:pol_x_preferred":[
        "Mu\u010d\u00edn"
    ],
    "name:ron_x_preferred":[
        "Mu\u010d\u00edn"
    ],
    "name:slk_x_preferred":[
        "Mu\u010d\u00edn"
    ],
    "name:spa_x_preferred":[
        "Mu\u010d\u00edn"
    ],
    "name:srp_x_preferred":[
        "\u041c\u0443\u0447\u0438\u043d"
    ],
    "name:ukr_x_preferred":[
        "\u041c\u0443\u0447\u0438\u043d"
    ],
    "name:und_x_variant":[
        "Mu\u010d\u00edn"
    ],
    "name:war_x_preferred":[
        "Mu\u010d\u00edn"
    ],
    "wof:name":"Mucin",
    "wof:placetype":"locality"
},
  "geometry": {"coordinates":[19.70252,48.24425],"type":"Point"}
}