{
  "type": "Feature",
  "properties": {
    "gn:admin1_code":"08",
    "gn:asciiname":"Rakovo",
    "gn:country_code":"SK",
    "gn:dem":429,
    "gn:feature_class":"P",
    "gn:feature_code":"PPL",
    "gn:name":"Rakovo",
    "gn:population":0,
    "gn:timezone":"Europe/Bratislava",
    "iso:country":"SK",
    "name:cat_x_preferred":[
        "Rakovo"
    ],
    "name:ces_x_preferred":[
        "Rakovo"
    ],
    "name:deu_x_preferred":[
        "Rakovo"
    ],
    "name:epo_x_preferred":[
        "Rakovo"
    ],
    "name:eus_x_preferred":[
        "Rakovo"
    ],
    "name:hun_x_preferred":[
        "Nagyr\u00e1k\u00f3"
    ],
    "name:ita_x_preferred":[
        "Rakovo"
    ],
    "name:msa_x_preferred":[
        "Rakovo"
    ],
    "name:nld_x_preferred":[
        "Rakovo"
    ],
    "name:pol_x_preferred":[
        "Rakovo"
    ],
    "name:ron_x_preferred":[
        "Rakovo"
    ],
    "name:slk_x_preferred":[
        "Rakovo"
    ],
    "name:spa_x_preferred":[
        "Rakovo"
    ],
    "name:srp_x_preferred":[
        "\u0420\u0430\u043a\u043e\u0432\u043e"
    ],
    "name:war_x_preferred":[
        "Rakovo"
    ],
    "wof:name":"Rakovo",
    "wof:placetype":"locality"
},
  "geometry": {"coordinates":[18.88196,48.98876],"type":"Point"}
}