{
  "type": "Feature",
  "properties": {
    "gn:admin1_code":"08",
    "gn:asciiname":"Rakovo",
    "gn:country_code":"SK",
    "gn:dem":429,
    "gn:feature_class":"P",
    "gn:feature_code":"PPL",
    "gn:name":"Rakovo",
    "gn:population":0,
    "gn:timezone":"Europe/Bratislava",
    "iso:country":"SK",
    "wof:name":"Rakovo",
    "wof:placetype":"locality"
},
  "geometry": {"coordinates":[18.88196,48.98876],"type":"Point"}
}