{
  "type": "Feature",
  "properties": {
    "gn:admin1_code":"01",
    "gn:admin2_code":"601.0",
    "gn:asciiname":"Novy Svet",
    "gn:country_code":"SK",
    "gn:dem":379,
    "gn:feature_class":"P",
    "gn:feature_code":"PPL",
    "gn:name":"Nov\u00fd Svet",
    "gn:population":0,
    "gn:timezone":"Europe/Bratislava",
    "iso:country":"SK",
    "wof:name":"Novy Svet",
    "wof:placetype":"locality"
},
  "geometry": {"coordinates":[19.12792,48.77691],"type":"Point"}
}