{
  "type": "Feature",
  "properties": {
    "gn:admin1_code":"01",
    "gn:asciiname":"Kotmanova",
    "gn:country_code":"SK",
    "gn:dem":301,
    "gn:feature_class":"P",
    "gn:feature_code":"PPL",
    "gn:name":"Kotmanov\u00e1",
    "gn:population":0,
    "gn:timezone":"Europe/Bratislava",
    "iso:country":"SK",
    "name:und_x_variant":[
        "Dobro\u010dsk\u00e1 Lehota",
        "Kotmanov\u00e1"
    ],
    "wof:name":"Kotmanova",
    "wof:placetype":"locality"
},
  "geometry": {"coordinates":[19.58037,48.48492],"type":"Point"}
}