{
  "type": "Feature",
  "properties": {
    "gn:admin1_code":"01",
    "gn:asciiname":"Kotmanova",
    "gn:country_code":"SK",
    "gn:dem":301,
    "gn:feature_class":"P",
    "gn:feature_code":"PPL",
    "gn:name":"Kotmanov\u00e1",
    "gn:population":0,
    "gn:timezone":"Europe/Bratislava",
    "iso:country":"SK",
    "name:cat_x_preferred":[
        "Kotmanov\u00e1"
    ],
    "name:epo_x_preferred":[
        "Kotmanov\u00e1"
    ],
    "name:eus_x_preferred":[
        "Kotmanov\u00e1"
    ],
    "name:fra_x_preferred":[
        "Kotmanov\u00e1"
    ],
    "name:hun_x_preferred":[
        "Kotm\u00e1ny"
    ],
    "name:ita_x_preferred":[
        "Kotmanov\u00e1"
    ],
    "name:msa_x_preferred":[
        "Kotmanov\u00e1"
    ],
    "name:nld_x_preferred":[
        "Kotmanov\u00e1"
    ],
    "name:pol_x_preferred":[
        "Kotmanov\u00e1"
    ],
    "name:ron_x_preferred":[
        "Kotmanov\u00e1"
    ],
    "name:slk_x_preferred":[
        "Kotmanov\u00e1"
    ],
    "name:spa_x_preferred":[
        "Kotmanov\u00e1"
    ],
    "name:srp_x_preferred":[
        "\u041a\u043e\u0442\u043c\u0430\u043d\u043e\u0432\u0430"
    ],
    "name:ukr_x_preferred":[
        "\u041a\u043e\u0442\u043c\u0430\u043d\u043e\u0432\u0430"
    ],
    "name:und_x_variant":[
        "Dobro\u010dsk\u00e1 Lehota"
    ],
    "name:war_x_preferred":[
        "Kotmanov\u00e1"
    ],
    "wof:name":"Kotmanova",
    "wof:placetype":"locality"
},
  "geometry": {"coordinates":[19.58037,48.48492],"type":"Point"}
}