{
  "type": "Feature",
  "properties": {
    "gn:admin1_code":"07",
    "gn:asciiname":"Sisulaky",
    "gn:country_code":"SK",
    "gn:dem":194,
    "gn:feature_class":"P",
    "gn:feature_code":"PPL",
    "gn:name":"\u0160i\u0161ul\u00e1ky",
    "gn:population":0,
    "gn:timezone":"Europe/Bratislava",
    "iso:country":"SK",
    "wof:name":"Sisulaky",
    "wof:placetype":"locality"
},
  "geometry": {"coordinates":[17.13655,48.57176],"type":"Point"}
}