{
  "type": "Feature",
  "properties": {
    "gn:admin1_code":"08",
    "gn:asciiname":"Babisis",
    "gn:country_code":"SK",
    "gn:dem":730,
    "gn:feature_class":"P",
    "gn:feature_code":"PPL",
    "gn:name":"Babi\u0161is",
    "gn:population":0,
    "gn:timezone":"Europe/Bratislava",
    "iso:country":"SK",
    "wof:name":"Babisis",
    "wof:placetype":"locality"
},
  "geometry": {"coordinates":[18.50637,49.33511],"type":"Point"}
}