{
  "type": "Feature",
  "properties": {
    "gn:admin1_code":"05",
    "gn:asciiname":"Zatkovce",
    "gn:country_code":"SK",
    "gn:dem":490,
    "gn:feature_class":"P",
    "gn:feature_code":"PPL",
    "gn:name":"\u017datkovce",
    "gn:population":0,
    "gn:timezone":"Europe/Bratislava",
    "iso:country":"SK",
    "wof:name":"Zatkovce",
    "wof:placetype":"locality"
},
  "geometry": {"coordinates":[21.26521,49.1364],"type":"Point"}
}