{
  "type": "Feature",
  "properties": {
    "gn:admin1_code":"04",
    "gn:asciiname":"Horny Pial",
    "gn:country_code":"SK",
    "gn:dem":178,
    "gn:feature_class":"P",
    "gn:feature_code":"PPL",
    "gn:name":"Horn\u00fd Pial",
    "gn:population":0,
    "gn:timezone":"Europe/Bratislava",
    "iso:country":"SK",
    "name:cat_x_preferred":[
        "Horn\u00fd Pial"
    ],
    "name:ces_x_preferred":[
        "Horn\u00fd Pial"
    ],
    "name:epo_x_preferred":[
        "Horn\u00fd Pial"
    ],
    "name:eus_x_preferred":[
        "Horn\u00fd Pial"
    ],
    "name:fra_x_preferred":[
        "Horn\u00fd Pial"
    ],
    "name:hun_x_preferred":[
        "Fels\u0151p\u00e9l"
    ],
    "name:ita_x_preferred":[
        "Horn\u00fd Pial"
    ],
    "name:msa_x_preferred":[
        "Horn\u00fd Pial"
    ],
    "name:nld_x_preferred":[
        "Horn\u00fd Pial"
    ],
    "name:pol_x_preferred":[
        "Horn\u00fd Pial"
    ],
    "name:ron_x_preferred":[
        "Horn\u00fd Pial"
    ],
    "name:slk_x_preferred":[
        "Horn\u00fd Pial"
    ],
    "name:spa_x_preferred":[
        "Horn\u00fd Pial"
    ],
    "name:srp_x_preferred":[
        "\u0425\u043e\u0440\u043d\u0438 \u041f\u0458\u0430\u043b"
    ],
    "name:und_x_variant":[
        "Fels\u0151 P\u00e9l",
        "Horn\u00ed Pial",
        "Horn\u00fd Pial"
    ],
    "name:war_x_preferred":[
        "Horn\u00fd Pial"
    ],
    "wof:name":"Horny Pial",
    "wof:placetype":"locality"
},
  "geometry": {"coordinates":[18.45039,48.15544000000001],"type":"Point"}
}