{
  "type": "Feature",
  "properties": {
    "gn:admin1_code":"04",
    "gn:asciiname":"Horny Pial",
    "gn:country_code":"SK",
    "gn:dem":178,
    "gn:feature_class":"P",
    "gn:feature_code":"PPL",
    "gn:name":"Horn\u00fd Pial",
    "gn:population":0,
    "gn:timezone":"Europe/Bratislava",
    "iso:country":"SK",
    "name:und_x_variant":[
        "Fels\u0151 P\u00e9l",
        "Horn\u00ed Pial",
        "Horn\u00fd Pial"
    ],
    "wof:name":"Horny Pial",
    "wof:placetype":"locality"
},
  "geometry": {"coordinates":[18.45039,48.15544000000001],"type":"Point"}
}