{
  "type": "Feature",
  "properties": {
    "gn:admin1_code":"03",
    "gn:asciiname":"Gombasek",
    "gn:country_code":"SK",
    "gn:dem":234,
    "gn:feature_class":"P",
    "gn:feature_code":"PPL",
    "gn:name":"Gombasek",
    "gn:population":0,
    "gn:timezone":"Europe/Bratislava",
    "iso:country":"SK",
    "wof:name":"Gombasek",
    "wof:placetype":"locality"
},
  "geometry": {"coordinates":[20.46517,48.56844],"type":"Point"}
}