{
  "type": "Feature",
  "properties": {
    "gn:admin1_code":"05",
    "gn:asciiname":"Potok",
    "gn:country_code":"SK",
    "gn:dem":590,
    "gn:feature_class":"P",
    "gn:feature_code":"PPL",
    "gn:name":"Potok",
    "gn:population":0,
    "gn:timezone":"Europe/Bratislava",
    "iso:country":"SK",
    "wof:name":"Potok",
    "wof:placetype":"locality"
},
  "geometry": {"coordinates":[20.34867,49.34129],"type":"Point"}
}