{
  "type": "Feature",
  "properties": {
    "gn:admin1_code":"05",
    "gn:asciiname":"Kupele Cerveny Klastor",
    "gn:country_code":"SK",
    "gn:dem":476,
    "gn:feature_class":"P",
    "gn:feature_code":"PPL",
    "gn:name":"K\u00fapele \u010cerven\u00fd Kl\u00e1\u0161tor",
    "gn:population":0,
    "gn:timezone":"Europe/Bratislava",
    "iso:country":"SK",
    "name:und_x_variant":[
        "Smerd\u017eonka"
    ],
    "wof:name":"Kupele Cerveny Klastor",
    "wof:placetype":"locality"
},
  "geometry": {"coordinates":[20.42341,49.38539],"type":"Point"}
}