{
  "type": "Feature",
  "properties": {
    "gn:admin1_code":"01",
    "gn:asciiname":"Neklen",
    "gn:country_code":"SK",
    "gn:dem":731,
    "gn:feature_class":"P",
    "gn:feature_code":"PPL",
    "gn:name":"Neklen",
    "gn:population":0,
    "gn:timezone":"Europe/Bratislava",
    "iso:country":"SK",
    "wof:name":"Neklen",
    "wof:placetype":"locality"
},
  "geometry": {"coordinates":[19.75044,48.53372],"type":"Point"}
}