{
  "type": "Feature",
  "properties": {
    "gn:admin1_code":"04",
    "gn:asciiname":"Horne Sl'azany",
    "gn:country_code":"SK",
    "gn:dem":195,
    "gn:feature_class":"P",
    "gn:feature_code":"PPL",
    "gn:name":"Horn\u00e9 Sl\u2019a\u017eany",
    "gn:population":0,
    "gn:timezone":"Europe/Bratislava",
    "iso:country":"SK",
    "name:und_x_variant":[
        "Horn\u00ed-Sla\u017eany",
        "Hornie Sla\u017eany",
        "Horn\u00e9 Sl\u2019a\u017eany"
    ],
    "wof:name":"Horne Sl'azany",
    "wof:placetype":"locality"
},
  "geometry": {"coordinates":[18.32848,48.39487],"type":"Point"}
}