{
  "type": "Feature",
  "properties": {
    "gn:admin1_code":"03",
    "gn:asciiname":"Puste Cemerne",
    "gn:country_code":"SK",
    "gn:dem":134,
    "gn:feature_class":"P",
    "gn:feature_code":"PPL",
    "gn:name":"Pust\u00e9 \u010cemern\u00e9",
    "gn:population":0,
    "gn:timezone":"Europe/Bratislava",
    "iso:country":"SK",
    "name:und_x_variant":[
        "Pust\u00e9 \u010cemern\u00e9"
    ],
    "wof:name":"Puste Cemerne",
    "wof:placetype":"locality"
},
  "geometry": {"coordinates":[21.8166,48.84221],"type":"Point"}
}