{
  "type": "Feature",
  "properties": {
    "gn:admin1_code":"03",
    "gn:asciiname":"Puste Cemerne",
    "gn:country_code":"SK",
    "gn:dem":134,
    "gn:feature_class":"P",
    "gn:feature_code":"PPL",
    "gn:name":"Pust\u00e9 \u010cemern\u00e9",
    "gn:population":0,
    "gn:timezone":"Europe/Bratislava",
    "iso:country":"SK",
    "name:cat_x_preferred":[
        "Pust\u00e9 \u010cemern\u00e9"
    ],
    "name:epo_x_preferred":[
        "Pust\u00e9 \u010cemern\u00e9"
    ],
    "name:eus_x_preferred":[
        "Pust\u00e9 \u010cemern\u00e9"
    ],
    "name:fra_x_preferred":[
        "Pust\u00e9 \u010cemern\u00e9"
    ],
    "name:hun_x_preferred":[
        "M\u00e1rkcsemernye"
    ],
    "name:ita_x_preferred":[
        "Pust\u00e9 \u010cemern\u00e9"
    ],
    "name:msa_x_preferred":[
        "Pust\u00e9 \u010cemern\u00e9"
    ],
    "name:nld_x_preferred":[
        "Pust\u00e9 \u010cemern\u00e9"
    ],
    "name:pol_x_preferred":[
        "Pust\u00e9 \u010cemern\u00e9"
    ],
    "name:ron_x_preferred":[
        "Pust\u00e9 \u010cemern\u00e9"
    ],
    "name:slk_x_preferred":[
        "Pust\u00e9 \u010cemern\u00e9"
    ],
    "name:spa_x_preferred":[
        "Pust\u00e9 \u010cemern\u00e9"
    ],
    "name:srp_x_preferred":[
        "\u041f\u0443\u0441\u0442\u0458\u0435 \u0427\u0435\u043c\u0435\u0440\u045a\u0435"
    ],
    "name:ukr_x_preferred":[
        "\u041f\u0443\u0441\u0442\u0435 \u0427\u0435\u043c\u0435\u0440\u043d\u0435"
    ],
    "name:und_x_variant":[
        "Pust\u00e9 \u010cemern\u00e9"
    ],
    "name:war_x_preferred":[
        "Pust\u00e9 \u010cemern\u00e9"
    ],
    "wof:name":"Puste Cemerne",
    "wof:placetype":"locality"
},
  "geometry": {"coordinates":[21.8166,48.84221],"type":"Point"}
}