{
  "type": "Feature",
  "properties": {
    "gn:admin1_code":"07",
    "gn:asciiname":"Jelenova",
    "gn:country_code":"SK",
    "gn:dem":177,
    "gn:feature_class":"P",
    "gn:feature_code":"PPL",
    "gn:name":"Jelenov\u00e1",
    "gn:population":0,
    "gn:timezone":"Europe/Bratislava",
    "iso:country":"SK",
    "wof:name":"Jelenova",
    "wof:placetype":"locality"
},
  "geometry": {"coordinates":[17.89009,48.44007],"type":"Point"}
}