{
  "type": "Feature",
  "properties": {
    "gn:admin1_code":"01",
    "gn:asciiname":"Breznicka",
    "gn:country_code":"SK",
    "gn:dem":212,
    "gn:feature_class":"P",
    "gn:feature_code":"PPL",
    "gn:name":"Brezni\u010dka",
    "gn:population":0,
    "gn:timezone":"Europe/Bratislava",
    "iso:country":"SK",
    "name:cat_x_preferred":[
        "Brezni\u010dka"
    ],
    "name:ces_x_preferred":[
        "Brezni\u010dka"
    ],
    "name:deu_x_preferred":[
        "Brezni\u010dka"
    ],
    "name:epo_x_preferred":[
        "Brezni\u010dka"
    ],
    "name:eus_x_preferred":[
        "Brezni\u010dka"
    ],
    "name:hun_x_preferred":[
        "Ipolyberzence"
    ],
    "name:ita_x_preferred":[
        "Brezni\u010dka"
    ],
    "name:msa_x_preferred":[
        "Brezni\u010dka"
    ],
    "name:nld_x_preferred":[
        "Brezni\u010dka"
    ],
    "name:pol_x_preferred":[
        "Brezni\u010dka"
    ],
    "name:ron_x_preferred":[
        "Brezni\u010dka"
    ],
    "name:slk_x_preferred":[
        "Brezni\u010dka"
    ],
    "name:spa_x_preferred":[
        "Brezni\u010dka"
    ],
    "name:srp_x_preferred":[
        "\u0411\u0440\u0435\u0437\u045a\u0438\u0447\u043a\u0430"
    ],
    "name:ukr_x_preferred":[
        "\u0411\u0440\u0435\u0437\u043d\u0438\u0447\u043a\u0430"
    ],
    "name:war_x_preferred":[
        "Brezni\u010dka"
    ],
    "wof:name":"Breznicka",
    "wof:placetype":"locality"
},
  "geometry": {"coordinates":[19.73577,48.42226],"type":"Point"}
}