{
  "type": "Feature",
  "properties": {
    "gn:admin1_code":"01",
    "gn:asciiname":"Ratkovska Lehota",
    "gn:country_code":"SK",
    "gn:dem":285,
    "gn:feature_class":"P",
    "gn:feature_code":"PPL",
    "gn:name":"Ratkovsk\u00e1 Lehota",
    "gn:population":0,
    "gn:timezone":"Europe/Bratislava",
    "iso:country":"SK",
    "name:und_x_variant":[
        "Ratkovsk\u00e1 Lehota"
    ],
    "wof:name":"Ratkovska Lehota",
    "wof:placetype":"locality"
},
  "geometry": {"coordinates":[20.09992,48.5624],"type":"Point"}
}