{
  "type": "Feature",
  "properties": {
    "gn:admin1_code":"01",
    "gn:asciiname":"Ratkovska Lehota",
    "gn:country_code":"SK",
    "gn:dem":285,
    "gn:feature_class":"P",
    "gn:feature_code":"PPL",
    "gn:name":"Ratkovsk\u00e1 Lehota",
    "gn:population":0,
    "gn:timezone":"Europe/Bratislava",
    "iso:country":"SK",
    "name:cat_x_preferred":[
        "Ratkovsk\u00e1 Lehota"
    ],
    "name:epo_x_preferred":[
        "Ratkovsk\u00e1 Lehota"
    ],
    "name:eus_x_preferred":[
        "Ratkovsk\u00e1 Lehota"
    ],
    "name:fra_x_preferred":[
        "Ratkovsk\u00e1 Lehota"
    ],
    "name:hun_x_preferred":[
        "Ratk\u00f3szabadi"
    ],
    "name:ita_x_preferred":[
        "Ratkovsk\u00e1 Lehota"
    ],
    "name:msa_x_preferred":[
        "Ratkovsk\u00e1 Lehota"
    ],
    "name:nld_x_preferred":[
        "Ratkovsk\u00e1 Lehota"
    ],
    "name:pol_x_preferred":[
        "Ratkovsk\u00e1 Lehota"
    ],
    "name:ron_x_preferred":[
        "Ratkovsk\u00e1 Lehota"
    ],
    "name:slk_x_preferred":[
        "Ratkovsk\u00e1 Lehota"
    ],
    "name:spa_x_preferred":[
        "Ratkovsk\u00e1 Lehota"
    ],
    "name:srp_x_preferred":[
        "\u0420\u0430\u0442\u043a\u043e\u0432\u0441\u043a\u0430 \u0409\u0435\u0445\u043e\u0442\u0430"
    ],
    "name:ukr_x_preferred":[
        "\u0420\u0430\u0442\u043a\u043e\u0432\u0441\u043a\u0430 \u041b\u0435\u0433\u043e\u0442\u0430"
    ],
    "name:war_x_preferred":[
        "Ratkovsk\u00e1 Lehota"
    ],
    "wof:name":"Ratkovska Lehota",
    "wof:placetype":"locality"
},
  "geometry": {"coordinates":[20.09992,48.5624],"type":"Point"}
}