{
  "type": "Feature",
  "properties": {
    "gn:admin1_code":"08",
    "gn:asciiname":"Kladivovci",
    "gn:country_code":"SK",
    "gn:dem":496,
    "gn:feature_class":"P",
    "gn:feature_code":"PPL",
    "gn:name":"Kladivovci",
    "gn:population":0,
    "gn:timezone":"Europe/Bratislava",
    "iso:country":"SK",
    "wof:name":"Kladivovci",
    "wof:placetype":"locality"
},
  "geometry": {"coordinates":[18.44682,49.27624],"type":"Point"}
}