{
  "type": "Feature",
  "properties": {
    "gn:country":"SK",
    "gn:fcode":"PPL",
    "gn:population":0,
    "iso:country":"SK",
    "name:cat_x_preferred":[
        "\u010castkov"
    ],
    "name:ces_x_preferred":[
        "\u010castkov"
    ],
    "name:deu_x_preferred":[
        "\u010castkov"
    ],
    "name:epo_x_preferred":[
        "\u010castkov"
    ],
    "name:eus_x_preferred":[
        "\u010castkov"
    ],
    "name:fra_x_preferred":[
        "\u010castkov"
    ],
    "name:hun_x_preferred":[
        "Cs\u00e1szk\u00f3"
    ],
    "name:ita_x_preferred":[
        "\u010castkov"
    ],
    "name:msa_x_preferred":[
        "\u010castkov"
    ],
    "name:nld_x_preferred":[
        "\u010castkov"
    ],
    "name:por_x_preferred":[
        "\u010castkov"
    ],
    "name:ron_x_preferred":[
        "\u010castkov"
    ],
    "name:slk_x_preferred":[
        "\u010castkov"
    ],
    "name:spa_x_preferred":[
        "\u010castkov"
    ],
    "name:srp_x_preferred":[
        "\u0427\u0430\u0441\u0442\u043a\u043e\u0432"
    ],
    "name:war_x_preferred":[
        "\u010castkov"
    ],
    "qs_pg:aaroncc":"SK",
    "qs_pg:gn_country":"SK",
    "qs_pg:gn_fcode":"PPL",
    "qs_pg:gn_pop":0,
    "qs_pg:name":"\u010castkov",
    "qs_pg:name_adm0":"Slovensk\u00e1",
    "qs_pg:name_adm1":"Trnavsky",
    "qs_pg:photos_9r":0,
    "qs_pg:photos_sr":0,
    "qs_pg:pop_sr":0,
    "qs_pg:qs_pg_placetype":"locality",
    "qs_pg:qs_pg_placetype_gp":"Town",
    "qs_pg:woe_adm0":23424877,
    "woe:adm0_id":23424877,
    "woe:name_adm0":"Slovensk\u00e1",
    "woe:name_adm1":"Trnavsky",
    "woe:placetype":"Town",
    "wof:name":"\u010castkov",
    "wof:placetype":"locality"
},
  "geometry": {"coordinates":[17.3528,48.74826],"type":"Point"}
}