{
  "type": "Feature",
  "properties": {
    "gn:admin1_code":"04",
    "gn:asciiname":"Horna Strednia",
    "gn:country_code":"SK",
    "gn:dem":635,
    "gn:feature_class":"P",
    "gn:feature_code":"PPL",
    "gn:name":"Horn\u00e1 Strednia",
    "gn:population":0,
    "gn:timezone":"Europe/Bratislava",
    "iso:country":"SK",
    "name:und_x_variant":[
        "Strednia",
        "Horn\u00e1 Strednia"
    ],
    "wof:name":"Horna Strednia",
    "wof:placetype":"locality"
},
  "geometry": {"coordinates":[18.38951,48.9391],"type":"Point"}
}