{
  "type": "Feature",
  "properties": {
    "gn:admin1_code":"03",
    "gn:asciiname":"Gocovo",
    "gn:country_code":"SK",
    "gn:dem":393,
    "gn:feature_class":"P",
    "gn:feature_code":"PPL",
    "gn:name":"Go\u010dovo",
    "gn:population":0,
    "gn:timezone":"Europe/Bratislava",
    "iso:country":"SK",
    "name:cat_x_preferred":[
        "Go\u010dovo"
    ],
    "name:ces_x_preferred":[
        "Go\u010dovo"
    ],
    "name:deu_x_preferred":[
        "Go\u010dovo"
    ],
    "name:epo_x_preferred":[
        "Go\u010dovo"
    ],
    "name:eus_x_preferred":[
        "Go\u010dovo"
    ],
    "name:fra_x_preferred":[
        "Go\u010dovo"
    ],
    "name:hun_x_preferred":[
        "G\u00f3cs"
    ],
    "name:ita_x_preferred":[
        "Go\u010dovo"
    ],
    "name:msa_x_preferred":[
        "Go\u010dovo"
    ],
    "name:nld_x_preferred":[
        "Go\u010dovo"
    ],
    "name:pol_x_preferred":[
        "Go\u010dovo"
    ],
    "name:ron_x_preferred":[
        "Go\u010dovo"
    ],
    "name:slk_x_preferred":[
        "Go\u010dovo"
    ],
    "name:spa_x_preferred":[
        "Go\u010dovo"
    ],
    "name:srp_x_preferred":[
        "\u0413\u043e\u0447\u043e\u0432\u043e"
    ],
    "name:ukr_x_preferred":[
        "\u0490\u043e\u0447\u043e\u0432\u043e"
    ],
    "name:war_x_preferred":[
        "Go\u010dovo"
    ],
    "wof:name":"Gocovo",
    "wof:placetype":"locality"
},
  "geometry": {"coordinates":[20.42018,48.75931],"type":"Point"}
}