{
  "type": "Feature",
  "properties": {
    "gn:admin1_code":"03",
    "gn:asciiname":"Gocovo",
    "gn:country_code":"SK",
    "gn:dem":393,
    "gn:feature_class":"P",
    "gn:feature_code":"PPL",
    "gn:name":"Go\u010dovo",
    "gn:population":0,
    "gn:timezone":"Europe/Bratislava",
    "iso:country":"SK",
    "name:und_x_variant":[
        "Go\u010dovo"
    ],
    "wof:name":"Gocovo",
    "wof:placetype":"locality"
},
  "geometry": {"coordinates":[20.42018,48.75931],"type":"Point"}
}