{
  "type": "Feature",
  "properties": {
    "iso:country":"SK",
    "name:ces_x_preferred":[
        "Leteck\u00e1 z\u00e1kladna Malacky"
    ],
    "name:deu_x_preferred":[
        "Luftwaffenst\u00fctzpunkt Malatzka"
    ],
    "name:eng_x_preferred":[
        "Malacky Air Base"
    ],
    "name:eng_x_variant":[
        "LZMC"
    ],
    "name:fas_x_preferred":[
        "\u067e\u0627\u06cc\u06af\u0627\u0647 \u0647\u0648\u0627\u06cc\u06cc \u0645\u0627\u0644\u0627\u06a9\u06cc"
    ],
    "name:jpn_x_preferred":[
        "\u30de\u30e9\u30c4\u30ad\u7a7a\u8ecd\u57fa\u5730"
    ],
    "name:msa_x_preferred":[
        "Lapangan Terbang Malacky"
    ],
    "name:pol_x_preferred":[
        "Port lotniczy Kuchy\u0148a"
    ],
    "name:slk_x_preferred":[
        "Leteck\u00e1 z\u00e1klad\u0148a Malacky"
    ],
    "name:ukr_x_preferred":[
        "\u0410\u0432\u0456\u0430\u0431\u0430\u0437\u0430 \u041c\u0430\u043b\u0430\u0446\u043a\u0438"
    ],
    "oa:elevation_ft":"679",
    "oa:type":"medium_airport",
    "wd:wordcount":80,
    "woe:hierarchy":{
        "country_id":23424877,
        "county_id":29399337,
        "localadmin_id":29401240,
        "planet_id":1,
        "state_id":20070505
    },
    "wof:name":"Malacky Airport",
    "wof:placetype":"campus"
},
  "geometry": {"coordinates":[17.118333,48.401944],"type":"Point"}
}