{
  "type": "Feature",
  "properties": {
    "gn:admin1_code":"04",
    "gn:asciiname":"Diva",
    "gn:country_code":"SK",
    "gn:dem":124,
    "gn:feature_class":"P",
    "gn:feature_code":"PPL",
    "gn:name":"Diva",
    "gn:population":0,
    "gn:timezone":"Europe/Bratislava",
    "iso:country":"SK",
    "name:aze_x_preferred":[
        "Diva"
    ],
    "name:cat_x_preferred":[
        "Diva"
    ],
    "name:ces_x_preferred":[
        "Diva"
    ],
    "name:cym_x_preferred":[
        "Diva"
    ],
    "name:dan_x_preferred":[
        "Diva"
    ],
    "name:deu_x_preferred":[
        "Diva"
    ],
    "name:eus_x_preferred":[
        "Diva"
    ],
    "name:fin_x_preferred":[
        "Diiva"
    ],
    "name:fra_x_preferred":[
        "Diva"
    ],
    "name:heb_x_preferred":[
        "\u05d3\u05d9\u05d5\u05d5\u05d4"
    ],
    "name:ind_x_preferred":[
        "Diva"
    ],
    "name:jpn_x_preferred":[
        "\u30c7\u30a3\u30fc\u30f4\u30a1"
    ],
    "name:kor_x_preferred":[
        "\ub514\ubc14"
    ],
    "name:mkd_x_preferred":[
        "\u0414\u0438\u0432\u0430"
    ],
    "name:msa_x_preferred":[
        "Diva"
    ],
    "name:nld_x_preferred":[
        "Diva"
    ],
    "name:nor_x_preferred":[
        "Diva"
    ],
    "name:pol_x_preferred":[
        "Diwa"
    ],
    "name:ron_x_preferred":[
        "Div\u0103"
    ],
    "name:rus_x_preferred":[
        "\u0414\u0438\u0432\u0430"
    ],
    "name:spa_x_preferred":[
        "Diva"
    ],
    "name:sqi_x_preferred":[
        "Diva"
    ],
    "name:swe_x_preferred":[
        "Diva"
    ],
    "name:tha_x_preferred":[
        "\u0e14\u0e35\u0e27\u0e32"
    ],
    "name:tur_x_preferred":[
        "Diva"
    ],
    "name:und_x_variant":[
        "Gyiva",
        "Diva"
    ],
    "name:vie_x_preferred":[
        "Diva"
    ],
    "name:zho_x_preferred":[
        "Diva"
    ],
    "wof:name":"Diva",
    "wof:placetype":"locality"
},
  "geometry": {"coordinates":[18.56569,47.86787],"type":"Point"}
}