{
  "type": "Feature",
  "properties": {
    "gn:admin1_code":"04",
    "gn:asciiname":"Diva",
    "gn:country_code":"SK",
    "gn:dem":124,
    "gn:feature_class":"P",
    "gn:feature_code":"PPL",
    "gn:name":"Diva",
    "gn:population":0,
    "gn:timezone":"Europe/Bratislava",
    "iso:country":"SK",
    "name:und_x_variant":[
        "Gyiva",
        "Diva"
    ],
    "wof:name":"Diva",
    "wof:placetype":"locality"
},
  "geometry": {"coordinates":[18.56569,47.86787],"type":"Point"}
}