{
  "type": "Feature",
  "properties": {
    "gn:admin1_code":"05",
    "gn:asciiname":"Vlaca",
    "gn:country_code":"SK",
    "gn:dem":188,
    "gn:feature_class":"P",
    "gn:feature_code":"PPL",
    "gn:name":"Vla\u010da",
    "gn:population":0,
    "gn:timezone":"Europe/Bratislava",
    "iso:country":"SK",
    "name:cat_x_preferred":[
        "Vla\u010da"
    ],
    "name:ces_x_preferred":[
        "Vla\u010da"
    ],
    "name:epo_x_preferred":[
        "Vla\u010da"
    ],
    "name:eus_x_preferred":[
        "Vla\u010da"
    ],
    "name:fra_x_preferred":[
        "Vla\u010da"
    ],
    "name:hun_x_preferred":[
        "Bal\u00e1zsi"
    ],
    "name:ita_x_preferred":[
        "Vla\u010da"
    ],
    "name:msa_x_preferred":[
        "Vla\u010da"
    ],
    "name:nld_x_preferred":[
        "Vla\u010da"
    ],
    "name:pol_x_preferred":[
        "Vla\u010da"
    ],
    "name:ron_x_preferred":[
        "Vla\u010da"
    ],
    "name:slk_x_preferred":[
        "Vla\u010da"
    ],
    "name:spa_x_preferred":[
        "Vla\u010da"
    ],
    "name:srp_x_preferred":[
        "\u0412\u043b\u0430\u0447\u0430"
    ],
    "name:ukr_x_preferred":[
        "\u0412\u043b\u0430\u0447\u0430"
    ],
    "name:war_x_preferred":[
        "Vla\u010da"
    ],
    "wof:name":"Vlaca",
    "wof:placetype":"locality"
},
  "geometry": {"coordinates":[21.51063,49.04877000000001],"type":"Point"}
}