{
  "type": "Feature",
  "properties": {
    "iso:country":"SK",
    "name:eng_x_preferred":[
        "Vtacnik"
    ],
    "name:slk_x_preferred":[
        "Vt\u00e1\u010dnik"
    ],
    "wof:name":"Vtacnik",
    "wof:placetype":"neighbourhood"
},
  "geometry": {"coordinates":[17.11791291845056,48.1673137721165],"type":"Point"}
}