{
  "type": "Feature",
  "properties": {
    "gn:admin1_code":"04",
    "gn:asciiname":"Machulince",
    "gn:country_code":"SK",
    "gn:dem":226,
    "gn:feature_class":"P",
    "gn:feature_code":"PPL",
    "gn:name":"Machulince",
    "gn:population":0,
    "gn:timezone":"Europe/Bratislava",
    "iso:country":"SK",
    "wof:name":"Machulince",
    "wof:placetype":"locality"
},
  "geometry": {"coordinates":[18.43223,48.41182],"type":"Point"}
}