{
  "type": "Feature",
  "properties": {
    "gn:admin1_code":"04",
    "gn:asciiname":"Machulince",
    "gn:country_code":"SK",
    "gn:dem":226,
    "gn:feature_class":"P",
    "gn:feature_code":"PPL",
    "gn:name":"Machulince",
    "gn:population":0,
    "gn:timezone":"Europe/Bratislava",
    "iso:country":"SK",
    "name:cat_x_preferred":[
        "Machulince"
    ],
    "name:ces_x_preferred":[
        "Machulince"
    ],
    "name:deu_x_preferred":[
        "Machulince"
    ],
    "name:epo_x_preferred":[
        "Machulince"
    ],
    "name:eus_x_preferred":[
        "Machulince"
    ],
    "name:fra_x_preferred":[
        "Machulince"
    ],
    "name:hun_x_preferred":[
        "Mahol\u00e1ny"
    ],
    "name:ita_x_preferred":[
        "Machulince"
    ],
    "name:msa_x_preferred":[
        "Machulince"
    ],
    "name:nld_x_preferred":[
        "Machulince"
    ],
    "name:ron_x_preferred":[
        "Machulince"
    ],
    "name:slk_x_preferred":[
        "Machulince"
    ],
    "name:spa_x_preferred":[
        "Machulince"
    ],
    "name:srp_x_preferred":[
        "\u041c\u0430\u0445\u0443\u043b\u0438\u043d\u0446\u0435"
    ],
    "name:ukr_x_preferred":[
        "\u041c\u0430\u0445\u0443\u043b\u0456\u043d\u0446\u0435"
    ],
    "name:war_x_preferred":[
        "Machulince"
    ],
    "wof:name":"Machulince",
    "wof:placetype":"locality"
},
  "geometry": {"coordinates":[18.43223,48.41182],"type":"Point"}
}