{
  "type": "Feature",
  "properties": {
    "gn:admin1_code":"01",
    "gn:asciiname":"U Medved'ov",
    "gn:country_code":"SK",
    "gn:dem":605,
    "gn:feature_class":"P",
    "gn:feature_code":"PPL",
    "gn:name":"U Medve\u010fov",
    "gn:population":0,
    "gn:timezone":"Europe/Bratislava",
    "iso:country":"SK",
    "wof:name":"U Medved'ov",
    "wof:placetype":"locality"
},
  "geometry": {"coordinates":[19.61667000000001,48.75],"type":"Point"}
}