{
  "type": "Feature",
  "properties": {
    "gn:admin1_code":"07",
    "gn:asciiname":"Janosikovo na Ostrove",
    "gn:country_code":"SK",
    "gn:dem":110,
    "gn:feature_class":"P",
    "gn:feature_code":"PPL",
    "gn:name":"J\u00e1no\u0161\u00edkovo na Ostrove",
    "gn:population":0,
    "gn:timezone":"Europe/Bratislava",
    "iso:country":"SK",
    "name:hun_x_preferred":[
        "Bellepuszta"
    ],
    "name:und_x_variant":[
        "B\u00e9lle Pusta",
        "J\u00e1no\u0161\u00edkovo na Ostrove"
    ],
    "wof:name":"Janosikovo na Ostrove",
    "wof:placetype":"locality"
},
  "geometry": {"coordinates":[17.75734,47.90933],"type":"Point"}
}