{
  "type": "Feature",
  "properties": {
    "gn:admin1_code":"08",
    "gn:asciiname":"Brezany",
    "gn:country_code":"SK",
    "gn:dem":381,
    "gn:feature_class":"P",
    "gn:feature_code":"PPL",
    "gn:name":"Brezany",
    "gn:population":0,
    "gn:timezone":"Europe/Bratislava",
    "iso:country":"SK",
    "name:ceb_x_preferred":[
        "B\u0159e\u017eany"
    ],
    "name:ces_x_preferred":[
        "B\u0159e\u017eany"
    ],
    "name:deu_x_preferred":[
        "B\u0159e\u017eany"
    ],
    "name:eus_x_preferred":[
        "Brezany"
    ],
    "name:fra_x_preferred":[
        "B\u0159e\u017eany"
    ],
    "name:ita_x_preferred":[
        "B\u0159e\u017eany"
    ],
    "name:nld_x_preferred":[
        "Brezany"
    ],
    "name:pol_x_preferred":[
        "B\u0159e\u017eany"
    ],
    "name:slk_x_preferred":[
        "B\u0159e\u017eany"
    ],
    "name:swe_x_preferred":[
        "B\u0159e\u017eany"
    ],
    "wof:name":"Brezany",
    "wof:placetype":"locality"
},
  "geometry": {"coordinates":[18.6715,49.18885],"type":"Point"}
}