{
  "type": "Feature",
  "properties": {
    "gn:admin1_code":"08",
    "gn:asciiname":"Brezany",
    "gn:country_code":"SK",
    "gn:dem":381,
    "gn:feature_class":"P",
    "gn:feature_code":"PPL",
    "gn:name":"Brezany",
    "gn:population":0,
    "gn:timezone":"Europe/Bratislava",
    "iso:country":"SK",
    "wof:name":"Brezany",
    "wof:placetype":"locality"
},
  "geometry": {"coordinates":[18.6715,49.18885],"type":"Point"}
}