{
  "type": "Feature",
  "properties": {
    "gn:gn_country":"SK",
    "gn:gn_fcode":"PPL",
    "gn:gn_pop":0,
    "iso:country":"SK",
    "name:cat_x_preferred":[
        "Kamanov\u00e1"
    ],
    "name:cze_x_preferred":[
        "Kamanov\u00e1"
    ],
    "name:dut_x_preferred":[
        "Kamanov\u00e1"
    ],
    "name:eng_x_preferred":[
        "Kamanov\u00e1"
    ],
    "name:epo_x_preferred":[
        "Kamanov\u00e1"
    ],
    "name:fre_x_preferred":[
        "Kamanov\u00e1"
    ],
    "name:hun_x_preferred":[
        "K\u00e1lm\u00e1nfalva"
    ],
    "name:ita_x_preferred":[
        "Kamanov\u00e1"
    ],
    "name:may_x_preferred":[
        "Kamanov\u00e1"
    ],
    "name:slo_x_preferred":[
        "Kamanov\u00e1"
    ],
    "name:srp_x_preferred":[
        "kamanova"
    ],
    "name:war_x_preferred":[
        "Kamanov\u00e1"
    ],
    "qs_pg:aaroncc":"SK",
    "qs_pg:gn_country":"SK",
    "qs_pg:gn_fcode":"PPL",
    "qs_pg:gn_pop":0,
    "qs_pg:name":"Kamanov\u00e1",
    "qs_pg:name_adm0":"Slovensk\u00e1",
    "qs_pg:name_adm1":"Nitriansky",
    "qs_pg:photos_9r":0,
    "qs_pg:photos_sr":0,
    "qs_pg:pop_sr":0,
    "qs_pg:qs_pg_placetype":"locality",
    "qs_pg:qs_pg_placetype_gp":"Town",
    "qs_pg:woe_adm0":23424877,
    "woe:adm0_id":23424877,
    "woe:name_adm0":"Slovensk\u00e1",
    "woe:name_adm1":"Nitriansky",
    "woe:placetype":"Town",
    "wof:name":"Kamanov\u00e1",
    "wof:placetype":"locality"
},
  "geometry": {"coordinates":[18.10205,48.47524],"type":"Point"}
}