{
  "type": "Feature",
  "properties": {
    "iso:country":"SK",
    "name:cat_x_preferred":[
        "Nemce"
    ],
    "name:ces_x_preferred":[
        "Nemce"
    ],
    "name:deu_x_preferred":[
        "Nemce"
    ],
    "name:epo_x_preferred":[
        "Nemce"
    ],
    "name:eus_x_preferred":[
        "Nemce"
    ],
    "name:fra_x_preferred":[
        "Nemce"
    ],
    "name:hun_x_preferred":[
        "Z\u00f3lyomn\u00e9meti"
    ],
    "name:ita_x_preferred":[
        "Nemce"
    ],
    "name:msa_x_preferred":[
        "Nemce"
    ],
    "name:nld_x_preferred":[
        "Nemce"
    ],
    "name:pol_x_preferred":[
        "Nemce"
    ],
    "name:ron_x_preferred":[
        "Nemce"
    ],
    "name:slk_x_preferred":[
        "Nemce"
    ],
    "name:spa_x_preferred":[
        "Nemce"
    ],
    "name:srp_x_preferred":[
        "\u040a\u0435\u043c\u0446\u0435"
    ],
    "name:ukr_x_preferred":[
        "\u041d\u0454\u043c\u0446\u0435"
    ],
    "name:war_x_preferred":[
        "Nemce"
    ],
    "qs_pg:aaroncc":"SK",
    "qs_pg:name":"Nemce",
    "qs_pg:name_adm0":"Slovensk\u00e1",
    "qs_pg:name_adm1":"Banskobystricky",
    "qs_pg:photos":1,
    "qs_pg:photos_1k":1,
    "qs_pg:photos_9k":1,
    "qs_pg:photos_9r":1,
    "qs_pg:photos_all":1,
    "qs_pg:photos_sr":1,
    "qs_pg:pop_sr":0,
    "qs_pg:qs_pg_placetype":"localadmin",
    "qs_pg:qs_pg_placetype_gp":"LocalAdmin",
    "qs_pg:woe_adm0":23424877,
    "woe:adm0_id":23424877,
    "woe:name_adm0":"Slovensk\u00e1",
    "woe:name_adm1":"Banskobystricky",
    "woe:placetype":"LocalAdmin",
    "wof:name":"Nemce",
    "wof:placetype":"localadmin"
},
  "geometry": {"coordinates":[18.98953,48.28627],"type":"Point"}
}