{
  "type": "Feature",
  "properties": {
    "gn:admin1_code":"05",
    "gn:asciiname":"Stefurov",
    "gn:country_code":"SK",
    "gn:dem":234,
    "gn:feature_class":"P",
    "gn:feature_code":"PPL",
    "gn:name":"\u0160tefurov",
    "gn:population":0,
    "gn:timezone":"Europe/Bratislava",
    "iso:country":"SK",
    "name:bak_x_preferred":[
        "\u0428\u0442\u0435\u0444\u0443\u0440\u043e\u0432"
    ],
    "name:cat_x_preferred":[
        "\u0160tefurov"
    ],
    "name:epo_x_preferred":[
        "\u0160tefurov"
    ],
    "name:eus_x_preferred":[
        "\u0160tefurov"
    ],
    "name:fra_x_preferred":[
        "\u0160tefurov"
    ],
    "name:hun_x_preferred":[
        "Istv\u00e1nd"
    ],
    "name:ita_x_preferred":[
        "\u0160tefurov"
    ],
    "name:msa_x_preferred":[
        "\u0160tefurov"
    ],
    "name:nld_x_preferred":[
        "\u0160tefurov"
    ],
    "name:pol_x_preferred":[
        "\u0160tefurov"
    ],
    "name:ron_x_preferred":[
        "\u0160tefurov"
    ],
    "name:rue_x_preferred":[
        "\u0428\u0442\u0435\u0444\u0443\u0440\u0456\u0432"
    ],
    "name:slk_x_preferred":[
        "\u0160tefurov"
    ],
    "name:spa_x_preferred":[
        "\u0160tefurov"
    ],
    "name:srp_x_preferred":[
        "\u0428\u0442\u0458\u0435\u0444\u0443\u0440\u043e\u0432"
    ],
    "name:ukr_x_preferred":[
        "\u0428\u0442\u0435\u0444\u0443\u0440\u0456\u0432"
    ],
    "name:war_x_preferred":[
        "\u0160tefurov"
    ],
    "wof:name":"Stefurov",
    "wof:placetype":"locality"
},
  "geometry": {"coordinates":[21.50693,49.17588],"type":"Point"}
}