{
  "type": "Feature",
  "properties": {
    "gn:admin1_code":"05",
    "gn:asciiname":"Stefurov",
    "gn:country_code":"SK",
    "gn:dem":234,
    "gn:feature_class":"P",
    "gn:feature_code":"PPL",
    "gn:name":"\u0160tefurov",
    "gn:population":0,
    "gn:timezone":"Europe/Bratislava",
    "iso:country":"SK",
    "name:und_x_variant":[
        "\u0160tefurov"
    ],
    "wof:name":"Stefurov",
    "wof:placetype":"locality"
},
  "geometry": {"coordinates":[21.50693,49.17588],"type":"Point"}
}