{
  "type": "Feature",
  "properties": {
    "gn:admin1_code":"08",
    "gn:asciiname":"Dolna Stubna",
    "gn:country_code":"SK",
    "gn:dem":529,
    "gn:feature_class":"P",
    "gn:feature_code":"PPL",
    "gn:name":"Doln\u00e1 \u0160tub\u0148a",
    "gn:population":0,
    "gn:timezone":"Europe/Bratislava",
    "iso:country":"SK",
    "name:deu_x_preferred":[
        "Unter-Stuben"
    ],
    "name:hun_x_preferred":[
        "Als\u00f3stubnya"
    ],
    "name:und_x_variant":[
        "Doln\u00e1 \u0160tub\u0148a"
    ],
    "wof:name":"Dolna Stubna",
    "wof:placetype":"locality"
},
  "geometry": {"coordinates":[18.86215,48.84671],"type":"Point"}
}