{
  "type": "Feature",
  "properties": {
    "gn:admin1_code":"08",
    "gn:asciiname":"Turciansky Svaty Michal",
    "gn:country_code":"SK",
    "gn:dem":492,
    "gn:feature_class":"P",
    "gn:feature_code":"PPL",
    "gn:name":"Tur\u010diansky Sv\u00e4t\u00fd Michal",
    "gn:population":0,
    "gn:timezone":"Europe/Bratislava",
    "iso:country":"SK",
    "name:und_x_variant":[
        "Sv\u00e4t\u00fd Michal",
        "Tur\u010diansky Sv\u00e4t\u00fd Michal"
    ],
    "wof:name":"Turciansky Svaty Michal",
    "wof:placetype":"locality"
},
  "geometry": {"coordinates":[18.86301,48.8847],"type":"Point"}
}