{
  "type": "Feature",
  "properties": {
    "gn:admin1_code":"08",
    "gn:asciiname":"Rybove",
    "gn:country_code":"SK",
    "gn:dem":712,
    "gn:feature_class":"P",
    "gn:feature_code":"PPL",
    "gn:name":"Rybov\u00e9",
    "gn:population":0,
    "gn:timezone":"Europe/Bratislava",
    "iso:country":"SK",
    "wof:name":"Rybove",
    "wof:placetype":"locality"
},
  "geometry": {"coordinates":[18.56667,49.43333],"type":"Point"}
}