{
  "type": "Feature",
  "properties": {
    "gn:admin1_code":"05",
    "gn:asciiname":"Havka",
    "gn:country_code":"SK",
    "gn:dem":629,
    "gn:feature_class":"P",
    "gn:feature_code":"PPL",
    "gn:name":"Havka",
    "gn:population":0,
    "gn:timezone":"Europe/Bratislava",
    "iso:country":"SK",
    "name:cat_x_preferred":[
        "Havka"
    ],
    "name:ces_x_preferred":[
        "Havka"
    ],
    "name:deu_x_preferred":[
        "Havka"
    ],
    "name:epo_x_preferred":[
        "Havka"
    ],
    "name:eus_x_preferred":[
        "Havka"
    ],
    "name:fra_x_preferred":[
        "Havka"
    ],
    "name:hun_x_preferred":[
        "H\u00f3ka"
    ],
    "name:ita_x_preferred":[
        "Havka"
    ],
    "name:msa_x_preferred":[
        "Havka"
    ],
    "name:nld_x_preferred":[
        "Havka"
    ],
    "name:pol_x_preferred":[
        "Havka"
    ],
    "name:ron_x_preferred":[
        "Havka"
    ],
    "name:rue_x_preferred":[
        "\u0413\u0430\u0432\u043a\u0430"
    ],
    "name:slk_x_preferred":[
        "Havka"
    ],
    "name:spa_x_preferred":[
        "Havka"
    ],
    "name:srp_x_preferred":[
        "\u0425\u0430\u0432\u043a\u0430"
    ],
    "name:ukr_x_preferred":[
        "\u0413\u0430\u0432\u043a\u0430"
    ],
    "name:war_x_preferred":[
        "Havka"
    ],
    "wof:name":"Havka",
    "wof:placetype":"locality"
},
  "geometry": {"coordinates":[20.40672,49.3451],"type":"Point"}
}