{
  "type": "Feature",
  "properties": {
    "gn:admin1_code":"05",
    "gn:asciiname":"Havka",
    "gn:country_code":"SK",
    "gn:dem":629,
    "gn:feature_class":"P",
    "gn:feature_code":"PPL",
    "gn:name":"Havka",
    "gn:population":0,
    "gn:timezone":"Europe/Bratislava",
    "iso:country":"SK",
    "wof:name":"Havka",
    "wof:placetype":"locality"
},
  "geometry": {"coordinates":[20.40672,49.3451],"type":"Point"}
}