{
  "type": "Feature",
  "properties": {
    "gn:admin1_code":"04",
    "gn:asciiname":"Hontianska Vrbica",
    "gn:country_code":"SK",
    "gn:dem":153,
    "gn:feature_class":"P",
    "gn:feature_code":"PPL",
    "gn:name":"Hontianska Vrbica",
    "gn:population":0,
    "gn:timezone":"Europe/Bratislava",
    "iso:country":"SK",
    "name:cat_x_preferred":[
        "Hontianska Vrbica"
    ],
    "name:ces_x_preferred":[
        "Hontianska Vrbica"
    ],
    "name:deu_x_preferred":[
        "Hontianska Vrbica"
    ],
    "name:epo_x_preferred":[
        "Hontianska Vrbica"
    ],
    "name:eus_x_preferred":[
        "Hontianska Vrbica"
    ],
    "name:fra_x_preferred":[
        "Hontianska Vrbica"
    ],
    "name:hun_x_preferred":[
        "Hontf\u00fczesgyarmat"
    ],
    "name:ita_x_preferred":[
        "Hontianska Vrbica"
    ],
    "name:msa_x_preferred":[
        "Hontianska Vrbica"
    ],
    "name:nld_x_preferred":[
        "Hontianska Vrbica"
    ],
    "name:pol_x_preferred":[
        "Hontianska Vrbica"
    ],
    "name:ron_x_preferred":[
        "Hontianska Vrbica"
    ],
    "name:slk_x_preferred":[
        "Hontianska Vrbica"
    ],
    "name:spa_x_preferred":[
        "Hontianska Vrbica"
    ],
    "name:srp_x_preferred":[
        "\u0425\u043e\u043d\u0442\u0458\u0430\u043d\u0441\u043a\u0430 \u0412\u0440\u0431\u0438\u0446\u0430"
    ],
    "name:und_x_variant":[
        "Hontianske \u010earmoty",
        "F\u00fczes-Gyarmat",
        "Hontianska Vrbica"
    ],
    "name:war_x_preferred":[
        "Hontianska Vrbica"
    ],
    "wof:name":"Hontianska Vrbica",
    "wof:placetype":"locality"
},
  "geometry": {"coordinates":[18.70359,48.13479],"type":"Point"}
}