{
  "type": "Feature",
  "properties": {
    "gn:admin1_code":"04",
    "gn:asciiname":"Hontianska Vrbica",
    "gn:country_code":"SK",
    "gn:dem":153,
    "gn:feature_class":"P",
    "gn:feature_code":"PPL",
    "gn:name":"Hontianska Vrbica",
    "gn:population":0,
    "gn:timezone":"Europe/Bratislava",
    "iso:country":"SK",
    "name:und_x_variant":[
        "Hontianske \u010earmoty",
        "F\u00fczes-Gyarmat",
        "Hontianska Vrbica"
    ],
    "wof:name":"Hontianska Vrbica",
    "wof:placetype":"locality"
},
  "geometry": {"coordinates":[18.70359,48.13479],"type":"Point"}
}