{
  "type": "Feature",
  "properties": {
    "gn:admin1_code":"04",
    "gn:asciiname":"Marianska Calad'",
    "gn:country_code":"SK",
    "gn:dem":184,
    "gn:feature_class":"P",
    "gn:feature_code":"PPL",
    "gn:name":"Mariansk\u00e1 \u010cala\u010f",
    "gn:population":0,
    "gn:timezone":"Europe/Bratislava",
    "iso:country":"SK",
    "wof:name":"Marianska Calad'",
    "wof:placetype":"locality"
},
  "geometry": {"coordinates":[18.37157,48.06848],"type":"Point"}
}