{
  "type": "Feature",
  "properties": {
    "gn:admin1_code":"01",
    "gn:asciiname":"Ilonahalma",
    "gn:country_code":"SK",
    "gn:dem":260,
    "gn:feature_class":"P",
    "gn:feature_code":"PPL",
    "gn:name":"Ilonahalma",
    "gn:population":0,
    "gn:timezone":"Europe/Bratislava",
    "iso:country":"SK",
    "wof:name":"Ilonahalma",
    "wof:placetype":"locality"
},
  "geometry": {"coordinates":[20.21667,48.48333],"type":"Point"}
}