{
  "type": "Feature",
  "properties": {
    "gn:admin1_code":"04",
    "gn:asciiname":"Agov",
    "gn:country_code":"SK",
    "gn:dem":144,
    "gn:feature_class":"P",
    "gn:feature_code":"PPL",
    "gn:name":"Agov",
    "gn:population":0,
    "gn:timezone":"Europe/Bratislava",
    "iso:country":"SK",
    "name:hun_x_preferred":[
        "\u00c1g\u00f3"
    ],
    "wof:name":"Agov",
    "wof:placetype":"locality"
},
  "geometry": {"coordinates":[18.58333,48.01667],"type":"Point"}
}