{
  "type": "Feature",
  "properties": {
    "gn:admin1_code":"04",
    "gn:asciiname":"Bastin",
    "gn:country_code":"SK",
    "gn:dem":179,
    "gn:feature_class":"P",
    "gn:feature_code":"PPL",
    "gn:name":"Ba\u0161t\u00edn",
    "gn:population":0,
    "gn:timezone":"Europe/Bratislava",
    "iso:country":"SK",
    "wof:name":"Bastin",
    "wof:placetype":"locality"
},
  "geometry": {"coordinates":[18.23805,48.55958],"type":"Point"}
}