{
  "type": "Feature",
  "properties": {
    "gn:admin1_code":"01",
    "gn:asciiname":"Horne Opatovce",
    "gn:country_code":"SK",
    "gn:dem":292,
    "gn:feature_class":"P",
    "gn:feature_code":"PPL",
    "gn:name":"Horn\u00e9 Opatovce",
    "gn:population":0,
    "gn:timezone":"Europe/Bratislava",
    "iso:country":"SK",
    "name:und_x_variant":[
        "Horn\u00ed Opatovce",
        "Hornie Opatovce",
        "Horn\u00e9 Opatovce"
    ],
    "wof:name":"Horne Opatovce",
    "wof:placetype":"locality"
},
  "geometry": {"coordinates":[18.85178,48.55781],"type":"Point"}
}