{
  "type": "Feature",
  "properties": {
    "gn:country":"SK",
    "gn:fcode":"PPL",
    "gn:population":0,
    "iso:country":"SK",
    "name:cat_x_preferred":[
        "Krahule"
    ],
    "name:ces_x_preferred":[
        "Krahule"
    ],
    "name:deu_x_preferred":[
        "Krahule"
    ],
    "name:eng_x_preferred":[
        "Krahule"
    ],
    "name:epo_x_preferred":[
        "Krahule"
    ],
    "name:eus_x_preferred":[
        "Krahule"
    ],
    "name:fra_x_preferred":[
        "Krahule"
    ],
    "name:hun_x_preferred":[
        "K\u00e9kell\u0151"
    ],
    "name:ita_x_preferred":[
        "Krahule"
    ],
    "name:lit_x_preferred":[
        "Krahul\u0117"
    ],
    "name:msa_x_preferred":[
        "Krahule"
    ],
    "name:nan_x_preferred":[
        "Krahule"
    ],
    "name:nld_x_preferred":[
        "Krahule"
    ],
    "name:nob_x_preferred":[
        "Krahule"
    ],
    "name:pol_x_preferred":[
        "Krahule/Blaufu\u00df"
    ],
    "name:por_x_preferred":[
        "Krahule"
    ],
    "name:ron_x_preferred":[
        "Krahule"
    ],
    "name:rus_x_preferred":[
        "\u041a\u0440\u0430\u0445\u0443\u043b\u0435"
    ],
    "name:slk_x_preferred":[
        "Krahule"
    ],
    "name:spa_x_preferred":[
        "Krahule"
    ],
    "name:srp_x_preferred":[
        "\u041a\u0440\u0430\u0445\u0443\u0459\u0435"
    ],
    "name:ukr_x_preferred":[
        "\u041a\u0440\u0430\u0433\u0443\u043b\u0435"
    ],
    "name:und_x_variant":[
        "Blaufuss"
    ],
    "name:war_x_preferred":[
        "Krahule"
    ],
    "qs_pg:aaroncc":"SK",
    "qs_pg:gn_country":"SK",
    "qs_pg:gn_fcode":"PPL",
    "qs_pg:gn_pop":0,
    "qs_pg:name":"Krahule",
    "qs_pg:name_adm0":"Slovensk\u00e1",
    "qs_pg:name_adm1":"Banskobystricky",
    "qs_pg:photos":63,
    "qs_pg:photos_1k":13,
    "qs_pg:photos_9k":1,
    "qs_pg:photos_9r":2,
    "qs_pg:photos_all":63,
    "qs_pg:photos_sr":2,
    "qs_pg:pop_sr":0,
    "qs_pg:qs_pg_placetype":"locality",
    "qs_pg:qs_pg_placetype_gp":"Town",
    "qs_pg:woe_adm0":23424877,
    "woe:adm0_id":23424877,
    "woe:name_adm0":"Slovensk\u00e1",
    "woe:name_adm1":"Banskobystricky",
    "woe:placetype":"Town",
    "wof:name":"Krahule",
    "wof:placetype":"locality"
},
  "geometry": {"coordinates":[18.94055,48.72608],"type":"Point"}
}