{
  "type": "Feature",
  "properties": {
    "gn:admin1_code":"07",
    "gn:asciiname":"Dec",
    "gn:country_code":"SK",
    "gn:dem":204,
    "gn:feature_class":"P",
    "gn:feature_code":"PPL",
    "gn:name":"De\u010d",
    "gn:population":0,
    "gn:timezone":"Europe/Bratislava",
    "iso:country":"SK",
    "name:pol_x_preferred":[
        "Dec"
    ],
    "wof:name":"Dec",
    "wof:placetype":"locality"
},
  "geometry": {"coordinates":[17.85,48.38333],"type":"Point"}
}