{
  "type": "Feature",
  "properties": {
    "gn:admin1_code":"04",
    "gn:asciiname":"Maly Valkaz",
    "gn:country_code":"SK",
    "gn:dem":126,
    "gn:feature_class":"P",
    "gn:feature_code":"PPL",
    "gn:name":"Mal\u00fd Valk\u00e1z",
    "gn:population":0,
    "gn:timezone":"Europe/Bratislava",
    "iso:country":"SK",
    "name:und_x_variant":[
        "Dvor Mal\u00fd Valk\u00e1z",
        "Mal\u00fd Valk\u00e1z"
    ],
    "wof:name":"Maly Valkaz",
    "wof:placetype":"locality"
},
  "geometry": {"coordinates":[18.28333,48.13333],"type":"Point"}
}