{
  "type": "Feature",
  "properties": {
    "gn:admin1_code":"03",
    "gn:asciiname":"Kobeliarovo",
    "gn:country_code":"SK",
    "gn:dem":461,
    "gn:feature_class":"P",
    "gn:feature_code":"PPL",
    "gn:name":"Kobeliarovo",
    "gn:population":0,
    "gn:timezone":"Europe/Bratislava",
    "iso:country":"SK",
    "name:bul_x_preferred":[
        "\u041a\u043e\u0431\u0435\u043b\u044f\u0440\u043e\u0432\u043e"
    ],
    "name:cat_x_preferred":[
        "Kobeliarovo"
    ],
    "name:ces_x_preferred":[
        "Kobeliarovo"
    ],
    "name:deu_x_preferred":[
        "Kobeliarovo"
    ],
    "name:epo_x_preferred":[
        "Kobeliarovo"
    ],
    "name:eus_x_preferred":[
        "Kobeliarovo"
    ],
    "name:fra_x_preferred":[
        "Kobeliarovo"
    ],
    "name:hun_x_preferred":[
        "Kisfeketepatak"
    ],
    "name:ita_x_preferred":[
        "Kobeliarovo"
    ],
    "name:msa_x_preferred":[
        "Kobeliarovo"
    ],
    "name:nld_x_preferred":[
        "Kobeliarovo"
    ],
    "name:pol_x_preferred":[
        "Kobeliarovo"
    ],
    "name:ron_x_preferred":[
        "Kobeliarovo"
    ],
    "name:slk_x_preferred":[
        "Kobeliarovo"
    ],
    "name:spa_x_preferred":[
        "Kobeliarovo"
    ],
    "name:srp_x_preferred":[
        "\u041a\u043e\u0431\u0435\u0459\u0430\u0440\u043e\u0432\u043e"
    ],
    "name:ukr_x_preferred":[
        "\u041a\u043e\u0431\u0435\u043b\u044f\u0440\u043e\u0432\u043e"
    ],
    "name:war_x_preferred":[
        "Kobeliarovo"
    ],
    "wof:name":"Kobeliarovo",
    "wof:placetype":"locality"
},
  "geometry": {"coordinates":[20.37085,48.74456],"type":"Point"}
}