{
  "type": "Feature",
  "properties": {
    "gn:admin1_code":"05",
    "gn:asciiname":"Mokroluh",
    "gn:country_code":"SK",
    "gn:dem":312,
    "gn:feature_class":"P",
    "gn:feature_code":"PPL",
    "gn:name":"Mokroluh",
    "gn:population":0,
    "gn:timezone":"Europe/Bratislava",
    "iso:country":"SK",
    "name:cat_x_preferred":[
        "Mokroluh"
    ],
    "name:ces_x_preferred":[
        "Mokroluh"
    ],
    "name:epo_x_preferred":[
        "Mokroluh"
    ],
    "name:eus_x_preferred":[
        "Mokroluh"
    ],
    "name:fra_x_preferred":[
        "Mokroluh"
    ],
    "name:hun_x_preferred":[
        "Tapolys\u00e1rpatak"
    ],
    "name:ita_x_preferred":[
        "Mokroluh"
    ],
    "name:msa_x_preferred":[
        "Mokroluh"
    ],
    "name:nld_x_preferred":[
        "Mokroluh"
    ],
    "name:pol_x_preferred":[
        "Mokroluh"
    ],
    "name:ron_x_preferred":[
        "Mokroluh"
    ],
    "name:rue_x_preferred":[
        "\u041c\u043e\u043a\u0440\u043e\u043b\u0443\u0433"
    ],
    "name:slk_x_preferred":[
        "Mokroluh"
    ],
    "name:spa_x_preferred":[
        "Mokroluh"
    ],
    "name:srp_x_preferred":[
        "\u041c\u043e\u043a\u0440\u043e\u043b\u0443\u0445"
    ],
    "name:ukr_x_preferred":[
        "\u041c\u043e\u043a\u0440\u043e\u043b\u0443\u0433"
    ],
    "name:war_x_preferred":[
        "Mokroluh"
    ],
    "wof:name":"Mokroluh",
    "wof:placetype":"locality"
},
  "geometry": {"coordinates":[21.21249,49.3089],"type":"Point"}
}