{
  "type": "Feature",
  "properties": {
    "gn:admin1_code":"04",
    "gn:asciiname":"Macov",
    "gn:country_code":"SK",
    "gn:dem":289,
    "gn:feature_class":"P",
    "gn:feature_code":"PPL",
    "gn:name":"Ma\u010dov",
    "gn:population":0,
    "gn:timezone":"Europe/Bratislava",
    "iso:country":"SK",
    "name:cat_x_preferred":[
        "Macov"
    ],
    "name:deu_x_preferred":[
        "Macov"
    ],
    "name:epo_x_preferred":[
        "Macov"
    ],
    "name:eus_x_preferred":[
        "Macov"
    ],
    "name:fra_x_preferred":[
        "Macov"
    ],
    "name:hun_x_preferred":[
        "Mach\u00e1za"
    ],
    "name:ita_x_preferred":[
        "Macov"
    ],
    "name:msa_x_preferred":[
        "Macov"
    ],
    "name:nld_x_preferred":[
        "Macov"
    ],
    "name:por_x_preferred":[
        "Macov"
    ],
    "name:ron_x_preferred":[
        "Macov"
    ],
    "name:slk_x_preferred":[
        "Macov"
    ],
    "name:spa_x_preferred":[
        "Macov"
    ],
    "name:srp_x_preferred":[
        "\u041c\u0430\u0446\u043e\u0432"
    ],
    "name:ukr_x_preferred":[
        "\u041c\u0430\u0446\u043e\u0432"
    ],
    "name:und_x_variant":[
        "Ma\u010dov"
    ],
    "name:war_x_preferred":[
        "Macov"
    ],
    "wof:name":"Macov",
    "wof:placetype":"locality"
},
  "geometry": {"coordinates":[18.5014,48.77155],"type":"Point"}
}