{
  "type": "Feature",
  "properties": {
    "gn:admin1_code":"04",
    "gn:asciiname":"Macov",
    "gn:country_code":"SK",
    "gn:dem":289,
    "gn:feature_class":"P",
    "gn:feature_code":"PPL",
    "gn:name":"Ma\u010dov",
    "gn:population":0,
    "gn:timezone":"Europe/Bratislava",
    "iso:country":"SK",
    "name:und_x_variant":[
        "Ma\u010dov"
    ],
    "wof:name":"Macov",
    "wof:placetype":"locality"
},
  "geometry": {"coordinates":[18.5014,48.77155],"type":"Point"}
}