{
  "type": "Feature",
  "properties": {
    "gn:admin1_code":"04",
    "gn:asciiname":"Mala Lehotka",
    "gn:country_code":"SK",
    "gn:dem":350,
    "gn:feature_class":"P",
    "gn:feature_code":"PPL",
    "gn:name":"Mal\u00e1 Leh\u00f4tka",
    "gn:population":0,
    "gn:timezone":"Europe/Bratislava",
    "iso:country":"SK",
    "name:und_x_variant":[
        "Mal\u00e1 Lehota",
        "Mal\u00e1 Lihotka",
        "Mal\u00e1 Leh\u00f4tka"
    ],
    "wof:name":"Mala Lehotka",
    "wof:placetype":"locality"
},
  "geometry": {"coordinates":[18.66643,48.76592],"type":"Point"}
}