{
  "type": "Feature",
  "properties": {
    "gn:admin1_code":"03",
    "gn:asciiname":"Jablonov nad Turnou",
    "gn:country_code":"SK",
    "gn:dem":238,
    "gn:feature_class":"P",
    "gn:feature_code":"PPL",
    "gn:name":"Jablonov nad Turnou",
    "gn:population":0,
    "gn:timezone":"Europe/Bratislava",
    "iso:country":"SK",
    "name:cat_x_preferred":[
        "Jablonov nad Tur\u0148ou"
    ],
    "name:ces_x_preferred":[
        "Jablonov nad Tur\u0148ou"
    ],
    "name:deu_x_preferred":[
        "Jablonov nad Tur\u0148ou"
    ],
    "name:epo_x_preferred":[
        "Jablonov nad Tur\u0148ou"
    ],
    "name:eus_x_preferred":[
        "Jablonov nad Tur\u0148ou"
    ],
    "name:fra_x_preferred":[
        "Jablonov nad Tur\u0148ou"
    ],
    "name:hun_x_preferred":[
        "Sz\u00e1dalm\u00e1s"
    ],
    "name:ita_x_preferred":[
        "Jablonov nad Tur\u0148ou"
    ],
    "name:msa_x_preferred":[
        "Jablonov nad Tur\u0148ou"
    ],
    "name:nld_x_preferred":[
        "Jablonov nad Tur\u0148ou"
    ],
    "name:pol_x_preferred":[
        "Jablonov nad Tur\u0148ou"
    ],
    "name:ron_x_preferred":[
        "Jablonov nad Tur\u0148ou"
    ],
    "name:slk_x_preferred":[
        "Jablonov nad Tur\u0148ou"
    ],
    "name:spa_x_preferred":[
        "Jablonov nad Tur\u0148ou"
    ],
    "name:srp_x_preferred":[
        "\u0408\u0430\u0431\u043b\u043e\u043d\u043e\u0432 \u043d\u0430 \u0422\u0443\u0440\u045a\u0438"
    ],
    "name:ukr_x_preferred":[
        "\u042f\u0431\u043b\u043e\u043d\u043e\u0432-\u043d\u0430\u0434-\u0422\u0443\u0440\u043d\u044c\u043e\u0443"
    ],
    "name:und_x_variant":[
        "Sz\u00e1dalm\u00e1s",
        "Jablonov nad Turnou"
    ],
    "name:war_x_preferred":[
        "Jablonov nad Tur\u0148ou"
    ],
    "wof:name":"Jablonov nad Turnou",
    "wof:placetype":"locality"
},
  "geometry": {"coordinates":[20.67449,48.59392],"type":"Point"}
}