{
  "type": "Feature",
  "properties": {
    "gn:admin1_code":"03",
    "gn:asciiname":"Jablonov nad Turnou",
    "gn:country_code":"SK",
    "gn:dem":238,
    "gn:feature_class":"P",
    "gn:feature_code":"PPL",
    "gn:name":"Jablonov nad Turnou",
    "gn:population":0,
    "gn:timezone":"Europe/Bratislava",
    "iso:country":"SK",
    "name:und_x_variant":[
        "Sz\u00e1dalm\u00e1s",
        "Jablonov nad Turnou"
    ],
    "wof:name":"Jablonov nad Turnou",
    "wof:placetype":"locality"
},
  "geometry": {"coordinates":[20.67449,48.59392],"type":"Point"}
}