{
  "type": "Feature",
  "properties": {
    "iso:country":"SK",
    "name:eng_x_preferred":[
        "Zrkadlovy haj"
    ],
    "name:slk_x_preferred":[
        "Zrkadlov\u00fd h\u00e1j"
    ],
    "wof:name":"Zrkadlovy haj",
    "wof:placetype":"neighbourhood"
},
  "geometry": {"coordinates":[17.11038667113808,48.10692467294239],"type":"Point"}
}