{
  "type": "Feature",
  "properties": {
    "gn:admin1_code":"05",
    "gn:asciiname":"Kecerovske Pavlovce",
    "gn:country_code":"SK",
    "gn:dem":288,
    "gn:feature_class":"P",
    "gn:feature_code":"PPL",
    "gn:name":"Kecerovsk\u00e9 Pavlovce",
    "gn:population":0,
    "gn:timezone":"Europe/Bratislava",
    "iso:country":"SK",
    "wof:name":"Kecerovske Pavlovce",
    "wof:placetype":"locality"
},
  "geometry": {"coordinates":[21.45,49.03333],"type":"Point"}
}