{
  "type": "Feature",
  "properties": {
    "gn:admin1_code":"04",
    "gn:asciiname":"Male Chyndice",
    "gn:country_code":"SK",
    "gn:dem":178,
    "gn:feature_class":"P",
    "gn:feature_code":"PPL",
    "gn:name":"Mal\u00e9 Chyndice",
    "gn:population":0,
    "gn:timezone":"Europe/Bratislava",
    "iso:country":"SK",
    "name:cat_x_preferred":[
        "Mal\u00e9 Chyndice"
    ],
    "name:epo_x_preferred":[
        "Mal\u00e9 Chyndice"
    ],
    "name:eus_x_preferred":[
        "Mal\u00e9 Chyndice"
    ],
    "name:fra_x_preferred":[
        "Mal\u00e9 Chyndice"
    ],
    "name:hun_x_preferred":[
        "Kishind"
    ],
    "name:ita_x_preferred":[
        "Mal\u00e9 Chyndice"
    ],
    "name:msa_x_preferred":[
        "Mal\u00e9 Chyndice"
    ],
    "name:nld_x_preferred":[
        "Mal\u00e9 Chyndice"
    ],
    "name:ron_x_preferred":[
        "Mal\u00e9 Chyndice"
    ],
    "name:slk_x_preferred":[
        "Mal\u00e9 Chyndice"
    ],
    "name:spa_x_preferred":[
        "Mal\u00e9 Chyndice"
    ],
    "name:srp_x_preferred":[
        "\u041c\u0430\u0459\u0435 \u0425\u0438\u043d\u0434\u0438\u0446\u0435"
    ],
    "name:und_x_variant":[
        "Mal\u00e9 Hyndice"
    ],
    "name:war_x_preferred":[
        "Mal\u00e9 Chyndice"
    ],
    "wof:name":"Male Chyndice",
    "wof:placetype":"locality"
},
  "geometry": {"coordinates":[18.28604,48.30316],"type":"Point"}
}