{
  "type": "Feature",
  "properties": {
    "gn:admin1_code":"04",
    "gn:asciiname":"Korytnianske-Kopanice",
    "gn:country_code":"SK",
    "gn:dem":275,
    "gn:feature_class":"P",
    "gn:feature_code":"PPL",
    "gn:name":"Korytnianske-Kopanice",
    "gn:population":0,
    "gn:timezone":"Europe/Bratislava",
    "iso:country":"SK",
    "name:und_x_variant":[
        "Koryt\u0148ansk\u00e9 Kopanice",
        "Korytnianske-Kopanice"
    ],
    "wof:name":"Korytnianske-Kopanice",
    "wof:placetype":"locality"
},
  "geometry": {"coordinates":[17.72486,48.67855],"type":"Point"}
}