{
  "type": "Feature",
  "properties": {
    "gn:admin1_code":"01",
    "gn:asciiname":"Bravacov",
    "gn:country_code":"SK",
    "gn:dem":613,
    "gn:feature_class":"P",
    "gn:feature_code":"PPL",
    "gn:name":"Brava\u010dov",
    "gn:population":0,
    "gn:timezone":"Europe/Bratislava",
    "iso:country":"SK",
    "wof:name":"Bravacov",
    "wof:placetype":"locality"
},
  "geometry": {"coordinates":[19.74481,48.83914],"type":"Point"}
}