{
  "type": "Feature",
  "properties": {
    "gn:admin1_code":"02",
    "gn:asciiname":"Kral'ova",
    "gn:country_code":"SK",
    "gn:dem":231,
    "gn:feature_class":"P",
    "gn:feature_code":"PPL",
    "gn:name":"Kr\u00e1\u013eov\u00e1",
    "gn:population":0,
    "gn:timezone":"Europe/Bratislava",
    "iso:country":"SK",
    "wof:name":"Kral'ova",
    "wof:placetype":"locality"
},
  "geometry": {"coordinates":[17.32307999999999,48.35202],"type":"Point"}
}