{
  "type": "Feature",
  "properties": {
    "iso:country":"SK",
    "name:eng_x_preferred":[
        "Drotarska cesta"
    ],
    "name:slk_x_preferred":[
        "Drot\u00e1rska cesta"
    ],
    "name:slk_x_variant":[
        "Oblas\u0165 Drot\u00e1rska cesta"
    ],
    "wof:name":"Drotarska cesta",
    "wof:placetype":"neighbourhood"
},
  "geometry": {"coordinates":[17.08455337407778,48.15601609010586],"type":"Point"}
}