{
  "type": "Feature",
  "properties": {
    "gn:admin1_code":"04",
    "gn:asciiname":"Dolna Malanta",
    "gn:country_code":"SK",
    "gn:dem":164,
    "gn:feature_class":"P",
    "gn:feature_code":"PPL",
    "gn:name":"Doln\u00e1 Malanta",
    "gn:population":0,
    "gn:timezone":"Europe/Bratislava",
    "iso:country":"SK",
    "name:und_x_variant":[
        "Dvor Doln\u00e1 Malanta",
        "Doln\u00e1 Malanta"
    ],
    "wof:name":"Dolna Malanta",
    "wof:placetype":"locality"
},
  "geometry": {"coordinates":[18.15,48.31667],"type":"Point"}
}