{
  "type": "Feature",
  "properties": {
    "gn:admin1_code":"05",
    "gn:asciiname":"Vislava",
    "gn:country_code":"SK",
    "gn:dem":259,
    "gn:feature_class":"P",
    "gn:feature_code":"PPL",
    "gn:name":"Vislava",
    "gn:population":0,
    "gn:timezone":"Europe/Bratislava",
    "iso:country":"SK",
    "wof:name":"Vislava",
    "wof:placetype":"locality"
},
  "geometry": {"coordinates":[21.66012000000001,49.28154],"type":"Point"}
}