{
  "type": "Feature",
  "properties": {
    "gn:admin1_code":"04",
    "gn:asciiname":"Jablonovce",
    "gn:country_code":"SK",
    "gn:dem":279,
    "gn:feature_class":"P",
    "gn:feature_code":"PPL",
    "gn:name":"Jablo\u0148ovce",
    "gn:population":0,
    "gn:timezone":"Europe/Bratislava",
    "iso:country":"SK",
    "name:cat_x_preferred":[
        "Jablo\u0148ovce"
    ],
    "name:ces_x_preferred":[
        "Jablo\u0148ovce"
    ],
    "name:deu_x_preferred":[
        "Jablo\u0148ovce"
    ],
    "name:epo_x_preferred":[
        "Jablo\u0148ovce"
    ],
    "name:eus_x_preferred":[
        "Jablo\u0148ovce"
    ],
    "name:fra_x_preferred":[
        "Jablo\u0148ovce"
    ],
    "name:hun_x_preferred":[
        "Hontalm\u00e1s"
    ],
    "name:ita_x_preferred":[
        "Jablo\u0148ovce"
    ],
    "name:msa_x_preferred":[
        "Jablo\u0148ovce"
    ],
    "name:nld_x_preferred":[
        "Jablo\u0148ovce"
    ],
    "name:pol_x_preferred":[
        "Jablo\u0148ovce"
    ],
    "name:ron_x_preferred":[
        "Jablo\u0148ovce"
    ],
    "name:slk_x_preferred":[
        "Jablo\u0148ovce"
    ],
    "name:spa_x_preferred":[
        "Jablo\u0148ovce"
    ],
    "name:srp_x_preferred":[
        "\u0408\u0430\u0431\u043b\u043e\u045a\u043e\u0432\u0446\u0435"
    ],
    "name:und_x_variant":[
        "Alm\u00e1\u0161"
    ],
    "name:war_x_preferred":[
        "Jablo\u0148ovce"
    ],
    "wof:name":"Jablonovce",
    "wof:placetype":"locality"
},
  "geometry": {"coordinates":[18.78891,48.31853],"type":"Point"}
}