{
  "type": "Feature",
  "properties": {
    "gn:admin1_code":"04",
    "gn:asciiname":"Jablonovce",
    "gn:country_code":"SK",
    "gn:dem":279,
    "gn:feature_class":"P",
    "gn:feature_code":"PPL",
    "gn:name":"Jablo\u0148ovce",
    "gn:population":0,
    "gn:timezone":"Europe/Bratislava",
    "iso:country":"SK",
    "name:und_x_variant":[
        "Alm\u00e1\u0161",
        "Jablo\u0148ovce"
    ],
    "wof:name":"Jablonovce",
    "wof:placetype":"locality"
},
  "geometry": {"coordinates":[18.78891,48.31853],"type":"Point"}
}