{
  "type": "Feature",
  "properties": {
    "gn:admin1_code":"01",
    "gn:asciiname":"Horny Dacov Lom",
    "gn:country_code":"SK",
    "gn:dem":484,
    "gn:feature_class":"P",
    "gn:feature_code":"PPL",
    "gn:name":"Horn\u00fd Da\u010dov Lom",
    "gn:population":0,
    "gn:timezone":"Europe/Bratislava",
    "iso:country":"SK",
    "name:und_x_variant":[
        "Horn\u00ed Da\u010dov Lom",
        "Horn\u00fd Da\u010dov Lom"
    ],
    "wof:name":"Horny Dacov Lom",
    "wof:placetype":"locality"
},
  "geometry": {"coordinates":[19.25008,48.32259000000001],"type":"Point"}
}