{
  "type": "Feature",
  "properties": {
    "iso:country":"SK",
    "name:eng_x_preferred":[
        "Podhorske"
    ],
    "name:slk_x_preferred":[
        "Podhorsk\u00e9"
    ],
    "wof:name":"Podhorske",
    "wof:placetype":"neighbourhood"
},
  "geometry": {"coordinates":[16.97736016883841,48.20393798122324],"type":"Point"}
}