{
  "type": "Feature",
  "properties": {
    "gn:admin1_code":"03",
    "gn:asciiname":"Stretavka",
    "gn:country_code":"SK",
    "gn:dem":103,
    "gn:feature_class":"P",
    "gn:feature_code":"PPL",
    "gn:name":"Stretavka",
    "gn:population":0,
    "gn:timezone":"Europe/Bratislava",
    "iso:country":"SK",
    "name:cat_x_preferred":[
        "Stretavka"
    ],
    "name:ces_x_preferred":[
        "Stretavka"
    ],
    "name:epo_x_preferred":[
        "Stretavka"
    ],
    "name:eus_x_preferred":[
        "Stretavka"
    ],
    "name:fra_x_preferred":[
        "Stretavka"
    ],
    "name:hun_x_preferred":[
        "Kisszeretva"
    ],
    "name:ita_x_preferred":[
        "Stretavka"
    ],
    "name:msa_x_preferred":[
        "Stretavka"
    ],
    "name:nld_x_preferred":[
        "Stretavka"
    ],
    "name:pol_x_preferred":[
        "Stretavka"
    ],
    "name:ron_x_preferred":[
        "Stretavka"
    ],
    "name:slk_x_preferred":[
        "Stretavka"
    ],
    "name:spa_x_preferred":[
        "Stretavka"
    ],
    "name:srp_x_preferred":[
        "\u0421\u0442\u0440\u0435\u0442\u0430\u0432\u043a\u0430"
    ],
    "name:ukr_x_preferred":[
        "\u0421\u0442\u0440\u0435\u0442\u0430\u0432\u043a\u0430"
    ],
    "name:war_x_preferred":[
        "Stretavka"
    ],
    "wof:name":"Stretavka",
    "wof:placetype":"locality"
},
  "geometry": {"coordinates":[21.98718,48.6225],"type":"Point"}
}