{
  "type": "Feature",
  "properties": {
    "gn:admin1_code":"03",
    "gn:asciiname":"Stretavka",
    "gn:country_code":"SK",
    "gn:dem":103,
    "gn:feature_class":"P",
    "gn:feature_code":"PPL",
    "gn:name":"Stretavka",
    "gn:population":0,
    "gn:timezone":"Europe/Bratislava",
    "iso:country":"SK",
    "wof:name":"Stretavka",
    "wof:placetype":"locality"
},
  "geometry": {"coordinates":[21.98718,48.6225],"type":"Point"}
}