{
  "type": "Feature",
  "properties": {
    "gn:admin1_code":"05",
    "gn:asciiname":"Vydran",
    "gn:country_code":"SK",
    "gn:dem":362,
    "gn:feature_class":"P",
    "gn:feature_code":"PPL",
    "gn:name":"Vydra\u0148",
    "gn:population":0,
    "gn:timezone":"Europe/Bratislava",
    "iso:country":"SK",
    "wof:name":"Vydran",
    "wof:placetype":"locality"
},
  "geometry": {"coordinates":[21.93386,49.28931],"type":"Point"}
}