{
  "type": "Feature",
  "properties": {
    "gn:admin1_code":"03",
    "gn:asciiname":"Krasnovce",
    "gn:country_code":"SK",
    "gn:dem":109,
    "gn:feature_class":"P",
    "gn:feature_code":"PPL",
    "gn:name":"Kr\u00e1snovce",
    "gn:population":0,
    "gn:timezone":"Europe/Bratislava",
    "iso:country":"SK",
    "name:und_x_variant":[
        "Kr\u00e1snovce"
    ],
    "wof:name":"Krasnovce",
    "wof:placetype":"locality"
},
  "geometry": {"coordinates":[21.88415,48.72114000000001],"type":"Point"}
}