{
  "type": "Feature",
  "properties": {
    "gn:admin1_code":"03",
    "gn:asciiname":"Krasnovce",
    "gn:country_code":"SK",
    "gn:dem":109,
    "gn:feature_class":"P",
    "gn:feature_code":"PPL",
    "gn:name":"Kr\u00e1snovce",
    "gn:population":0,
    "gn:timezone":"Europe/Bratislava",
    "iso:country":"SK",
    "name:cat_x_preferred":[
        "Kr\u00e1snovce"
    ],
    "name:ces_x_preferred":[
        "Kr\u00e1snovce"
    ],
    "name:epo_x_preferred":[
        "Kr\u00e1snovce"
    ],
    "name:eus_x_preferred":[
        "Kr\u00e1snovce"
    ],
    "name:fra_x_preferred":[
        "Kr\u00e1snovce"
    ],
    "name:hun_x_preferred":[
        "Karaszna"
    ],
    "name:ita_x_preferred":[
        "Kr\u00e1snovce"
    ],
    "name:msa_x_preferred":[
        "Kr\u00e1snovce"
    ],
    "name:nld_x_preferred":[
        "Kr\u00e1snovce"
    ],
    "name:pol_x_preferred":[
        "Kr\u00e1snovce"
    ],
    "name:ron_x_preferred":[
        "Kr\u00e1snovce"
    ],
    "name:slk_x_preferred":[
        "Kr\u00e1snovce"
    ],
    "name:spa_x_preferred":[
        "Kr\u00e1snovce"
    ],
    "name:srp_x_preferred":[
        "\u041a\u0440\u0430\u0441\u043d\u043e\u0432\u0446\u0435"
    ],
    "name:ukr_x_preferred":[
        "\u041a\u0440\u0430\u0441\u043d\u043e\u0432\u0446\u0435"
    ],
    "name:und_x_variant":[
        "Kr\u00e1snovce"
    ],
    "name:war_x_preferred":[
        "Kr\u00e1snovce"
    ],
    "wof:name":"Krasnovce",
    "wof:placetype":"locality"
},
  "geometry": {"coordinates":[21.88415,48.72114000000001],"type":"Point"}
}