{
  "type": "Feature",
  "properties": {
    "iso:country":"SK",
    "name:eng_x_preferred":[
        "Emyhaza"
    ],
    "name:slk_x_preferred":[
        "Emyh\u00e1za"
    ],
    "name:slk_x_variant":[
        "Z\u00e1ti\u0161ie",
        "\u0160tvr\u0165 Emyh\u00e1za"
    ],
    "wof:name":"Emyhaza",
    "wof:placetype":"neighbourhood"
},
  "geometry": {"coordinates":[17.13442102917364,48.17341959128424],"type":"Point"}
}