{
  "type": "Feature",
  "properties": {
    "gn:admin1_code":"07",
    "gn:asciiname":"Mliecno",
    "gn:country_code":"SK",
    "gn:dem":123,
    "gn:feature_class":"P",
    "gn:feature_code":"PPL",
    "gn:name":"Mlie\u010dno",
    "gn:population":0,
    "gn:timezone":"Europe/Bratislava",
    "iso:country":"SK",
    "name:und_x_variant":[
        "Tejfalu",
        "Mlie\u010dno"
    ],
    "wof:name":"Mliecno",
    "wof:placetype":"locality"
},
  "geometry": {"coordinates":[17.33508,48.01786],"type":"Point"}
}