{
  "type": "Feature",
  "properties": {
    "gn:admin1_code":"04",
    "gn:asciiname":"Minarovci",
    "gn:country_code":"SK",
    "gn:dem":356,
    "gn:feature_class":"P",
    "gn:feature_code":"PPL",
    "gn:name":"Minarovci",
    "gn:population":0,
    "gn:timezone":"Europe/Bratislava",
    "iso:country":"SK",
    "wof:name":"Minarovci",
    "wof:placetype":"locality"
},
  "geometry": {"coordinates":[17.60326000000001,48.67336],"type":"Point"}
}