{
  "type": "Feature",
  "properties": {
    "gn:admin1_code":"01",
    "gn:asciiname":"Dobra",
    "gn:country_code":"SK",
    "gn:dem":208,
    "gn:feature_class":"P",
    "gn:feature_code":"PPL",
    "gn:name":"Dobr\u00e1",
    "gn:population":0,
    "gn:timezone":"Europe/Bratislava",
    "iso:country":"SK",
    "wof:name":"Dobra",
    "wof:placetype":"locality"
},
  "geometry": {"coordinates":[20.10123,48.32033],"type":"Point"}
}