{
  "type": "Feature",
  "properties": {
    "gn:admin1_code":"04",
    "gn:asciiname":"Krivoklat",
    "gn:country_code":"SK",
    "gn:dem":326,
    "gn:feature_class":"P",
    "gn:feature_code":"PPL",
    "gn:name":"Krivokl\u00e1t",
    "gn:population":0,
    "gn:timezone":"Europe/Bratislava",
    "iso:country":"SK",
    "name:und_x_variant":[
        "Krivokl\u00e1t"
    ],
    "wof:name":"Krivoklat",
    "wof:placetype":"locality"
},
  "geometry": {"coordinates":[18.16741,49.04492],"type":"Point"}
}