{
  "type": "Feature",
  "properties": {
    "gn:admin1_code":"04",
    "gn:asciiname":"Krivoklat",
    "gn:country_code":"SK",
    "gn:dem":326,
    "gn:feature_class":"P",
    "gn:feature_code":"PPL",
    "gn:name":"Krivokl\u00e1t",
    "gn:population":0,
    "gn:timezone":"Europe/Bratislava",
    "iso:country":"SK",
    "name:cat_x_preferred":[
        "Krivokl\u00e1t"
    ],
    "name:ces_x_preferred":[
        "Krivokl\u00e1t"
    ],
    "name:deu_x_preferred":[
        "Krivokl\u00e1t"
    ],
    "name:epo_x_preferred":[
        "Krivokl\u00e1t"
    ],
    "name:eus_x_preferred":[
        "Krivokl\u00e1t"
    ],
    "name:fra_x_preferred":[
        "Krivokl\u00e1t"
    ],
    "name:hun_x_preferred":[
        "Sz\u00e9ppatak"
    ],
    "name:ita_x_preferred":[
        "Krivokl\u00e1t"
    ],
    "name:msa_x_preferred":[
        "Krivokl\u00e1t"
    ],
    "name:nld_x_preferred":[
        "Krivokl\u00e1t"
    ],
    "name:ron_x_preferred":[
        "Krivokl\u00e1t"
    ],
    "name:slk_x_preferred":[
        "Krivokl\u00e1t"
    ],
    "name:spa_x_preferred":[
        "Krivokl\u00e1t"
    ],
    "name:srp_x_preferred":[
        "\u041a\u0440\u0438\u0432\u043e\u043a\u043b\u0430\u0442"
    ],
    "name:ukr_x_preferred":[
        "\u041a\u0440\u0438\u0432\u043e\u043a\u043b\u0430\u0442"
    ],
    "name:war_x_preferred":[
        "Krivokl\u00e1t"
    ],
    "wof:name":"Krivoklat",
    "wof:placetype":"locality"
},
  "geometry": {"coordinates":[18.16741,49.04492],"type":"Point"}
}