{
  "type": "Feature",
  "properties": {
    "gn:admin1_code":"04",
    "gn:asciiname":"Horna Polianka",
    "gn:country_code":"SK",
    "gn:dem":437,
    "gn:feature_class":"P",
    "gn:feature_code":"PPL",
    "gn:name":"Horn\u00e1 Polianka",
    "gn:population":0,
    "gn:timezone":"Europe/Bratislava",
    "iso:country":"SK",
    "wof:name":"Horna Polianka",
    "wof:placetype":"locality"
},
  "geometry": {"coordinates":[17.57973,48.72699],"type":"Point"}
}