{
  "type": "Feature",
  "properties": {
    "gn:admin1_code":"05",
    "gn:asciiname":"Tokajik",
    "gn:country_code":"SK",
    "gn:dem":221,
    "gn:feature_class":"P",
    "gn:feature_code":"PPL",
    "gn:name":"Tokaj\u00edk",
    "gn:population":0,
    "gn:timezone":"Europe/Bratislava",
    "iso:country":"SK",
    "name:cat_x_preferred":[
        "Tokaj\u00edk"
    ],
    "name:ces_x_preferred":[
        "Tokaj\u00edk"
    ],
    "name:deu_x_preferred":[
        "Tokaj\u00edk"
    ],
    "name:epo_x_preferred":[
        "Tokaj\u00edk"
    ],
    "name:eus_x_preferred":[
        "Tokaj\u00edk"
    ],
    "name:fra_x_preferred":[
        "Tokaj\u00edk"
    ],
    "name:hun_x_preferred":[
        "Fels\u0151tokaj"
    ],
    "name:ita_x_preferred":[
        "Tokaj\u00edk"
    ],
    "name:msa_x_preferred":[
        "Tokaj\u00edk"
    ],
    "name:nld_x_preferred":[
        "Tokaj\u00edk"
    ],
    "name:pol_x_preferred":[
        "Tokaj\u00edk"
    ],
    "name:ron_x_preferred":[
        "Tokaj\u00edk"
    ],
    "name:rue_x_preferred":[
        "\u0422\u043e\u043a\u0430\u0457\u043a"
    ],
    "name:slk_x_preferred":[
        "Tokaj\u00edk"
    ],
    "name:spa_x_preferred":[
        "Tokaj\u00edk"
    ],
    "name:srp_x_preferred":[
        "\u0422\u043e\u043a\u0430\u0458\u0438\u043a"
    ],
    "name:ukr_x_preferred":[
        "\u0422\u043e\u043a\u0430\u0457\u043a"
    ],
    "name:und_x_variant":[
        "Tokaj\u00edk"
    ],
    "name:war_x_preferred":[
        "Tokaj\u00edk"
    ],
    "wof:name":"Tokajik",
    "wof:placetype":"locality"
},
  "geometry": {"coordinates":[21.70802,49.10634],"type":"Point"}
}