{
  "type": "Feature",
  "properties": {
    "gn:admin1_code":"05",
    "gn:asciiname":"Tokajik",
    "gn:country_code":"SK",
    "gn:dem":221,
    "gn:feature_class":"P",
    "gn:feature_code":"PPL",
    "gn:name":"Tokaj\u00edk",
    "gn:population":0,
    "gn:timezone":"Europe/Bratislava",
    "iso:country":"SK",
    "name:und_x_variant":[
        "Tokaj\u00edk"
    ],
    "wof:name":"Tokajik",
    "wof:placetype":"locality"
},
  "geometry": {"coordinates":[21.70802,49.10634],"type":"Point"}
}