{
  "type": "Feature",
  "properties": {
    "gn:admin1_code":"07",
    "gn:asciiname":"Popudiny",
    "gn:country_code":"SK",
    "gn:dem":196,
    "gn:feature_class":"P",
    "gn:feature_code":"PPL",
    "gn:name":"Popudiny",
    "gn:population":0,
    "gn:timezone":"Europe/Bratislava",
    "iso:country":"SK",
    "wof:name":"Popudiny",
    "wof:placetype":"locality"
},
  "geometry": {"coordinates":[17.21842,48.78825],"type":"Point"}
}