{
  "type": "Feature",
  "properties": {
    "gn:admin1_code":"04",
    "gn:asciiname":"Kl'acno",
    "gn:country_code":"SK",
    "gn:dem":404,
    "gn:feature_class":"P",
    "gn:feature_code":"PPL",
    "gn:name":"K\u013ea\u010dno",
    "gn:population":0,
    "gn:timezone":"Europe/Bratislava",
    "iso:country":"SK",
    "name:cat_x_preferred":[
        "K\u013ea\u010dno"
    ],
    "name:ces_x_preferred":[
        "K\u013ea\u010dno"
    ],
    "name:deu_x_preferred":[
        "K\u013ea\u010dno"
    ],
    "name:epo_x_preferred":[
        "K\u013ea\u010dno"
    ],
    "name:eus_x_preferred":[
        "K\u013ea\u010dno"
    ],
    "name:fra_x_preferred":[
        "K\u013ea\u010dno"
    ],
    "name:hun_x_preferred":[
        "Nyitraf\u0151"
    ],
    "name:ita_x_preferred":[
        "K\u013ea\u010dno"
    ],
    "name:msa_x_preferred":[
        "K\u013ea\u010dno"
    ],
    "name:nld_x_preferred":[
        "K\u013ea\u010dno"
    ],
    "name:ron_x_preferred":[
        "K\u013ea\u010dno"
    ],
    "name:slk_x_preferred":[
        "K\u013ea\u010dno"
    ],
    "name:spa_x_preferred":[
        "K\u013ea\u010dno"
    ],
    "name:srp_x_preferred":[
        "\u041a\u0459\u0430\u0447\u043d\u043e"
    ],
    "name:und_x_variant":[
        "Gajdel"
    ],
    "name:war_x_preferred":[
        "K\u013ea\u010dno"
    ],
    "wof:name":"Kl'acno",
    "wof:placetype":"locality"
},
  "geometry": {"coordinates":[18.659,48.91582],"type":"Point"}
}