{
  "type": "Feature",
  "properties": {
    "gn:admin1_code":"04",
    "gn:asciiname":"Kl'acno",
    "gn:country_code":"SK",
    "gn:dem":404,
    "gn:feature_class":"P",
    "gn:feature_code":"PPL",
    "gn:name":"K\u013ea\u010dno",
    "gn:population":0,
    "gn:timezone":"Europe/Bratislava",
    "iso:country":"SK",
    "name:und_x_variant":[
        "Gajdel",
        "K\u013ea\u010dno"
    ],
    "wof:name":"Kl'acno",
    "wof:placetype":"locality"
},
  "geometry": {"coordinates":[18.659,48.91582],"type":"Point"}
}