{
  "type": "Feature",
  "properties": {
    "gn:admin1_code":"01",
    "gn:asciiname":"Podlavice",
    "gn:country_code":"SK",
    "gn:dem":393,
    "gn:feature_class":"P",
    "gn:feature_code":"PPL",
    "gn:name":"Podlavice",
    "gn:population":0,
    "gn:timezone":"Europe/Bratislava",
    "iso:country":"SK",
    "wof:name":"Podlavice",
    "wof:placetype":"locality"
},
  "geometry": {"coordinates":[19.10579,48.74203],"type":"Point"}
}