{
  "type": "Feature",
  "properties": {
    "gn:admin1_code":"01",
    "gn:asciiname":"Polom",
    "gn:country_code":"SK",
    "gn:dem":699,
    "gn:feature_class":"P",
    "gn:feature_code":"PPL",
    "gn:name":"Polom",
    "gn:population":0,
    "gn:timezone":"Europe/Bratislava",
    "iso:country":"SK",
    "wof:name":"Polom",
    "wof:placetype":"locality"
},
  "geometry": {"coordinates":[19.99144,48.60486],"type":"Point"}
}