{
  "type": "Feature",
  "properties": {
    "gn:admin1_code":"03",
    "gn:asciiname":"Hnojne",
    "gn:country_code":"SK",
    "gn:dem":106,
    "gn:feature_class":"P",
    "gn:feature_code":"PPL",
    "gn:name":"Hnojn\u00e9",
    "gn:population":0,
    "gn:timezone":"Europe/Bratislava",
    "iso:country":"SK",
    "name:und_x_variant":[
        "Hnojn\u00e9"
    ],
    "wof:name":"Hnojne",
    "wof:placetype":"locality"
},
  "geometry": {"coordinates":[22.06913,48.77843],"type":"Point"}
}