{
  "type": "Feature",
  "properties": {
    "gn:gn_country":"SK",
    "gn:gn_fcode":"PPL",
    "gn:gn_pop":0,
    "iso:country":"SK",
    "name:cat_x_preferred":[
        "\u0160pania Dolina"
    ],
    "name:cze_x_preferred":[
        "\u0160pania Dolina"
    ],
    "name:dut_x_preferred":[
        "\u0160pania Dolina"
    ],
    "name:eng_x_preferred":[
        "\u0160pania Dolina"
    ],
    "name:epo_x_preferred":[
        "\u0160pania Dolina"
    ],
    "name:fre_x_preferred":[
        "\u0160pania Dolina"
    ],
    "name:ger_x_preferred":[
        "\u0160pania Dolina"
    ],
    "name:hun_x_preferred":[
        "\u00darv\u00f6lgy"
    ],
    "name:ita_x_preferred":[
        "\u0160pania Dolina"
    ],
    "name:jpn_x_preferred":[
        "\u30b9\u30d1\u30cb\u30a2\u30fb\u30c9\u30ea\u30ca"
    ],
    "name:may_x_preferred":[
        "\u0160pania Dolina"
    ],
    "name:nan_x_preferred":[
        "\u0160pania Dolina"
    ],
    "name:pol_x_preferred":[
        "\u0160pania Dolina"
    ],
    "name:rus_x_preferred":[
        "\u0428\u043f\u0430\u043d\u044c\u044f-\u0414\u043e\u043b\u0438\u043d\u0430"
    ],
    "name:slo_x_preferred":[
        "\u0160pania Dolina"
    ],
    "name:srp_x_preferred":[
        "\u0428\u043f\u0430\u045a\u0430 \u0414\u043e\u043b\u0438\u043d\u0430"
    ],
    "name:ukr_x_preferred":[
        "\u0428\u043f\u0430\u043d\u044c\u044f \u0414\u043e\u043b\u0456\u043d\u0430"
    ],
    "name:war_x_preferred":[
        "\u0160pania Dolina"
    ],
    "qs_pg:aaroncc":"SK",
    "qs_pg:gn_country":"SK",
    "qs_pg:gn_fcode":"PPL",
    "qs_pg:gn_pop":0,
    "qs_pg:name":"\u00c5 pania Dolina",
    "qs_pg:name_adm0":"Slovensk\u00e1",
    "qs_pg:name_adm1":"Banskobystricky",
    "qs_pg:photos":45,
    "qs_pg:photos_1k":9,
    "qs_pg:photos_9k":1,
    "qs_pg:photos_9r":2,
    "qs_pg:photos_all":45,
    "qs_pg:photos_sr":2,
    "qs_pg:pop_sr":0,
    "qs_pg:qs_pg_placetype":"locality",
    "qs_pg:qs_pg_placetype_gp":"Town",
    "qs_pg:woe_adm0":23424877,
    "woe:adm0_id":23424877,
    "woe:name_adm0":"Slovensk\u00e1",
    "woe:name_adm1":"Banskobystricky",
    "woe:placetype":"Town",
    "wof:name":"\u00c5 pania Dolina",
    "wof:placetype":"locality"
},
  "geometry": {"coordinates":[19.13406,48.80754],"type":"Point"}
}