{
  "type": "Feature",
  "properties": {
    "gn:admin1_code":"01",
    "gn:asciiname":"Horna Turecka",
    "gn:country_code":"SK",
    "gn:dem":642,
    "gn:feature_class":"P",
    "gn:feature_code":"PPL",
    "gn:name":"Horn\u00e1 Tureck\u00e1",
    "gn:population":0,
    "gn:timezone":"Europe/Bratislava",
    "iso:country":"SK",
    "wof:name":"Horna Turecka",
    "wof:placetype":"locality"
},
  "geometry": {"coordinates":[19.08333,48.85],"type":"Point"}
}