{
  "type": "Feature",
  "properties": {
    "gn:asciiname":"Pavlova Ves",
    "gn:country_code":"SK",
    "gn:dem":621,
    "gn:feature_class":"P",
    "gn:feature_code":"PPL",
    "gn:name":"Pavlova Ves",
    "gn:population":0,
    "gn:timezone":"Europe/Bratislava",
    "iso:country":"SK",
    "name:cat_x_preferred":[
        "Pavlova Ves"
    ],
    "name:ces_x_preferred":[
        "Pavlova Ves"
    ],
    "name:epo_x_preferred":[
        "Pavlova Ves"
    ],
    "name:eus_x_preferred":[
        "Pavlova Ves"
    ],
    "name:fra_x_preferred":[
        "Pavlova Ves"
    ],
    "name:hun_x_preferred":[
        "P\u00e1lfalu"
    ],
    "name:ita_x_preferred":[
        "Pavlova Ves"
    ],
    "name:msa_x_preferred":[
        "Pavlova Ves"
    ],
    "name:nld_x_preferred":[
        "Pavlova Ves"
    ],
    "name:pol_x_preferred":[
        "Pavlova Ves"
    ],
    "name:ron_x_preferred":[
        "Pavlova Ves"
    ],
    "name:slk_x_preferred":[
        "Pavlova Ves"
    ],
    "name:spa_x_preferred":[
        "Pavlova Ves"
    ],
    "name:srp_x_preferred":[
        "\u041f\u0430\u0432\u043b\u043e\u0432\u0430 \u0412\u0435\u0441"
    ],
    "name:war_x_preferred":[
        "Pavlova Ves"
    ],
    "wof:name":"Pavlova Ves",
    "wof:placetype":"locality"
},
  "geometry": {"coordinates":[19.58416,49.12927],"type":"Point"}
}