{
  "type": "Feature",
  "properties": {
    "gn:asciiname":"Pavlova Ves",
    "gn:country_code":"SK",
    "gn:dem":621,
    "gn:feature_class":"P",
    "gn:feature_code":"PPL",
    "gn:name":"Pavlova Ves",
    "gn:population":0,
    "gn:timezone":"Europe/Bratislava",
    "iso:country":"SK",
    "wof:name":"Pavlova Ves",
    "wof:placetype":"locality"
},
  "geometry": {"coordinates":[19.58416,49.12927],"type":"Point"}
}