{
  "type": "Feature",
  "properties": {
    "gn:admin1_code":"04",
    "gn:asciiname":"Nemecky",
    "gn:country_code":"SK",
    "gn:dem":270,
    "gn:feature_class":"P",
    "gn:feature_code":"PPL",
    "gn:name":"Neme\u010dky",
    "gn:population":0,
    "gn:timezone":"Europe/Bratislava",
    "iso:country":"SK",
    "name:und_x_variant":[
        "Neme\u010dky"
    ],
    "wof:name":"Nemecky",
    "wof:placetype":"locality"
},
  "geometry": {"coordinates":[18.11724,48.67287],"type":"Point"}
}