{
  "type": "Feature",
  "properties": {
    "gn:admin1_code":"01",
    "gn:asciiname":"Strelniky",
    "gn:country_code":"SK",
    "gn:dem":648,
    "gn:feature_class":"P",
    "gn:feature_code":"PPL",
    "gn:name":"Streln\u00edky",
    "gn:population":0,
    "gn:timezone":"Europe/Bratislava",
    "iso:country":"SK",
    "name:cat_x_preferred":[
        "Streln\u00edky"
    ],
    "name:deu_x_preferred":[
        "Streln\u00edky"
    ],
    "name:epo_x_preferred":[
        "Streln\u00edky"
    ],
    "name:eus_x_preferred":[
        "Streln\u00edky"
    ],
    "name:fra_x_preferred":[
        "Streln\u00edky"
    ],
    "name:hun_x_preferred":[
        "Seb\u0151"
    ],
    "name:ita_x_preferred":[
        "Streln\u00edky"
    ],
    "name:msa_x_preferred":[
        "Streln\u00edky"
    ],
    "name:nld_x_preferred":[
        "Streln\u00edky"
    ],
    "name:pol_x_preferred":[
        "Streln\u00edky"
    ],
    "name:ron_x_preferred":[
        "Streln\u00edky"
    ],
    "name:slk_x_preferred":[
        "Streln\u00edky"
    ],
    "name:spa_x_preferred":[
        "Streln\u00edky"
    ],
    "name:srp_x_preferred":[
        "\u0421\u0442\u0440\u0435\u043b\u045a\u0438\u043a\u0438"
    ],
    "name:ukr_x_preferred":[
        "\u0421\u0442\u0440\u0435\u043b\u044c\u043d\u0456\u043a\u0438"
    ],
    "name:und_x_variant":[
        "\u0160ajba",
        "Streln\u00edky"
    ],
    "name:war_x_preferred":[
        "Streln\u00edky"
    ],
    "wof:name":"Strelniky",
    "wof:placetype":"locality"
},
  "geometry": {"coordinates":[19.39223,48.72293],"type":"Point"}
}