{
  "type": "Feature",
  "properties": {
    "gn:admin1_code":"06",
    "gn:asciiname":"Cerveny Kamen",
    "gn:country_code":"SK",
    "gn:dem":377,
    "gn:feature_class":"P",
    "gn:feature_code":"PPL",
    "gn:name":"\u010cerven\u00fd Kame\u0148",
    "gn:population":0,
    "gn:timezone":"Europe/Bratislava",
    "iso:country":"SK",
    "name:cat_x_preferred":[
        "\u010cerven\u00fd Kame\u0148"
    ],
    "name:ces_x_preferred":[
        "\u010cerven\u00fd Kame\u0148"
    ],
    "name:deu_x_preferred":[
        "\u010cerven\u00fd Kame\u0148"
    ],
    "name:epo_x_preferred":[
        "\u010cerven\u00fd Kame\u0148"
    ],
    "name:eus_x_preferred":[
        "\u010cerven\u00fd Kame\u0148"
    ],
    "name:fra_x_preferred":[
        "\u010cerven\u00fd Kame\u0148"
    ],
    "name:hun_x_preferred":[
        "V\u00f6r\u00f6sk\u0151"
    ],
    "name:ita_x_preferred":[
        "\u010cerven\u00fd Kame\u0148"
    ],
    "name:msa_x_preferred":[
        "\u010cerven\u00fd Kame\u0148"
    ],
    "name:nld_x_preferred":[
        "\u010cerven\u00fd Kame\u0148"
    ],
    "name:pol_x_preferred":[
        "\u010cerven\u00fd Kame\u0148"
    ],
    "name:ron_x_preferred":[
        "\u010cerven\u00fd Kame\u0148"
    ],
    "name:slk_x_preferred":[
        "\u010cerven\u00fd Kame\u0148"
    ],
    "name:spa_x_preferred":[
        "\u010cerven\u00fd Kame\u0148"
    ],
    "name:srp_x_preferred":[
        "\u0427\u0435\u0440\u0432\u0435\u043d\u0438 \u041a\u0430\u043c\u0435\u045a"
    ],
    "name:ukr_x_preferred":[
        "\u0427\u0435\u0440\u0432\u0435\u043d\u0438 \u041a\u0430\u043c\u0435\u043d\u044c"
    ],
    "name:und_x_variant":[
        "V\u00f6r\u00f6k\u00f6"
    ],
    "name:war_x_preferred":[
        "\u010cerven\u00fd Kame\u0148"
    ],
    "wof:name":"Cerveny Kamen",
    "wof:placetype":"locality"
},
  "geometry": {"coordinates":[18.17738,49.09027],"type":"Point"}
}