{
  "type": "Feature",
  "properties": {
    "gn:admin1_code":"06",
    "gn:asciiname":"Cerveny Kamen",
    "gn:country_code":"SK",
    "gn:dem":377,
    "gn:feature_class":"P",
    "gn:feature_code":"PPL",
    "gn:name":"\u010cerven\u00fd Kame\u0148",
    "gn:population":0,
    "gn:timezone":"Europe/Bratislava",
    "iso:country":"SK",
    "name:und_x_variant":[
        "V\u00f6r\u00f6k\u00f6",
        "\u010cerven\u00fd Kame\u0148"
    ],
    "wof:name":"Cerveny Kamen",
    "wof:placetype":"locality"
},
  "geometry": {"coordinates":[18.17738,49.09027],"type":"Point"}
}