{
  "type": "Feature",
  "properties": {
    "gn:admin1_code":"01",
    "gn:asciiname":"Lieskovec",
    "gn:country_code":"SK",
    "gn:dem":305,
    "gn:feature_class":"P",
    "gn:feature_code":"PPL",
    "gn:name":"Lieskovec",
    "gn:population":0,
    "gn:timezone":"Europe/Bratislava",
    "iso:country":"SK",
    "name:cat_x_preferred":[
        "Lieskovec"
    ],
    "name:ces_x_preferred":[
        "Lieskovec"
    ],
    "name:deu_x_preferred":[
        "Lieskovec"
    ],
    "name:epo_x_preferred":[
        "Lieskovec"
    ],
    "name:eus_x_preferred":[
        "Lieskovec"
    ],
    "name:hun_x_preferred":[
        "\u00dajmogyor\u00f3d"
    ],
    "name:ita_x_preferred":[
        "Lieskovec"
    ],
    "name:msa_x_preferred":[
        "Lieskovec"
    ],
    "name:nld_x_preferred":[
        "Lieskovec"
    ],
    "name:pol_x_preferred":[
        "Lieskovec"
    ],
    "name:ron_x_preferred":[
        "Lieskovec"
    ],
    "name:slk_x_preferred":[
        "Lieskovec"
    ],
    "name:spa_x_preferred":[
        "Lieskovec"
    ],
    "name:srp_x_preferred":[
        "\u0409\u0435\u0441\u043a\u043e\u0432\u0435\u0446"
    ],
    "name:ukr_x_preferred":[
        "\u041b\u0454\u0441\u043a\u043e\u0432\u0435\u0446"
    ],
    "name:war_x_preferred":[
        "Lieskovec"
    ],
    "wof:name":"Lieskovec",
    "wof:placetype":"locality"
},
  "geometry": {"coordinates":[19.19249,48.57291],"type":"Point"}
}