{
  "type": "Feature",
  "properties": {
    "gn:admin1_code":"01",
    "gn:asciiname":"Lieskovec",
    "gn:country_code":"SK",
    "gn:dem":305,
    "gn:feature_class":"P",
    "gn:feature_code":"PPL",
    "gn:name":"Lieskovec",
    "gn:population":0,
    "gn:timezone":"Europe/Bratislava",
    "iso:country":"SK",
    "wof:name":"Lieskovec",
    "wof:placetype":"locality"
},
  "geometry": {"coordinates":[19.19249,48.57291],"type":"Point"}
}