{
  "type": "Feature",
  "properties": {
    "gn:admin1_code":"01",
    "gn:asciiname":"Gemercek",
    "gn:country_code":"SK",
    "gn:dem":245,
    "gn:feature_class":"P",
    "gn:feature_code":"PPL",
    "gn:name":"Gemer\u010dek",
    "gn:population":0,
    "gn:timezone":"Europe/Bratislava",
    "iso:country":"SK",
    "name:cat_x_preferred":[
        "Gemer\u010dek"
    ],
    "name:ces_x_preferred":[
        "Gemer\u010dek"
    ],
    "name:epo_x_preferred":[
        "Gemer\u010dek"
    ],
    "name:eus_x_preferred":[
        "Gemer\u010dek"
    ],
    "name:fra_x_preferred":[
        "Gemer\u010dek"
    ],
    "name:hun_x_preferred":[
        "Kisg\u00f6m\u00f6ri"
    ],
    "name:ita_x_preferred":[
        "Gemer\u010dek"
    ],
    "name:msa_x_preferred":[
        "Gemer\u010dek"
    ],
    "name:nld_x_preferred":[
        "Gemer\u010dek"
    ],
    "name:pol_x_preferred":[
        "Gemer\u010dek"
    ],
    "name:ron_x_preferred":[
        "Gemer\u010dek"
    ],
    "name:slk_x_preferred":[
        "Gemer\u010dek"
    ],
    "name:spa_x_preferred":[
        "Gemer\u010dek"
    ],
    "name:srp_x_preferred":[
        "\u0413\u0435\u043c\u0435\u0440\u0447\u0435\u043a"
    ],
    "name:ukr_x_preferred":[
        "\u0413\u0435\u043c\u0435\u0440\u0447\u0435\u043a"
    ],
    "name:und_x_variant":[
        "Kis-G\u00f6m\u00f6ri",
        "Gemer\u010dek"
    ],
    "name:war_x_preferred":[
        "Gemer\u010dek"
    ],
    "wof:name":"Gemercek",
    "wof:placetype":"locality"
},
  "geometry": {"coordinates":[19.99142,48.31788],"type":"Point"}
}