{
  "type": "Feature",
  "properties": {
    "gn:admin1_code":"01",
    "gn:asciiname":"Gemercek",
    "gn:country_code":"SK",
    "gn:dem":245,
    "gn:feature_class":"P",
    "gn:feature_code":"PPL",
    "gn:name":"Gemer\u010dek",
    "gn:population":0,
    "gn:timezone":"Europe/Bratislava",
    "iso:country":"SK",
    "name:und_x_variant":[
        "Kis-G\u00f6m\u00f6ri",
        "Gemer\u010dek"
    ],
    "wof:name":"Gemercek",
    "wof:placetype":"locality"
},
  "geometry": {"coordinates":[19.99142,48.31788],"type":"Point"}
}