{
  "type": "Feature",
  "properties": {
    "gn:admin1_code":"04",
    "gn:asciiname":"Kl'ucove",
    "gn:country_code":"SK",
    "gn:dem":221,
    "gn:feature_class":"P",
    "gn:feature_code":"PPL",
    "gn:name":"K\u013e\u00fa\u010dov\u00e9",
    "gn:population":0,
    "gn:timezone":"Europe/Bratislava",
    "iso:country":"SK",
    "wof:name":"Kl'ucove",
    "wof:placetype":"locality"
},
  "geometry": {"coordinates":[18.09205,48.94699],"type":"Point"}
}