{
  "type": "Feature",
  "properties": {
    "gn:admin1_code":"05",
    "gn:asciiname":"Petrovenec",
    "gn:country_code":"SK",
    "gn:dem":408,
    "gn:feature_class":"P",
    "gn:feature_code":"PPL",
    "gn:name":"Petrovenec",
    "gn:population":0,
    "gn:timezone":"Europe/Bratislava",
    "iso:country":"SK",
    "wof:name":"Petrovenec",
    "wof:placetype":"locality"
},
  "geometry": {"coordinates":[20.98333,49.15],"type":"Point"}
}