{
  "type": "Feature",
  "properties": {
    "gn:admin1_code":"08",
    "gn:asciiname":"Liesno",
    "gn:country_code":"SK",
    "gn:dem":471,
    "gn:feature_class":"P",
    "gn:feature_code":"PPL",
    "gn:name":"Lie\u0161no",
    "gn:population":0,
    "gn:timezone":"Europe/Bratislava",
    "iso:country":"SK",
    "name:cat_x_preferred":[
        "Lie\u0161no"
    ],
    "name:ces_x_preferred":[
        "Lie\u0161no"
    ],
    "name:epo_x_preferred":[
        "Lie\u0161no"
    ],
    "name:eus_x_preferred":[
        "Lie\u0161no"
    ],
    "name:fra_x_preferred":[
        "Lie\u0161no"
    ],
    "name:hun_x_preferred":[
        "Tur\u00f3cerd\u0151d"
    ],
    "name:ita_x_preferred":[
        "Lie\u0161no"
    ],
    "name:msa_x_preferred":[
        "Lie\u0161no"
    ],
    "name:nld_x_preferred":[
        "Lie\u0161no"
    ],
    "name:pol_x_preferred":[
        "Lie\u0161no"
    ],
    "name:ron_x_preferred":[
        "Lie\u0161no"
    ],
    "name:slk_x_preferred":[
        "Lie\u0161no"
    ],
    "name:spa_x_preferred":[
        "Lie\u0161no"
    ],
    "name:srp_x_preferred":[
        "\u0409\u0435\u0448\u043d\u043e"
    ],
    "name:und_x_variant":[
        "Lie\u0161n\u00e9",
        "Lie\u0161no"
    ],
    "name:war_x_preferred":[
        "Lie\u0161no"
    ],
    "wof:name":"Liesno",
    "wof:placetype":"locality"
},
  "geometry": {"coordinates":[18.76431,48.88835],"type":"Point"}
}