{
  "type": "Feature",
  "properties": {
    "gn:admin1_code":"08",
    "gn:asciiname":"Liesno",
    "gn:country_code":"SK",
    "gn:dem":471,
    "gn:feature_class":"P",
    "gn:feature_code":"PPL",
    "gn:name":"Lie\u0161no",
    "gn:population":0,
    "gn:timezone":"Europe/Bratislava",
    "iso:country":"SK",
    "name:und_x_variant":[
        "Lie\u0161n\u00e9",
        "Lie\u0161no"
    ],
    "wof:name":"Liesno",
    "wof:placetype":"locality"
},
  "geometry": {"coordinates":[18.76431,48.88835],"type":"Point"}
}