{
  "type": "Feature",
  "properties": {
    "gn:gn_country":"SK",
    "gn:gn_fcode":"PPL",
    "gn:gn_pop":0,
    "iso:country":"SK",
    "name:cat_x_preferred":[
        "Pernek"
    ],
    "name:cze_x_preferred":[
        "Pernek"
    ],
    "name:dut_x_preferred":[
        "Pernek"
    ],
    "name:eng_x_preferred":[
        "Pernek"
    ],
    "name:epo_x_preferred":[
        "Pernek"
    ],
    "name:fre_x_preferred":[
        "Pernek"
    ],
    "name:ger_x_preferred":[
        "Pernek"
    ],
    "name:hun_x_preferred":[
        "Pernyek"
    ],
    "name:ita_x_preferred":[
        "Pernek"
    ],
    "name:may_x_preferred":[
        "Pernek"
    ],
    "name:por_x_preferred":[
        "Pernek"
    ],
    "name:slo_x_preferred":[
        "Pernek"
    ],
    "name:srp_x_preferred":[
        "\u041f\u0435\u0440\u045a\u0435\u043a"
    ],
    "name:war_x_preferred":[
        "Pernek"
    ],
    "qs_pg:aaroncc":"SK",
    "qs_pg:gn_country":"SK",
    "qs_pg:gn_fcode":"PPL",
    "qs_pg:gn_pop":0,
    "qs_pg:name":"Pernek",
    "qs_pg:name_adm0":"Slovensk\u00e1",
    "qs_pg:name_adm1":"Bratislavsky",
    "qs_pg:photos_9k":1,
    "qs_pg:photos_9r":1,
    "qs_pg:photos_all":1,
    "qs_pg:photos_sr":0,
    "qs_pg:pop_sr":0,
    "qs_pg:qs_pg_placetype":"locality",
    "qs_pg:qs_pg_placetype_gp":"Town",
    "qs_pg:woe_adm0":23424877,
    "woe:adm0_id":23424877,
    "woe:name_adm0":"Slovensk\u00e1",
    "woe:name_adm1":"Bratislavsky",
    "woe:placetype":"Town",
    "wof:name":"Pernek",
    "wof:placetype":"locality"
},
  "geometry": {"coordinates":[17.14416,48.36689],"type":"Point"}
}