{
  "type": "Feature",
  "properties": {
    "gn:admin1_code":"07",
    "gn:asciiname":"Male Brestovany",
    "gn:country_code":"SK",
    "gn:dem":152,
    "gn:feature_class":"P",
    "gn:feature_code":"PPL",
    "gn:name":"Mal\u00e9 Brestovany",
    "gn:population":0,
    "gn:timezone":"Europe/Bratislava",
    "iso:country":"SK",
    "name:und_x_variant":[
        "Mal\u00e9 Brestovany"
    ],
    "wof:name":"Male Brestovany",
    "wof:placetype":"locality"
},
  "geometry": {"coordinates":[17.68332999999999,48.38333],"type":"Point"}
}