{
  "type": "Feature",
  "properties": {
    "gn:admin1_code":"01",
    "gn:asciiname":"Tisovnik",
    "gn:country_code":"SK",
    "gn:dem":705,
    "gn:feature_class":"P",
    "gn:feature_code":"PPL",
    "gn:name":"Tisovn\u00edk",
    "gn:population":0,
    "gn:timezone":"Europe/Bratislava",
    "iso:country":"SK",
    "wof:name":"Tisovnik",
    "wof:placetype":"locality"
},
  "geometry": {"coordinates":[19.58333,48.51667],"type":"Point"}
}