{
  "type": "Feature",
  "properties": {
    "gn:admin1_code":"05",
    "gn:asciiname":"Hrabske",
    "gn:country_code":"SK",
    "gn:dem":466,
    "gn:feature_class":"P",
    "gn:feature_code":"PPL",
    "gn:name":"Hrabsk\u011b",
    "gn:population":0,
    "gn:timezone":"Europe/Bratislava",
    "iso:country":"SK",
    "name:und_x_variant":[
        "Hrabsk\u011b"
    ],
    "wof:name":"Hrabske",
    "wof:placetype":"locality"
},
  "geometry": {"coordinates":[21.07265,49.34028],"type":"Point"}
}