{
  "type": "Feature",
  "properties": {
    "gn:admin1_code":"05",
    "gn:asciiname":"Hrabske",
    "gn:country_code":"SK",
    "gn:dem":466,
    "gn:feature_class":"P",
    "gn:feature_code":"PPL",
    "gn:name":"Hrabsk\u011b",
    "gn:population":0,
    "gn:timezone":"Europe/Bratislava",
    "iso:country":"SK",
    "name:cat_x_preferred":[
        "Hrabsk\u00e9"
    ],
    "name:ces_x_preferred":[
        "Hrabsk\u00e9"
    ],
    "name:deu_x_preferred":[
        "Hrabsk\u00e9"
    ],
    "name:epo_x_preferred":[
        "Hrabsk\u00e9"
    ],
    "name:eus_x_preferred":[
        "Hrabsk\u00e9"
    ],
    "name:fra_x_preferred":[
        "Hrabsk\u00e9"
    ],
    "name:hun_x_preferred":[
        "Ger\u00e9b"
    ],
    "name:ita_x_preferred":[
        "Hrabsk\u00e9"
    ],
    "name:msa_x_preferred":[
        "Hrabsk\u00e9"
    ],
    "name:nld_x_preferred":[
        "Hrabsk\u00e9"
    ],
    "name:pol_x_preferred":[
        "Hrabsk\u00e9"
    ],
    "name:ron_x_preferred":[
        "Hrabsk\u00e9"
    ],
    "name:rue_x_preferred":[
        "\u0413\u0440\u0430\u0431\u0441\u043a\u0435"
    ],
    "name:slk_x_preferred":[
        "Hrabsk\u00e9"
    ],
    "name:spa_x_preferred":[
        "Hrabsk\u00e9"
    ],
    "name:srp_x_preferred":[
        "\u0425\u0440\u0430\u0431\u0441\u043a\u0435"
    ],
    "name:ukr_x_preferred":[
        "\u0413\u0440\u0430\u0431\u0441\u044c\u043a\u0435"
    ],
    "name:und_x_variant":[
        "Hrabsk\u011b"
    ],
    "name:war_x_preferred":[
        "Hrabsk\u00e9"
    ],
    "wof:name":"Hrabske",
    "wof:placetype":"locality"
},
  "geometry": {"coordinates":[21.07265,49.34028],"type":"Point"}
}