{
  "type": "Feature",
  "properties": {
    "gn:admin1_code":"05",
    "gn:asciiname":"Pritul'any",
    "gn:country_code":"SK",
    "gn:dem":231,
    "gn:feature_class":"P",
    "gn:feature_code":"PPL",
    "gn:name":"Pritu\u013eany",
    "gn:population":0,
    "gn:timezone":"Europe/Bratislava",
    "iso:country":"SK",
    "name:cat_x_preferred":[
        "Pritu\u013eany"
    ],
    "name:ces_x_preferred":[
        "Pritu\u013eany"
    ],
    "name:epo_x_preferred":[
        "Pritu\u013eany"
    ],
    "name:eus_x_preferred":[
        "Pritu\u013eany"
    ],
    "name:fra_x_preferred":[
        "Pritu\u013eany"
    ],
    "name:hun_x_preferred":[
        "Hegyv\u00e9g"
    ],
    "name:ita_x_preferred":[
        "Pritu\u013eany"
    ],
    "name:msa_x_preferred":[
        "Pritu\u013eany"
    ],
    "name:nld_x_preferred":[
        "Pritu\u013eany"
    ],
    "name:pol_x_preferred":[
        "Pritu\u013eany"
    ],
    "name:ron_x_preferred":[
        "Pritu\u013eany"
    ],
    "name:rue_x_preferred":[
        "\u041f\u0440\u0438\u0442\u0443\u043b\u044f\u043d\u044b"
    ],
    "name:slk_x_preferred":[
        "Pritu\u013eany"
    ],
    "name:spa_x_preferred":[
        "Pritu\u013eany"
    ],
    "name:srp_x_preferred":[
        "\u041f\u0440\u0438\u0442\u0443\u0459\u0430\u043d\u0438"
    ],
    "name:ukr_x_preferred":[
        "\u041f\u0440\u0438\u0442\u0443\u043b\u044f\u043d\u0438"
    ],
    "name:war_x_preferred":[
        "Pritu\u013eany"
    ],
    "wof:name":"Pritul'any",
    "wof:placetype":"locality"
},
  "geometry": {"coordinates":[21.77432,49.12973],"type":"Point"}
}