{
  "type": "Feature",
  "properties": {
    "gn:admin1_code":"05",
    "gn:asciiname":"Pritul'any",
    "gn:country_code":"SK",
    "gn:dem":231,
    "gn:feature_class":"P",
    "gn:feature_code":"PPL",
    "gn:name":"Pritu\u013eany",
    "gn:population":0,
    "gn:timezone":"Europe/Bratislava",
    "iso:country":"SK",
    "name:und_x_variant":[
        "Pritu\u013eany"
    ],
    "wof:name":"Pritul'any",
    "wof:placetype":"locality"
},
  "geometry": {"coordinates":[21.77432,49.12973],"type":"Point"}
}