{
  "type": "Feature",
  "properties": {
    "gn:gn_country":"SK",
    "gn:gn_fcode":"PPL",
    "gn:gn_pop":0,
    "iso:country":"SK",
    "name:cat_x_preferred":[
        "Turie"
    ],
    "name:ces_x_preferred":[
        "Turie"
    ],
    "name:deu_x_preferred":[
        "Turie"
    ],
    "name:epo_x_preferred":[
        "Turie"
    ],
    "name:eus_x_preferred":[
        "Turie"
    ],
    "name:fra_x_preferred":[
        "Turie"
    ],
    "name:hun_x_preferred":[
        "H\u00e1romudvar"
    ],
    "name:ita_x_preferred":[
        "Turie"
    ],
    "name:msa_x_preferred":[
        "Turie"
    ],
    "name:nld_x_preferred":[
        "Turie"
    ],
    "name:pol_x_preferred":[
        "Turie"
    ],
    "name:ron_x_preferred":[
        "Turie"
    ],
    "name:slk_x_preferred":[
        "Turie"
    ],
    "name:spa_x_preferred":[
        "Turie"
    ],
    "name:srp_x_preferred":[
        "\u0422\u0443\u0440\u0458\u0435"
    ],
    "name:unk_x_variant":[
        "Turo"
    ],
    "name:war_x_preferred":[
        "Turie"
    ],
    "qs_pg:aaroncc":"SK",
    "qs_pg:gn_country":"SK",
    "qs_pg:gn_fcode":"PPL",
    "qs_pg:gn_pop":0,
    "qs_pg:name":"Turie",
    "qs_pg:name_adm0":"Slovensk\u00e1",
    "qs_pg:name_adm1":"Zilinsky",
    "qs_pg:photos_9r":0,
    "qs_pg:photos_sr":0,
    "qs_pg:pop_sr":0,
    "qs_pg:qs_pg_placetype":"localadmin",
    "qs_pg:qs_pg_placetype_gp":"LocalAdmin",
    "qs_pg:woe_adm0":23424877,
    "woe:adm0_id":23424877,
    "woe:name_adm0":"Slovensk\u00e1",
    "woe:name_adm1":"Zilinsky",
    "woe:placetype":"LocalAdmin",
    "wof:name":"Turie",
    "wof:placetype":"localadmin"
},
  "geometry": {"coordinates":[18.74983,49.14907],"type":"Point"}
}