{
  "type": "Feature",
  "properties": {
    "gn:admin1_code":"07",
    "gn:asciiname":"Vojka nad Dunajom",
    "gn:country_code":"SK",
    "gn:dem":119,
    "gn:feature_class":"P",
    "gn:feature_code":"PPL",
    "gn:name":"Vojka nad Dunajom",
    "gn:population":0,
    "gn:timezone":"Europe/Bratislava",
    "iso:country":"SK",
    "name:cat_x_preferred":[
        "Vojka nad Dunajom"
    ],
    "name:deu_x_preferred":[
        "Vojka nad Dunajom"
    ],
    "name:epo_x_preferred":[
        "Vojka nad Dunajom"
    ],
    "name:eus_x_preferred":[
        "Vojka nad Dunajom"
    ],
    "name:fra_x_preferred":[
        "Vojka nad Dunajom"
    ],
    "name:hun_x_preferred":[
        "Vajka"
    ],
    "name:ita_x_preferred":[
        "Vojka nad Dunajom"
    ],
    "name:msa_x_preferred":[
        "Vojka nad Dunajom"
    ],
    "name:nld_x_preferred":[
        "Vojka nad Dunajom"
    ],
    "name:por_x_preferred":[
        "Vojka nad Dunajom"
    ],
    "name:ron_x_preferred":[
        "Vojka nad Dunajom"
    ],
    "name:slk_x_preferred":[
        "Vojka nad Dunajom"
    ],
    "name:spa_x_preferred":[
        "Vojka nad Dunajom"
    ],
    "name:srp_x_preferred":[
        "\u0412\u043e\u0458\u043a\u0430 \u043d\u0430 \u0414\u0443\u043d\u0430\u0432\u0443"
    ],
    "name:ukr_x_preferred":[
        "\u0412\u043e\u0439\u043a\u0430-\u043d\u0430\u0434-\u0414\u0443\u043d\u0430\u0454\u043c"
    ],
    "name:und_x_variant":[
        "Duna-Vajka",
        "Vajka nad Dunajom"
    ],
    "name:war_x_preferred":[
        "Vojka nad Dunajom"
    ],
    "wof:name":"Vojka nad Dunajom",
    "wof:placetype":"locality"
},
  "geometry": {"coordinates":[17.38148,47.97346],"type":"Point"}
}