{
  "type": "Feature",
  "properties": {
    "gn:admin1_code":"07",
    "gn:asciiname":"Vojka nad Dunajom",
    "gn:country_code":"SK",
    "gn:dem":119,
    "gn:feature_class":"P",
    "gn:feature_code":"PPL",
    "gn:name":"Vojka nad Dunajom",
    "gn:population":0,
    "gn:timezone":"Europe/Bratislava",
    "iso:country":"SK",
    "name:hun_x_preferred":[
        "Vajka"
    ],
    "name:und_x_variant":[
        "Duna-Vajka",
        "Vajka nad Dunajom",
        "Vojka nad Dunajom"
    ],
    "wof:name":"Vojka nad Dunajom",
    "wof:placetype":"locality"
},
  "geometry": {"coordinates":[17.38148,47.97346],"type":"Point"}
}