{
  "type": "Feature",
  "properties": {
    "gn:admin1_code":"04",
    "gn:asciiname":"Potvorice",
    "gn:country_code":"SK",
    "gn:dem":173,
    "gn:feature_class":"P",
    "gn:feature_code":"PPL",
    "gn:name":"Potvorice",
    "gn:population":0,
    "gn:timezone":"Europe/Bratislava",
    "iso:country":"SK",
    "name:cat_x_preferred":[
        "Potvorice"
    ],
    "name:ces_x_preferred":[
        "Potvorice"
    ],
    "name:deu_x_preferred":[
        "Potvorice"
    ],
    "name:epo_x_preferred":[
        "Potvorice"
    ],
    "name:eus_x_preferred":[
        "Potvorice"
    ],
    "name:fra_x_preferred":[
        "Potvorice"
    ],
    "name:hun_x_preferred":[
        "Patvar\u00f3c"
    ],
    "name:ita_x_preferred":[
        "Potvorice"
    ],
    "name:msa_x_preferred":[
        "Potvorice"
    ],
    "name:nld_x_preferred":[
        "Potvorice"
    ],
    "name:pol_x_preferred":[
        "Potvorice"
    ],
    "name:ron_x_preferred":[
        "Potvorice"
    ],
    "name:slk_x_preferred":[
        "Potvorice"
    ],
    "name:spa_x_preferred":[
        "Potvorice"
    ],
    "name:srp_x_preferred":[
        "\u041f\u043e\u0442\u0432\u043e\u0440\u0438\u0446\u0435"
    ],
    "name:war_x_preferred":[
        "Potvorice"
    ],
    "wof:name":"Potvorice",
    "wof:placetype":"locality"
},
  "geometry": {"coordinates":[17.84757,48.6887],"type":"Point"}
}