{
  "type": "Feature",
  "properties": {
    "gn:admin1_code":"04",
    "gn:asciiname":"Potvorice",
    "gn:country_code":"SK",
    "gn:dem":173,
    "gn:feature_class":"P",
    "gn:feature_code":"PPL",
    "gn:name":"Potvorice",
    "gn:population":0,
    "gn:timezone":"Europe/Bratislava",
    "iso:country":"SK",
    "wof:name":"Potvorice",
    "wof:placetype":"locality"
},
  "geometry": {"coordinates":[17.84757,48.6887],"type":"Point"}
}