{
  "type": "Feature",
  "properties": {
    "gn:admin1_code":"07",
    "gn:asciiname":"Vojtechovce",
    "gn:country_code":"SK",
    "gn:dem":119,
    "gn:feature_class":"P",
    "gn:feature_code":"PPL",
    "gn:name":"Vojtechovce",
    "gn:population":0,
    "gn:timezone":"Europe/Bratislava",
    "iso:country":"SK",
    "name:und_x_variant":[
        "B\u00e9l-Vata",
        "Vojtechovce"
    ],
    "wof:name":"Vojtechovce",
    "wof:placetype":"locality"
},
  "geometry": {"coordinates":[17.47685,48.10135],"type":"Point"}
}