{
  "type": "Feature",
  "properties": {
    "gn:gn_country":"SK",
    "gn:gn_fcode":"PPL",
    "gn:gn_pop":0,
    "iso:country":"SK",
    "name:cat_x_preferred":[
        "Komo\u010da"
    ],
    "name:ces_x_preferred":[
        "Komo\u010da"
    ],
    "name:deu_x_preferred":[
        "Komo\u010da"
    ],
    "name:eng_x_preferred":[
        "Komo\u010da"
    ],
    "name:epo_x_preferred":[
        "Komo\u010da"
    ],
    "name:eus_x_preferred":[
        "Komo\u010da"
    ],
    "name:fra_x_preferred":[
        "Komo\u010da"
    ],
    "name:hun_x_preferred":[
        "Kamocsa"
    ],
    "name:ita_x_preferred":[
        "Komo\u010da"
    ],
    "name:msa_x_preferred":[
        "Komo\u010da"
    ],
    "name:nan_x_preferred":[
        "Komo\u010da"
    ],
    "name:nld_x_preferred":[
        "Komo\u010da"
    ],
    "name:ron_x_preferred":[
        "Komo\u010da"
    ],
    "name:slk_x_preferred":[
        "Komo\u010da"
    ],
    "name:spa_x_preferred":[
        "Komo\u010da"
    ],
    "name:srp_x_preferred":[
        "\u041a\u043e\u043c\u043e\u0447\u0430"
    ],
    "name:srp_x_variant":[
        "\u0417\u0430\u0459\u0435\u0441\u0458\u0435"
    ],
    "name:unk_x_variant":[
        "Kamo\u010da"
    ],
    "name:war_x_preferred":[
        "Komo\u010da"
    ],
    "qs_pg:aaroncc":"SK",
    "qs_pg:gn_country":"SK",
    "qs_pg:gn_fcode":"PPL",
    "qs_pg:gn_pop":0,
    "qs_pg:name":"Komo\u010da",
    "qs_pg:name_adm0":"Slovensk\u00e1",
    "qs_pg:name_adm1":"Nitriansky",
    "qs_pg:photos_9k":1,
    "qs_pg:photos_9r":1,
    "qs_pg:photos_all":1,
    "qs_pg:photos_sr":0,
    "qs_pg:pop_sr":0,
    "qs_pg:qs_pg_placetype":"locality",
    "qs_pg:qs_pg_placetype_gp":"Town",
    "qs_pg:woe_adm0":23424877,
    "woe:adm0_id":23424877,
    "woe:name_adm0":"Slovensk\u00e1",
    "woe:name_adm1":"Nitriansky",
    "woe:placetype":"Town",
    "wof:name":"Komo\u010da",
    "wof:placetype":"locality"
},
  "geometry": {"coordinates":[18.02032,47.94866],"type":"Point"}
}