{
  "type": "Feature",
  "properties": {
    "iso:country":"SK",
    "name:eng_x_preferred":[
        "Ludova stvrt"
    ],
    "name:slk_x_preferred":[
        "\u013dudov\u00e1 \u0161tvr\u0165"
    ],
    "wof:name":"Ludova stvrt",
    "wof:placetype":"neighbourhood"
},
  "geometry": {"coordinates":[17.13459269063696,48.1692982430873],"type":"Point"}
}