{
  "type": "Feature",
  "properties": {
    "gn:admin1_code":"05",
    "gn:asciiname":"Hrisovce",
    "gn:country_code":"SK",
    "gn:dem":460,
    "gn:feature_class":"P",
    "gn:feature_code":"PPL",
    "gn:name":"Hri\u0161ovce",
    "gn:population":0,
    "gn:timezone":"Europe/Bratislava",
    "iso:country":"SK",
    "name:cat_x_preferred":[
        "Hri\u0161ovce"
    ],
    "name:ces_x_preferred":[
        "Hri\u0161ovce"
    ],
    "name:deu_x_preferred":[
        "Hri\u0161ovce"
    ],
    "name:epo_x_preferred":[
        "Hri\u0161ovce"
    ],
    "name:eus_x_preferred":[
        "Hri\u0161ovce"
    ],
    "name:fra_x_preferred":[
        "Hri\u0161ovce"
    ],
    "name:hun_x_preferred":[
        "Gy\u00f3nfalva"
    ],
    "name:ita_x_preferred":[
        "Hri\u0161ovce"
    ],
    "name:msa_x_preferred":[
        "Hri\u0161ovce"
    ],
    "name:nld_x_preferred":[
        "Hri\u0161ovce"
    ],
    "name:pol_x_preferred":[
        "Hri\u0161ovce"
    ],
    "name:ron_x_preferred":[
        "Hri\u0161ovce"
    ],
    "name:slk_x_preferred":[
        "Hri\u0161ovce"
    ],
    "name:spa_x_preferred":[
        "Hri\u0161ovce"
    ],
    "name:srp_x_preferred":[
        "\u0425\u0440\u0438\u0448\u043e\u0432\u0446\u0435"
    ],
    "name:ukr_x_preferred":[
        "\u0413\u0440\u0438\u0448\u043e\u0432\u0446\u0435"
    ],
    "name:und_x_variant":[
        "Hri\u0161ovce"
    ],
    "name:war_x_preferred":[
        "Hri\u0161ovce"
    ],
    "wof:name":"Hrisovce",
    "wof:placetype":"locality"
},
  "geometry": {"coordinates":[20.9078,48.94655],"type":"Point"}
}