{
  "type": "Feature",
  "properties": {
    "gn:admin1_code":"05",
    "gn:asciiname":"Hrisovce",
    "gn:country_code":"SK",
    "gn:dem":460,
    "gn:feature_class":"P",
    "gn:feature_code":"PPL",
    "gn:name":"Hri\u0161ovce",
    "gn:population":0,
    "gn:timezone":"Europe/Bratislava",
    "iso:country":"SK",
    "name:und_x_variant":[
        "Hri\u0161ovce"
    ],
    "wof:name":"Hrisovce",
    "wof:placetype":"locality"
},
  "geometry": {"coordinates":[20.9078,48.94655],"type":"Point"}
}