{
  "type": "Feature",
  "properties": {
    "gn:admin1_code":"01",
    "gn:asciiname":"Horna Ves",
    "gn:country_code":"SK",
    "gn:dem":440,
    "gn:feature_class":"P",
    "gn:feature_code":"PPL",
    "gn:name":"Horn\u00e1 Ves",
    "gn:population":0,
    "gn:timezone":"Europe/Bratislava",
    "iso:country":"SK",
    "name:und_x_variant":[
        "Horn\u00e1 Ves"
    ],
    "wof:name":"Horna Ves",
    "wof:placetype":"locality"
},
  "geometry": {"coordinates":[18.91012000000001,48.67674],"type":"Point"}
}