{
  "type": "Feature",
  "properties": {
    "gn:admin1_code":"01",
    "gn:asciiname":"Horna Ves",
    "gn:country_code":"SK",
    "gn:dem":440,
    "gn:feature_class":"P",
    "gn:feature_code":"PPL",
    "gn:name":"Horn\u00e1 Ves",
    "gn:population":0,
    "gn:timezone":"Europe/Bratislava",
    "iso:country":"SK",
    "name:cat_x_preferred":[
        "Horn\u00e1 Ves"
    ],
    "name:ces_x_preferred":[
        "Horn\u00e1 Ves"
    ],
    "name:deu_x_preferred":[
        "Horn\u00e1 Ves"
    ],
    "name:epo_x_preferred":[
        "Horn\u00e1 Ves"
    ],
    "name:eus_x_preferred":[
        "Horn\u00e1 Ves"
    ],
    "name:hun_x_preferred":[
        "Fels\u0151t\u00f3ti"
    ],
    "name:ita_x_preferred":[
        "Horn\u00e1 Ves"
    ],
    "name:msa_x_preferred":[
        "Horn\u00e1 Ves"
    ],
    "name:nld_x_preferred":[
        "Horn\u00e1 Ves"
    ],
    "name:pol_x_preferred":[
        "Horn\u00e1 Ves"
    ],
    "name:ron_x_preferred":[
        "Horn\u00e1 Ves"
    ],
    "name:slk_x_preferred":[
        "Horn\u00e1 Ves"
    ],
    "name:spa_x_preferred":[
        "Horn\u00e1 Ves"
    ],
    "name:srp_x_preferred":[
        "\u0425\u043e\u0440\u043d\u0430 \u0412\u0435\u0441"
    ],
    "name:ukr_x_preferred":[
        "\u0413\u043e\u0440\u043d\u0430 \u0412\u0435\u0441\u044c"
    ],
    "name:war_x_preferred":[
        "Horn\u00e1 Ves"
    ],
    "wof:name":"Horna Ves",
    "wof:placetype":"locality"
},
  "geometry": {"coordinates":[18.91012000000001,48.67674],"type":"Point"}
}