{
  "type": "Feature",
  "properties": {
    "gn:admin1_code":"03",
    "gn:asciiname":"Hacava",
    "gn:country_code":"SK",
    "gn:dem":689,
    "gn:feature_class":"P",
    "gn:feature_code":"PPL",
    "gn:name":"Ha\u010dava",
    "gn:population":0,
    "gn:timezone":"Europe/Bratislava",
    "iso:country":"SK",
    "name:cat_x_preferred":[
        "Ha\u010dava"
    ],
    "name:ces_x_preferred":[
        "Ha\u010dava"
    ],
    "name:deu_x_preferred":[
        "Ha\u010dava"
    ],
    "name:epo_x_preferred":[
        "Ha\u010dava"
    ],
    "name:eus_x_preferred":[
        "Ha\u010dava"
    ],
    "name:fra_x_preferred":[
        "Ha\u010dava"
    ],
    "name:hun_x_preferred":[
        "\u00c1jfalucska"
    ],
    "name:ita_x_preferred":[
        "Ha\u010dava"
    ],
    "name:msa_x_preferred":[
        "Ha\u010dava"
    ],
    "name:nld_x_preferred":[
        "Ha\u010dava"
    ],
    "name:pol_x_preferred":[
        "Ha\u010dava"
    ],
    "name:ron_x_preferred":[
        "Ha\u010dava"
    ],
    "name:rue_x_preferred":[
        "\u0413\u0430\u0447\u0430\u0432\u0430"
    ],
    "name:slk_x_preferred":[
        "Ha\u010dava"
    ],
    "name:spa_x_preferred":[
        "Ha\u010dava"
    ],
    "name:srp_x_preferred":[
        "\u0425\u0430\u0447\u0430\u0432\u0430"
    ],
    "name:ukr_x_preferred":[
        "\u0413\u0430\u0447\u0430\u0432\u0430"
    ],
    "name:und_x_variant":[
        "Ha\u010dava"
    ],
    "name:war_x_preferred":[
        "Ha\u010dava"
    ],
    "wof:name":"Hacava",
    "wof:placetype":"locality"
},
  "geometry": {"coordinates":[20.83333,48.66667],"type":"Point"}
}