{
  "type": "Feature",
  "properties": {
    "gn:admin1_code":"03",
    "gn:asciiname":"Hacava",
    "gn:country_code":"SK",
    "gn:dem":689,
    "gn:feature_class":"P",
    "gn:feature_code":"PPL",
    "gn:name":"Ha\u010dava",
    "gn:population":0,
    "gn:timezone":"Europe/Bratislava",
    "iso:country":"SK",
    "name:und_x_variant":[
        "Ha\u010dava"
    ],
    "wof:name":"Hacava",
    "wof:placetype":"locality"
},
  "geometry": {"coordinates":[20.83333,48.66667],"type":"Point"}
}