{
  "type": "Feature",
  "properties": {
    "gn:asciiname":"Palcmanska Masa",
    "gn:country_code":"SK",
    "gn:dem":794,
    "gn:feature_class":"P",
    "gn:feature_code":"PPL",
    "gn:name":"Palcmansk\u00e1 Ma\u0161a",
    "gn:population":0,
    "gn:timezone":"Europe/Bratislava",
    "iso:country":"SK",
    "name:und_x_variant":[
        "Palcmanska-Ma\u0161ka"
    ],
    "wof:name":"Palcmanska Masa",
    "wof:placetype":"locality"
},
  "geometry": {"coordinates":[20.38754,48.85376],"type":"Point"}
}