{
  "type": "Feature",
  "properties": {
    "gn:gn_country":"SK",
    "gn:gn_fcode":"PPL",
    "gn:gn_pop":0,
    "iso:country":"SK",
    "name:cat_x_preferred":[
        "Dubov\u00e1"
    ],
    "name:ces_x_preferred":[
        "Dubov\u00e1"
    ],
    "name:deu_x_preferred":[
        "Dubov\u00e1"
    ],
    "name:eng_x_preferred":[
        "Dubov\u00e1"
    ],
    "name:epo_x_preferred":[
        "Dubov\u00e1"
    ],
    "name:eus_x_preferred":[
        "Dubov\u00e1"
    ],
    "name:fra_x_preferred":[
        "Dubov\u00e1"
    ],
    "name:hun_x_preferred":[
        "Cserfalu"
    ],
    "name:ita_x_preferred":[
        "Dubov\u00e1"
    ],
    "name:lit_x_preferred":[
        "Dubova"
    ],
    "name:msa_x_preferred":[
        "Dubov\u00e1"
    ],
    "name:nan_x_preferred":[
        "Dubov\u00e1"
    ],
    "name:nld_x_preferred":[
        "Dubov\u00e1"
    ],
    "name:por_x_preferred":[
        "Dubov\u00e1"
    ],
    "name:ron_x_preferred":[
        "Dubov\u00e1"
    ],
    "name:slk_x_preferred":[
        "Dubov\u00e1"
    ],
    "name:spa_x_preferred":[
        "Dubov\u00e1"
    ],
    "name:srp_x_preferred":[
        "\u0414\u0443\u0431\u043e\u0432\u0430"
    ],
    "name:war_x_preferred":[
        "Dubov\u00e1"
    ],
    "qs_pg:aaroncc":"SK",
    "qs_pg:gn_country":"SK",
    "qs_pg:gn_fcode":"PPL",
    "qs_pg:gn_pop":0,
    "qs_pg:name":"Dubov\u00e1",
    "qs_pg:name_adm0":"Slovensk\u00e1",
    "qs_pg:name_adm1":"Bratislavsky",
    "qs_pg:photos":22,
    "qs_pg:photos_1k":4,
    "qs_pg:photos_9k":1,
    "qs_pg:photos_9r":1,
    "qs_pg:photos_all":22,
    "qs_pg:photos_sr":1,
    "qs_pg:pop_sr":0,
    "qs_pg:qs_pg_placetype":"locality",
    "qs_pg:qs_pg_placetype_gp":"Town",
    "qs_pg:woe_adm0":23424877,
    "woe:adm0_id":23424877,
    "woe:name_adm0":"Slovensk\u00e1",
    "woe:name_adm1":"Bratislavsky",
    "woe:placetype":"Town",
    "wof:name":"Dubov\u00e1",
    "wof:placetype":"locality"
},
  "geometry": {"coordinates":[17.33965,48.36676],"type":"Point"}
}