{
  "type": "Feature",
  "properties": {
    "gn:admin1_code":"04",
    "gn:asciiname":"Vel'ke Stankovce",
    "gn:country_code":"SK",
    "gn:dem":225,
    "gn:feature_class":"P",
    "gn:feature_code":"PPL",
    "gn:name":"Ve\u013ek\u00e9 Stankovce",
    "gn:population":0,
    "gn:timezone":"Europe/Bratislava",
    "iso:country":"SK",
    "wof:name":"Vel'ke Stankovce",
    "wof:placetype":"locality"
},
  "geometry": {"coordinates":[17.98927,48.82787],"type":"Point"}
}