{
  "type": "Feature",
  "properties": {
    "gn:admin1_code":"01",
    "gn:asciiname":"Stredne Plachtince",
    "gn:country_code":"SK",
    "gn:dem":218,
    "gn:feature_class":"P",
    "gn:feature_code":"PPL",
    "gn:name":"Stredn\u00e9 Plachtince",
    "gn:population":0,
    "gn:timezone":"Europe/Bratislava",
    "iso:country":"SK",
    "name:und_x_variant":[
        "Strednie Plachtince",
        "Stredn\u00ed Plachtince",
        "Stredn\u00e9 Plachtince"
    ],
    "wof:name":"Stredne Plachtince",
    "wof:placetype":"locality"
},
  "geometry": {"coordinates":[19.29192,48.22628],"type":"Point"}
}