{
  "type": "Feature",
  "properties": {
    "gn:admin1_code":"01",
    "gn:asciiname":"Stredne Plachtince",
    "gn:country_code":"SK",
    "gn:dem":218,
    "gn:feature_class":"P",
    "gn:feature_code":"PPL",
    "gn:name":"Stredn\u00e9 Plachtince",
    "gn:population":0,
    "gn:timezone":"Europe/Bratislava",
    "iso:country":"SK",
    "name:cat_x_preferred":[
        "Stredn\u00e9 Plachtince"
    ],
    "name:deu_x_preferred":[
        "Stredn\u00e9 Plachtince"
    ],
    "name:epo_x_preferred":[
        "Stredn\u00e9 Plachtince"
    ],
    "name:eus_x_preferred":[
        "Stredn\u00e9 Plachtince"
    ],
    "name:fra_x_preferred":[
        "Stredn\u00e9 Plachtince"
    ],
    "name:hun_x_preferred":[
        "K\u00f6z\u00e9ppalojta"
    ],
    "name:ita_x_preferred":[
        "Stredn\u00e9 Plachtince"
    ],
    "name:msa_x_preferred":[
        "Stredn\u00e9 Plachtince"
    ],
    "name:nld_x_preferred":[
        "Stredn\u00e9 Plachtince"
    ],
    "name:pol_x_preferred":[
        "Stredn\u00e9 Plachtince"
    ],
    "name:ron_x_preferred":[
        "Stredn\u00e9 Plachtince"
    ],
    "name:slk_x_preferred":[
        "Stredn\u00e9 Plachtince"
    ],
    "name:spa_x_preferred":[
        "Stredn\u00e9 Plachtince"
    ],
    "name:srp_x_preferred":[
        "\u0421\u0442\u0440\u0435\u0434\u045a\u0435 \u041f\u043b\u0430\u0445\u0442\u0438\u043d\u0446\u0435"
    ],
    "name:ukr_x_preferred":[
        "\u0421\u0442\u0440\u0435\u0434\u043d\u0435 \u041f\u043b\u0430\u0445\u0442\u0456\u043d\u0446\u0435"
    ],
    "name:und_x_variant":[
        "Strednie Plachtince",
        "Stredn\u00ed Plachtince",
        "Stredn\u00e9 Plachtince"
    ],
    "name:war_x_preferred":[
        "Stredn\u00e9 Plachtince"
    ],
    "wof:name":"Stredne Plachtince",
    "wof:placetype":"locality"
},
  "geometry": {"coordinates":[19.29192,48.22628],"type":"Point"}
}