{
  "type": "Feature",
  "properties": {
    "gn:gn_country":"SK",
    "gn:gn_fcode":"PPL",
    "gn:gn_pop":0,
    "iso:country":"SK",
    "name:cat_x_preferred":[
        "Malat\u00edny"
    ],
    "name:ces_x_preferred":[
        "Malat\u00edny"
    ],
    "name:eng_x_preferred":[
        "Malat\u00edny"
    ],
    "name:epo_x_preferred":[
        "Malat\u00edny"
    ],
    "name:fra_x_preferred":[
        "Malat\u00edny"
    ],
    "name:hun_x_preferred":[
        "H\u00e1rommalatin"
    ],
    "name:ita_x_preferred":[
        "Malat\u00edny"
    ],
    "name:msa_x_preferred":[
        "Malat\u00edny"
    ],
    "name:nld_x_preferred":[
        "Malat\u00edny"
    ],
    "name:pol_x_preferred":[
        "Malat\u00edny"
    ],
    "name:slk_x_preferred":[
        "Malat\u00edny"
    ],
    "name:srp_x_preferred":[
        "\u041c\u0430\u043b\u0430\u0442\u0438\u043d\u0438"
    ],
    "name:unk_x_variant":[
        "Ni\u017enie Malat\u00edny"
    ],
    "name:war_x_preferred":[
        "Malat\u00edny"
    ],
    "qs_pg:aaroncc":"SK",
    "qs_pg:gn_country":"SK",
    "qs_pg:gn_fcode":"PPL",
    "qs_pg:gn_pop":0,
    "qs_pg:name":"Ni\u017en\u00e9 Malat\u00edny",
    "qs_pg:name_adm0":"Slovensk\u00e1",
    "qs_pg:name_adm1":"Zilinsky",
    "qs_pg:photos_9r":0,
    "qs_pg:photos_sr":0,
    "qs_pg:pop_sr":0,
    "qs_pg:qs_pg_placetype":"locality",
    "qs_pg:qs_pg_placetype_gp":"Town",
    "qs_pg:woe_adm0":23424877,
    "woe:adm0_id":23424877,
    "woe:name_adm0":"Slovensk\u00e1",
    "woe:name_adm1":"Zilinsky",
    "woe:placetype":"Town",
    "wof:name":"Ni\u017en\u00e9 Malat\u00edny",
    "wof:placetype":"locality"
},
  "geometry": {"coordinates":[19.45918,49.06925],"type":"Point"}
}