{
  "type": "Feature",
  "properties": {
    "gn:admin1_code":"04",
    "gn:asciiname":"Jurakovce",
    "gn:country_code":"SK",
    "gn:dem":387,
    "gn:feature_class":"P",
    "gn:feature_code":"PPL",
    "gn:name":"Jur\u00e1kovce",
    "gn:population":0,
    "gn:timezone":"Europe/Bratislava",
    "iso:country":"SK",
    "wof:name":"Jurakovce",
    "wof:placetype":"locality"
},
  "geometry": {"coordinates":[17.88278,48.87402],"type":"Point"}
}