{
  "type": "Feature",
  "properties": {
    "gn:gn_country":"SK",
    "gn:gn_fcode":"PPL",
    "gn:gn_pop":0,
    "iso:country":"SK",
    "name:ces_x_preferred":[
        "Jarovce"
    ],
    "name:deu_x_preferred":[
        "Jarovce"
    ],
    "name:deu_x_variant":[
        "Kroatisch Jahrndorf"
    ],
    "name:eng_x_preferred":[
        "Kroatisch Jahrndorf"
    ],
    "name:eng_x_variant":[
        "Kroatisch Jahrndorf",
        "Horvathjarfalu"
    ],
    "name:epo_x_preferred":[
        "Jarovce"
    ],
    "name:fin_x_preferred":[
        "Jarovce"
    ],
    "name:fra_x_preferred":[
        "Jarovce"
    ],
    "name:hbs_x_preferred":[
        "Jarovce"
    ],
    "name:hrv_x_preferred":[
        "Hrvatski Jandrof"
    ],
    "name:hun_x_preferred":[
        "Horv\u00e1tj\u00e1rfalu"
    ],
    "name:hun_x_variant":[
        "Horvathjarfalu",
        "Horb\u00e1tj\u00e1rfalu"
    ],
    "name:ita_x_preferred":[
        "Jarovce"
    ],
    "name:nld_x_preferred":[
        "Jarovce"
    ],
    "name:pol_x_preferred":[
        "Jarovce"
    ],
    "name:slk_x_preferred":[
        "Bratislava \u2013 mestsk\u00e1 \u010das\u0165 Jarovce"
    ],
    "name:slk_x_variant":[
        "Jarovce"
    ],
    "name:srp_x_preferred":[
        "\u0408\u0430\u0440\u043e\u0432\u0446\u0435"
    ],
    "name:und_x_colloquial":[
        "Horbatjarfalu"
    ],
    "name:und_x_preferred":[
        "Jarovce"
    ],
    "name:und_x_variant":[
        "Horb\u00e1tj\u00e1rfalu"
    ],
    "name:unk_x_variant":[
        "Kroatisch Jahrndorf",
        "Jarovce"
    ],
    "name:zho_x_preferred":[
        "\u96c5\u7f85\u7dad\u7b56"
    ],
    "qs:gn_adm0_cc":"SK",
    "qs:gn_fcode":"PPL",
    "qs:gn_local":3060972,
    "qs:gn_namadm1":"02",
    "qs:gn_name":"Jarovce",
    "qs:local_max":14839,
    "qs:local_sum":27271,
    "qs:localhoods":23,
    "qs:name":"Jarovce",
    "qs:name_adm0":"Slovensk\u00e1",
    "qs:name_adm1":"Bratislavsky",
    "qs:name_adm2":"Bratislava",
    "qs:name_en":"Kroatisch Jahrndorf",
    "qs:name_lau":"Bratislava V",
    "qs:name_local":"Bratislava",
    "qs:photo_max":35,
    "qs:photo_sum":97,
    "qs:placetype":"Suburb",
    "qs:quad_count":19,
    "qs:woe_adm0":23424877,
    "qs:woe_adm1":20070505,
    "qs:woe_adm2":29399347,
    "qs:woe_lau":29402280,
    "qs:woe_local":818717,
    "qs:woe_ver":"7.10.0",
    "qs_pg:aaroncc":"SK",
    "qs_pg:gn_country":"SK",
    "qs_pg:gn_fcode":"PPL",
    "qs_pg:gn_pop":0,
    "qs_pg:name":"Jarovce",
    "qs_pg:name_adm0":"Slovensk\u00e1",
    "qs_pg:name_adm1":"Bratislavsky",
    "qs_pg:photos":97,
    "qs_pg:photos_1k":20,
    "qs_pg:photos_9k":1,
    "qs_pg:photos_9r":3,
    "qs_pg:photos_all":97,
    "qs_pg:photos_sr":3,
    "qs_pg:pop_sr":0,
    "qs_pg:qs_pg_placetype":"neighbourhood",
    "qs_pg:qs_pg_placetype_gp":"Suburb",
    "qs_pg:woe_adm0":23424877,
    "wd:wordcount":321,
    "wof:lang":[
        "unk"
    ],
    "wof:name":"Jarovce",
    "wof:placetype":"neighbourhood"
},
  "geometry": {"coordinates":[17.126624,48.081094],"type":"Point"}
}