{
  "type": "Feature",
  "properties": {
    "gn:admin1_code":"01",
    "gn:asciiname":"Prostredna Molca",
    "gn:country_code":"SK",
    "gn:dem":439,
    "gn:feature_class":"P",
    "gn:feature_code":"PPL",
    "gn:name":"Prostredn\u00e1 M\u00f4l\u010da",
    "gn:population":0,
    "gn:timezone":"Europe/Bratislava",
    "iso:country":"SK",
    "name:und_x_variant":[
        "Prostrednia-M\u00f4l\u010da",
        "Prostredn\u00e1 M\u00f4l\u010da"
    ],
    "wof:name":"Prostredna Molca",
    "wof:placetype":"locality"
},
  "geometry": {"coordinates":[19.22827,48.71574],"type":"Point"}
}