{
  "type": "Feature",
  "properties": {
    "gn:admin1_code":"08",
    "gn:asciiname":"Korytnica",
    "gn:country_code":"SK",
    "gn:dem":851,
    "gn:feature_class":"P",
    "gn:feature_code":"PPL",
    "gn:name":"Korytnica",
    "gn:population":0,
    "gn:timezone":"Europe/Bratislava",
    "iso:country":"SK",
    "wof:name":"Korytnica",
    "wof:placetype":"locality"
},
  "geometry": {"coordinates":[19.2865,48.8896],"type":"Point"}
}