{
  "type": "Feature",
  "properties": {
    "gn:admin1_code":"08",
    "gn:asciiname":"Korytnica",
    "gn:country_code":"SK",
    "gn:dem":851,
    "gn:feature_class":"P",
    "gn:feature_code":"PPL",
    "gn:name":"Korytnica",
    "gn:population":0,
    "gn:timezone":"Europe/Bratislava",
    "iso:country":"SK",
    "name:bel_x_preferred":[
        "\u041a\u0430\u0440\u044b\u0442\u043d\u0456\u0446\u0430"
    ],
    "name:ceb_x_preferred":[
        "Korytnica"
    ],
    "name:deu_x_preferred":[
        "Korytnica"
    ],
    "name:fra_x_preferred":[
        "Korytnica"
    ],
    "name:nld_x_preferred":[
        "Korytnica"
    ],
    "name:pol_x_preferred":[
        "Korytnica"
    ],
    "name:rus_x_preferred":[
        "\u041a\u043e\u0440\u044b\u0442\u043d\u0438\u0446\u0430"
    ],
    "name:slk_x_preferred":[
        "Korytnica"
    ],
    "name:ukr_x_preferred":[
        "\u041a\u043e\u0440\u0438\u0442\u043d\u0438\u0446\u044f"
    ],
    "wof:name":"Korytnica",
    "wof:placetype":"locality"
},
  "geometry": {"coordinates":[19.2865,48.8896],"type":"Point"}
}