{
  "type": "Feature",
  "properties": {
    "gn:admin1_code":"01",
    "gn:asciiname":"Ples",
    "gn:country_code":"SK",
    "gn:dem":222,
    "gn:feature_class":"P",
    "gn:feature_code":"PPL",
    "gn:name":"Ple\u0161",
    "gn:population":0,
    "gn:timezone":"Europe/Bratislava",
    "iso:country":"SK",
    "name:hun_x_preferred":[
        "F\u00fclekpilis"
    ],
    "name:und_x_variant":[
        "Pilis",
        "Ple\u0161"
    ],
    "wof:name":"Ples",
    "wof:placetype":"locality"
},
  "geometry": {"coordinates":[19.74937000000001,48.23147],"type":"Point"}
}