{
  "type": "Feature",
  "properties": {
    "gn:admin1_code":"03",
    "gn:asciiname":"Kapona",
    "gn:country_code":"SK",
    "gn:dem":100,
    "gn:feature_class":"P",
    "gn:feature_code":"PPL",
    "gn:name":"Kapo\u0148a",
    "gn:population":0,
    "gn:timezone":"Europe/Bratislava",
    "iso:country":"SK",
    "wof:name":"Kapona",
    "wof:placetype":"locality"
},
  "geometry": {"coordinates":[22.05149,48.46217],"type":"Point"}
}