{
  "type": "Feature",
  "properties": {
    "gn:admin1_code":"05",
    "gn:asciiname":"Baranie",
    "gn:country_code":"SK",
    "gn:dem":833,
    "gn:feature_class":"P",
    "gn:feature_code":"PPL",
    "gn:name":"Baranie",
    "gn:population":0,
    "gn:timezone":"Europe/Bratislava",
    "iso:country":"SK",
    "wof:name":"Baranie",
    "wof:placetype":"locality"
},
  "geometry": {"coordinates":[21.14115,49.17098],"type":"Point"}
}