{
  "type": "Feature",
  "properties": {
    "gn:admin1_code":"07",
    "gn:asciiname":"Palkovicovo",
    "gn:country_code":"SK",
    "gn:dem":109,
    "gn:feature_class":"P",
    "gn:feature_code":"PPL",
    "gn:name":"Palkovi\u010dovo",
    "gn:population":0,
    "gn:timezone":"Europe/Bratislava",
    "iso:country":"SK",
    "name:und_x_variant":[
        "Sap",
        "Szap",
        "Palkovi\u010dovo"
    ],
    "wof:name":"Palkovicovo",
    "wof:placetype":"locality"
},
  "geometry": {"coordinates":[17.61667000000001,47.81667],"type":"Point"}
}