{
  "type": "Feature",
  "properties": {
    "gn:admin1_code":"05",
    "gn:asciiname":"Kyjov",
    "gn:country_code":"SK",
    "gn:dem":668,
    "gn:feature_class":"P",
    "gn:feature_code":"PPL",
    "gn:name":"Kyjov",
    "gn:population":0,
    "gn:timezone":"Europe/Bratislava",
    "iso:country":"SK",
    "wof:name":"Kyjov",
    "wof:placetype":"locality"
},
  "geometry": {"coordinates":[20.94227,49.21934],"type":"Point"}
}