{
  "type": "Feature",
  "properties": {
    "gn:admin1_code":"05",
    "gn:asciiname":"Kyjov",
    "gn:country_code":"SK",
    "gn:dem":668,
    "gn:feature_class":"P",
    "gn:feature_code":"PPL",
    "gn:name":"Kyjov",
    "gn:population":0,
    "gn:timezone":"Europe/Bratislava",
    "iso:country":"SK",
    "name:cat_x_preferred":[
        "Kyjov"
    ],
    "name:ces_x_preferred":[
        "Kyjov"
    ],
    "name:deu_x_preferred":[
        "Kyjov"
    ],
    "name:epo_x_preferred":[
        "Kyjov"
    ],
    "name:eus_x_preferred":[
        "Kyjov"
    ],
    "name:hun_x_preferred":[
        "Kij\u00f3"
    ],
    "name:ita_x_preferred":[
        "Kyjov"
    ],
    "name:msa_x_preferred":[
        "Kyjov"
    ],
    "name:nld_x_preferred":[
        "Kyjov"
    ],
    "name:pol_x_preferred":[
        "Kyjov"
    ],
    "name:ron_x_preferred":[
        "Kyjov"
    ],
    "name:rue_x_preferred":[
        "\u041a\u044b\u0451\u0432"
    ],
    "name:slk_x_preferred":[
        "Kyjov"
    ],
    "name:spa_x_preferred":[
        "Kyjov"
    ],
    "name:srp_x_preferred":[
        "\u041a\u0438\u0458\u043e\u0432"
    ],
    "name:ukr_x_preferred":[
        "\u041a\u0438\u0439\u043e\u0432"
    ],
    "name:war_x_preferred":[
        "Kyjov"
    ],
    "wof:name":"Kyjov",
    "wof:placetype":"locality"
},
  "geometry": {"coordinates":[20.94227,49.21934],"type":"Point"}
}