{
  "type": "Feature",
  "properties": {
    "gn:admin1_code":"03",
    "gn:asciiname":"Semsa",
    "gn:country_code":"SK",
    "gn:dem":302,
    "gn:feature_class":"P",
    "gn:feature_code":"PPL",
    "gn:name":"\u0160em\u0161a",
    "gn:population":0,
    "gn:timezone":"Europe/Bratislava",
    "iso:country":"SK",
    "name:hun_x_preferred":[
        "Semse"
    ],
    "name:und_x_variant":[
        "\u0160em\u0161a"
    ],
    "wof:name":"Semsa",
    "wof:placetype":"locality"
},
  "geometry": {"coordinates":[21.11372,48.67616],"type":"Point"}
}