{
  "type": "Feature",
  "properties": {
    "gn:admin1_code":"03",
    "gn:asciiname":"Semsa",
    "gn:country_code":"SK",
    "gn:dem":302,
    "gn:feature_class":"P",
    "gn:feature_code":"PPL",
    "gn:name":"\u0160em\u0161a",
    "gn:population":0,
    "gn:timezone":"Europe/Bratislava",
    "iso:country":"SK",
    "name:cat_x_preferred":[
        "\u0160em\u0161a"
    ],
    "name:deu_x_preferred":[
        "\u0160em\u0161a"
    ],
    "name:epo_x_preferred":[
        "\u0160em\u0161a"
    ],
    "name:eus_x_preferred":[
        "\u0160em\u0161a"
    ],
    "name:fra_x_preferred":[
        "\u0160em\u0161a"
    ],
    "name:hun_x_preferred":[
        "Semse"
    ],
    "name:ita_x_preferred":[
        "\u0160em\u0161a"
    ],
    "name:msa_x_preferred":[
        "\u0160em\u0161a"
    ],
    "name:nld_x_preferred":[
        "\u0160em\u0161a"
    ],
    "name:pol_x_preferred":[
        "\u0160em\u0161a"
    ],
    "name:ron_x_preferred":[
        "\u0160em\u0161a"
    ],
    "name:slk_x_preferred":[
        "\u0160em\u0161a"
    ],
    "name:spa_x_preferred":[
        "\u0160em\u0161a"
    ],
    "name:srp_x_preferred":[
        "\u0428\u0435\u043c\u0448\u0430"
    ],
    "name:ukr_x_preferred":[
        "\u0428\u0435\u043c\u0448\u0430"
    ],
    "name:und_x_variant":[
        "\u0160em\u0161a"
    ],
    "name:war_x_preferred":[
        "\u0160em\u0161a"
    ],
    "wof:name":"Semsa",
    "wof:placetype":"locality"
},
  "geometry": {"coordinates":[21.11372,48.67616],"type":"Point"}
}