{
  "type": "Feature",
  "properties": {
    "iso:country":"SK",
    "name:eng_x_preferred":[
        "500 bytov"
    ],
    "name:slk_x_preferred":[
        "500 bytov"
    ],
    "wof:name":"500 bytov",
    "wof:placetype":"neighbourhood"
},
  "geometry": {"coordinates":[17.12947145698112,48.14983184572036],"type":"Point"}
}