{
  "type": "Feature",
  "properties": {
    "gn:admin1_code":"01",
    "gn:asciiname":"Konradovce",
    "gn:country_code":"SK",
    "gn:dem":234,
    "gn:feature_class":"P",
    "gn:feature_code":"PPL",
    "gn:name":"Konr\u00e1dovce",
    "gn:population":0,
    "gn:timezone":"Europe/Bratislava",
    "iso:country":"SK",
    "name:cat_x_preferred":[
        "Konr\u00e1dovce"
    ],
    "name:epo_x_preferred":[
        "Konr\u00e1dovce"
    ],
    "name:eus_x_preferred":[
        "Konr\u00e1dovce"
    ],
    "name:fra_x_preferred":[
        "Konr\u00e1dovce"
    ],
    "name:hun_x_preferred":[
        "Korl\u00e1ti"
    ],
    "name:ita_x_preferred":[
        "Konr\u00e1dovce"
    ],
    "name:msa_x_preferred":[
        "Konr\u00e1dovce"
    ],
    "name:nld_x_preferred":[
        "Konr\u00e1dovce"
    ],
    "name:pol_x_preferred":[
        "Konr\u00e1dovce"
    ],
    "name:ron_x_preferred":[
        "Konr\u00e1dovce"
    ],
    "name:slk_x_preferred":[
        "Konr\u00e1dovce"
    ],
    "name:spa_x_preferred":[
        "Konr\u00e1dovce"
    ],
    "name:srp_x_preferred":[
        "\u041a\u043e\u043d\u0440\u0430\u0434\u043e\u0432\u0446\u0435"
    ],
    "name:ukr_x_preferred":[
        "\u041a\u043e\u043d\u0440\u0430\u0434\u043e\u0432\u0446\u0435"
    ],
    "name:und_x_variant":[
        "Korl\u00e1t",
        "Konr\u00e1dovce"
    ],
    "name:war_x_preferred":[
        "Konr\u00e1dovce"
    ],
    "wof:name":"Konradovce",
    "wof:placetype":"locality"
},
  "geometry": {"coordinates":[19.90383,48.29977],"type":"Point"}
}