{
  "type": "Feature",
  "properties": {
    "gn:admin1_code":"01",
    "gn:asciiname":"Konradovce",
    "gn:country_code":"SK",
    "gn:dem":234,
    "gn:feature_class":"P",
    "gn:feature_code":"PPL",
    "gn:name":"Konr\u00e1dovce",
    "gn:population":0,
    "gn:timezone":"Europe/Bratislava",
    "iso:country":"SK",
    "name:und_x_variant":[
        "Korl\u00e1t",
        "Konr\u00e1dovce"
    ],
    "wof:name":"Konradovce",
    "wof:placetype":"locality"
},
  "geometry": {"coordinates":[19.90383,48.29977],"type":"Point"}
}