{
  "type": "Feature",
  "properties": {
    "gn:admin1_code":"05",
    "gn:asciiname":"Vojnany",
    "gn:country_code":"SK",
    "gn:dem":664,
    "gn:feature_class":"P",
    "gn:feature_code":"PPL",
    "gn:name":"Voj\u0148any",
    "gn:population":0,
    "gn:timezone":"Europe/Bratislava",
    "iso:country":"SK",
    "name:cat_x_preferred":[
        "Voj\u0148any"
    ],
    "name:ces_x_preferred":[
        "Voj\u0148any"
    ],
    "name:deu_x_preferred":[
        "Voj\u0148any"
    ],
    "name:epo_x_preferred":[
        "Voj\u0148any"
    ],
    "name:eus_x_preferred":[
        "Voj\u0148any"
    ],
    "name:fra_x_preferred":[
        "Voj\u0148any"
    ],
    "name:hun_x_preferred":[
        "Krig"
    ],
    "name:ita_x_preferred":[
        "Voj\u0148any"
    ],
    "name:msa_x_preferred":[
        "Voj\u0148any"
    ],
    "name:nld_x_preferred":[
        "Voj\u0148any"
    ],
    "name:pol_x_preferred":[
        "Voj\u0148any"
    ],
    "name:ron_x_preferred":[
        "Voj\u0148any"
    ],
    "name:rue_x_preferred":[
        "\u0412\u043e\u0439\u043d\u044f\u043d\u0456"
    ],
    "name:slk_x_preferred":[
        "Voj\u0148any"
    ],
    "name:spa_x_preferred":[
        "Voj\u0148any"
    ],
    "name:srp_x_preferred":[
        "\u0412\u043e\u0458\u045a\u0430\u043d\u0438"
    ],
    "name:ukr_x_preferred":[
        "\u0412\u043e\u0439\u043d\u044f\u043d\u0438"
    ],
    "name:und_x_variant":[
        "Krig",
        "Voj\u0148any"
    ],
    "name:war_x_preferred":[
        "Voj\u0148any"
    ],
    "wof:name":"Vojnany",
    "wof:placetype":"locality"
},
  "geometry": {"coordinates":[20.44182,49.24853],"type":"Point"}
}