{
  "type": "Feature",
  "properties": {
    "gn:admin1_code":"01",
    "gn:asciiname":"Blh nad Ipl'om",
    "gn:country_code":"SK",
    "gn:dem":135,
    "gn:feature_class":"P",
    "gn:feature_code":"PPL",
    "gn:name":"Blh nad Ip\u013eom",
    "gn:population":0,
    "gn:timezone":"Europe/Bratislava",
    "iso:country":"SK",
    "name:und_x_variant":[
        "Balog",
        "Blh nad Ip\u013eom"
    ],
    "wof:name":"Blh nad Ipl'om",
    "wof:placetype":"locality"
},
  "geometry": {"coordinates":[19.13094,48.07781],"type":"Point"}
}