{
  "type": "Feature",
  "properties": {
    "gn:country":"SK",
    "gn:fcode":"PPL",
    "gn:population":0,
    "iso:country":"SK",
    "name:ara_x_preferred":[
        "\u0641\u064a\u0644\u0643\u0627 \u0645\u0627\u0643\u0627"
    ],
    "name:cat_x_preferred":[
        "Ve\u013ek\u00e1 Ma\u010da"
    ],
    "name:ces_x_preferred":[
        "Ve\u013ek\u00e1 Ma\u010da"
    ],
    "name:che_x_preferred":[
        "\u0412\u0435\u043b\u044c\u043a\u0430 \u041c\u0430\u0447\u0430"
    ],
    "name:deu_x_preferred":[
        "Ve\u013ek\u00e1 Ma\u010da"
    ],
    "name:eng_x_preferred":[
        "Ve\u013ek\u00e1 Ma\u010da"
    ],
    "name:epo_x_preferred":[
        "Ve\u013ek\u00e1 Ma\u010da"
    ],
    "name:eus_x_preferred":[
        "Ve\u013ek\u00e1 Ma\u010da"
    ],
    "name:fra_x_preferred":[
        "Ve\u013ek\u00e1 Ma\u010da"
    ],
    "name:gle_x_preferred":[
        "Ve\u013ek\u00e1 Ma\u010da"
    ],
    "name:hun_x_preferred":[
        "Nagym\u00e1cs\u00e9d"
    ],
    "name:ita_x_preferred":[
        "Ve\u013ek\u00e1 Ma\u010da"
    ],
    "name:msa_x_preferred":[
        "Ve\u013ek\u00e1 Ma\u010da"
    ],
    "name:nan_x_preferred":[
        "Ve\u013ek\u00e1 Ma\u010da"
    ],
    "name:nld_x_preferred":[
        "Ve\u013ek\u00e1 Ma\u010da"
    ],
    "name:pol_x_preferred":[
        "Ve\u013ek\u00e1 Ma\u010da"
    ],
    "name:por_x_preferred":[
        "Ve\u013ek\u00e1 Ma\u010da"
    ],
    "name:ron_x_preferred":[
        "Ve\u013ek\u00e1 Ma\u010da"
    ],
    "name:rus_x_preferred":[
        "\u0412\u0435\u043b\u044c\u043a\u0430 \u041c\u0430\u0447\u0430"
    ],
    "name:slk_x_preferred":[
        "Ve\u013ek\u00e1 Ma\u010da"
    ],
    "name:spa_x_preferred":[
        "Ve\u013ek\u00e1 Ma\u010da"
    ],
    "name:srp_x_preferred":[
        "\u0412\u0435\u0459\u043a\u0430 \u041c\u0430\u0447\u0430"
    ],
    "name:szl_x_preferred":[
        "Ve\u013ek\u00e1 Ma\u010da"
    ],
    "name:tat_x_preferred":[
        "\u0412\u0435\u043b\u044c\u043a\u0430 \u041c\u0430\u0447\u0430"
    ],
    "name:ukr_x_preferred":[
        "\u0412\u0435\u043b\u044c\u043a\u0430 \u041c\u0430\u0447\u0430"
    ],
    "name:und_x_variant":[
        "Nagy-M\u00e1cs\u00e9d"
    ],
    "name:war_x_preferred":[
        "Ve\u013ek\u00e1 Ma\u010da"
    ],
    "qs_pg:aaroncc":"SK",
    "qs_pg:gn_country":"SK",
    "qs_pg:gn_fcode":"PPL",
    "qs_pg:gn_pop":0,
    "qs_pg:name":"Vel\u0315k\u00e1 Ma\u010da",
    "qs_pg:name_adm0":"Slovensk\u00e1",
    "qs_pg:name_adm1":"Trnavsky",
    "qs_pg:photos_9k":1,
    "qs_pg:photos_9r":1,
    "qs_pg:photos_all":2,
    "qs_pg:photos_sr":0,
    "qs_pg:pop_sr":0,
    "qs_pg:qs_pg_placetype":"locality",
    "qs_pg:qs_pg_placetype_gp":"Town",
    "qs_pg:woe_adm0":23424877,
    "woe:adm0_id":23424877,
    "woe:name_adm0":"Slovensk\u00e1",
    "woe:name_adm1":"Trnavsky",
    "woe:placetype":"Town",
    "wof:name":"Vel\u0315k\u00e1 Ma\u010da",
    "wof:placetype":"locality"
},
  "geometry": {"coordinates":[17.68991,48.24146],"type":"Point"}
}