{
  "type": "Feature",
  "properties": {
    "gn:asciiname":"Liptovske Matiasovce",
    "gn:country_code":"SK",
    "gn:dem":706,
    "gn:feature_class":"P",
    "gn:feature_code":"PPL",
    "gn:name":"Liptovsk\u00e9 Matia\u0161ovce",
    "gn:population":0,
    "gn:timezone":"Europe/Bratislava",
    "iso:country":"SK",
    "name:cat_x_preferred":[
        "Liptovsk\u00e9 Matia\u0161ovce"
    ],
    "name:ces_x_preferred":[
        "Liptovsk\u00e9 Matia\u0161ovce"
    ],
    "name:epo_x_preferred":[
        "Liptovsk\u00e9 Matia\u0161ovce"
    ],
    "name:eus_x_preferred":[
        "Liptovsk\u00e9 Matia\u0161ovce"
    ],
    "name:fra_x_preferred":[
        "Liptovsk\u00e9 Matia\u0161ovce"
    ],
    "name:hun_x_preferred":[
        "Mattyas\u00f3c"
    ],
    "name:ita_x_preferred":[
        "Liptovsk\u00e9 Matia\u0161ovce"
    ],
    "name:msa_x_preferred":[
        "Liptovsk\u00e9 Matia\u0161ovce"
    ],
    "name:nld_x_preferred":[
        "Liptovsk\u00e9 Matia\u0161ovce"
    ],
    "name:pol_x_preferred":[
        "Liptowskie Matiaszowce"
    ],
    "name:ron_x_preferred":[
        "Liptovsk\u00e9 Matia\u0161ovce"
    ],
    "name:slk_x_preferred":[
        "Liptovsk\u00e9 Matia\u0161ovce"
    ],
    "name:spa_x_preferred":[
        "Liptovsk\u00e9 Matia\u0161ovce"
    ],
    "name:srp_x_preferred":[
        "\u041b\u0438\u043f\u0442\u043e\u0432\u0441\u043a\u0435 \u041c\u0430\u0442\u0458\u0430\u0448\u043e\u0432\u0446\u0435"
    ],
    "name:war_x_preferred":[
        "Liptovsk\u00e9 Matia\u0161ovce"
    ],
    "wof:name":"Liptovske Matiasovce",
    "wof:placetype":"locality"
},
  "geometry": {"coordinates":[19.56493,49.1606],"type":"Point"}
}