{
  "type": "Feature",
  "properties": {
    "gn:asciiname":"Liptovske Matiasovce",
    "gn:country_code":"SK",
    "gn:dem":706,
    "gn:feature_class":"P",
    "gn:feature_code":"PPL",
    "gn:name":"Liptovsk\u00e9 Matia\u0161ovce",
    "gn:population":0,
    "gn:timezone":"Europe/Bratislava",
    "iso:country":"SK",
    "wof:name":"Liptovske Matiasovce",
    "wof:placetype":"locality"
},
  "geometry": {"coordinates":[19.56493,49.1606],"type":"Point"}
}