{
  "type": "Feature",
  "properties": {
    "gn:admin1_code":"01",
    "gn:asciiname":"Stara Basta",
    "gn:country_code":"SK",
    "gn:dem":271,
    "gn:feature_class":"P",
    "gn:feature_code":"PPL",
    "gn:name":"Star\u00e1 Ba\u0161ta",
    "gn:population":0,
    "gn:timezone":"Europe/Bratislava",
    "iso:country":"SK",
    "name:und_x_variant":[
        "\u00d3-B\u00e1st",
        "Star\u00e1 Ba\u0161ta"
    ],
    "wof:name":"Stara Basta",
    "wof:placetype":"locality"
},
  "geometry": {"coordinates":[19.9446,48.18104],"type":"Point"}
}