{
  "type": "Feature",
  "properties": {
    "gn:admin1_code":"01",
    "gn:asciiname":"Stara Basta",
    "gn:country_code":"SK",
    "gn:dem":271,
    "gn:feature_class":"P",
    "gn:feature_code":"PPL",
    "gn:name":"Star\u00e1 Ba\u0161ta",
    "gn:population":0,
    "gn:timezone":"Europe/Bratislava",
    "iso:country":"SK",
    "name:cat_x_preferred":[
        "Star\u00e1 Ba\u0161ta"
    ],
    "name:ces_x_preferred":[
        "Star\u00e1 Ba\u0161ta"
    ],
    "name:epo_x_preferred":[
        "Star\u00e1 Ba\u0161ta"
    ],
    "name:eus_x_preferred":[
        "Star\u00e1 Ba\u0161ta"
    ],
    "name:fra_x_preferred":[
        "Star\u00e1 Ba\u0161ta"
    ],
    "name:hun_x_preferred":[
        "\u00d3b\u00e1st"
    ],
    "name:ita_x_preferred":[
        "Star\u00e1 Ba\u0161ta"
    ],
    "name:msa_x_preferred":[
        "Star\u00e1 Ba\u0161ta"
    ],
    "name:nld_x_preferred":[
        "Star\u00e1 Ba\u0161ta"
    ],
    "name:pol_x_preferred":[
        "Star\u00e1 Ba\u0161ta"
    ],
    "name:ron_x_preferred":[
        "Star\u00e1 Ba\u0161ta"
    ],
    "name:slk_x_preferred":[
        "Star\u00e1 Ba\u0161ta"
    ],
    "name:spa_x_preferred":[
        "Star\u00e1 Ba\u0161ta"
    ],
    "name:srp_x_preferred":[
        "\u0421\u0442\u0430\u0440\u0430 \u0411\u0430\u0448\u0442\u0430"
    ],
    "name:ukr_x_preferred":[
        "\u0421\u0442\u0430\u0440\u0430 \u0411\u0430\u0448\u0442\u0430"
    ],
    "name:und_x_variant":[
        "\u00d3-B\u00e1st",
        "Star\u00e1 Ba\u0161ta"
    ],
    "name:war_x_preferred":[
        "Star\u00e1 Ba\u0161ta"
    ],
    "wof:name":"Stara Basta",
    "wof:placetype":"locality"
},
  "geometry": {"coordinates":[19.9446,48.18104],"type":"Point"}
}