{
  "type": "Feature",
  "properties": {
    "gn:admin1_code":"03",
    "gn:asciiname":"Luckovce",
    "gn:country_code":"SK",
    "gn:dem":109,
    "gn:feature_class":"P",
    "gn:feature_code":"PPL",
    "gn:name":"Lu\u010dkovce",
    "gn:population":0,
    "gn:timezone":"Europe/Bratislava",
    "iso:country":"SK",
    "wof:name":"Luckovce",
    "wof:placetype":"locality"
},
  "geometry": {"coordinates":[21.79314,48.71873],"type":"Point"}
}