{
  "type": "Feature",
  "properties": {
    "gn:admin1_code":"04",
    "gn:asciiname":"Cankov",
    "gn:country_code":"SK",
    "gn:dem":164,
    "gn:feature_class":"P",
    "gn:feature_code":"PPL",
    "gn:name":"\u010cankov",
    "gn:population":0,
    "gn:timezone":"Europe/Bratislava",
    "iso:country":"SK",
    "name:hun_x_preferred":[
        "Cs\u00e1nk"
    ],
    "name:slk_x_preferred":[
        "\u010cankov"
    ],
    "wof:name":"Cankov",
    "wof:placetype":"locality"
},
  "geometry": {"coordinates":[18.70797,48.19536],"type":"Point"}
}