{
  "type": "Feature",
  "properties": {
    "gn:admin1_code":"01",
    "gn:asciiname":"Vysne Valice",
    "gn:country_code":"SK",
    "gn:dem":228,
    "gn:feature_class":"P",
    "gn:feature_code":"PPL",
    "gn:name":"Vy\u0161n\u00e9 Valice",
    "gn:population":0,
    "gn:timezone":"Europe/Bratislava",
    "iso:country":"SK",
    "name:und_x_variant":[
        "Fels\u0151-V\u00e1ly",
        "Vy\u0161nie Valice",
        "Vy\u0161n\u00ed Valice",
        "Valice",
        "Vy\u0161n\u00e9 Valice"
    ],
    "wof:name":"Vysne Valice",
    "wof:placetype":"locality"
},
  "geometry": {"coordinates":[20.18824,48.45774],"type":"Point"}
}