{
  "type": "Feature",
  "properties": {
    "gn:admin1_code":"01",
    "gn:asciiname":"Vysne Valice",
    "gn:country_code":"SK",
    "gn:dem":228,
    "gn:feature_class":"P",
    "gn:feature_code":"PPL",
    "gn:name":"Vy\u0161n\u00e9 Valice",
    "gn:population":0,
    "gn:timezone":"Europe/Bratislava",
    "iso:country":"SK",
    "name:cat_x_preferred":[
        "Vy\u0161n\u00e9 Valice"
    ],
    "name:epo_x_preferred":[
        "Vy\u0161n\u00e9 Valice"
    ],
    "name:eus_x_preferred":[
        "Vy\u0161n\u00e9 Valice"
    ],
    "name:fra_x_preferred":[
        "Vy\u0161n\u00e9 Valice"
    ],
    "name:hun_x_preferred":[
        "Fels\u0151v\u00e1ly"
    ],
    "name:ita_x_preferred":[
        "Vy\u0161n\u00e9 Valice"
    ],
    "name:msa_x_preferred":[
        "Vy\u0161n\u00e9 Valice"
    ],
    "name:nld_x_preferred":[
        "Vy\u0161n\u00e9 Valice"
    ],
    "name:pol_x_preferred":[
        "Vy\u0161n\u00e9 Valice"
    ],
    "name:ron_x_preferred":[
        "Vy\u0161n\u00e9 Valice"
    ],
    "name:slk_x_preferred":[
        "Vy\u0161n\u00e9 Valice"
    ],
    "name:spa_x_preferred":[
        "Vy\u0161n\u00e9 Valice"
    ],
    "name:srp_x_preferred":[
        "\u0412\u0438\u0448\u045a\u0435 \u0412\u0430\u043b\u0438\u0446\u0435"
    ],
    "name:ukr_x_preferred":[
        "\u0412\u0438\u0448\u043d\u0435 \u0412\u0430\u043b\u0456\u0446\u0435"
    ],
    "name:und_x_variant":[
        "Fels\u0151-V\u00e1ly",
        "Vy\u0161nie Valice",
        "Vy\u0161n\u00ed Valice",
        "Valice"
    ],
    "name:war_x_preferred":[
        "Vy\u0161n\u00e9 Valice"
    ],
    "wof:name":"Vysne Valice",
    "wof:placetype":"locality"
},
  "geometry": {"coordinates":[20.18824,48.45774],"type":"Point"}
}