{
  "type": "Feature",
  "properties": {
    "gn:admin1_code":"03",
    "gn:asciiname":"Vysny Klatov",
    "gn:country_code":"SK",
    "gn:dem":497,
    "gn:feature_class":"P",
    "gn:feature_code":"PPL",
    "gn:name":"Vy\u0161n\u00fd Kl\u00e1tov",
    "gn:population":0,
    "gn:timezone":"Europe/Bratislava",
    "iso:country":"SK",
    "name:cat_x_preferred":[
        "Vy\u0161n\u00fd Kl\u00e1tov"
    ],
    "name:deu_x_preferred":[
        "Vy\u0161n\u00fd Kl\u00e1tov"
    ],
    "name:epo_x_preferred":[
        "Vy\u0161n\u00fd Kl\u00e1tov"
    ],
    "name:eus_x_preferred":[
        "Vy\u0161n\u00fd Kl\u00e1tov"
    ],
    "name:fra_x_preferred":[
        "Vy\u0161n\u00fd Kl\u00e1tov"
    ],
    "name:hun_x_preferred":[
        "Fels\u0151t\u0151k\u00e9s"
    ],
    "name:ita_x_preferred":[
        "Vy\u0161n\u00fd Kl\u00e1tov"
    ],
    "name:msa_x_preferred":[
        "Vy\u0161n\u00fd Kl\u00e1tov"
    ],
    "name:nld_x_preferred":[
        "Vy\u0161n\u00fd Kl\u00e1tov"
    ],
    "name:pol_x_preferred":[
        "Vy\u0161n\u00fd Kl\u00e1tov"
    ],
    "name:ron_x_preferred":[
        "Vy\u0161n\u00fd Kl\u00e1tov"
    ],
    "name:slk_x_preferred":[
        "Vy\u0161n\u00fd Kl\u00e1tov"
    ],
    "name:spa_x_preferred":[
        "Vy\u0161n\u00fd Kl\u00e1tov"
    ],
    "name:srp_x_preferred":[
        "\u0412\u0438\u0448\u043d\u0438 \u041a\u043b\u0430\u0442\u043e\u0432"
    ],
    "name:ukr_x_preferred":[
        "\u0412\u0438\u0448\u043d\u0456\u0439 \u041a\u043b\u0430\u0442\u043e\u0432"
    ],
    "name:und_x_variant":[
        "Vy\u0161n\u00ed Tejke\u0161",
        "Vy\u0161n\u00fd Kl\u00e1tov"
    ],
    "name:war_x_preferred":[
        "Vy\u0161n\u00fd Kl\u00e1tov"
    ],
    "wof:name":"Vysny Klatov",
    "wof:placetype":"locality"
},
  "geometry": {"coordinates":[21.12456,48.74482],"type":"Point"}
}