{
  "type": "Feature",
  "properties": {
    "gn:admin1_code":"01",
    "gn:asciiname":"Selist'any",
    "gn:country_code":"SK",
    "gn:dem":146,
    "gn:feature_class":"P",
    "gn:feature_code":"PPL",
    "gn:name":"Seli\u0161t\u2019any",
    "gn:population":0,
    "gn:timezone":"Europe/Bratislava",
    "iso:country":"SK",
    "wof:name":"Selist'any",
    "wof:placetype":"locality"
},
  "geometry": {"coordinates":[19.33485,48.09306],"type":"Point"}
}