{
  "type": "Feature",
  "properties": {
    "gn:admin1_code":"01",
    "gn:asciiname":"Rimavske Janovce",
    "gn:country_code":"SK",
    "gn:dem":194,
    "gn:feature_class":"P",
    "gn:feature_code":"PPL",
    "gn:name":"Rimavsk\u00e9 Janovce",
    "gn:population":0,
    "gn:timezone":"Europe/Bratislava",
    "iso:country":"SK",
    "name:cat_x_preferred":[
        "Rimavsk\u00e9 Janovce"
    ],
    "name:deu_x_preferred":[
        "Rimavsk\u00e9 Janovce"
    ],
    "name:epo_x_preferred":[
        "Rimavsk\u00e9 Janovce"
    ],
    "name:eus_x_preferred":[
        "Rimavsk\u00e9 Janovce"
    ],
    "name:fra_x_preferred":[
        "Rimavsk\u00e9 Janovce"
    ],
    "name:hun_x_preferred":[
        "J\u00e1nosi"
    ],
    "name:ita_x_preferred":[
        "Rimavsk\u00e9 Janovce"
    ],
    "name:msa_x_preferred":[
        "Rimavsk\u00e9 Janovce"
    ],
    "name:nld_x_preferred":[
        "Rimavsk\u00e9 Janovce"
    ],
    "name:pol_x_preferred":[
        "Rimavsk\u00e9 Janovce"
    ],
    "name:ron_x_preferred":[
        "Rimavsk\u00e9 Janovce"
    ],
    "name:slk_x_preferred":[
        "Rimavsk\u00e9 Janovce"
    ],
    "name:spa_x_preferred":[
        "Rimavsk\u00e9 Janovce"
    ],
    "name:srp_x_preferred":[
        "\u0420\u0438\u043c\u0430\u0432\u0441\u043a\u0435 \u0408\u0430\u043d\u043e\u0432\u0446\u0435"
    ],
    "name:ukr_x_preferred":[
        "\u0420\u0456\u043c\u0430\u0432\u0441\u043a\u0435 \u042f\u043d\u043e\u0432\u0446\u0435"
    ],
    "name:und_x_variant":[
        "J\u00e1no\u0161ovce",
        "Rimavsk\u00e9 Janovce"
    ],
    "name:war_x_preferred":[
        "Rimavsk\u00e9 Janovce"
    ],
    "wof:name":"Rimavske Janovce",
    "wof:placetype":"locality"
},
  "geometry": {"coordinates":[20.0628,48.3417],"type":"Point"}
}