{
  "type": "Feature",
  "properties": {
    "gn:admin1_code":"01",
    "gn:asciiname":"Rimavske Janovce",
    "gn:country_code":"SK",
    "gn:dem":194,
    "gn:feature_class":"P",
    "gn:feature_code":"PPL",
    "gn:name":"Rimavsk\u00e9 Janovce",
    "gn:population":0,
    "gn:timezone":"Europe/Bratislava",
    "iso:country":"SK",
    "name:und_x_variant":[
        "J\u00e1no\u0161ovce",
        "Rimavsk\u00e9 Janovce"
    ],
    "wof:name":"Rimavske Janovce",
    "wof:placetype":"locality"
},
  "geometry": {"coordinates":[20.0628,48.3417],"type":"Point"}
}