{
  "type": "Feature",
  "properties": {
    "gn:admin1_code":"08",
    "gn:asciiname":"Necpaly",
    "gn:country_code":"SK",
    "gn:dem":495,
    "gn:feature_class":"P",
    "gn:feature_code":"PPL",
    "gn:name":"Necpaly",
    "gn:population":0,
    "gn:timezone":"Europe/Bratislava",
    "iso:country":"SK",
    "wof:name":"Necpaly",
    "wof:placetype":"locality"
},
  "geometry": {"coordinates":[18.96593,48.98713],"type":"Point"}
}