{
  "type": "Feature",
  "properties": {
    "gn:admin1_code":"08",
    "gn:asciiname":"Necpaly",
    "gn:country_code":"SK",
    "gn:dem":495,
    "gn:feature_class":"P",
    "gn:feature_code":"PPL",
    "gn:name":"Necpaly",
    "gn:population":0,
    "gn:timezone":"Europe/Bratislava",
    "iso:country":"SK",
    "name:cat_x_preferred":[
        "Necpaly"
    ],
    "name:ces_x_preferred":[
        "Necpaly"
    ],
    "name:deu_x_preferred":[
        "Necpaly"
    ],
    "name:epo_x_preferred":[
        "Necpaly"
    ],
    "name:eus_x_preferred":[
        "Necpaly"
    ],
    "name:fra_x_preferred":[
        "Necpaly"
    ],
    "name:hun_x_preferred":[
        "Necp\u00e1l"
    ],
    "name:ita_x_preferred":[
        "Necpaly"
    ],
    "name:msa_x_preferred":[
        "Necpaly"
    ],
    "name:nld_x_preferred":[
        "Necpaly"
    ],
    "name:pol_x_preferred":[
        "Necpaly"
    ],
    "name:ron_x_preferred":[
        "Necpaly"
    ],
    "name:slk_x_preferred":[
        "Necpaly"
    ],
    "name:spa_x_preferred":[
        "Necpaly"
    ],
    "name:srp_x_preferred":[
        "\u040a\u0435\u0446\u043f\u0430\u043b\u0438"
    ],
    "name:war_x_preferred":[
        "Necpaly"
    ],
    "wof:name":"Necpaly",
    "wof:placetype":"locality"
},
  "geometry": {"coordinates":[18.96593,48.98713],"type":"Point"}
}