{
  "type": "Feature",
  "properties": {
    "gn:admin1_code":"01",
    "gn:asciiname":"Nizny Petrovec",
    "gn:country_code":"SK",
    "gn:dem":212,
    "gn:feature_class":"P",
    "gn:feature_code":"PPL",
    "gn:name":"Ni\u017en\u00fd Petrovec",
    "gn:population":0,
    "gn:timezone":"Europe/Bratislava",
    "iso:country":"SK",
    "name:und_x_variant":[
        "Dvor Ni\u017en\u00fd Petrovec",
        "Ni\u017en\u00fd Petrovec"
    ],
    "wof:name":"Nizny Petrovec",
    "wof:placetype":"locality"
},
  "geometry": {"coordinates":[19.75331,48.38523],"type":"Point"}
}