{
  "type": "Feature",
  "properties": {
    "gn:admin1_code":"01",
    "gn:asciiname":"Rusniak",
    "gn:country_code":"SK",
    "gn:dem":434,
    "gn:feature_class":"P",
    "gn:feature_code":"PPL",
    "gn:name":"Rusniak",
    "gn:population":0,
    "gn:timezone":"Europe/Bratislava",
    "iso:country":"SK",
    "wof:name":"Rusniak",
    "wof:placetype":"locality"
},
  "geometry": {"coordinates":[19.11667000000001,48.36667],"type":"Point"}
}