{
  "type": "Feature",
  "properties": {
    "gn:country":"SK",
    "gn:fcode":"PPL",
    "gn:population":0,
    "iso:country":"SK",
    "qs_pg:aaroncc":"SK",
    "qs_pg:gn_country":"SK",
    "qs_pg:gn_fcode":"PPL",
    "qs_pg:gn_pop":0,
    "qs_pg:name":"Revi\u0161tsk\u00e9 Podz\u00e1m\u010die",
    "qs_pg:name_adm0":"Slovensk\u00e1",
    "qs_pg:name_adm1":"Banskobystricky",
    "qs_pg:photos_9k":1,
    "qs_pg:photos_9r":1,
    "qs_pg:photos_all":4,
    "qs_pg:photos_sr":0,
    "qs_pg:pop_sr":0,
    "qs_pg:qs_pg_placetype":"locality",
    "qs_pg:qs_pg_placetype_gp":"Town",
    "qs_pg:woe_adm0":23424877,
    "woe:adm0_id":23424877,
    "woe:name_adm0":"Slovensk\u00e1",
    "woe:name_adm1":"Banskobystricky",
    "woe:placetype":"Town",
    "wof:name":"Revi\u0161tsk\u00e9 Podz\u00e1m\u010die",
    "wof:placetype":"locality"
},
  "geometry": {"coordinates":[18.72005,48.52198],"type":"Point"}
}