{
  "type": "Feature",
  "properties": {
    "gn:admin1_code":"07",
    "gn:asciiname":"Kl'acany",
    "gn:country_code":"SK",
    "gn:dem":165,
    "gn:feature_class":"P",
    "gn:feature_code":"PPL",
    "gn:name":"K\u013ea\u010dany",
    "gn:population":0,
    "gn:timezone":"Europe/Bratislava",
    "iso:country":"SK",
    "name:cat_x_preferred":[
        "K\u013ea\u010dany"
    ],
    "name:ces_x_preferred":[
        "K\u013ea\u010dany"
    ],
    "name:deu_x_preferred":[
        "K\u013ea\u010dany"
    ],
    "name:epo_x_preferred":[
        "K\u013ea\u010dany"
    ],
    "name:eus_x_preferred":[
        "K\u013ea\u010dany"
    ],
    "name:fra_x_preferred":[
        "K\u013ea\u010dany"
    ],
    "name:hun_x_preferred":[
        "D\u00e9cskelecs\u00e9ny"
    ],
    "name:ita_x_preferred":[
        "K\u013ea\u010dany"
    ],
    "name:msa_x_preferred":[
        "K\u013ea\u010dany"
    ],
    "name:nld_x_preferred":[
        "K\u013ea\u010dany"
    ],
    "name:ron_x_preferred":[
        "K\u013ea\u010dany"
    ],
    "name:slk_x_preferred":[
        "K\u013ea\u010dany"
    ],
    "name:spa_x_preferred":[
        "K\u013ea\u010dany"
    ],
    "name:srp_x_preferred":[
        "\u041a\u0459\u0430\u0447\u0430\u043d\u0438"
    ],
    "name:ukr_x_preferred":[
        "\u041a\u043b\u044f\u0447\u0430\u043d\u0438"
    ],
    "name:war_x_preferred":[
        "K\u013ea\u010dany"
    ],
    "wof:name":"Kl'acany",
    "wof:placetype":"locality"
},
  "geometry": {"coordinates":[17.87121,48.38978],"type":"Point"}
}