{
  "type": "Feature",
  "properties": {
    "gn:admin1_code":"07",
    "gn:asciiname":"Kl'acany",
    "gn:country_code":"SK",
    "gn:dem":165,
    "gn:feature_class":"P",
    "gn:feature_code":"PPL",
    "gn:name":"K\u013ea\u010dany",
    "gn:population":0,
    "gn:timezone":"Europe/Bratislava",
    "iso:country":"SK",
    "name:und_x_variant":[
        "K\u013ea\u010dany"
    ],
    "wof:name":"Kl'acany",
    "wof:placetype":"locality"
},
  "geometry": {"coordinates":[17.87121,48.38978],"type":"Point"}
}