{
  "type": "Feature",
  "properties": {
    "gn:admin1_code":"05",
    "gn:asciiname":"Nova Polianka",
    "gn:country_code":"SK",
    "gn:dem":335,
    "gn:feature_class":"P",
    "gn:feature_code":"PPL",
    "gn:name":"Nov\u00e1 Polianka",
    "gn:population":0,
    "gn:timezone":"Europe/Bratislava",
    "iso:country":"SK",
    "name:und_x_variant":[
        "Merge\u0161ka",
        "Nov\u00e1 Polianka"
    ],
    "wof:name":"Nova Polianka",
    "wof:placetype":"locality"
},
  "geometry": {"coordinates":[21.61997,49.28746],"type":"Point"}
}