{
  "type": "Feature",
  "properties": {
    "gn:admin1_code":"04",
    "gn:asciiname":"Majtani",
    "gn:country_code":"SK",
    "gn:dem":378,
    "gn:feature_class":"P",
    "gn:feature_code":"PPL",
    "gn:name":"Majt\u00e1ni",
    "gn:population":0,
    "gn:timezone":"Europe/Bratislava",
    "iso:country":"SK",
    "wof:name":"Majtani",
    "wof:placetype":"locality"
},
  "geometry": {"coordinates":[17.53196,48.77631],"type":"Point"}
}