{
  "type": "Feature",
  "properties": {
    "gn:admin1_code":"01",
    "gn:asciiname":"Diel",
    "gn:country_code":"SK",
    "gn:dem":850,
    "gn:feature_class":"P",
    "gn:feature_code":"PPL",
    "gn:name":"Diel",
    "gn:population":0,
    "gn:timezone":"Europe/Bratislava",
    "iso:country":"SK",
    "wof:name":"Diel",
    "wof:placetype":"locality"
},
  "geometry": {"coordinates":[19.56667,48.53333],"type":"Point"}
}