{
  "type": "Feature",
  "properties": {
    "gn:asciiname":"Vitalisovce",
    "gn:country_code":"SK",
    "gn:dem":624,
    "gn:feature_class":"P",
    "gn:feature_code":"PPL",
    "gn:name":"Vit\u00e1li\u0161ovce",
    "gn:population":0,
    "gn:timezone":"Europe/Bratislava",
    "iso:country":"SK",
    "wof:name":"Vitalisovce",
    "wof:placetype":"locality"
},
  "geometry": {"coordinates":[19.65042,49.08843],"type":"Point"}
}