{
  "type": "Feature",
  "properties": {
    "gn:admin1_code":"01",
    "gn:asciiname":"Oremov Laz",
    "gn:country_code":"SK",
    "gn:dem":668,
    "gn:feature_class":"P",
    "gn:feature_code":"PPL",
    "gn:name":"Oremov Laz",
    "gn:population":0,
    "gn:timezone":"Europe/Bratislava",
    "iso:country":"SK",
    "wof:name":"Oremov Laz",
    "wof:placetype":"locality"
},
  "geometry": {"coordinates":[19.25583,48.39905],"type":"Point"}
}