{
  "type": "Feature",
  "properties": {
    "gn:admin1_code":"05",
    "gn:asciiname":"Tovarnianska Polianka",
    "gn:country_code":"SK",
    "gn:dem":133,
    "gn:feature_class":"P",
    "gn:feature_code":"PPL",
    "gn:name":"Tovarnianska Polianka",
    "gn:population":0,
    "gn:timezone":"Europe/Bratislava",
    "iso:country":"SK",
    "name:und_x_variant":[
        "Tovarnianska Po\u013eanka",
        "Tovarnianska Polianka"
    ],
    "wof:name":"Tovarnianska Polianka",
    "wof:placetype":"locality"
},
  "geometry": {"coordinates":[21.77257,48.89865],"type":"Point"}
}