{
  "type": "Feature",
  "properties": {
    "gn:admin1_code":"05",
    "gn:asciiname":"Tovarnianska Polianka",
    "gn:country_code":"SK",
    "gn:dem":133,
    "gn:feature_class":"P",
    "gn:feature_code":"PPL",
    "gn:name":"Tovarnianska Polianka",
    "gn:population":0,
    "gn:timezone":"Europe/Bratislava",
    "iso:country":"SK",
    "name:cat_x_preferred":[
        "Tovarnianska Polianka"
    ],
    "name:epo_x_preferred":[
        "Tovarnianska Polianka"
    ],
    "name:eus_x_preferred":[
        "Tovarnianska Polianka"
    ],
    "name:fra_x_preferred":[
        "Tovarnianska Polianka"
    ],
    "name:hun_x_preferred":[
        "Tavarnamez\u0151"
    ],
    "name:ita_x_preferred":[
        "Tovarnianska Polianka"
    ],
    "name:msa_x_preferred":[
        "Tovarnianska Polianka"
    ],
    "name:nld_x_preferred":[
        "Tovarnianska Polianka"
    ],
    "name:pol_x_preferred":[
        "Tovarnianska Polianka"
    ],
    "name:ron_x_preferred":[
        "Tovarnianska Polianka"
    ],
    "name:slk_x_preferred":[
        "Tovarnianska Polianka"
    ],
    "name:spa_x_preferred":[
        "Tovarnianska Polianka"
    ],
    "name:srp_x_preferred":[
        "\u0422\u043e\u0432\u0430\u0440\u045a\u0430\u043d\u0441\u043a\u0430 \u041f\u043e\u0459\u0430\u043d\u043a\u0430"
    ],
    "name:ukr_x_preferred":[
        "\u0422\u043e\u0432\u0430\u0440\u043d\u044f\u043d\u0441\u044c\u043a\u0430 \u041f\u043e\u043b\u044f\u043d\u043a\u0430"
    ],
    "name:und_x_variant":[
        "Tovarnianska Po\u013eanka"
    ],
    "name:war_x_preferred":[
        "Tovarnianska Polianka"
    ],
    "wof:name":"Tovarnianska Polianka",
    "wof:placetype":"locality"
},
  "geometry": {"coordinates":[21.77257,48.89865],"type":"Point"}
}