{
  "type": "Feature",
  "properties": {
    "gn:admin1_code":"04",
    "gn:asciiname":"Zubak",
    "gn:country_code":"SK",
    "gn:dem":432,
    "gn:feature_class":"P",
    "gn:feature_code":"PPL",
    "gn:name":"Zub\u00e1k",
    "gn:population":0,
    "gn:timezone":"Europe/Bratislava",
    "iso:country":"SK",
    "name:cat_x_preferred":[
        "Zub\u00e1k"
    ],
    "name:ces_x_preferred":[
        "Zub\u00e1k"
    ],
    "name:deu_x_preferred":[
        "Zub\u00e1k"
    ],
    "name:epo_x_preferred":[
        "Zub\u00e1k"
    ],
    "name:eus_x_preferred":[
        "Zub\u00e1k"
    ],
    "name:fra_x_preferred":[
        "Zub\u00e1k"
    ],
    "name:hun_x_preferred":[
        "Trencs\u00e9nfogas"
    ],
    "name:ita_x_preferred":[
        "Zub\u00e1k"
    ],
    "name:msa_x_preferred":[
        "Zub\u00e1k"
    ],
    "name:nld_x_preferred":[
        "Zub\u00e1k"
    ],
    "name:ron_x_preferred":[
        "Zub\u00e1k"
    ],
    "name:slk_x_preferred":[
        "Zub\u00e1k"
    ],
    "name:spa_x_preferred":[
        "Zub\u00e1k"
    ],
    "name:srp_x_preferred":[
        "\u0417\u0443\u0431\u0430\u043a"
    ],
    "name:und_x_variant":[
        "Zub\u00e1k"
    ],
    "name:war_x_preferred":[
        "Zub\u00e1k"
    ],
    "wof:name":"Zubak",
    "wof:placetype":"locality"
},
  "geometry": {"coordinates":[18.216,49.14973],"type":"Point"}
}