{
  "type": "Feature",
  "properties": {
    "gn:admin1_code":"05",
    "gn:asciiname":"Vysne Ladickovce",
    "gn:country_code":"SK",
    "gn:dem":243,
    "gn:feature_class":"P",
    "gn:feature_code":"PPL",
    "gn:name":"Vy\u0161n\u00e9 Ladi\u010dkovce",
    "gn:population":0,
    "gn:timezone":"Europe/Bratislava",
    "iso:country":"SK",
    "name:und_x_variant":[
        "Vy\u0161n\u00e9 Ladi\u010dkovce"
    ],
    "wof:name":"Vysne Ladickovce",
    "wof:placetype":"locality"
},
  "geometry": {"coordinates":[21.89155,49.03975],"type":"Point"}
}