{
  "type": "Feature",
  "properties": {
    "gn:admin1_code":"05",
    "gn:asciiname":"Vysne Ladickovce",
    "gn:country_code":"SK",
    "gn:dem":243,
    "gn:feature_class":"P",
    "gn:feature_code":"PPL",
    "gn:name":"Vy\u0161n\u00e9 Ladi\u010dkovce",
    "gn:population":0,
    "gn:timezone":"Europe/Bratislava",
    "iso:country":"SK",
    "name:cat_x_preferred":[
        "Vy\u0161n\u00e9 Ladi\u010dkovce"
    ],
    "name:ces_x_preferred":[
        "Vy\u0161n\u00e9 Ladi\u010dkovce"
    ],
    "name:epo_x_preferred":[
        "Vy\u0161n\u00e9 Ladi\u010dkovce"
    ],
    "name:eus_x_preferred":[
        "Vy\u0161n\u00e9 Ladi\u010dkovce"
    ],
    "name:fra_x_preferred":[
        "Vy\u0161n\u00e9 Ladi\u010dkovce"
    ],
    "name:hun_x_preferred":[
        "Fels\u0151l\u00e1szl\u00f3falva"
    ],
    "name:ita_x_preferred":[
        "Vy\u0161n\u00e9 Ladi\u010dkovce"
    ],
    "name:msa_x_preferred":[
        "Vy\u0161n\u00e9 Ladi\u010dkovce"
    ],
    "name:nld_x_preferred":[
        "Vy\u0161n\u00e9 Ladi\u010dkovce"
    ],
    "name:pol_x_preferred":[
        "Vy\u0161n\u00e9 Ladi\u010dkovce"
    ],
    "name:ron_x_preferred":[
        "Vy\u0161n\u00e9 Ladi\u010dkovce"
    ],
    "name:rue_x_preferred":[
        "\u0412\u044b\u0448\u043d\u0457 \u041b\u0430\u0434\u0456\u0447\u043a\u043e\u0432\u0446\u0457"
    ],
    "name:slk_x_preferred":[
        "Vy\u0161n\u00e9 Ladi\u010dkovce"
    ],
    "name:spa_x_preferred":[
        "Vy\u0161n\u00e9 Ladi\u010dkovce"
    ],
    "name:srp_x_preferred":[
        "\u0412\u0438\u0448\u045a\u0435 \u041b\u0430\u0434\u0438\u0447\u043a\u043e\u0432\u0446\u0435"
    ],
    "name:ukr_x_preferred":[
        "\u0412\u0438\u0448\u043d\u0456 \u041b\u0430\u0434\u0438\u0447\u043a\u043e\u0432\u0446\u0456"
    ],
    "name:und_x_variant":[
        "Vy\u0161n\u00e9 Ladi\u010dkovce"
    ],
    "name:war_x_preferred":[
        "Vy\u0161n\u00e9 Ladi\u010dkovce"
    ],
    "wof:name":"Vysne Ladickovce",
    "wof:placetype":"locality"
},
  "geometry": {"coordinates":[21.89155,49.03975],"type":"Point"}
}