{
  "type": "Feature",
  "properties": {
    "gn:admin1_code":"05",
    "gn:asciiname":"Havaj",
    "gn:country_code":"SK",
    "gn:dem":279,
    "gn:feature_class":"P",
    "gn:feature_code":"PPL",
    "gn:name":"Havaj",
    "gn:population":0,
    "gn:timezone":"Europe/Bratislava",
    "iso:country":"SK",
    "name:cat_x_preferred":[
        "Havaj"
    ],
    "name:ces_x_preferred":[
        "Havaj"
    ],
    "name:deu_x_preferred":[
        "Havaj"
    ],
    "name:epo_x_preferred":[
        "Havaj"
    ],
    "name:eus_x_preferred":[
        "Havaj"
    ],
    "name:fra_x_preferred":[
        "Havaj"
    ],
    "name:hun_x_preferred":[
        "Havaj"
    ],
    "name:ita_x_preferred":[
        "Havaj"
    ],
    "name:msa_x_preferred":[
        "Havaj"
    ],
    "name:nld_x_preferred":[
        "Havaj"
    ],
    "name:pol_x_preferred":[
        "Havaj"
    ],
    "name:ron_x_preferred":[
        "Havaj"
    ],
    "name:rue_x_preferred":[
        "\u0413\u0430\u0432\u0430\u0439"
    ],
    "name:slk_x_preferred":[
        "Havaj"
    ],
    "name:spa_x_preferred":[
        "Havaj"
    ],
    "name:srp_x_preferred":[
        "\u0425\u0430\u0432\u0430\u0458"
    ],
    "name:ukr_x_preferred":[
        "\u0413\u0430\u0432\u0430\u0439"
    ],
    "name:war_x_preferred":[
        "Havaj"
    ],
    "wof:name":"Havaj",
    "wof:placetype":"locality"
},
  "geometry": {"coordinates":[21.78665,49.25669],"type":"Point"}
}