{
  "type": "Feature",
  "properties": {
    "gn:admin1_code":"05",
    "gn:asciiname":"Havaj",
    "gn:country_code":"SK",
    "gn:dem":279,
    "gn:feature_class":"P",
    "gn:feature_code":"PPL",
    "gn:name":"Havaj",
    "gn:population":0,
    "gn:timezone":"Europe/Bratislava",
    "iso:country":"SK",
    "wof:name":"Havaj",
    "wof:placetype":"locality"
},
  "geometry": {"coordinates":[21.78665,49.25669],"type":"Point"}
}