{
  "type": "Feature",
  "properties": {
    "gn:admin1_code":"04",
    "gn:asciiname":"Prejta",
    "gn:country_code":"SK",
    "gn:dem":258,
    "gn:feature_class":"P",
    "gn:feature_code":"PPL",
    "gn:name":"Prejta",
    "gn:population":0,
    "gn:timezone":"Europe/Bratislava",
    "iso:country":"SK",
    "wof:name":"Prejta",
    "wof:placetype":"locality"
},
  "geometry": {"coordinates":[18.21001,48.97507],"type":"Point"}
}