{
  "type": "Feature",
  "properties": {
    "gn:admin1_code":"04",
    "gn:asciiname":"Ligasovci",
    "gn:country_code":"SK",
    "gn:dem":616,
    "gn:feature_class":"P",
    "gn:feature_code":"PPL",
    "gn:name":"Lig\u00e1sovci",
    "gn:population":0,
    "gn:timezone":"Europe/Bratislava",
    "iso:country":"SK",
    "wof:name":"Ligasovci",
    "wof:placetype":"locality"
},
  "geometry": {"coordinates":[18.31667,49.26667],"type":"Point"}
}