{
  "type": "Feature",
  "properties": {
    "gn:admin1_code":"03",
    "gn:asciiname":"Rolova Huta",
    "gn:country_code":"SK",
    "gn:dem":331,
    "gn:feature_class":"P",
    "gn:feature_code":"PPL",
    "gn:name":"Rolova Huta",
    "gn:population":0,
    "gn:timezone":"Europe/Bratislava",
    "iso:country":"SK",
    "wof:name":"Rolova Huta",
    "wof:placetype":"locality"
},
  "geometry": {"coordinates":[21.04088,48.88955],"type":"Point"}
}