{
  "type": "Feature",
  "properties": {
    "gn:admin1_code":"07",
    "gn:asciiname":"Etreove Kracany",
    "gn:country_code":"SK",
    "gn:dem":117,
    "gn:feature_class":"P",
    "gn:feature_code":"PPL",
    "gn:name":"Etreove Kra\u010dany",
    "gn:population":0,
    "gn:timezone":"Europe/Bratislava",
    "iso:country":"SK",
    "name:und_x_variant":[
        "Etre-Karcsa",
        "Etreove Kra\u010dany"
    ],
    "wof:name":"Etreove Kracany",
    "wof:placetype":"locality"
},
  "geometry": {"coordinates":[17.55,47.98333],"type":"Point"}
}