{
  "type": "Feature",
  "properties": {
    "gn:admin1_code":"05",
    "gn:asciiname":"Nizny Orlik",
    "gn:country_code":"SK",
    "gn:dem":252,
    "gn:feature_class":"P",
    "gn:feature_code":"PPL",
    "gn:name":"Ni\u017en\u00fd Orl\u00edk",
    "gn:population":0,
    "gn:timezone":"Europe/Bratislava",
    "iso:country":"SK",
    "name:und_x_variant":[
        "Ni\u017enyj Orlich",
        "Ni\u017en\u00ed Orl\u00edk",
        "Ni\u017en\u00fd Orl\u00edk"
    ],
    "wof:name":"Nizny Orlik",
    "wof:placetype":"locality"
},
  "geometry": {"coordinates":[21.52861,49.33316],"type":"Point"}
}