{
  "type": "Feature",
  "properties": {
    "gn:admin1_code":"05",
    "gn:asciiname":"Nizny Orlik",
    "gn:country_code":"SK",
    "gn:dem":252,
    "gn:feature_class":"P",
    "gn:feature_code":"PPL",
    "gn:name":"Ni\u017en\u00fd Orl\u00edk",
    "gn:population":0,
    "gn:timezone":"Europe/Bratislava",
    "iso:country":"SK",
    "name:cat_x_preferred":[
        "Ni\u017en\u00fd Orl\u00edk"
    ],
    "name:epo_x_preferred":[
        "Ni\u017en\u00fd Orl\u00edk"
    ],
    "name:eus_x_preferred":[
        "Ni\u017en\u00fd Orl\u00edk"
    ],
    "name:fra_x_preferred":[
        "Ni\u017en\u00fd Orl\u00edk"
    ],
    "name:hun_x_preferred":[
        "Als\u00f3odor"
    ],
    "name:ita_x_preferred":[
        "Ni\u017en\u00fd Orl\u00edk"
    ],
    "name:msa_x_preferred":[
        "Ni\u017en\u00fd Orl\u00edk"
    ],
    "name:nld_x_preferred":[
        "Ni\u017en\u00fd Orl\u00edk"
    ],
    "name:pol_x_preferred":[
        "Ni\u017en\u00fd Orl\u00edk"
    ],
    "name:ron_x_preferred":[
        "Ni\u017en\u00fd Orl\u00edk"
    ],
    "name:rue_x_preferred":[
        "\u041d\u0438\u0436\u043d\u0457\u0439 \u0412\u0435\u0440\u043b\u0456\u0445"
    ],
    "name:slk_x_preferred":[
        "Ni\u017en\u00fd Orl\u00edk"
    ],
    "name:spa_x_preferred":[
        "Ni\u017en\u00fd Orl\u00edk"
    ],
    "name:srp_x_preferred":[
        "\u040a\u0438\u0436\u043d\u0438 \u041e\u0440\u043b\u0438\u043a"
    ],
    "name:ukr_x_preferred":[
        "\u041d\u0438\u0436\u043d\u0456\u0439 \u041e\u0440\u043b\u0438\u043a"
    ],
    "name:und_x_variant":[
        "Ni\u017enyj Orlich",
        "Ni\u017en\u00ed Orl\u00edk",
        "Ni\u017en\u00fd Orl\u00edk"
    ],
    "name:war_x_preferred":[
        "Ni\u017en\u00fd Orl\u00edk"
    ],
    "wof:name":"Nizny Orlik",
    "wof:placetype":"locality"
},
  "geometry": {"coordinates":[21.52861,49.33316],"type":"Point"}
}