{
  "type": "Feature",
  "properties": {
    "gn:asciiname":"Hrabova Roztoka",
    "gn:country_code":"SK",
    "gn:dem":396,
    "gn:feature_class":"P",
    "gn:feature_code":"PPL",
    "gn:name":"Hrabov\u00e1 Roztoka",
    "gn:population":0,
    "gn:timezone":"Europe/Bratislava",
    "iso:country":"SK",
    "wof:name":"Hrabova Roztoka",
    "wof:placetype":"locality"
},
  "geometry": {"coordinates":[22.30036,48.8786],"type":"Point"}
}