{
  "type": "Feature",
  "properties": {
    "gn:asciiname":"Hrabova Roztoka",
    "gn:country_code":"SK",
    "gn:dem":396,
    "gn:feature_class":"P",
    "gn:feature_code":"PPL",
    "gn:name":"Hrabov\u00e1 Roztoka",
    "gn:population":0,
    "gn:timezone":"Europe/Bratislava",
    "iso:country":"SK",
    "name:cat_x_preferred":[
        "Hrabov\u00e1 Roztoka"
    ],
    "name:ces_x_preferred":[
        "Hrabov\u00e1 Roztoka"
    ],
    "name:epo_x_preferred":[
        "Hrabov\u00e1 Roztoka"
    ],
    "name:eus_x_preferred":[
        "Hrabov\u00e1 Roztoka"
    ],
    "name:fas_x_preferred":[
        "\u0647\u0631\u0627\u0628\u0648\u0648\u0627 \u0631\u0648\u0632\u062a\u0648\u06a9\u0627"
    ],
    "name:fra_x_preferred":[
        "Hrabov\u00e1 Roztoka"
    ],
    "name:hun_x_preferred":[
        "Kisgerebly\u00e9s"
    ],
    "name:ita_x_preferred":[
        "Hrabov\u00e1 Roztoka"
    ],
    "name:msa_x_preferred":[
        "Hrabov\u00e1 Roztoka"
    ],
    "name:nld_x_preferred":[
        "Hrabov\u00e1 Roztoka"
    ],
    "name:pol_x_preferred":[
        "Hrabov\u00e1 Roztoka"
    ],
    "name:ron_x_preferred":[
        "Hrabov\u00e1 Roztoka"
    ],
    "name:rue_x_preferred":[
        "\u0413\u0440\u0430\u0431\u043e\u0432\u0430 \u0420\u043e\u0437\u0442\u043e\u043a\u0430"
    ],
    "name:slk_x_preferred":[
        "Hrabov\u00e1 Roztoka"
    ],
    "name:spa_x_preferred":[
        "Hrabov\u00e1 Roztoka"
    ],
    "name:srp_x_preferred":[
        "\u0425\u0440\u0430\u0431\u043e\u0432\u0430 \u0420\u043e\u0441\u0442\u043e\u043a\u0430"
    ],
    "name:ukr_x_preferred":[
        "\u0413\u0440\u0430\u0431\u043e\u0432\u0430 \u0420\u043e\u0437\u0442\u043e\u043a\u0430"
    ],
    "name:war_x_preferred":[
        "Hrabov\u00e1 Roztoka"
    ],
    "wof:name":"Hrabova Roztoka",
    "wof:placetype":"locality"
},
  "geometry": {"coordinates":[22.30036,48.8786],"type":"Point"}
}