{
  "type": "Feature",
  "properties": {
    "iso:country":"SK",
    "name:eng_x_preferred":[
        "Gastanovy hajik"
    ],
    "name:slk_x_preferred":[
        "Ga\u0161tanov\u00fd h\u00e1jik"
    ],
    "wof:name":"Gastanovy hajik",
    "wof:placetype":"neighbourhood"
},
  "geometry": {"coordinates":[17.13287607600371,48.18551459854649],"type":"Point"}
}