{
  "type": "Feature",
  "properties": {
    "gn:admin1_code":"01",
    "gn:asciiname":"Stozok",
    "gn:country_code":"SK",
    "gn:dem":397,
    "gn:feature_class":"P",
    "gn:feature_code":"PPL",
    "gn:name":"Sto\u017eok",
    "gn:population":0,
    "gn:timezone":"Europe/Bratislava",
    "iso:country":"SK",
    "name:cat_x_preferred":[
        "Sto\u017eok"
    ],
    "name:ces_x_preferred":[
        "Sto\u017eok"
    ],
    "name:deu_x_preferred":[
        "Sto\u017eok"
    ],
    "name:epo_x_preferred":[
        "Sto\u017eok"
    ],
    "name:eus_x_preferred":[
        "Sto\u017eok"
    ],
    "name:fra_x_preferred":[
        "Sto\u017eok"
    ],
    "name:hun_x_preferred":[
        "Dombsz\u00f6g"
    ],
    "name:ita_x_preferred":[
        "Sto\u017eok"
    ],
    "name:msa_x_preferred":[
        "Sto\u017eok"
    ],
    "name:nld_x_preferred":[
        "Sto\u017eok"
    ],
    "name:pol_x_preferred":[
        "Sto\u017eok"
    ],
    "name:ron_x_preferred":[
        "Sto\u017eok"
    ],
    "name:slk_x_preferred":[
        "Sto\u017eok"
    ],
    "name:spa_x_preferred":[
        "Sto\u017eok"
    ],
    "name:srp_x_preferred":[
        "\u0421\u0442\u043e\u0436\u043e\u043a"
    ],
    "name:ukr_x_preferred":[
        "\u0421\u0442\u043e\u0436\u043e\u043a"
    ],
    "name:und_x_variant":[
        "Sto\u017eok"
    ],
    "name:war_x_preferred":[
        "Sto\u017eok"
    ],
    "wof:name":"Stozok",
    "wof:placetype":"locality"
},
  "geometry": {"coordinates":[19.35795,48.52916],"type":"Point"}
}