{
  "type": "Feature",
  "properties": {
    "gn:admin1_code":"04",
    "gn:asciiname":"Dolne Lelovce",
    "gn:country_code":"SK",
    "gn:dem":247,
    "gn:feature_class":"P",
    "gn:feature_code":"PPL",
    "gn:name":"Doln\u00e9 Lelovce",
    "gn:population":0,
    "gn:timezone":"Europe/Bratislava",
    "iso:country":"SK",
    "wof:name":"Dolne Lelovce",
    "wof:placetype":"locality"
},
  "geometry": {"coordinates":[18.51093,48.69416],"type":"Point"}
}