{
  "type": "Feature",
  "properties": {
    "gn:admin1_code":"04",
    "gn:asciiname":"Male Bosany",
    "gn:country_code":"SK",
    "gn:dem":212,
    "gn:feature_class":"P",
    "gn:feature_code":"PPL",
    "gn:name":"Mal\u00e9 Bo\u0161any",
    "gn:population":0,
    "gn:timezone":"Europe/Bratislava",
    "iso:country":"SK",
    "name:und_x_variant":[
        "Mal\u00e9 Bo\u0161any"
    ],
    "wof:name":"Male Bosany",
    "wof:placetype":"locality"
},
  "geometry": {"coordinates":[18.28333,48.58333],"type":"Point"}
}