{
  "type": "Feature",
  "properties": {
    "gn:admin1_code":"05",
    "gn:asciiname":"Nizne Raslavice",
    "gn:country_code":"SK",
    "gn:dem":316,
    "gn:feature_class":"P",
    "gn:feature_code":"PPL",
    "gn:name":"Ni\u017en\u00e9 Raslavice",
    "gn:population":0,
    "gn:timezone":"Europe/Bratislava",
    "iso:country":"SK",
    "name:und_x_variant":[
        "Uhorsk\u00e9 Raslavice",
        "Ni\u017en\u00e9 Raslavice"
    ],
    "wof:name":"Nizne Raslavice",
    "wof:placetype":"locality"
},
  "geometry": {"coordinates":[21.32587,49.14919],"type":"Point"}
}