{
  "type": "Feature",
  "properties": {
    "gn:admin1_code":"07",
    "gn:asciiname":"Majericky",
    "gn:country_code":"SK",
    "gn:dem":281,
    "gn:feature_class":"P",
    "gn:feature_code":"PPL",
    "gn:name":"Majer\u00ed\u010dky",
    "gn:population":0,
    "gn:timezone":"Europe/Bratislava",
    "iso:country":"SK",
    "wof:name":"Majericky",
    "wof:placetype":"locality"
},
  "geometry": {"coordinates":[17.4338,48.73864],"type":"Point"}
}