{
  "type": "Feature",
  "properties": {
    "gn:admin1_code":"05",
    "gn:asciiname":"Rokytovce",
    "gn:country_code":"SK",
    "gn:dem":335,
    "gn:feature_class":"P",
    "gn:feature_code":"PPL",
    "gn:name":"Rokytovce",
    "gn:population":0,
    "gn:timezone":"Europe/Bratislava",
    "iso:country":"SK",
    "wof:name":"Rokytovce",
    "wof:placetype":"locality"
},
  "geometry": {"coordinates":[21.87751,49.26141],"type":"Point"}
}