{
  "type": "Feature",
  "properties": {
    "gn:admin1_code":"05",
    "gn:asciiname":"Rokytovce",
    "gn:country_code":"SK",
    "gn:dem":335,
    "gn:feature_class":"P",
    "gn:feature_code":"PPL",
    "gn:name":"Rokytovce",
    "gn:population":0,
    "gn:timezone":"Europe/Bratislava",
    "iso:country":"SK",
    "name:cat_x_preferred":[
        "Rokytovce"
    ],
    "name:ces_x_preferred":[
        "Rokytovce"
    ],
    "name:epo_x_preferred":[
        "Rokytovce"
    ],
    "name:eus_x_preferred":[
        "Rokytovce"
    ],
    "name:fra_x_preferred":[
        "Rokytovce"
    ],
    "name:hun_x_preferred":[
        "Rokit\u00f3c"
    ],
    "name:ita_x_preferred":[
        "Rokytovce"
    ],
    "name:msa_x_preferred":[
        "Rokytovce"
    ],
    "name:nld_x_preferred":[
        "Rokytovce"
    ],
    "name:pol_x_preferred":[
        "Rokytovce"
    ],
    "name:ron_x_preferred":[
        "Rokytovce"
    ],
    "name:rue_x_preferred":[
        "\u0420\u043e\u043a\u044b\u0442\u0456\u0432\u0446\u0457"
    ],
    "name:slk_x_preferred":[
        "Rokytovce"
    ],
    "name:spa_x_preferred":[
        "Rokytovce"
    ],
    "name:srp_x_preferred":[
        "\u0420\u043e\u043a\u0438\u0442\u043e\u0432\u0446\u0435"
    ],
    "name:ukr_x_preferred":[
        "\u0420\u043e\u043a\u0438\u0442\u0456\u0432\u0446\u0456"
    ],
    "name:war_x_preferred":[
        "Rokytovce"
    ],
    "wof:name":"Rokytovce",
    "wof:placetype":"locality"
},
  "geometry": {"coordinates":[21.87751,49.26141],"type":"Point"}
}