{
  "type": "Feature",
  "properties": {
    "iso:country":"SK",
    "name:eng_x_preferred":[
        "Haje"
    ],
    "name:slk_x_preferred":[
        "H\u00e1je"
    ],
    "wof:name":"Haje",
    "wof:placetype":"neighbourhood"
},
  "geometry": {"coordinates":[17.12194520966863,48.12304615481125],"type":"Point"}
}