{
  "type": "Feature",
  "properties": {
    "gn:admin1_code":"04",
    "gn:asciiname":"Michalsky Majer",
    "gn:country_code":"SK",
    "gn:dem":175,
    "gn:feature_class":"P",
    "gn:feature_code":"PPL",
    "gn:name":"Michalsk\u00fd Majer",
    "gn:population":0,
    "gn:timezone":"Europe/Bratislava",
    "iso:country":"SK",
    "name:und_x_variant":[
        "Michalsk\u00fd Dvor",
        "Michalsk\u00fd Majer"
    ],
    "wof:name":"Michalsky Majer",
    "wof:placetype":"locality"
},
  "geometry": {"coordinates":[18.25,48.18333],"type":"Point"}
}