{
  "type": "Feature",
  "properties": {
    "gn:admin1_code":"05",
    "gn:asciiname":"Hagy",
    "gn:country_code":"SK",
    "gn:dem":706,
    "gn:feature_class":"P",
    "gn:feature_code":"PPL",
    "gn:name":"H\u00e1gy",
    "gn:population":0,
    "gn:timezone":"Europe/Bratislava",
    "iso:country":"SK",
    "wof:name":"Hagy",
    "wof:placetype":"locality"
},
  "geometry": {"coordinates":[20.37588,49.30207],"type":"Point"}
}