{
  "type": "Feature",
  "properties": {
    "gn:admin1_code":"01",
    "gn:asciiname":"Dolne Rykyncice",
    "gn:country_code":"SK",
    "gn:dem":166,
    "gn:feature_class":"P",
    "gn:feature_code":"PPL",
    "gn:name":"Doln\u00e9 Rykyn\u010dice",
    "gn:population":0,
    "gn:timezone":"Europe/Bratislava",
    "iso:country":"SK",
    "name:hun_x_preferred":[
        "Als\u00f3rakonca"
    ],
    "name:slk_x_preferred":[
        "Doln\u00e9 Rykyn\u010dice"
    ],
    "wof:name":"Dolne Rykyncice",
    "wof:placetype":"locality"
},
  "geometry": {"coordinates":[18.97089,48.19933],"type":"Point"}
}