{
  "type": "Feature",
  "properties": {
    "gn:admin1_code":"07",
    "gn:asciiname":"Izapska samota",
    "gn:country_code":"SK",
    "gn:dem":110,
    "gn:feature_class":"P",
    "gn:feature_code":"PPL",
    "gn:name":"I\u017eapsk\u00e1 samota",
    "gn:population":0,
    "gn:timezone":"Europe/Bratislava",
    "iso:country":"SK",
    "name:hun_x_preferred":[
        "Izsapimajor"
    ],
    "wof:name":"Izapska samota",
    "wof:placetype":"locality"
},
  "geometry": {"coordinates":[17.71391000000001,47.85925],"type":"Point"}
}