{
  "type": "Feature",
  "properties": {
    "gn:admin1_code":"01",
    "gn:asciiname":"Brezina",
    "gn:country_code":"SK",
    "gn:dem":384,
    "gn:feature_class":"P",
    "gn:feature_code":"PPL",
    "gn:name":"Brezina",
    "gn:population":0,
    "gn:timezone":"Europe/Bratislava",
    "iso:country":"SK",
    "name:und_x_variant":[
        "Dvor Brezina",
        "Brezina"
    ],
    "wof:name":"Brezina",
    "wof:placetype":"locality"
},
  "geometry": {"coordinates":[18.75897,48.37747],"type":"Point"}
}