{
  "type": "Feature",
  "properties": {
    "iso:country":"SK",
    "name:cat_x_preferred":[
        "Divina"
    ],
    "name:ces_x_preferred":[
        "Divina"
    ],
    "name:che_x_preferred":[
        "\u0414\u0438\u0432\u0438\u043d\u0430"
    ],
    "name:deu_x_preferred":[
        "Divina"
    ],
    "name:eng_x_preferred":[
        "Divina"
    ],
    "name:epo_x_preferred":[
        "Divina"
    ],
    "name:eus_x_preferred":[
        "Divina"
    ],
    "name:fra_x_preferred":[
        "Divina"
    ],
    "name:gle_x_preferred":[
        "Divina"
    ],
    "name:hbs_x_preferred":[
        "Divina"
    ],
    "name:hun_x_preferred":[
        "Nagydiv\u00e9ny"
    ],
    "name:ita_x_preferred":[
        "Divina"
    ],
    "name:msa_x_preferred":[
        "Divina"
    ],
    "name:nan_x_preferred":[
        "Divina"
    ],
    "name:nld_x_preferred":[
        "Divina"
    ],
    "name:pol_x_preferred":[
        "Divina"
    ],
    "name:por_x_preferred":[
        "Divina"
    ],
    "name:ron_x_preferred":[
        "Divina"
    ],
    "name:slk_x_preferred":[
        "Divina"
    ],
    "name:spa_x_preferred":[
        "Divina"
    ],
    "name:srp_x_preferred":[
        "\u0414\u0438\u0432\u0438\u043d\u0430"
    ],
    "name:tat_x_preferred":[
        "\u0414\u0438\u0432\u0438\u043d\u0430"
    ],
    "name:ukr_x_preferred":[
        "\u0414\u0456\u0432\u0456\u043d\u0430"
    ],
    "name:war_x_preferred":[
        "Divina"
    ],
    "name:zho_min_nan_x_preferred":[
        "Divina"
    ],
    "qs:a0":"Slovensko",
    "qs:a1":"*\u017dilinsk\u00fd kraj",
    "qs:a1r":"0",
    "qs:a2":"\u017dilina",
    "qs:adm0":"Slovensko",
    "qs:la_lc":"*",
    "qs:level":"locality",
    "qs:loc":"Divina",
    "qs:loc_alt":"Divina",
    "qs:pop":0,
    "qs:type":"buffered point",
    "wd:wordcount":123,
    "wof:lang":[
        "unk"
    ],
    "wof:name":"Divina",
    "wof:placetype":"locality"
},
  "geometry": {"coordinates":[18.696268,49.288124],"type":"Point"}
}