{
  "type": "Feature",
  "properties": {
    "gn:admin1_code":"01",
    "gn:asciiname":"Kysla",
    "gn:country_code":"SK",
    "gn:dem":662,
    "gn:feature_class":"P",
    "gn:feature_code":"PPL",
    "gn:name":"Kysl\u00e1",
    "gn:population":0,
    "gn:timezone":"Europe/Bratislava",
    "iso:country":"SK",
    "wof:name":"Kysla",
    "wof:placetype":"locality"
},
  "geometry": {"coordinates":[19.2755,48.8485],"type":"Point"}
}