{
  "type": "Feature",
  "properties": {
    "gn:admin1_code":"05",
    "gn:asciiname":"Licartovce",
    "gn:country_code":"SK",
    "gn:dem":216,
    "gn:feature_class":"P",
    "gn:feature_code":"PPL",
    "gn:name":"Li\u010dartovce",
    "gn:population":0,
    "gn:timezone":"Europe/Bratislava",
    "iso:country":"SK",
    "name:cat_x_preferred":[
        "Li\u010dartovce"
    ],
    "name:ces_x_preferred":[
        "Li\u010dartovce"
    ],
    "name:deu_x_preferred":[
        "Li\u010dartovce"
    ],
    "name:epo_x_preferred":[
        "Li\u010dartovce"
    ],
    "name:eus_x_preferred":[
        "Li\u010dartovce"
    ],
    "name:fra_x_preferred":[
        "Li\u010dartovce"
    ],
    "name:hun_x_preferred":[
        "Lics\u00e9rd"
    ],
    "name:ita_x_preferred":[
        "Li\u010dartovce"
    ],
    "name:lit_x_preferred":[
        "Li\u010dartovc\u0117s"
    ],
    "name:msa_x_preferred":[
        "Li\u010dartovce"
    ],
    "name:nld_x_preferred":[
        "Li\u010dartovce"
    ],
    "name:pol_x_preferred":[
        "Li\u010dartovce"
    ],
    "name:ron_x_preferred":[
        "Li\u010dartovce"
    ],
    "name:rue_x_preferred":[
        "\u041b\u0456\u0447\u0430\u0440\u0442\u043e\u0432\u0446\u0435"
    ],
    "name:slk_x_preferred":[
        "Li\u010dartovce"
    ],
    "name:spa_x_preferred":[
        "Li\u010dartovce"
    ],
    "name:srp_x_preferred":[
        "\u041b\u0438\u0447\u0430\u0440\u0442\u043e\u0432\u0446\u0435"
    ],
    "name:ukr_x_preferred":[
        "\u041b\u0438\u0447\u0430\u0440\u0442\u043e\u0432\u0446\u0435"
    ],
    "name:war_x_preferred":[
        "Li\u010dartovce"
    ],
    "wof:name":"Licartovce",
    "wof:placetype":"locality"
},
  "geometry": {"coordinates":[21.2467,48.8761],"type":"Point"}
}