{
  "type": "Feature",
  "properties": {
    "gn:admin1_code":"05",
    "gn:asciiname":"Licartovce",
    "gn:country_code":"SK",
    "gn:dem":216,
    "gn:feature_class":"P",
    "gn:feature_code":"PPL",
    "gn:name":"Li\u010dartovce",
    "gn:population":0,
    "gn:timezone":"Europe/Bratislava",
    "iso:country":"SK",
    "name:und_x_variant":[
        "Li\u010dartovce"
    ],
    "wof:name":"Licartovce",
    "wof:placetype":"locality"
},
  "geometry": {"coordinates":[21.2467,48.8761],"type":"Point"}
}