{
  "type": "Feature",
  "properties": {
    "iso:country":"SK",
    "qs_pg:aaroncc":"SK",
    "qs_pg:name":"Hronsky Benadik",
    "qs_pg:name_adm0":"Slovensk\u00e1",
    "qs_pg:name_adm1":"Banskobystricky",
    "qs_pg:photos":14,
    "qs_pg:photos_1k":3,
    "qs_pg:photos_9k":1,
    "qs_pg:photos_9r":1,
    "qs_pg:photos_all":14,
    "qs_pg:photos_sr":1,
    "qs_pg:pop_sr":0,
    "qs_pg:qs_pg_placetype":"localadmin",
    "qs_pg:qs_pg_placetype_gp":"LocalAdmin",
    "qs_pg:woe_adm0":23424877,
    "woe:adm0_id":23424877,
    "woe:name_adm0":"Slovensk\u00e1",
    "woe:name_adm1":"Banskobystricky",
    "woe:placetype":"LocalAdmin",
    "wof:name":"Hronsky Benadik",
    "wof:placetype":"localadmin"
},
  "geometry": {"coordinates":[18.56059,48.341166],"type":"Point"}
}