{
  "type": "Feature",
  "properties": {
    "iso:country":"SK",
    "name:eng_x_preferred":[
        "Dev\u00ednske Jazero"
    ],
    "name:slk_x_preferred":[
        "Dev\u00ednske Jazero"
    ],
    "wof:name":"Dev\u00ednske Jazero",
    "wof:placetype":"neighbourhood"
},
  "geometry": {"coordinates":[16.95939293567707,48.25080520189208],"type":"Point"}
}