{
  "type": "Feature",
  "properties": {
    "gn:country":"SK",
    "gn:fcode":"PPL",
    "gn:population":938,
    "iso:country":"SK",
    "name:bel_x_preferred":[
        "\u0411\u0435\u0442\u043b\u044c\u044f\u0440"
    ],
    "name:bul_x_preferred":[
        "\u0411\u0435\u0442\u043b\u0438\u0430\u0440"
    ],
    "name:cat_x_preferred":[
        "Betliar"
    ],
    "name:ceb_x_preferred":[
        "Betliar"
    ],
    "name:ces_x_preferred":[
        "Betliar"
    ],
    "name:deu_x_preferred":[
        "Betliar"
    ],
    "name:eng_x_preferred":[
        "Betliar"
    ],
    "name:epo_x_preferred":[
        "Betliar"
    ],
    "name:eus_x_preferred":[
        "Betliar"
    ],
    "name:fra_x_preferred":[
        "Betliar"
    ],
    "name:gle_x_preferred":[
        "Betliar"
    ],
    "name:hun_x_preferred":[
        "Betl\u00e9r"
    ],
    "name:ita_x_preferred":[
        "Betliar"
    ],
    "name:msa_x_preferred":[
        "Betliar"
    ],
    "name:nan_x_preferred":[
        "Betliar"
    ],
    "name:nld_x_preferred":[
        "Betliar"
    ],
    "name:nob_x_preferred":[
        "Betliar"
    ],
    "name:pol_x_preferred":[
        "Betliar"
    ],
    "name:por_x_preferred":[
        "Betliar"
    ],
    "name:ron_x_preferred":[
        "Betliar"
    ],
    "name:rus_x_preferred":[
        "\u0411\u0435\u0442\u043b\u044c\u044f\u0440"
    ],
    "name:slk_x_preferred":[
        "Betliar"
    ],
    "name:spa_x_preferred":[
        "Betliar"
    ],
    "name:srp_x_preferred":[
        "\u0411\u0435\u0442\u0459\u0430\u0440"
    ],
    "name:ukr_x_preferred":[
        "\u0411\u0435\u0442\u043b\u044c\u044f\u0440"
    ],
    "name:war_x_preferred":[
        "Betliar"
    ],
    "qs_pg:aaroncc":"SK",
    "qs_pg:gn_country":"SK",
    "qs_pg:gn_fcode":"PPL",
    "qs_pg:gn_pop":938,
    "qs_pg:name":"Betliar",
    "qs_pg:name_adm0":"Slovensk\u00e1",
    "qs_pg:name_adm1":"Kosicky",
    "qs_pg:photos_9k":1,
    "qs_pg:photos_9r":1,
    "qs_pg:photos_all":1,
    "qs_pg:photos_sr":0,
    "qs_pg:pop_sr":2,
    "qs_pg:qs_pg_placetype":"locality",
    "qs_pg:qs_pg_placetype_gp":"Town",
    "qs_pg:woe_adm0":23424877,
    "woe:adm0_id":23424877,
    "woe:name_adm0":"Slovensk\u00e1",
    "woe:name_adm1":"Kosicky",
    "woe:placetype":"Town",
    "wof:name":"Betliar",
    "wof:placetype":"locality",
    "wof:population":938
},
  "geometry": {"coordinates":[20.50805,48.70274],"type":"Point"}
}