{
  "type": "Feature",
  "properties": {
    "gn:admin1_code":"04",
    "gn:asciiname":"Brunovce",
    "gn:country_code":"SK",
    "gn:dem":171,
    "gn:feature_class":"P",
    "gn:feature_code":"PPL",
    "gn:name":"Brunovce",
    "gn:population":0,
    "gn:timezone":"Europe/Bratislava",
    "iso:country":"SK",
    "name:cat_x_preferred":[
        "Brunovce"
    ],
    "name:ces_x_preferred":[
        "Brunovce"
    ],
    "name:deu_x_preferred":[
        "Brunovce"
    ],
    "name:epo_x_preferred":[
        "Brunovce"
    ],
    "name:eus_x_preferred":[
        "Brunovce"
    ],
    "name:fra_x_preferred":[
        "Brunovce"
    ],
    "name:hun_x_preferred":[
        "Brun\u00f3c"
    ],
    "name:ita_x_preferred":[
        "Brunovce"
    ],
    "name:msa_x_preferred":[
        "Brunovce"
    ],
    "name:nld_x_preferred":[
        "Brunovce"
    ],
    "name:pol_x_preferred":[
        "Brunovce"
    ],
    "name:ron_x_preferred":[
        "Brunovce"
    ],
    "name:slk_x_preferred":[
        "Brunovce"
    ],
    "name:spa_x_preferred":[
        "Brunovce"
    ],
    "name:srp_x_preferred":[
        "\u0411\u0440\u0443\u043d\u043e\u0432\u0446\u0435"
    ],
    "name:war_x_preferred":[
        "Brunovce"
    ],
    "wof:name":"Brunovce",
    "wof:placetype":"locality"
},
  "geometry": {"coordinates":[17.85333,48.67415],"type":"Point"}
}