{
  "type": "Feature",
  "properties": {
    "gn:admin1_code":"04",
    "gn:asciiname":"Brunovce",
    "gn:country_code":"SK",
    "gn:dem":171,
    "gn:feature_class":"P",
    "gn:feature_code":"PPL",
    "gn:name":"Brunovce",
    "gn:population":0,
    "gn:timezone":"Europe/Bratislava",
    "iso:country":"SK",
    "wof:name":"Brunovce",
    "wof:placetype":"locality"
},
  "geometry": {"coordinates":[17.85333,48.67415],"type":"Point"}
}