{
  "type": "Feature",
  "properties": {
    "gn:admin1_code":"04",
    "gn:asciiname":"Rudica",
    "gn:country_code":"SK",
    "gn:dem":316,
    "gn:feature_class":"P",
    "gn:feature_code":"PPL",
    "gn:name":"Rudica",
    "gn:population":0,
    "gn:timezone":"Europe/Bratislava",
    "iso:country":"SK",
    "wof:name":"Rudica",
    "wof:placetype":"locality"
},
  "geometry": {"coordinates":[18.4509,48.58431],"type":"Point"}
}