{
  "type": "Feature",
  "properties": {
    "gn:admin1_code":"03",
    "gn:asciiname":"Rochovce",
    "gn:country_code":"SK",
    "gn:dem":369,
    "gn:feature_class":"P",
    "gn:feature_code":"PPL",
    "gn:name":"Rochovce",
    "gn:population":0,
    "gn:timezone":"Europe/Bratislava",
    "iso:country":"SK",
    "name:cat_x_preferred":[
        "Rochovce"
    ],
    "name:epo_x_preferred":[
        "Rochovce"
    ],
    "name:eus_x_preferred":[
        "Rochovce"
    ],
    "name:fra_x_preferred":[
        "Rochovce"
    ],
    "name:hun_x_preferred":[
        "Rozsfalva"
    ],
    "name:ita_x_preferred":[
        "Rochovce"
    ],
    "name:msa_x_preferred":[
        "Rochovce"
    ],
    "name:nld_x_preferred":[
        "Rochovce"
    ],
    "name:pol_x_preferred":[
        "Rochovce"
    ],
    "name:ron_x_preferred":[
        "Rochovce"
    ],
    "name:slk_x_preferred":[
        "Rochovce"
    ],
    "name:spa_x_preferred":[
        "Rochovce"
    ],
    "name:srp_x_preferred":[
        "\u0420\u043e\u0445\u043e\u0432\u0446\u0435"
    ],
    "name:ukr_x_preferred":[
        "\u0420\u043e\u0445\u043e\u0432\u0446\u0435"
    ],
    "name:war_x_preferred":[
        "Rochovce"
    ],
    "wof:name":"Rochovce",
    "wof:placetype":"locality"
},
  "geometry": {"coordinates":[20.30133,48.70239],"type":"Point"}
}