{
  "type": "Feature",
  "properties": {
    "gn:gn_country":"SK",
    "gn:gn_fcode":"PPL",
    "gn:gn_pop":0,
    "iso:country":"SK",
    "name:cat_x_preferred":[
        "Martovce"
    ],
    "name:deu_x_preferred":[
        "Martovce"
    ],
    "name:eng_x_preferred":[
        "Martovce"
    ],
    "name:epo_x_preferred":[
        "Martovce"
    ],
    "name:eus_x_preferred":[
        "Martovce"
    ],
    "name:fra_x_preferred":[
        "Martovce"
    ],
    "name:hun_x_preferred":[
        "Martos"
    ],
    "name:ita_x_preferred":[
        "Martovce"
    ],
    "name:msa_x_preferred":[
        "Martovce"
    ],
    "name:nan_x_preferred":[
        "Martovce"
    ],
    "name:nld_x_preferred":[
        "Martovce"
    ],
    "name:pol_x_preferred":[
        "Martovce"
    ],
    "name:ron_x_preferred":[
        "Martovce"
    ],
    "name:slk_x_preferred":[
        "Martovce"
    ],
    "name:spa_x_preferred":[
        "Martovce"
    ],
    "name:srp_x_preferred":[
        "\u041c\u0430\u0440\u0442\u043e\u0432\u0446\u0435"
    ],
    "name:ukr_x_preferred":[
        "\u041c\u0430\u0440\u0442\u043e\u0432\u0446\u0435"
    ],
    "name:unk_x_variant":[
        "Marto\u0161"
    ],
    "name:war_x_preferred":[
        "Martovce"
    ],
    "name:war_x_variant":[
        "Jaku\u0161ovce"
    ],
    "qs_pg:aaroncc":"SK",
    "qs_pg:gn_country":"SK",
    "qs_pg:gn_fcode":"PPL",
    "qs_pg:gn_pop":0,
    "qs_pg:name":"Martovce",
    "qs_pg:name_adm0":"Slovensk\u00e1",
    "qs_pg:name_adm1":"Nitriansky",
    "qs_pg:photos_9k":1,
    "qs_pg:photos_9r":1,
    "qs_pg:photos_all":1,
    "qs_pg:photos_sr":0,
    "qs_pg:pop_sr":0,
    "qs_pg:qs_pg_placetype":"locality",
    "qs_pg:qs_pg_placetype_gp":"Town",
    "qs_pg:woe_adm0":23424877,
    "woe:adm0_id":23424877,
    "woe:name_adm0":"Slovensk\u00e1",
    "woe:name_adm1":"Nitriansky",
    "woe:placetype":"Town",
    "wof:name":"Martovce",
    "wof:placetype":"locality"
},
  "geometry": {"coordinates":[18.12452,47.85498],"type":"Point"}
}